Workbook

Sheet KamstrupData
B1: Active from date | C1: End date | D1: Chose the capability | E1: Auto fill Level 1 | F1: Auto fill Level 2 | G1: Auto fill Level 3 | H1: Not used | I1: Country code | J1: Business Area using/doing the capability | K1: Department or Team using/doing the capability | L1: Chose the application | M1: Auto fill application | N1: Evaluation of Gartner TIME for the application only in relation to this Capability | O1: Classifications for Business Criticality: Administrative Service Business Operational Business Critical Mission Critical. | P1: Business process applying to the capability | Q1: Value Stream applying to the process and application | R1: Value Stream order | S1: Projects involving the current Capability, Process and Application | T1: Comment reletad to the current row
B2: Dates | D2: B-Business Capability | I2: O-Organization | L2: A-Applications | P2: C-Business Context | S2: I-Initiative | T2: Comment
B4: FromDate | C4: EndDate | D4: IdLevel123 | E4: Capbility level 1 | F4: Capbility level 2 | G4: Capbility level 3 | H4: Capbility level 4 | I4: CountryCode | J4: Business Area | K4: DepartmentTeam | L4: NoApplication | M4: Application | N4: Gartner TIME | O4: Business Criticality | P4: NoProcess | Q4: Value Stream | R4: Value Stream Order | S4: Projects | T4: Comment
D5: 1007-Strategic Management-- | E5: =VLOOKUP(D5,'B-Business Capability'!B:H,5,FALSE) -> Strategic Management | F5: =VLOOKUP(D5,'B-Business Capability'!B:H,6,FALSE) -> 0 | G5: =VLOOKUP(D5,'B-Business Capability'!B:H,7,FALSE) -> 0 | I5: DK10 | J5: DK_Executive Management office_Executive Management office | L5: 1 - IFS ERP | M5: =VLOOKUP(L5,'A-Applications'!B:D,3,FALSE) -> IFS ERP | N5: Tolerate | O5: Business Operational | P5: No-NoProcess-- | Q5: =VLOOKUP(KamstrupData[[#This Row],[IdLevel123]],'B-Business Capability'!B:L,10,FALSE) -> N/A | R5: =VLOOKUP(KamstrupData[[#This Row],[IdLevel123]],'B-Business Capability'!B:L,11,FALSE) -> 0 | T5: MJTA
D6: 1022-Finance-Accounting- | E6: =VLOOKUP(D6,'B-Business Capability'!B:H,5,FALSE) -> Finance | F6: =VLOOKUP(D6,'B-Business Capability'!B:H,6,FALSE) -> Accounting | G6: =VLOOKUP(D6,'B-Business Capability'!B:H,7,FALSE) -> 0 | I6: DK10 | J6: DK_Digitalization_EA, Infrastructure and Platforms | K6: DK_Digitalization_EA, Infrastructure and Platforms_Cloud and Platforms | L6: 1 - IFS ERP | M6: =VLOOKUP(L6,'A-Applications'!B:D,3,FALSE) -> IFS ERP | N6: Invest | O6: Administrative Service | P6: P-Not mapped to process-- | Q6: =VLOOKUP(KamstrupData[[#This Row],[IdLevel123]],'B-Business Capability'!B:L,10,FALSE) -> N/A | R6: =VLOOKUP(KamstrupData[[#This Row],[IdLevel123]],'B-Business Capability'!B:L,11,FALSE) -> 0
D7: 1027-Finance-Tax Management- | E7: =VLOOKUP(D7,'B-Business Capability'!B:H,5,FALSE) -> Finance | F7: =VLOOKUP(D7,'B-Business Capability'!B:H,6,FALSE) -> Tax Management | G7: =VLOOKUP(D7,'B-Business Capability'!B:H,7,FALSE) -> 0 | I7: US10 | J7: US_Finance | L7: 1 - IFS ERP | M7: =VLOOKUP(L7,'A-Applications'!B:D,3,FALSE) -> IFS ERP | N7: Tolerate | O7: Business Operational | P7: No-NoProcess-- | Q7: =VLOOKUP(KamstrupData[[#This Row],[IdLevel123]],'B-Business Capability'!B:L,10,FALSE) -> N/A | R7: =VLOOKUP(KamstrupData[[#This Row],[IdLevel123]],'B-Business Capability'!B:L,11,FALSE) -> 0 | T7: JEBL
D8: 1034-Procurement & Logistics-Purchasing- | E8: =VLOOKUP(D8,'B-Business Capability'!B:H,5,FALSE) -> Procurement & Logistics | F8: =VLOOKUP(D8,'B-Business Capability'!B:H,6,FALSE) -> Purchasing | G8: =VLOOKUP(D8,'B-Business Capability'!B:H,7,FALSE) -> 0 | I8: DK10 | J8: Supply Chain | K8: Sourcing | L8: 1 - IFS ERP | M8: =VLOOKUP(L8,'A-Applications'!B:D,3,FALSE) -> IFS ERP | N8: Tolerate | O8: Business Operational | P8: P10-Sourcing-- | Q8: =VLOOKUP(KamstrupData[[#This Row],[IdLevel123]],'B-Business Capability'!B:L,10,FALSE) -> Procure-to-Pay (P2P) | R8: =VLOOKUP(KamstrupData[[#This Row],[IdLevel123]],'B-Business Capability'!B:L,11,FALSE) -> 300 | T8: JEMA
D9: 1034-Procurement & Logistics-Purchasing- | E9: =VLOOKUP(D9,'B-Business Capability'!B:H,5,FALSE) -> Procurement & Logistics | F9: =VLOOKUP(D9,'B-Business Capability'!B:H,6,FALSE) -> Purchasing | G9: =VLOOKUP(D9,'B-Business Capability'!B:H,7,FALSE) -> 0 | I9: US10 | J9: Supply Chain | K9: Sourcing | L9: 1 - IFS ERP | M9: =VLOOKUP(L9,'A-Applications'!B:D,3,FALSE) -> IFS ERP | N9: Tolerate | O9: Business Operational | P9: P10-Sourcing-- | Q9: =VLOOKUP(KamstrupData[[#This Row],[IdLevel123]],'B-Business Capability'!B:L,10,FALSE) -> Procure-to-Pay (P2P) | R9: =VLOOKUP(KamstrupData[[#This Row],[IdLevel123]],'B-Business Capability'!B:L,11,FALSE) -> 300 | T9: JSY
D10: 1035-Procurement & Logistics-Sourcing- | E10: =VLOOKUP(D10,'B-Business Capability'!B:H,5,FALSE) -> Procurement & Logistics | F10: =VLOOKUP(D10,'B-Business Capability'!B:H,6,FALSE) -> Sourcing | G10: =VLOOKUP(D10,'B-Business Capability'!B:H,7,FALSE) -> 0 | I10: DK10 | J10: Supply Chain | K10: Sourcing | L10: 1 - IFS ERP | M10: =VLOOKUP(L10,'A-Applications'!B:D,3,FALSE) -> IFS ERP | N10: Tolerate | O10: Administrative Service | P10: P10-Sourcing-SP10.9-Supplier Phase-Out | Q10: =VLOOKUP(KamstrupData[[#This Row],[IdLevel123]],'B-Business Capability'!B:L,10,FALSE) -> Procure-to-Pay (P2P) | R10: =VLOOKUP(KamstrupData[[#This Row],[IdLevel123]],'B-Business Capability'!B:L,11,FALSE) -> 100 | T10: JEMA, Det er og ændre det data, hvor vi har registreret noget i vedrørende leverandøren.
D11: 1035-Procurement & Logistics-Sourcing- | E11: =VLOOKUP(D11,'B-Business Capability'!B:H,5,FALSE) -> Procurement & Logistics | F11: =VLOOKUP(D11,'B-Business Capability'!B:H,6,FALSE) -> Sourcing | G11: =VLOOKUP(D11,'B-Business Capability'!B:H,7,FALSE) -> 0 | I11: DK10 | J11: Water - Technology Hardware | K11: Mech | L11: 1 - IFS ERP | M11: =VLOOKUP(L11,'A-Applications'!B:D,3,FALSE) -> IFS ERP | N11: Tolerate | O11: Business Operational | P11: P07-Innovation & Solution Development-- | Q11: =VLOOKUP(KamstrupData[[#This Row],[IdLevel123]],'B-Business Capability'!B:L,10,FALSE) -> Procure-to-Pay (P2P) | R11: =VLOOKUP(KamstrupData[[#This Row],[IdLevel123]],'B-Business Capability'!B:L,11,FALSE) -> 100 | T11: DBR, FRFS find capa, for supply change support
D12: 1046-Manufacturing-Change Management- | E12: =VLOOKUP(D12,'B-Business Capability'!B:H,5,FALSE) -> Manufacturing | F12: =VLOOKUP(D12,'B-Business Capability'!B:H,6,FALSE) -> Change Management | G12: =VLOOKUP(D12,'B-Business Capability'!B:H,7,FALSE) -> 0 | I12: DK10 | J12: Supply Chain | L12: 1 - IFS ERP | M12: =VLOOKUP(L12,'A-Applications'!B:D,3,FALSE) -> IFS ERP | N12: Tolerate | O12: Business Critical | P12: P11-Operations-- | Q12: =VLOOKUP(KamstrupData[[#This Row],[IdLevel123]],'B-Business Capability'!B:L,10,FALSE) -> Idea-to-Release (I2R) | R12: =VLOOKUP(KamstrupData[[#This Row],[IdLevel123]],'B-Business Capability'!B:L,11,FALSE) -> 470
D13: 1051-Manufacturing-Product Design & Planning- | E13: =VLOOKUP(D13,'B-Business Capability'!B:H,5,FALSE) -> Manufacturing | F13: =VLOOKUP(D13,'B-Business Capability'!B:H,6,FALSE) -> Product Design & Planning | G13: =VLOOKUP(D13,'B-Business Capability'!B:H,7,FALSE) -> 0 | I13: DK10 | J13: Supply Chain | L13: 1 - IFS ERP | M13: =VLOOKUP(L13,'A-Applications'!B:D,3,FALSE) -> IFS ERP | N13: Tolerate | O13: Business Operational | P13: P11-Operations-- | Q13: =VLOOKUP(KamstrupData[[#This Row],[IdLevel123]],'B-Business Capability'!B:L,10,FALSE) -> Idea-to-Release (I2R) | R13: =VLOOKUP(KamstrupData[[#This Row],[IdLevel123]],'B-Business Capability'!B:L,11,FALSE) -> 450
D14: 1051-Manufacturing-Product Design & Planning- | E14: =VLOOKUP(D14,'B-Business Capability'!B:H,5,FALSE) -> Manufacturing | F14: =VLOOKUP(D14,'B-Business Capability'!B:H,6,FALSE) -> Product Design & Planning | G14: =VLOOKUP(D14,'B-Business Capability'!B:H,7,FALSE) -> 0 | I14: US10 | J14: Supply Chain | L14: 1 - IFS ERP | M14: =VLOOKUP(L14,'A-Applications'!B:D,3,FALSE) -> IFS ERP | N14: Tolerate | O14: Business Operational | P14: P11-Operations-- | Q14: =VLOOKUP(KamstrupData[[#This Row],[IdLevel123]],'B-Business Capability'!B:L,10,FALSE) -> Idea-to-Release (I2R) | R14: =VLOOKUP(KamstrupData[[#This Row],[IdLevel123]],'B-Business Capability'!B:L,11,FALSE) -> 450 | T14: JSY
D15: 1052-Manufacturing-Manufacturing Order Management- | E15: =VLOOKUP(D15,'B-Business Capability'!B:H,5,FALSE) -> Manufacturing | F15: =VLOOKUP(D15,'B-Business Capability'!B:H,6,FALSE) -> Manufacturing Order Management | G15: =VLOOKUP(D15,'B-Business Capability'!B:H,7,FALSE) -> 0 | I15: DK10 | J15: Supply Chain | L15: 1 - IFS ERP | M15: =VLOOKUP(L15,'A-Applications'!B:D,3,FALSE) -> IFS ERP | N15: Tolerate | O15: Business Critical | P15: P11-Operations-- | Q15: =VLOOKUP(KamstrupData[[#This Row],[IdLevel123]],'B-Business Capability'!B:L,10,FALSE) -> Plan-to-Produce (P2P) | R15: =VLOOKUP(KamstrupData[[#This Row],[IdLevel123]],'B-Business Capability'!B:L,11,FALSE) -> 0
D16: 1052-Manufacturing-Manufacturing Order Management- | E16: =VLOOKUP(D16,'B-Business Capability'!B:H,5,FALSE) -> Manufacturing | F16: =VLOOKUP(D16,'B-Business Capability'!B:H,6,FALSE) -> Manufacturing Order Management | G16: =VLOOKUP(D16,'B-Business Capability'!B:H,7,FALSE) -> 0 | I16: US10 | J16: Supply Chain | L16: 1 - IFS ERP | M16: =VLOOKUP(L16,'A-Applications'!B:D,3,FALSE) -> IFS ERP | N16: Tolerate | O16: Business Critical | P16: P11-Operations-- | Q16: =VLOOKUP(KamstrupData[[#This Row],[IdLevel123]],'B-Business Capability'!B:L,10,FALSE) -> Plan-to-Produce (P2P) | R16: =VLOOKUP(KamstrupData[[#This Row],[IdLevel123]],'B-Business Capability'!B:L,11,FALSE) -> 0 | T16: JSY
B17: 45292 | D17: 1052-Manufacturing-Manufacturing Order Management- | E17: =VLOOKUP(D17,'B-Business Capability'!B:H,5,FALSE) -> Manufacturing | F17: =VLOOKUP(D17,'B-Business Capability'!B:H,6,FALSE) -> Manufacturing Order Management | G17: =VLOOKUP(D17,'B-Business Capability'!B:H,7,FALSE) -> 0 | I17: DK10 | J17: DK_Digitalization_Kamstrup Solutions | K17: DK_Digitalization_Kamstrup Solutions_Configuration Management | L17: 1 - IFS ERP | M17: =VLOOKUP(L17,'A-Applications'!B:D,3,FALSE) -> IFS ERP | N17: Invest | O17: Mission Critical | P17: P07-Innovation & Solution Development-SP07.2-Solution Development Model | Q17: =VLOOKUP(KamstrupData[[#This Row],[IdLevel123]],'B-Business Capability'!B:L,10,FALSE) -> Plan-to-Produce (P2P) | R17: =VLOOKUP(KamstrupData[[#This Row],[IdLevel123]],'B-Business Capability'!B:L,11,FALSE) -> 0
D18: 1053-Manufacturing-Manufacturing Steering- | E18: =VLOOKUP(D18,'B-Business Capability'!B:H,5,FALSE) -> Manufacturing | F18: =VLOOKUP(D18,'B-Business Capability'!B:H,6,FALSE) -> Manufacturing Steering | G18: =VLOOKUP(D18,'B-Business Capability'!B:H,7,FALSE) -> 0 | I18: DK10 | J18: Supply Chain | L18: 1 - IFS ERP | M18: =VLOOKUP(L18,'A-Applications'!B:D,3,FALSE) -> IFS ERP | N18: Invest | O18: Business Critical | P18: P11-Operations-SP11.36-Manufacturing Execution Printed Circuit Board Assembly (PCBA) DK | Q18: =VLOOKUP(KamstrupData[[#This Row],[IdLevel123]],'B-Business Capability'!B:L,10,FALSE) -> Plan-to-Produce (P2P) | R18: =VLOOKUP(KamstrupData[[#This Row],[IdLevel123]],'B-Business Capability'!B:L,11,FALSE) -> 0 | T18: Jes, JGN
D19: 1053-Manufacturing-Manufacturing Steering- | E19: =VLOOKUP(D19,'B-Business Capability'!B:H,5,FALSE) -> Manufacturing | F19: =VLOOKUP(D19,'B-Business Capability'!B:H,6,FALSE) -> Manufacturing Steering | G19: =VLOOKUP(D19,'B-Business Capability'!B:H,7,FALSE) -> 0 | I19: DK10 | J19: Supply Chain | L19: 1 - IFS ERP | M19: =VLOOKUP(L19,'A-Applications'!B:D,3,FALSE) -> IFS ERP | N19: Invest | O19: Business Critical | P19: P11-Operations-SP11.3-Manufacturing Planning | Q19: =VLOOKUP(KamstrupData[[#This Row],[IdLevel123]],'B-Business Capability'!B:L,10,FALSE) -> Plan-to-Produce (P2P) | R19: =VLOOKUP(KamstrupData[[#This Row],[IdLevel123]],'B-Business Capability'!B:L,11,FALSE) -> 0 | T19: Jes, JGN
D20: 1053-Manufacturing-Manufacturing Steering- | E20: =VLOOKUP(D20,'B-Business Capability'!B:H,5,FALSE) -> Manufacturing | F20: =VLOOKUP(D20,'B-Business Capability'!B:H,6,FALSE) -> Manufacturing Steering | G20: =VLOOKUP(D20,'B-Business Capability'!B:H,7,FALSE) -> 0 | I20: DK10 | J20: Supply Chain | L20: 1 - IFS ERP | M20: =VLOOKUP(L20,'A-Applications'!B:D,3,FALSE) -> IFS ERP | N20: Invest | O20: Business Critical | P20: P11-Operations-SP11.4-Manufacturing execution Heat & Cooling Temperature Sensors DK | Q20: =VLOOKUP(KamstrupData[[#This Row],[IdLevel123]],'B-Business Capability'!B:L,10,FALSE) -> Plan-to-Produce (P2P) | R20: =VLOOKUP(KamstrupData[[#This Row],[IdLevel123]],'B-Business Capability'!B:L,11,FALSE) -> 0 | T20: Jes, JGN
D21: 1053-Manufacturing-Manufacturing Steering- | E21: =VLOOKUP(D21,'B-Business Capability'!B:H,5,FALSE) -> Manufacturing | F21: =VLOOKUP(D21,'B-Business Capability'!B:H,6,FALSE) -> Manufacturing Steering | G21: =VLOOKUP(D21,'B-Business Capability'!B:H,7,FALSE) -> 0 | I21: DK10 | J21: Supply Chain | L21: 1 - IFS ERP | M21: =VLOOKUP(L21,'A-Applications'!B:D,3,FALSE) -> IFS ERP | N21: Invest | O21: Business Critical | P21: P11-Operations-SP11.5-Manufacturing execution Heat & Cooling DK | Q21: =VLOOKUP(KamstrupData[[#This Row],[IdLevel123]],'B-Business Capability'!B:L,10,FALSE) -> Plan-to-Produce (P2P) | R21: =VLOOKUP(KamstrupData[[#This Row],[IdLevel123]],'B-Business Capability'!B:L,11,FALSE) -> 0 | T21: Jes, JGN
D22: 1053-Manufacturing-Manufacturing Steering- | E22: =VLOOKUP(D22,'B-Business Capability'!B:H,5,FALSE) -> Manufacturing | F22: =VLOOKUP(D22,'B-Business Capability'!B:H,6,FALSE) -> Manufacturing Steering | G22: =VLOOKUP(D22,'B-Business Capability'!B:H,7,FALSE) -> 0 | I22: DK10 | J22: Supply Chain | L22: 1 - IFS ERP | M22: =VLOOKUP(L22,'A-Applications'!B:D,3,FALSE) -> IFS ERP | N22: Invest | O22: Business Critical | P22: P11-Operations-SP11.6-Manufacturing execution Electricity DK | Q22: =VLOOKUP(KamstrupData[[#This Row],[IdLevel123]],'B-Business Capability'!B:L,10,FALSE) -> Plan-to-Produce (P2P) | R22: =VLOOKUP(KamstrupData[[#This Row],[IdLevel123]],'B-Business Capability'!B:L,11,FALSE) -> 0 | T22: Jes, JGN
D23: 1053-Manufacturing-Manufacturing Steering- | E23: =VLOOKUP(D23,'B-Business Capability'!B:H,5,FALSE) -> Manufacturing | F23: =VLOOKUP(D23,'B-Business Capability'!B:H,6,FALSE) -> Manufacturing Steering | G23: =VLOOKUP(D23,'B-Business Capability'!B:H,7,FALSE) -> 0 | I23: DK10 | J23: Supply Chain | L23: 1 - IFS ERP | M23: =VLOOKUP(L23,'A-Applications'!B:D,3,FALSE) -> IFS ERP | N23: Invest | O23: Business Critical | P23: P11-Operations-SP11.7-Manufacturing execution Water DK | Q23: =VLOOKUP(KamstrupData[[#This Row],[IdLevel123]],'B-Business Capability'!B:L,10,FALSE) -> Plan-to-Produce (P2P) | R23: =VLOOKUP(KamstrupData[[#This Row],[IdLevel123]],'B-Business Capability'!B:L,11,FALSE) -> 0 | T23: Jes, JGN
D24: 1053-Manufacturing-Manufacturing Steering- | E24: =VLOOKUP(D24,'B-Business Capability'!B:H,5,FALSE) -> Manufacturing | F24: =VLOOKUP(D24,'B-Business Capability'!B:H,6,FALSE) -> Manufacturing Steering | G24: =VLOOKUP(D24,'B-Business Capability'!B:H,7,FALSE) -> 0 | I24: DK10 | J24: Supply Chain | L24: 1 - IFS ERP | M24: =VLOOKUP(L24,'A-Applications'!B:D,3,FALSE) -> IFS ERP | N24: Invest | O24: Business Critical | P24: P11-Operations-SP11.8-Manufacturing execution Water US | Q24: =VLOOKUP(KamstrupData[[#This Row],[IdLevel123]],'B-Business Capability'!B:L,10,FALSE) -> Plan-to-Produce (P2P) | R24: =VLOOKUP(KamstrupData[[#This Row],[IdLevel123]],'B-Business Capability'!B:L,11,FALSE) -> 0 | T24: Jes, JGN
D25: 1053-Manufacturing-Manufacturing Steering- | E25: =VLOOKUP(D25,'B-Business Capability'!B:H,5,FALSE) -> Manufacturing | F25: =VLOOKUP(D25,'B-Business Capability'!B:H,6,FALSE) -> Manufacturing Steering | G25: =VLOOKUP(D25,'B-Business Capability'!B:H,7,FALSE) -> 0 | I25: DK10 | J25: Supply Chain | L25: 1 - IFS ERP | M25: =VLOOKUP(L25,'A-Applications'!B:D,3,FALSE) -> IFS ERP | N25: Tolerate | O25: Business Critical | P25: P11-Operations-- | Q25: =VLOOKUP(KamstrupData[[#This Row],[IdLevel123]],'B-Business Capability'!B:L,10,FALSE) -> Plan-to-Produce (P2P) | R25: =VLOOKUP(KamstrupData[[#This Row],[IdLevel123]],'B-Business Capability'!B:L,11,FALSE) -> 0
D26: 1053-Manufacturing-Manufacturing Steering- | E26: =VLOOKUP(D26,'B-Business Capability'!B:H,5,FALSE) -> Manufacturing | F26: =VLOOKUP(D26,'B-Business Capability'!B:H,6,FALSE) -> Manufacturing Steering | G26: =VLOOKUP(D26,'B-Business Capability'!B:H,7,FALSE) -> 0 | I26: US10 | J26: Supply Chain | L26: 1 - IFS ERP | M26: =VLOOKUP(L26,'A-Applications'!B:D,3,FALSE) -> IFS ERP | N26: Tolerate | O26: Business Critical | P26: P11-Operations-- | Q26: =VLOOKUP(KamstrupData[[#This Row],[IdLevel123]],'B-Business Capability'!B:L,10,FALSE) -> Plan-to-Produce (P2P) | R26: =VLOOKUP(KamstrupData[[#This Row],[IdLevel123]],'B-Business Capability'!B:L,11,FALSE) -> 0 | T26: JSY
D27: 1087-Strategic Management-Enterprise Effectiveness & Project Management-Develop Projects | E27: =VLOOKUP(D27,'B-Business Capability'!B:H,5,FALSE) -> Strategic Management | F27: =VLOOKUP(D27,'B-Business Capability'!B:H,6,FALSE) -> Enterprise Effectiveness & Project Management | G27: =VLOOKUP(D27,'B-Business Capability'!B:H,7,FALSE) -> Develop Projects | I27: DK10 | J27: Electricity - Product Management | L27: 1 - IFS ERP | M27: =VLOOKUP(L27,'A-Applications'!B:D,3,FALSE) -> IFS ERP | N27: Tolerate | O27: Business Operational | P27: P07-Innovation & Solution Development-SP07.54-Product Management | Q27: =VLOOKUP(KamstrupData[[#This Row],[IdLevel123]],'B-Business Capability'!B:L,10,FALSE) -> N/A | R27: =VLOOKUP(KamstrupData[[#This Row],[IdLevel123]],'B-Business Capability'!B:L,11,FALSE) -> 0 | T27: HTA
B28: 45292 | D28: 1097-People and Culture-Compensation & Benefits- | E28: =VLOOKUP(D28,'B-Business Capability'!B:H,5,FALSE) -> People and Culture | F28: =VLOOKUP(D28,'B-Business Capability'!B:H,6,FALSE) -> Compensation & Benefits | G28: =VLOOKUP(D28,'B-Business Capability'!B:H,7,FALSE) -> 0 | I28: DK10 | J28: Electricity - Technology Hardware | L28: 1 - IFS ERP | M28: =VLOOKUP(L28,'A-Applications'!B:D,3,FALSE) -> IFS ERP | N28: Tolerate | O28: Business Operational | P28: P07-Innovation & Solution Development-- | Q28: =VLOOKUP(KamstrupData[[#This Row],[IdLevel123]],'B-Business Capability'!B:L,10,FALSE) -> Hire-to-Retire (H2R) | R28: =VLOOKUP(KamstrupData[[#This Row],[IdLevel123]],'B-Business Capability'!B:L,11,FALSE) -> 700 | S28: P&C-ASIS | T28: JKI
B29: 45292 | D29: 1097-People and Culture-Compensation & Benefits- | E29: =VLOOKUP(D29,'B-Business Capability'!B:H,5,FALSE) -> People and Culture | F29: =VLOOKUP(D29,'B-Business Capability'!B:H,6,FALSE) -> Compensation & Benefits | G29: =VLOOKUP(D29,'B-Business Capability'!B:H,7,FALSE) -> 0 | I29: DK10 | J29: Heat/Cooling - Technology Hardware | K29: Concentrators | L29: 1 - IFS ERP | M29: =VLOOKUP(L29,'A-Applications'!B:D,3,FALSE) -> IFS ERP | N29: Tolerate | O29: Administrative Service | P29: P34-Salary & Incentives-SP34.7-Registration of working hours | Q29: =VLOOKUP(KamstrupData[[#This Row],[IdLevel123]],'B-Business Capability'!B:L,10,FALSE) -> Hire-to-Retire (H2R) | R29: =VLOOKUP(KamstrupData[[#This Row],[IdLevel123]],'B-Business Capability'!B:L,11,FALSE) -> 700 | S29: P&C-ASIS | T29: JESP, RKL
B30: 45292 | D30: 1097-People and Culture-Compensation & Benefits- | E30: =VLOOKUP(D30,'B-Business Capability'!B:H,5,FALSE) -> People and Culture | F30: =VLOOKUP(D30,'B-Business Capability'!B:H,6,FALSE) -> Compensation & Benefits | G30: =VLOOKUP(D30,'B-Business Capability'!B:H,7,FALSE) -> 0 | I30: DK10 | J30: Heat/Cooling - Technology Hardware | K30: Embeded Software | L30: 1 - IFS ERP | M30: =VLOOKUP(L30,'A-Applications'!B:D,3,FALSE) -> IFS ERP | N30: Tolerate | O30: Administrative Service | P30: P34-Salary & Incentives-SP34.7-Registration of working hours | Q30: =VLOOKUP(KamstrupData[[#This Row],[IdLevel123]],'B-Business Capability'!B:L,10,FALSE) -> Hire-to-Retire (H2R) | R30: =VLOOKUP(KamstrupData[[#This Row],[IdLevel123]],'B-Business Capability'!B:L,11,FALSE) -> 700 | S30: P&C-ASIS | T30: BRR
B31: 45292 | D31: 1097-People and Culture-Compensation & Benefits- | E31: =VLOOKUP(D31,'B-Business Capability'!B:H,5,FALSE) -> People and Culture | F31: =VLOOKUP(D31,'B-Business Capability'!B:H,6,FALSE) -> Compensation & Benefits | G31: =VLOOKUP(D31,'B-Business Capability'!B:H,7,FALSE) -> 0 | I31: DK10 | J31: Heat/Cooling - Technology Hardware | K31: H/C Meters | L31: 1 - IFS ERP | M31: =VLOOKUP(L31,'A-Applications'!B:D,3,FALSE) -> IFS ERP | N31: Tolerate | O31: Administrative Service | P31: P34-Salary & Incentives-SP34.7-Registration of working hours | Q31: =VLOOKUP(KamstrupData[[#This Row],[IdLevel123]],'B-Business Capability'!B:L,10,FALSE) -> Hire-to-Retire (H2R) | R31: =VLOOKUP(KamstrupData[[#This Row],[IdLevel123]],'B-Business Capability'!B:L,11,FALSE) -> 700 | S31: P&C-ASIS | T31: JESP
B32: 45292 | D32: 1097-People and Culture-Compensation & Benefits- | E32: =VLOOKUP(D32,'B-Business Capability'!B:H,5,FALSE) -> People and Culture | F32: =VLOOKUP(D32,'B-Business Capability'!B:H,6,FALSE) -> Compensation & Benefits | G32: =VLOOKUP(D32,'B-Business Capability'!B:H,7,FALSE) -> 0 | I32: DK10 | J32: Heat/Cooling - Technology Hardware | K32: Hardware | L32: 1 - IFS ERP | M32: =VLOOKUP(L32,'A-Applications'!B:D,3,FALSE) -> IFS ERP | N32: Tolerate | O32: Administrative Service | P32: P34-Salary & Incentives-SP34.7-Registration of working hours | Q32: =VLOOKUP(KamstrupData[[#This Row],[IdLevel123]],'B-Business Capability'!B:L,10,FALSE) -> Hire-to-Retire (H2R) | R32: =VLOOKUP(KamstrupData[[#This Row],[IdLevel123]],'B-Business Capability'!B:L,11,FALSE) -> 700 | S32: P&C-ASIS | T32: BOR
B33: 45292 | D33: 1097-People and Culture-Compensation & Benefits- | E33: =VLOOKUP(D33,'B-Business Capability'!B:H,5,FALSE) -> People and Culture | F33: =VLOOKUP(D33,'B-Business Capability'!B:H,6,FALSE) -> Compensation & Benefits | G33: =VLOOKUP(D33,'B-Business Capability'!B:H,7,FALSE) -> 0 | I33: DK10 | J33: Heat/Cooling - Technology Hardware | K33: Tech. Lead | L33: 1 - IFS ERP | M33: =VLOOKUP(L33,'A-Applications'!B:D,3,FALSE) -> IFS ERP | N33: Tolerate | O33: Administrative Service | P33: P34-Salary & Incentives-SP34.7-Registration of working hours | Q33: =VLOOKUP(KamstrupData[[#This Row],[IdLevel123]],'B-Business Capability'!B:L,10,FALSE) -> Hire-to-Retire (H2R) | R33: =VLOOKUP(KamstrupData[[#This Row],[IdLevel123]],'B-Business Capability'!B:L,11,FALSE) -> 700 | S33: P&C-ASIS | T33: JESP, FHA
B34: 45292 | D34: 1097-People and Culture-Compensation & Benefits- | E34: =VLOOKUP(D34,'B-Business Capability'!B:H,5,FALSE) -> People and Culture | F34: =VLOOKUP(D34,'B-Business Capability'!B:H,6,FALSE) -> Compensation & Benefits | G34: =VLOOKUP(D34,'B-Business Capability'!B:H,7,FALSE) -> 0 | I34: DK10 | J34: Water - Technology Hardware | K34: Hardware | L34: 1 - IFS ERP | M34: =VLOOKUP(L34,'A-Applications'!B:D,3,FALSE) -> IFS ERP | N34: Tolerate | O34: Administrative Service | P34: P34-Salary & Incentives-SP34.7-Registration of working hours | Q34: =VLOOKUP(KamstrupData[[#This Row],[IdLevel123]],'B-Business Capability'!B:L,10,FALSE) -> Hire-to-Retire (H2R) | R34: =VLOOKUP(KamstrupData[[#This Row],[IdLevel123]],'B-Business Capability'!B:L,11,FALSE) -> 700 | S34: P&C-ASIS | T34: KEA
B35: 45292 | D35: 1097-People and Culture-Compensation & Benefits- | E35: =VLOOKUP(D35,'B-Business Capability'!B:H,5,FALSE) -> People and Culture | F35: =VLOOKUP(D35,'B-Business Capability'!B:H,6,FALSE) -> Compensation & Benefits | G35: =VLOOKUP(D35,'B-Business Capability'!B:H,7,FALSE) -> 0 | I35: DK10 | J35: Water - Technology Hardware | K35: Tech | L35: 1 - IFS ERP | M35: =VLOOKUP(L35,'A-Applications'!B:D,3,FALSE) -> IFS ERP | N35: Tolerate | O35: Business Operational | P35: P07-Innovation & Solution Development-- | Q35: =VLOOKUP(KamstrupData[[#This Row],[IdLevel123]],'B-Business Capability'!B:L,10,FALSE) -> Hire-to-Retire (H2R) | R35: =VLOOKUP(KamstrupData[[#This Row],[IdLevel123]],'B-Business Capability'!B:L,11,FALSE) -> 700 | S35: P&C-ASIS | T35: JDP
D36: 1101-Digital Platform and Operations-AI, Data & Analytics-Gather Data | E36: =VLOOKUP(D36,'B-Business Capability'!B:H,5,FALSE) -> Digital Platform and Operations | F36: =VLOOKUP(D36,'B-Business Capability'!B:H,6,FALSE) -> AI, Data & Analytics | G36: =VLOOKUP(D36,'B-Business Capability'!B:H,7,FALSE) -> Gather Data | I36: US10 | J36: US_Digitalization | L36: 1 - IFS ERP | M36: =VLOOKUP(L36,'A-Applications'!B:D,3,FALSE) -> IFS ERP | N36: Tolerate | O36: Business Critical | P36: No-NoProcess-- | Q36: =VLOOKUP(KamstrupData[[#This Row],[IdLevel123]],'B-Business Capability'!B:L,10,FALSE) -> N/A | R36: =VLOOKUP(KamstrupData[[#This Row],[IdLevel123]],'B-Business Capability'!B:L,11,FALSE) -> 0 | T36: WAPT
D37: 1107-Digital Management-IT Strategy & Transformation-IT Project Management | E37: =VLOOKUP(D37,'B-Business Capability'!B:H,5,FALSE) -> Digital Management | F37: =VLOOKUP(D37,'B-Business Capability'!B:H,6,FALSE) -> IT Strategy & Transformation | G37: =VLOOKUP(D37,'B-Business Capability'!B:H,7,FALSE) -> IT Project Management | I37: DK10 | J37: DK_Digitalization_Kamstrup Solutions | K37: DK_Digitalization_Kamstrup Solutions_Corporate Solutions | L37: 1 - IFS ERP | M37: =VLOOKUP(L37,'A-Applications'!B:D,3,FALSE) -> IFS ERP | N37: Tolerate | O37: Administrative Service | P37: P33-Project Management-SP33.4-IT Projects | Q37: =VLOOKUP(KamstrupData[[#This Row],[IdLevel123]],'B-Business Capability'!B:L,10,FALSE) -> N/A | R37: =VLOOKUP(KamstrupData[[#This Row],[IdLevel123]],'B-Business Capability'!B:L,11,FALSE) -> 0 | T37: KRTI
D38: 1123-Finance-Accounting-Inventory Valuation | E38: =VLOOKUP(D38,'B-Business Capability'!B:H,5,FALSE) -> Finance | F38: =VLOOKUP(D38,'B-Business Capability'!B:H,6,FALSE) -> Accounting | G38: =VLOOKUP(D38,'B-Business Capability'!B:H,7,FALSE) -> Inventory Valuation | I38: DK10 | J38: DK_Finance | L38: 1 - IFS ERP | M38: =VLOOKUP(L38,'A-Applications'!B:D,3,FALSE) -> IFS ERP | N38: Tolerate | O38: Administrative Service | P38: P-Not mapped to process-- | Q38: =VLOOKUP(KamstrupData[[#This Row],[IdLevel123]],'B-Business Capability'!B:L,10,FALSE) -> N/A | R38: =VLOOKUP(KamstrupData[[#This Row],[IdLevel123]],'B-Business Capability'!B:L,11,FALSE) -> 0
D39: 1123-Finance-Accounting-Inventory Valuation | E39: =VLOOKUP(D39,'B-Business Capability'!B:H,5,FALSE) -> Finance | F39: =VLOOKUP(D39,'B-Business Capability'!B:H,6,FALSE) -> Accounting | G39: =VLOOKUP(D39,'B-Business Capability'!B:H,7,FALSE) -> Inventory Valuation | I39: US10 | J39: US_Finance | L39: 1 - IFS ERP | M39: =VLOOKUP(L39,'A-Applications'!B:D,3,FALSE) -> IFS ERP | N39: Tolerate | O39: Business Operational | P39: No-NoProcess-- | Q39: =VLOOKUP(KamstrupData[[#This Row],[IdLevel123]],'B-Business Capability'!B:L,10,FALSE) -> N/A | R39: =VLOOKUP(KamstrupData[[#This Row],[IdLevel123]],'B-Business Capability'!B:L,11,FALSE) -> 0 | T39: JEBL
D40: 1123-Finance-Accounting-Inventory Valuation | E40: =VLOOKUP(D40,'B-Business Capability'!B:H,5,FALSE) -> Finance | F40: =VLOOKUP(D40,'B-Business Capability'!B:H,6,FALSE) -> Accounting | G40: =VLOOKUP(D40,'B-Business Capability'!B:H,7,FALSE) -> Inventory Valuation | I40: NL10 | J40: NL_Finance | L40: 1 - IFS ERP | M40: =VLOOKUP(L40,'A-Applications'!B:D,3,FALSE) -> IFS ERP | N40: Tolerate | O40: Administrative Service | P40: P-Not mapped to process-- | Q40: =VLOOKUP(KamstrupData[[#This Row],[IdLevel123]],'B-Business Capability'!B:L,10,FALSE) -> N/A | R40: =VLOOKUP(KamstrupData[[#This Row],[IdLevel123]],'B-Business Capability'!B:L,11,FALSE) -> 0
D41: 1123-Finance-Accounting-Inventory Valuation | E41: =VLOOKUP(D41,'B-Business Capability'!B:H,5,FALSE) -> Finance | F41: =VLOOKUP(D41,'B-Business Capability'!B:H,6,FALSE) -> Accounting | G41: =VLOOKUP(D41,'B-Business Capability'!B:H,7,FALSE) -> Inventory Valuation | I41: FR10 | J41: FR_Finance | L41: 1 - IFS ERP | M41: =VLOOKUP(L41,'A-Applications'!B:D,3,FALSE) -> IFS ERP | N41: Tolerate | O41: Business Critical | P41: P-Not mapped to process-- | Q41: =VLOOKUP(KamstrupData[[#This Row],[IdLevel123]],'B-Business Capability'!B:L,10,FALSE) -> N/A | R41: =VLOOKUP(KamstrupData[[#This Row],[IdLevel123]],'B-Business Capability'!B:L,11,FALSE) -> 0
D42: 1125-Finance-Accounting-Manage General Ledger | E42: =VLOOKUP(D42,'B-Business Capability'!B:H,5,FALSE) -> Finance | F42: =VLOOKUP(D42,'B-Business Capability'!B:H,6,FALSE) -> Accounting | G42: =VLOOKUP(D42,'B-Business Capability'!B:H,7,FALSE) -> Manage General Ledger | I42: DK10 | J42: DK_Finance | L42: 1 - IFS ERP | M42: =VLOOKUP(L42,'A-Applications'!B:D,3,FALSE) -> IFS ERP | N42: Tolerate | O42: Administrative Service | P42: P-Not mapped to process-- | Q42: =VLOOKUP(KamstrupData[[#This Row],[IdLevel123]],'B-Business Capability'!B:L,10,FALSE) -> N/A | R42: =VLOOKUP(KamstrupData[[#This Row],[IdLevel123]],'B-Business Capability'!B:L,11,FALSE) -> 0
D43: 1125-Finance-Accounting-Manage General Ledger | E43: =VLOOKUP(D43,'B-Business Capability'!B:H,5,FALSE) -> Finance | F43: =VLOOKUP(D43,'B-Business Capability'!B:H,6,FALSE) -> Accounting | G43: =VLOOKUP(D43,'B-Business Capability'!B:H,7,FALSE) -> Manage General Ledger | I43: NL10 | J43: NL_Finance | L43: 1 - IFS ERP | M43: =VLOOKUP(L43,'A-Applications'!B:D,3,FALSE) -> IFS ERP | N43: Tolerate | O43: Administrative Service | P43: P-Not mapped to process-- | Q43: =VLOOKUP(KamstrupData[[#This Row],[IdLevel123]],'B-Business Capability'!B:L,10,FALSE) -> N/A | R43: =VLOOKUP(KamstrupData[[#This Row],[IdLevel123]],'B-Business Capability'!B:L,11,FALSE) -> 0
D44: 1125-Finance-Accounting-Manage General Ledger | E44: =VLOOKUP(D44,'B-Business Capability'!B:H,5,FALSE) -> Finance | F44: =VLOOKUP(D44,'B-Business Capability'!B:H,6,FALSE) -> Accounting | G44: =VLOOKUP(D44,'B-Business Capability'!B:H,7,FALSE) -> Manage General Ledger | I44: FR10 | J44: FR_Finance | L44: 1 - IFS ERP | M44: =VLOOKUP(L44,'A-Applications'!B:D,3,FALSE) -> IFS ERP | N44: Tolerate | O44: Business Critical | P44: P-Not mapped to process-- | Q44: =VLOOKUP(KamstrupData[[#This Row],[IdLevel123]],'B-Business Capability'!B:L,10,FALSE) -> N/A | R44: =VLOOKUP(KamstrupData[[#This Row],[IdLevel123]],'B-Business Capability'!B:L,11,FALSE) -> 0
D45: 1126-Finance-Accounting-Performance Reporting | E45: =VLOOKUP(D45,'B-Business Capability'!B:H,5,FALSE) -> Finance | F45: =VLOOKUP(D45,'B-Business Capability'!B:H,6,FALSE) -> Accounting | G45: =VLOOKUP(D45,'B-Business Capability'!B:H,7,FALSE) -> Performance Reporting | I45: DK10 | J45: DK_Finance | L45: 1 - IFS ERP | M45: =VLOOKUP(L45,'A-Applications'!B:D,3,FALSE) -> IFS ERP | N45: Tolerate | O45: Administrative Service | P45: P-Not mapped to process-- | Q45: =VLOOKUP(KamstrupData[[#This Row],[IdLevel123]],'B-Business Capability'!B:L,10,FALSE) -> N/A | R45: =VLOOKUP(KamstrupData[[#This Row],[IdLevel123]],'B-Business Capability'!B:L,11,FALSE) -> 0
D46: 1126-Finance-Accounting-Performance Reporting | E46: =VLOOKUP(D46,'B-Business Capability'!B:H,5,FALSE) -> Finance | F46: =VLOOKUP(D46,'B-Business Capability'!B:H,6,FALSE) -> Accounting | G46: =VLOOKUP(D46,'B-Business Capability'!B:H,7,FALSE) -> Performance Reporting | I46: NL10 | J46: NL_Finance | L46: 1 - IFS ERP | M46: =VLOOKUP(L46,'A-Applications'!B:D,3,FALSE) -> IFS ERP | N46: Tolerate | O46: Administrative Service | P46: P-Not mapped to process-- | Q46: =VLOOKUP(KamstrupData[[#This Row],[IdLevel123]],'B-Business Capability'!B:L,10,FALSE) -> N/A | R46: =VLOOKUP(KamstrupData[[#This Row],[IdLevel123]],'B-Business Capability'!B:L,11,FALSE) -> 0
D47: 1126-Finance-Accounting-Performance Reporting | E47: =VLOOKUP(D47,'B-Business Capability'!B:H,5,FALSE) -> Finance | F47: =VLOOKUP(D47,'B-Business Capability'!B:H,6,FALSE) -> Accounting | G47: =VLOOKUP(D47,'B-Business Capability'!B:H,7,FALSE) -> Performance Reporting | I47: FR10 | J47: FR_Finance | L47: 1 - IFS ERP | M47: =VLOOKUP(L47,'A-Applications'!B:D,3,FALSE) -> IFS ERP | N47: Tolerate | O47: Business Critical | P47: P-Not mapped to process-- | Q47: =VLOOKUP(KamstrupData[[#This Row],[IdLevel123]],'B-Business Capability'!B:L,10,FALSE) -> N/A | R47: =VLOOKUP(KamstrupData[[#This Row],[IdLevel123]],'B-Business Capability'!B:L,11,FALSE) -> 0
D48: 1132-Finance-Financial Planning & Analysis-Cost Accounting_Plan | E48: =VLOOKUP(D48,'B-Business Capability'!B:H,5,FALSE) -> Finance | F48: =VLOOKUP(D48,'B-Business Capability'!B:H,6,FALSE) -> Financial Planning & Analysis | G48: =VLOOKUP(D48,'B-Business Capability'!B:H,7,FALSE) -> Cost Accounting_Plan | I48: US10 | J48: Customer Services | L48: 1 - IFS ERP | M48: =VLOOKUP(L48,'A-Applications'!B:D,3,FALSE) -> IFS ERP | N48: Invest | O48: Business Operational | P48: P18-Budget-- | Q48: =VLOOKUP(KamstrupData[[#This Row],[IdLevel123]],'B-Business Capability'!B:L,10,FALSE) -> N/A | R48: =VLOOKUP(KamstrupData[[#This Row],[IdLevel123]],'B-Business Capability'!B:L,11,FALSE) -> 0 | T48: AMYN
D49: 1132-Finance-Financial Planning & Analysis-Cost Accounting_Plan | E49: =VLOOKUP(D49,'B-Business Capability'!B:H,5,FALSE) -> Finance | F49: =VLOOKUP(D49,'B-Business Capability'!B:H,6,FALSE) -> Financial Planning & Analysis | G49: =VLOOKUP(D49,'B-Business Capability'!B:H,7,FALSE) -> Cost Accounting_Plan | I49: DK10 | J49: Electricity - Customer Services | L49: 1 - IFS ERP | M49: =VLOOKUP(L49,'A-Applications'!B:D,3,FALSE) -> IFS ERP | N49: Tolerate | O49: Business Operational | P49: P18-Budget-- | Q49: =VLOOKUP(KamstrupData[[#This Row],[IdLevel123]],'B-Business Capability'!B:L,10,FALSE) -> N/A | R49: =VLOOKUP(KamstrupData[[#This Row],[IdLevel123]],'B-Business Capability'!B:L,11,FALSE) -> 0
D50: 1132-Finance-Financial Planning & Analysis-Cost Accounting_Plan | E50: =VLOOKUP(D50,'B-Business Capability'!B:H,5,FALSE) -> Finance | F50: =VLOOKUP(D50,'B-Business Capability'!B:H,6,FALSE) -> Financial Planning & Analysis | G50: =VLOOKUP(D50,'B-Business Capability'!B:H,7,FALSE) -> Cost Accounting_Plan | I50: DK10 | J50: Heat/Cooling - Customer Services | L50: 1 - IFS ERP | M50: =VLOOKUP(L50,'A-Applications'!B:D,3,FALSE) -> IFS ERP | N50: Tolerate | O50: Business Operational | P50: P18-Budget-- | Q50: =VLOOKUP(KamstrupData[[#This Row],[IdLevel123]],'B-Business Capability'!B:L,10,FALSE) -> N/A | R50: =VLOOKUP(KamstrupData[[#This Row],[IdLevel123]],'B-Business Capability'!B:L,11,FALSE) -> 0 | T50: THB
D51: 1132-Finance-Financial Planning & Analysis-Cost Accounting_Plan | E51: =VLOOKUP(D51,'B-Business Capability'!B:H,5,FALSE) -> Finance | F51: =VLOOKUP(D51,'B-Business Capability'!B:H,6,FALSE) -> Financial Planning & Analysis | G51: =VLOOKUP(D51,'B-Business Capability'!B:H,7,FALSE) -> Cost Accounting_Plan | I51: DK10 | J51: Water - Customer Services | L51: 1 - IFS ERP | M51: =VLOOKUP(L51,'A-Applications'!B:D,3,FALSE) -> IFS ERP | N51: Tolerate | O51: Business Operational | P51: P18-Budget-- | Q51: =VLOOKUP(KamstrupData[[#This Row],[IdLevel123]],'B-Business Capability'!B:L,10,FALSE) -> N/A | R51: =VLOOKUP(KamstrupData[[#This Row],[IdLevel123]],'B-Business Capability'!B:L,11,FALSE) -> 0
D52: 1132-Finance-Financial Planning & Analysis-Cost Accounting_Plan | E52: =VLOOKUP(D52,'B-Business Capability'!B:H,5,FALSE) -> Finance | F52: =VLOOKUP(D52,'B-Business Capability'!B:H,6,FALSE) -> Financial Planning & Analysis | G52: =VLOOKUP(D52,'B-Business Capability'!B:H,7,FALSE) -> Cost Accounting_Plan | I52: ES10 | J52: ES_Customer Service | L52: 1 - IFS ERP | M52: =VLOOKUP(L52,'A-Applications'!B:D,3,FALSE) -> IFS ERP | N52: Tolerate | O52: Business Critical | P52: P18-Budget-- | Q52: =VLOOKUP(KamstrupData[[#This Row],[IdLevel123]],'B-Business Capability'!B:L,10,FALSE) -> N/A | R52: =VLOOKUP(KamstrupData[[#This Row],[IdLevel123]],'B-Business Capability'!B:L,11,FALSE) -> 0 | T52: RLF
D53: 1132-Finance-Financial Planning & Analysis-Cost Accounting_Plan | E53: =VLOOKUP(D53,'B-Business Capability'!B:H,5,FALSE) -> Finance | F53: =VLOOKUP(D53,'B-Business Capability'!B:H,6,FALSE) -> Financial Planning & Analysis | G53: =VLOOKUP(D53,'B-Business Capability'!B:H,7,FALSE) -> Cost Accounting_Plan | I53: NL10 | J53: NL_Sales & Marketing | K53: Customer Service/Project Management | L53: 1 - IFS ERP | M53: =VLOOKUP(L53,'A-Applications'!B:D,3,FALSE) -> IFS ERP | N53: Invest | O53: Business Operational | P53: P18-Budget-- | Q53: =VLOOKUP(KamstrupData[[#This Row],[IdLevel123]],'B-Business Capability'!B:L,10,FALSE) -> N/A | R53: =VLOOKUP(KamstrupData[[#This Row],[IdLevel123]],'B-Business Capability'!B:L,11,FALSE) -> 0
D54: 1132-Finance-Financial Planning & Analysis-Cost Accounting_Plan | E54: =VLOOKUP(D54,'B-Business Capability'!B:H,5,FALSE) -> Finance | F54: =VLOOKUP(D54,'B-Business Capability'!B:H,6,FALSE) -> Financial Planning & Analysis | G54: =VLOOKUP(D54,'B-Business Capability'!B:H,7,FALSE) -> Cost Accounting_Plan | I54: CH10 | J54: CH_Customer Services (Project & Support) | L54: 1 - IFS ERP | M54: =VLOOKUP(L54,'A-Applications'!B:D,3,FALSE) -> IFS ERP | N54: Tolerate | O54: Business Critical | P54: P18-Budget-- | Q54: =VLOOKUP(KamstrupData[[#This Row],[IdLevel123]],'B-Business Capability'!B:L,10,FALSE) -> N/A | R54: =VLOOKUP(KamstrupData[[#This Row],[IdLevel123]],'B-Business Capability'!B:L,11,FALSE) -> 0
D55: 1132-Finance-Financial Planning & Analysis-Cost Accounting_Plan | E55: =VLOOKUP(D55,'B-Business Capability'!B:H,5,FALSE) -> Finance | F55: =VLOOKUP(D55,'B-Business Capability'!B:H,6,FALSE) -> Financial Planning & Analysis | G55: =VLOOKUP(D55,'B-Business Capability'!B:H,7,FALSE) -> Cost Accounting_Plan | I55: FR10 | J55: FR_Customer Service & Support | K55: Support | L55: 1 - IFS ERP | M55: =VLOOKUP(L55,'A-Applications'!B:D,3,FALSE) -> IFS ERP | N55: Invest | O55: Business Operational | P55: P18-Budget-- | Q55: =VLOOKUP(KamstrupData[[#This Row],[IdLevel123]],'B-Business Capability'!B:L,10,FALSE) -> N/A | R55: =VLOOKUP(KamstrupData[[#This Row],[IdLevel123]],'B-Business Capability'!B:L,11,FALSE) -> 0
B56: 45292 | D56: 1136-Finance-Payroll-Time Stamp Report | E56: =VLOOKUP(D56,'B-Business Capability'!B:H,5,FALSE) -> Finance | F56: =VLOOKUP(D56,'B-Business Capability'!B:H,6,FALSE) -> Payroll | G56: =VLOOKUP(D56,'B-Business Capability'!B:H,7,FALSE) -> Time Stamp Report | I56: DK10 | J56: DK_Digitalization_Customer Operations | K56: DK_Digitalization_Customer Operations_ Global Operations | L56: 1 - IFS ERP | M56: =VLOOKUP(L56,'A-Applications'!B:D,3,FALSE) -> IFS ERP | N56: Tolerate | O56: Business Operational | Q56: =VLOOKUP(KamstrupData[[#This Row],[IdLevel123]],'B-Business Capability'!B:L,10,FALSE) -> N/A | R56: =VLOOKUP(KamstrupData[[#This Row],[IdLevel123]],'B-Business Capability'!B:L,11,FALSE) -> 0
D57: 1136-Finance-Payroll-Time Stamp Report | E57: =VLOOKUP(D57,'B-Business Capability'!B:H,5,FALSE) -> Finance | F57: =VLOOKUP(D57,'B-Business Capability'!B:H,6,FALSE) -> Payroll | G57: =VLOOKUP(D57,'B-Business Capability'!B:H,7,FALSE) -> Time Stamp Report | I57: DK10 | J57: DK_Digitalization_Customer Operations | K57: DK_Digitalization_Customer Operations_Enterprise Services | L57: 1 - IFS ERP | M57: =VLOOKUP(L57,'A-Applications'!B:D,3,FALSE) -> IFS ERP | N57: Tolerate | O57: Administrative Service | P57: NoProcess | Q57: =VLOOKUP(KamstrupData[[#This Row],[IdLevel123]],'B-Business Capability'!B:L,10,FALSE) -> N/A | R57: =VLOOKUP(KamstrupData[[#This Row],[IdLevel123]],'B-Business Capability'!B:L,11,FALSE) -> 0 | T57: SAST
B58: 45292 | D58: 1136-Finance-Payroll-Time Stamp Report | E58: =VLOOKUP(D58,'B-Business Capability'!B:H,5,FALSE) -> Finance | F58: =VLOOKUP(D58,'B-Business Capability'!B:H,6,FALSE) -> Payroll | G58: =VLOOKUP(D58,'B-Business Capability'!B:H,7,FALSE) -> Time Stamp Report | I58: DK10 | J58: DK_Digitalization_Customer Operations | K58: DK_Digitalization_Customer Operations_Hosting HCW | L58: 1 - IFS ERP | M58: =VLOOKUP(L58,'A-Applications'!B:D,3,FALSE) -> IFS ERP | N58: Tolerate | O58: Business Operational | P58: NoProcess | Q58: =VLOOKUP(KamstrupData[[#This Row],[IdLevel123]],'B-Business Capability'!B:L,10,FALSE) -> N/A | R58: =VLOOKUP(KamstrupData[[#This Row],[IdLevel123]],'B-Business Capability'!B:L,11,FALSE) -> 0
B59: 46023 | D59: 1136-Finance-Payroll-Time Stamp Report | E59: =VLOOKUP(D59,'B-Business Capability'!B:H,5,FALSE) -> Finance | F59: =VLOOKUP(D59,'B-Business Capability'!B:H,6,FALSE) -> Payroll | G59: =VLOOKUP(D59,'B-Business Capability'!B:H,7,FALSE) -> Time Stamp Report | I59: DK10 | J59: DK_Digitalization_Kamstrup Solutions | K59: DK_Digitalization_Kamstrup Solutions_Manufacturing IT | L59: 1 - IFS ERP | M59: =VLOOKUP(L59,'A-Applications'!B:D,3,FALSE) -> IFS ERP | N59: Tolerate | O59: Administrative Service | Q59: =VLOOKUP(KamstrupData[[#This Row],[IdLevel123]],'B-Business Capability'!B:L,10,FALSE) -> N/A | R59: =VLOOKUP(KamstrupData[[#This Row],[IdLevel123]],'B-Business Capability'!B:L,11,FALSE) -> 0
D60: 1137-Finance-Settlements & Payments-Account Payables | E60: =VLOOKUP(D60,'B-Business Capability'!B:H,5,FALSE) -> Finance | F60: =VLOOKUP(D60,'B-Business Capability'!B:H,6,FALSE) -> Settlements & Payments | G60: =VLOOKUP(D60,'B-Business Capability'!B:H,7,FALSE) -> Account Payables | I60: AT10 | J60: AT_Finance | L60: 1 - IFS ERP | M60: =VLOOKUP(L60,'A-Applications'!B:D,3,FALSE) -> IFS ERP | N60: Tolerate | O60: Administrative Service | P60: P14-Accounting-SP14.1-Procure to Pay | Q60: =VLOOKUP(KamstrupData[[#This Row],[IdLevel123]],'B-Business Capability'!B:L,10,FALSE) -> Procure-to-Pay (P2P) | R60: =VLOOKUP(KamstrupData[[#This Row],[IdLevel123]],'B-Business Capability'!B:L,11,FALSE) -> 500
D61: 1137-Finance-Settlements & Payments-Account Payables | E61: =VLOOKUP(D61,'B-Business Capability'!B:H,5,FALSE) -> Finance | F61: =VLOOKUP(D61,'B-Business Capability'!B:H,6,FALSE) -> Settlements & Payments | G61: =VLOOKUP(D61,'B-Business Capability'!B:H,7,FALSE) -> Account Payables | I61: CA10 | J61: CA_Finance | L61: 1 - IFS ERP | M61: =VLOOKUP(L61,'A-Applications'!B:D,3,FALSE) -> IFS ERP | N61: Tolerate | O61: Administrative Service | P61: P14-Accounting-SP14.1-Procure to Pay | Q61: =VLOOKUP(KamstrupData[[#This Row],[IdLevel123]],'B-Business Capability'!B:L,10,FALSE) -> Procure-to-Pay (P2P) | R61: =VLOOKUP(KamstrupData[[#This Row],[IdLevel123]],'B-Business Capability'!B:L,11,FALSE) -> 500
D62: 1137-Finance-Settlements & Payments-Account Payables | E62: =VLOOKUP(D62,'B-Business Capability'!B:H,5,FALSE) -> Finance | F62: =VLOOKUP(D62,'B-Business Capability'!B:H,6,FALSE) -> Settlements & Payments | G62: =VLOOKUP(D62,'B-Business Capability'!B:H,7,FALSE) -> Account Payables | I62: CH10 | J62: CH_Sales & Marketing | K62: Internal Sales | L62: 1 - IFS ERP | M62: =VLOOKUP(L62,'A-Applications'!B:D,3,FALSE) -> IFS ERP | N62: Tolerate | O62: Administrative Service | P62: P14-Accounting-SP14.1-Procure to Pay | Q62: =VLOOKUP(KamstrupData[[#This Row],[IdLevel123]],'B-Business Capability'!B:L,10,FALSE) -> Procure-to-Pay (P2P) | R62: =VLOOKUP(KamstrupData[[#This Row],[IdLevel123]],'B-Business Capability'!B:L,11,FALSE) -> 500
D63: 1137-Finance-Settlements & Payments-Account Payables | E63: =VLOOKUP(D63,'B-Business Capability'!B:H,5,FALSE) -> Finance | F63: =VLOOKUP(D63,'B-Business Capability'!B:H,6,FALSE) -> Settlements & Payments | G63: =VLOOKUP(D63,'B-Business Capability'!B:H,7,FALSE) -> Account Payables | I63: CN10 | J63: CN_Finance | L63: 1 - IFS ERP | M63: =VLOOKUP(L63,'A-Applications'!B:D,3,FALSE) -> IFS ERP | N63: Tolerate | O63: Administrative Service | P63: P14-Accounting-SP14.1-Procure to Pay | Q63: =VLOOKUP(KamstrupData[[#This Row],[IdLevel123]],'B-Business Capability'!B:L,10,FALSE) -> Procure-to-Pay (P2P) | R63: =VLOOKUP(KamstrupData[[#This Row],[IdLevel123]],'B-Business Capability'!B:L,11,FALSE) -> 500
D64: 1137-Finance-Settlements & Payments-Account Payables | E64: =VLOOKUP(D64,'B-Business Capability'!B:H,5,FALSE) -> Finance | F64: =VLOOKUP(D64,'B-Business Capability'!B:H,6,FALSE) -> Settlements & Payments | G64: =VLOOKUP(D64,'B-Business Capability'!B:H,7,FALSE) -> Account Payables | I64: DE10 | J64: DE_Finance | L64: 1 - IFS ERP | M64: =VLOOKUP(L64,'A-Applications'!B:D,3,FALSE) -> IFS ERP | N64: Tolerate | O64: Administrative Service | P64: P14-Accounting-SP14.1-Procure to Pay | Q64: =VLOOKUP(KamstrupData[[#This Row],[IdLevel123]],'B-Business Capability'!B:L,10,FALSE) -> Procure-to-Pay (P2P) | R64: =VLOOKUP(KamstrupData[[#This Row],[IdLevel123]],'B-Business Capability'!B:L,11,FALSE) -> 500
D65: 1137-Finance-Settlements & Payments-Account Payables | E65: =VLOOKUP(D65,'B-Business Capability'!B:H,5,FALSE) -> Finance | F65: =VLOOKUP(D65,'B-Business Capability'!B:H,6,FALSE) -> Settlements & Payments | G65: =VLOOKUP(D65,'B-Business Capability'!B:H,7,FALSE) -> Account Payables | I65: DK10 | J65: DK_Finance | L65: 1 - IFS ERP | M65: =VLOOKUP(L65,'A-Applications'!B:D,3,FALSE) -> IFS ERP | N65: Tolerate | O65: Administrative Service | P65: P14-Accounting-SP14.1-Procure to Pay | Q65: =VLOOKUP(KamstrupData[[#This Row],[IdLevel123]],'B-Business Capability'!B:L,10,FALSE) -> Procure-to-Pay (P2P) | R65: =VLOOKUP(KamstrupData[[#This Row],[IdLevel123]],'B-Business Capability'!B:L,11,FALSE) -> 500
D66: 1137-Finance-Settlements & Payments-Account Payables | E66: =VLOOKUP(D66,'B-Business Capability'!B:H,5,FALSE) -> Finance | F66: =VLOOKUP(D66,'B-Business Capability'!B:H,6,FALSE) -> Settlements & Payments | G66: =VLOOKUP(D66,'B-Business Capability'!B:H,7,FALSE) -> Account Payables | I66: ES10 | J66: ES_Finance | L66: 1 - IFS ERP | M66: =VLOOKUP(L66,'A-Applications'!B:D,3,FALSE) -> IFS ERP | N66: Tolerate | O66: Administrative Service | P66: P14-Accounting-SP14.1-Procure to Pay | Q66: =VLOOKUP(KamstrupData[[#This Row],[IdLevel123]],'B-Business Capability'!B:L,10,FALSE) -> Procure-to-Pay (P2P) | R66: =VLOOKUP(KamstrupData[[#This Row],[IdLevel123]],'B-Business Capability'!B:L,11,FALSE) -> 500 | T66: RLF
D67: 1137-Finance-Settlements & Payments-Account Payables | E67: =VLOOKUP(D67,'B-Business Capability'!B:H,5,FALSE) -> Finance | F67: =VLOOKUP(D67,'B-Business Capability'!B:H,6,FALSE) -> Settlements & Payments | G67: =VLOOKUP(D67,'B-Business Capability'!B:H,7,FALSE) -> Account Payables | I67: FI10 | J67: FI_Finance | L67: 1 - IFS ERP | M67: =VLOOKUP(L67,'A-Applications'!B:D,3,FALSE) -> IFS ERP | N67: Tolerate | O67: Administrative Service | P67: P14-Accounting-SP14.1-Procure to Pay | Q67: =VLOOKUP(KamstrupData[[#This Row],[IdLevel123]],'B-Business Capability'!B:L,10,FALSE) -> Procure-to-Pay (P2P) | R67: =VLOOKUP(KamstrupData[[#This Row],[IdLevel123]],'B-Business Capability'!B:L,11,FALSE) -> 500
D68: 1137-Finance-Settlements & Payments-Account Payables | E68: =VLOOKUP(D68,'B-Business Capability'!B:H,5,FALSE) -> Finance | F68: =VLOOKUP(D68,'B-Business Capability'!B:H,6,FALSE) -> Settlements & Payments | G68: =VLOOKUP(D68,'B-Business Capability'!B:H,7,FALSE) -> Account Payables | I68: FR10 | J68: FR_Finance | L68: 1 - IFS ERP | M68: =VLOOKUP(L68,'A-Applications'!B:D,3,FALSE) -> IFS ERP | N68: Tolerate | O68: Business Critical | P68: P14-Accounting-SP14.1-Procure to Pay | Q68: =VLOOKUP(KamstrupData[[#This Row],[IdLevel123]],'B-Business Capability'!B:L,10,FALSE) -> Procure-to-Pay (P2P) | R68: =VLOOKUP(KamstrupData[[#This Row],[IdLevel123]],'B-Business Capability'!B:L,11,FALSE) -> 500
D69: 1137-Finance-Settlements & Payments-Account Payables | E69: =VLOOKUP(D69,'B-Business Capability'!B:H,5,FALSE) -> Finance | F69: =VLOOKUP(D69,'B-Business Capability'!B:H,6,FALSE) -> Settlements & Payments | G69: =VLOOKUP(D69,'B-Business Capability'!B:H,7,FALSE) -> Account Payables | I69: IT10 | J69: IT_Finance | L69: 1 - IFS ERP | M69: =VLOOKUP(L69,'A-Applications'!B:D,3,FALSE) -> IFS ERP | N69: Tolerate | O69: Administrative Service | P69: P14-Accounting-SP14.1-Procure to Pay | Q69: =VLOOKUP(KamstrupData[[#This Row],[IdLevel123]],'B-Business Capability'!B:L,10,FALSE) -> Procure-to-Pay (P2P) | R69: =VLOOKUP(KamstrupData[[#This Row],[IdLevel123]],'B-Business Capability'!B:L,11,FALSE) -> 500
D70: 1137-Finance-Settlements & Payments-Account Payables | E70: =VLOOKUP(D70,'B-Business Capability'!B:H,5,FALSE) -> Finance | F70: =VLOOKUP(D70,'B-Business Capability'!B:H,6,FALSE) -> Settlements & Payments | G70: =VLOOKUP(D70,'B-Business Capability'!B:H,7,FALSE) -> Account Payables | I70: MY10 | J70: MY_Finance | L70: 1 - IFS ERP | M70: =VLOOKUP(L70,'A-Applications'!B:D,3,FALSE) -> IFS ERP | N70: Tolerate | O70: Administrative Service | P70: P14-Accounting-SP14.1-Procure to Pay | Q70: =VLOOKUP(KamstrupData[[#This Row],[IdLevel123]],'B-Business Capability'!B:L,10,FALSE) -> Procure-to-Pay (P2P) | R70: =VLOOKUP(KamstrupData[[#This Row],[IdLevel123]],'B-Business Capability'!B:L,11,FALSE) -> 500
D71: 1137-Finance-Settlements & Payments-Account Payables | E71: =VLOOKUP(D71,'B-Business Capability'!B:H,5,FALSE) -> Finance | F71: =VLOOKUP(D71,'B-Business Capability'!B:H,6,FALSE) -> Settlements & Payments | G71: =VLOOKUP(D71,'B-Business Capability'!B:H,7,FALSE) -> Account Payables | I71: NL10 | J71: NL_Finance | L71: 1 - IFS ERP | M71: =VLOOKUP(L71,'A-Applications'!B:D,3,FALSE) -> IFS ERP | N71: Tolerate | O71: Administrative Service | P71: P14-Accounting-SP14.1-Procure to Pay | Q71: =VLOOKUP(KamstrupData[[#This Row],[IdLevel123]],'B-Business Capability'!B:L,10,FALSE) -> Procure-to-Pay (P2P) | R71: =VLOOKUP(KamstrupData[[#This Row],[IdLevel123]],'B-Business Capability'!B:L,11,FALSE) -> 500
D72: 1137-Finance-Settlements & Payments-Account Payables | E72: =VLOOKUP(D72,'B-Business Capability'!B:H,5,FALSE) -> Finance | F72: =VLOOKUP(D72,'B-Business Capability'!B:H,6,FALSE) -> Settlements & Payments | G72: =VLOOKUP(D72,'B-Business Capability'!B:H,7,FALSE) -> Account Payables | I72: NO10 | J72: NO_Finance | L72: 1 - IFS ERP | M72: =VLOOKUP(L72,'A-Applications'!B:D,3,FALSE) -> IFS ERP | N72: Tolerate | O72: Administrative Service | P72: P14-Accounting-SP14.1-Procure to Pay | Q72: =VLOOKUP(KamstrupData[[#This Row],[IdLevel123]],'B-Business Capability'!B:L,10,FALSE) -> Procure-to-Pay (P2P) | R72: =VLOOKUP(KamstrupData[[#This Row],[IdLevel123]],'B-Business Capability'!B:L,11,FALSE) -> 500
D73: 1137-Finance-Settlements & Payments-Account Payables | E73: =VLOOKUP(D73,'B-Business Capability'!B:H,5,FALSE) -> Finance | F73: =VLOOKUP(D73,'B-Business Capability'!B:H,6,FALSE) -> Settlements & Payments | G73: =VLOOKUP(D73,'B-Business Capability'!B:H,7,FALSE) -> Account Payables | I73: SE10 | J73: SE_Finance | L73: 1 - IFS ERP | M73: =VLOOKUP(L73,'A-Applications'!B:D,3,FALSE) -> IFS ERP | N73: Tolerate | O73: Administrative Service | P73: P14-Accounting-SP14.1-Procure to Pay | Q73: =VLOOKUP(KamstrupData[[#This Row],[IdLevel123]],'B-Business Capability'!B:L,10,FALSE) -> Procure-to-Pay (P2P) | R73: =VLOOKUP(KamstrupData[[#This Row],[IdLevel123]],'B-Business Capability'!B:L,11,FALSE) -> 500
D74: 1137-Finance-Settlements & Payments-Account Payables | E74: =VLOOKUP(D74,'B-Business Capability'!B:H,5,FALSE) -> Finance | F74: =VLOOKUP(D74,'B-Business Capability'!B:H,6,FALSE) -> Settlements & Payments | G74: =VLOOKUP(D74,'B-Business Capability'!B:H,7,FALSE) -> Account Payables | I74: US10 | J74: US_Finance | L74: 1 - IFS ERP | M74: =VLOOKUP(L74,'A-Applications'!B:D,3,FALSE) -> IFS ERP | N74: Tolerate | O74: Business Operational | P74: No-NoProcess-- | Q74: =VLOOKUP(KamstrupData[[#This Row],[IdLevel123]],'B-Business Capability'!B:L,10,FALSE) -> Procure-to-Pay (P2P) | R74: =VLOOKUP(KamstrupData[[#This Row],[IdLevel123]],'B-Business Capability'!B:L,11,FALSE) -> 500 | T74: JEBL
D75: 1137-Finance-Settlements & Payments-Account Payables | E75: =VLOOKUP(D75,'B-Business Capability'!B:H,5,FALSE) -> Finance | F75: =VLOOKUP(D75,'B-Business Capability'!B:H,6,FALSE) -> Settlements & Payments | G75: =VLOOKUP(D75,'B-Business Capability'!B:H,7,FALSE) -> Account Payables | I75: FR10 | J75: FR_Finance | L75: 1 - IFS ERP | M75: =VLOOKUP(L75,'A-Applications'!B:D,3,FALSE) -> IFS ERP | N75: Tolerate | O75: Business Critical | P75: P14-Accounting-SP14.1-Procure to Pay | Q75: =VLOOKUP(KamstrupData[[#This Row],[IdLevel123]],'B-Business Capability'!B:L,10,FALSE) -> Procure-to-Pay (P2P) | R75: =VLOOKUP(KamstrupData[[#This Row],[IdLevel123]],'B-Business Capability'!B:L,11,FALSE) -> 500
D76: 1138-Finance-Settlements & Payments-Billing | E76: =VLOOKUP(D76,'B-Business Capability'!B:H,5,FALSE) -> Finance | F76: =VLOOKUP(D76,'B-Business Capability'!B:H,6,FALSE) -> Settlements & Payments | G76: =VLOOKUP(D76,'B-Business Capability'!B:H,7,FALSE) -> Billing | I76: NL10 | J76: NL_Finance | L76: 1 - IFS ERP | M76: =VLOOKUP(L76,'A-Applications'!B:D,3,FALSE) -> IFS ERP | N76: Tolerate | O76: Administrative Service | P76: P-Not mapped to process-- | Q76: =VLOOKUP(KamstrupData[[#This Row],[IdLevel123]],'B-Business Capability'!B:L,10,FALSE) -> N/A | R76: =VLOOKUP(KamstrupData[[#This Row],[IdLevel123]],'B-Business Capability'!B:L,11,FALSE) -> 0
D77: 1138-Finance-Settlements & Payments-Billing | E77: =VLOOKUP(D77,'B-Business Capability'!B:H,5,FALSE) -> Finance | F77: =VLOOKUP(D77,'B-Business Capability'!B:H,6,FALSE) -> Settlements & Payments | G77: =VLOOKUP(D77,'B-Business Capability'!B:H,7,FALSE) -> Billing | I77: DK10 | J77: DK_Finance | L77: 1 - IFS ERP | M77: =VLOOKUP(L77,'A-Applications'!B:D,3,FALSE) -> IFS ERP | N77: Tolerate | O77: Business Operational | P77: P-Not mapped to process-- | Q77: =VLOOKUP(KamstrupData[[#This Row],[IdLevel123]],'B-Business Capability'!B:L,10,FALSE) -> N/A | R77: =VLOOKUP(KamstrupData[[#This Row],[IdLevel123]],'B-Business Capability'!B:L,11,FALSE) -> 0 | T77: 100% Automatic, monitored by IT
D78: 1138-Finance-Settlements & Payments-Billing | E78: =VLOOKUP(D78,'B-Business Capability'!B:H,5,FALSE) -> Finance | F78: =VLOOKUP(D78,'B-Business Capability'!B:H,6,FALSE) -> Settlements & Payments | G78: =VLOOKUP(D78,'B-Business Capability'!B:H,7,FALSE) -> Billing | I78: US10 | J78: US_Finance | L78: 1 - IFS ERP | M78: =VLOOKUP(L78,'A-Applications'!B:D,3,FALSE) -> IFS ERP | N78: Tolerate | O78: Business Critical | P78: No-NoProcess-- | Q78: =VLOOKUP(KamstrupData[[#This Row],[IdLevel123]],'B-Business Capability'!B:L,10,FALSE) -> N/A | R78: =VLOOKUP(KamstrupData[[#This Row],[IdLevel123]],'B-Business Capability'!B:L,11,FALSE) -> 0 | T78: JEBL
D79: 1138-Finance-Settlements & Payments-Billing | E79: =VLOOKUP(D79,'B-Business Capability'!B:H,5,FALSE) -> Finance | F79: =VLOOKUP(D79,'B-Business Capability'!B:H,6,FALSE) -> Settlements & Payments | G79: =VLOOKUP(D79,'B-Business Capability'!B:H,7,FALSE) -> Billing | I79: FR10 | J79: FR_Finance | L79: 1 - IFS ERP | M79: =VLOOKUP(L79,'A-Applications'!B:D,3,FALSE) -> IFS ERP | N79: Tolerate | O79: Business Critical | P79: P-Not mapped to process-- | Q79: =VLOOKUP(KamstrupData[[#This Row],[IdLevel123]],'B-Business Capability'!B:L,10,FALSE) -> N/A | R79: =VLOOKUP(KamstrupData[[#This Row],[IdLevel123]],'B-Business Capability'!B:L,11,FALSE) -> 0
D80: 1143-Finance-Tax Management-Tax Determination | E80: =VLOOKUP(D80,'B-Business Capability'!B:H,5,FALSE) -> Finance | F80: =VLOOKUP(D80,'B-Business Capability'!B:H,6,FALSE) -> Tax Management | G80: =VLOOKUP(D80,'B-Business Capability'!B:H,7,FALSE) -> Tax Determination | I80: NL10 | J80: NL_Finance | L80: 1 - IFS ERP | M80: =VLOOKUP(L80,'A-Applications'!B:D,3,FALSE) -> IFS ERP | N80: Tolerate | O80: Administrative Service | P80: P-Not mapped to process-- | Q80: =VLOOKUP(KamstrupData[[#This Row],[IdLevel123]],'B-Business Capability'!B:L,10,FALSE) -> N/A | R80: =VLOOKUP(KamstrupData[[#This Row],[IdLevel123]],'B-Business Capability'!B:L,11,FALSE) -> 0
D81: 1143-Finance-Tax Management-Tax Determination | E81: =VLOOKUP(D81,'B-Business Capability'!B:H,5,FALSE) -> Finance | F81: =VLOOKUP(D81,'B-Business Capability'!B:H,6,FALSE) -> Tax Management | G81: =VLOOKUP(D81,'B-Business Capability'!B:H,7,FALSE) -> Tax Determination | I81: DK10 | J81: DK_Finance | L81: 1 - IFS ERP | M81: =VLOOKUP(L81,'A-Applications'!B:D,3,FALSE) -> IFS ERP | N81: Tolerate | O81: Administrative Service | P81: P-Not mapped to process-- | Q81: =VLOOKUP(KamstrupData[[#This Row],[IdLevel123]],'B-Business Capability'!B:L,10,FALSE) -> N/A | R81: =VLOOKUP(KamstrupData[[#This Row],[IdLevel123]],'B-Business Capability'!B:L,11,FALSE) -> 0 | T81: Samles evt på level 2
D82: 1143-Finance-Tax Management-Tax Determination | E82: =VLOOKUP(D82,'B-Business Capability'!B:H,5,FALSE) -> Finance | F82: =VLOOKUP(D82,'B-Business Capability'!B:H,6,FALSE) -> Tax Management | G82: =VLOOKUP(D82,'B-Business Capability'!B:H,7,FALSE) -> Tax Determination | I82: FR10 | J82: FR_Finance | L82: 1 - IFS ERP | M82: =VLOOKUP(L82,'A-Applications'!B:D,3,FALSE) -> IFS ERP | N82: Tolerate | O82: Business Critical | P82: P-Not mapped to process-- | Q82: =VLOOKUP(KamstrupData[[#This Row],[IdLevel123]],'B-Business Capability'!B:L,10,FALSE) -> N/A | R82: =VLOOKUP(KamstrupData[[#This Row],[IdLevel123]],'B-Business Capability'!B:L,11,FALSE) -> 0
D83: 1145-Finance-Tax Management-Tax Returns Mgmt. | E83: =VLOOKUP(D83,'B-Business Capability'!B:H,5,FALSE) -> Finance | F83: =VLOOKUP(D83,'B-Business Capability'!B:H,6,FALSE) -> Tax Management | G83: =VLOOKUP(D83,'B-Business Capability'!B:H,7,FALSE) -> Tax Returns Mgmt. | I83: NL10 | J83: NL_Finance | L83: 1 - IFS ERP | M83: =VLOOKUP(L83,'A-Applications'!B:D,3,FALSE) -> IFS ERP | N83: Tolerate | O83: Administrative Service | P83: P-Not mapped to process-- | Q83: =VLOOKUP(KamstrupData[[#This Row],[IdLevel123]],'B-Business Capability'!B:L,10,FALSE) -> N/A | R83: =VLOOKUP(KamstrupData[[#This Row],[IdLevel123]],'B-Business Capability'!B:L,11,FALSE) -> 0
D84: 1145-Finance-Tax Management-Tax Returns Mgmt. | E84: =VLOOKUP(D84,'B-Business Capability'!B:H,5,FALSE) -> Finance | F84: =VLOOKUP(D84,'B-Business Capability'!B:H,6,FALSE) -> Tax Management | G84: =VLOOKUP(D84,'B-Business Capability'!B:H,7,FALSE) -> Tax Returns Mgmt. | I84: DK10 | J84: DK_Finance | L84: 1 - IFS ERP | M84: =VLOOKUP(L84,'A-Applications'!B:D,3,FALSE) -> IFS ERP | N84: Tolerate | O84: Administrative Service | P84: P-Not mapped to process-- | Q84: =VLOOKUP(KamstrupData[[#This Row],[IdLevel123]],'B-Business Capability'!B:L,10,FALSE) -> N/A | R84: =VLOOKUP(KamstrupData[[#This Row],[IdLevel123]],'B-Business Capability'!B:L,11,FALSE) -> 0 | T84: Selvangivelse, Udarbejdes af ekstern firma. Data fra IFS, evt også excel
D85: 1145-Finance-Tax Management-Tax Returns Mgmt. | E85: =VLOOKUP(D85,'B-Business Capability'!B:H,5,FALSE) -> Finance | F85: =VLOOKUP(D85,'B-Business Capability'!B:H,6,FALSE) -> Tax Management | G85: =VLOOKUP(D85,'B-Business Capability'!B:H,7,FALSE) -> Tax Returns Mgmt. | I85: FR10 | J85: FR_Finance | L85: 1 - IFS ERP | M85: =VLOOKUP(L85,'A-Applications'!B:D,3,FALSE) -> IFS ERP | N85: Tolerate | O85: Business Critical | P85: P-Not mapped to process-- | Q85: =VLOOKUP(KamstrupData[[#This Row],[IdLevel123]],'B-Business Capability'!B:L,10,FALSE) -> N/A | R85: =VLOOKUP(KamstrupData[[#This Row],[IdLevel123]],'B-Business Capability'!B:L,11,FALSE) -> 0
D86: 1146-Finance-Tax Management-Tax Settlements | E86: =VLOOKUP(D86,'B-Business Capability'!B:H,5,FALSE) -> Finance | F86: =VLOOKUP(D86,'B-Business Capability'!B:H,6,FALSE) -> Tax Management | G86: =VLOOKUP(D86,'B-Business Capability'!B:H,7,FALSE) -> Tax Settlements | I86: NL10 | J86: NL_Finance | L86: 1 - IFS ERP | M86: =VLOOKUP(L86,'A-Applications'!B:D,3,FALSE) -> IFS ERP | N86: Tolerate | O86: Administrative Service | P86: P-Not mapped to process-- | Q86: =VLOOKUP(KamstrupData[[#This Row],[IdLevel123]],'B-Business Capability'!B:L,10,FALSE) -> N/A | R86: =VLOOKUP(KamstrupData[[#This Row],[IdLevel123]],'B-Business Capability'!B:L,11,FALSE) -> 0
D87: 1146-Finance-Tax Management-Tax Settlements | E87: =VLOOKUP(D87,'B-Business Capability'!B:H,5,FALSE) -> Finance | F87: =VLOOKUP(D87,'B-Business Capability'!B:H,6,FALSE) -> Tax Management | G87: =VLOOKUP(D87,'B-Business Capability'!B:H,7,FALSE) -> Tax Settlements | I87: DK10 | J87: DK_Finance | L87: 1 - IFS ERP | M87: =VLOOKUP(L87,'A-Applications'!B:D,3,FALSE) -> IFS ERP | N87: Tolerate | O87: Administrative Service | P87: P-Not mapped to process-- | Q87: =VLOOKUP(KamstrupData[[#This Row],[IdLevel123]],'B-Business Capability'!B:L,10,FALSE) -> N/A | R87: =VLOOKUP(KamstrupData[[#This Row],[IdLevel123]],'B-Business Capability'!B:L,11,FALSE) -> 0
D88: 1146-Finance-Tax Management-Tax Settlements | E88: =VLOOKUP(D88,'B-Business Capability'!B:H,5,FALSE) -> Finance | F88: =VLOOKUP(D88,'B-Business Capability'!B:H,6,FALSE) -> Tax Management | G88: =VLOOKUP(D88,'B-Business Capability'!B:H,7,FALSE) -> Tax Settlements | I88: FR10 | J88: FR_Finance | L88: 1 - IFS ERP | M88: =VLOOKUP(L88,'A-Applications'!B:D,3,FALSE) -> IFS ERP | N88: Tolerate | O88: Business Critical | P88: P-Not mapped to process-- | Q88: =VLOOKUP(KamstrupData[[#This Row],[IdLevel123]],'B-Business Capability'!B:L,10,FALSE) -> N/A | R88: =VLOOKUP(KamstrupData[[#This Row],[IdLevel123]],'B-Business Capability'!B:L,11,FALSE) -> 0
D89: 1147-Finance-Treasury-Cash Management | E89: =VLOOKUP(D89,'B-Business Capability'!B:H,5,FALSE) -> Finance | F89: =VLOOKUP(D89,'B-Business Capability'!B:H,6,FALSE) -> Treasury | G89: =VLOOKUP(D89,'B-Business Capability'!B:H,7,FALSE) -> Cash Management | I89: NL10 | J89: NL_Finance | L89: 1 - IFS ERP | M89: =VLOOKUP(L89,'A-Applications'!B:D,3,FALSE) -> IFS ERP | N89: Tolerate | O89: Administrative Service | P89: P-Not mapped to process-- | Q89: =VLOOKUP(KamstrupData[[#This Row],[IdLevel123]],'B-Business Capability'!B:L,10,FALSE) -> N/A | R89: =VLOOKUP(KamstrupData[[#This Row],[IdLevel123]],'B-Business Capability'!B:L,11,FALSE) -> 0
D90: 1147-Finance-Treasury-Cash Management | E90: =VLOOKUP(D90,'B-Business Capability'!B:H,5,FALSE) -> Finance | F90: =VLOOKUP(D90,'B-Business Capability'!B:H,6,FALSE) -> Treasury | G90: =VLOOKUP(D90,'B-Business Capability'!B:H,7,FALSE) -> Cash Management | I90: DK10 | J90: DK_Finance | L90: 1 - IFS ERP | M90: =VLOOKUP(L90,'A-Applications'!B:D,3,FALSE) -> IFS ERP | N90: Tolerate | O90: Administrative Service | P90: P-Not mapped to process-- | Q90: =VLOOKUP(KamstrupData[[#This Row],[IdLevel123]],'B-Business Capability'!B:L,10,FALSE) -> N/A | R90: =VLOOKUP(KamstrupData[[#This Row],[IdLevel123]],'B-Business Capability'!B:L,11,FALSE) -> 0
D91: 1147-Finance-Treasury-Cash Management | E91: =VLOOKUP(D91,'B-Business Capability'!B:H,5,FALSE) -> Finance | F91: =VLOOKUP(D91,'B-Business Capability'!B:H,6,FALSE) -> Treasury | G91: =VLOOKUP(D91,'B-Business Capability'!B:H,7,FALSE) -> Cash Management | I91: US10 | J91: US_Finance | L91: 1 - IFS ERP | M91: =VLOOKUP(L91,'A-Applications'!B:D,3,FALSE) -> IFS ERP | N91: Tolerate | O91: Business Operational | P91: No-NoProcess-- | Q91: =VLOOKUP(KamstrupData[[#This Row],[IdLevel123]],'B-Business Capability'!B:L,10,FALSE) -> N/A | R91: =VLOOKUP(KamstrupData[[#This Row],[IdLevel123]],'B-Business Capability'!B:L,11,FALSE) -> 0 | T91: JEBL
D92: 1147-Finance-Treasury-Cash Management | E92: =VLOOKUP(D92,'B-Business Capability'!B:H,5,FALSE) -> Finance | F92: =VLOOKUP(D92,'B-Business Capability'!B:H,6,FALSE) -> Treasury | G92: =VLOOKUP(D92,'B-Business Capability'!B:H,7,FALSE) -> Cash Management | I92: FR10 | J92: FR_Finance | L92: 1 - IFS ERP | M92: =VLOOKUP(L92,'A-Applications'!B:D,3,FALSE) -> IFS ERP | N92: Tolerate | O92: Business Critical | P92: P-Not mapped to process-- | Q92: =VLOOKUP(KamstrupData[[#This Row],[IdLevel123]],'B-Business Capability'!B:L,10,FALSE) -> N/A | R92: =VLOOKUP(KamstrupData[[#This Row],[IdLevel123]],'B-Business Capability'!B:L,11,FALSE) -> 0
D93: 1148-Finance-Treasury-Financial Risk Management | E93: =VLOOKUP(D93,'B-Business Capability'!B:H,5,FALSE) -> Finance | F93: =VLOOKUP(D93,'B-Business Capability'!B:H,6,FALSE) -> Treasury | G93: =VLOOKUP(D93,'B-Business Capability'!B:H,7,FALSE) -> Financial Risk Management | I93: NL10 | J93: NL_Finance | L93: 1 - IFS ERP | M93: =VLOOKUP(L93,'A-Applications'!B:D,3,FALSE) -> IFS ERP | N93: Tolerate | O93: Administrative Service | P93: P-Not mapped to process-- | Q93: =VLOOKUP(KamstrupData[[#This Row],[IdLevel123]],'B-Business Capability'!B:L,10,FALSE) -> N/A | R93: =VLOOKUP(KamstrupData[[#This Row],[IdLevel123]],'B-Business Capability'!B:L,11,FALSE) -> 0
D94: 1148-Finance-Treasury-Financial Risk Management | E94: =VLOOKUP(D94,'B-Business Capability'!B:H,5,FALSE) -> Finance | F94: =VLOOKUP(D94,'B-Business Capability'!B:H,6,FALSE) -> Treasury | G94: =VLOOKUP(D94,'B-Business Capability'!B:H,7,FALSE) -> Financial Risk Management | I94: DK10 | J94: DK_Finance | L94: 1 - IFS ERP | M94: =VLOOKUP(L94,'A-Applications'!B:D,3,FALSE) -> IFS ERP | N94: Tolerate | O94: Administrative Service | P94: P-Not mapped to process-- | Q94: =VLOOKUP(KamstrupData[[#This Row],[IdLevel123]],'B-Business Capability'!B:L,10,FALSE) -> N/A | R94: =VLOOKUP(KamstrupData[[#This Row],[IdLevel123]],'B-Business Capability'!B:L,11,FALSE) -> 0
D95: 1148-Finance-Treasury-Financial Risk Management | E95: =VLOOKUP(D95,'B-Business Capability'!B:H,5,FALSE) -> Finance | F95: =VLOOKUP(D95,'B-Business Capability'!B:H,6,FALSE) -> Treasury | G95: =VLOOKUP(D95,'B-Business Capability'!B:H,7,FALSE) -> Financial Risk Management | I95: US10 | J95: US_Finance | L95: 1 - IFS ERP | M95: =VLOOKUP(L95,'A-Applications'!B:D,3,FALSE) -> IFS ERP | N95: Tolerate | O95: Business Operational | P95: No-NoProcess-- | Q95: =VLOOKUP(KamstrupData[[#This Row],[IdLevel123]],'B-Business Capability'!B:L,10,FALSE) -> N/A | R95: =VLOOKUP(KamstrupData[[#This Row],[IdLevel123]],'B-Business Capability'!B:L,11,FALSE) -> 0 | T95: JEBL
D96: 1148-Finance-Treasury-Financial Risk Management | E96: =VLOOKUP(D96,'B-Business Capability'!B:H,5,FALSE) -> Finance | F96: =VLOOKUP(D96,'B-Business Capability'!B:H,6,FALSE) -> Treasury | G96: =VLOOKUP(D96,'B-Business Capability'!B:H,7,FALSE) -> Financial Risk Management | I96: FR10 | J96: FR_Finance | L96: 1 - IFS ERP | M96: =VLOOKUP(L96,'A-Applications'!B:D,3,FALSE) -> IFS ERP | N96: Tolerate | O96: Business Critical | P96: P-Not mapped to process-- | Q96: =VLOOKUP(KamstrupData[[#This Row],[IdLevel123]],'B-Business Capability'!B:L,10,FALSE) -> N/A | R96: =VLOOKUP(KamstrupData[[#This Row],[IdLevel123]],'B-Business Capability'!B:L,11,FALSE) -> 0
D97: 1149-Finance-Treasury-Foreign Exchange Management | E97: =VLOOKUP(D97,'B-Business Capability'!B:H,5,FALSE) -> Finance | F97: =VLOOKUP(D97,'B-Business Capability'!B:H,6,FALSE) -> Treasury | G97: =VLOOKUP(D97,'B-Business Capability'!B:H,7,FALSE) -> Foreign Exchange Management | I97: NL10 | J97: NL_Finance | L97: 1 - IFS ERP | M97: =VLOOKUP(L97,'A-Applications'!B:D,3,FALSE) -> IFS ERP | N97: Tolerate | O97: Administrative Service | P97: P-Not mapped to process-- | Q97: =VLOOKUP(KamstrupData[[#This Row],[IdLevel123]],'B-Business Capability'!B:L,10,FALSE) -> N/A | R97: =VLOOKUP(KamstrupData[[#This Row],[IdLevel123]],'B-Business Capability'!B:L,11,FALSE) -> 0
D98: 1149-Finance-Treasury-Foreign Exchange Management | E98: =VLOOKUP(D98,'B-Business Capability'!B:H,5,FALSE) -> Finance | F98: =VLOOKUP(D98,'B-Business Capability'!B:H,6,FALSE) -> Treasury | G98: =VLOOKUP(D98,'B-Business Capability'!B:H,7,FALSE) -> Foreign Exchange Management | I98: DK10 | J98: DK_Finance | L98: 1 - IFS ERP | M98: =VLOOKUP(L98,'A-Applications'!B:D,3,FALSE) -> IFS ERP | N98: Tolerate | O98: Administrative Service | P98: P-Not mapped to process-- | Q98: =VLOOKUP(KamstrupData[[#This Row],[IdLevel123]],'B-Business Capability'!B:L,10,FALSE) -> N/A | R98: =VLOOKUP(KamstrupData[[#This Row],[IdLevel123]],'B-Business Capability'!B:L,11,FALSE) -> 0
D99: 1149-Finance-Treasury-Foreign Exchange Management | E99: =VLOOKUP(D99,'B-Business Capability'!B:H,5,FALSE) -> Finance | F99: =VLOOKUP(D99,'B-Business Capability'!B:H,6,FALSE) -> Treasury | G99: =VLOOKUP(D99,'B-Business Capability'!B:H,7,FALSE) -> Foreign Exchange Management | I99: FR10 | J99: FR_Finance | L99: 1 - IFS ERP | M99: =VLOOKUP(L99,'A-Applications'!B:D,3,FALSE) -> IFS ERP | N99: Tolerate | O99: Business Critical | P99: P-Not mapped to process-- | Q99: =VLOOKUP(KamstrupData[[#This Row],[IdLevel123]],'B-Business Capability'!B:L,10,FALSE) -> N/A | R99: =VLOOKUP(KamstrupData[[#This Row],[IdLevel123]],'B-Business Capability'!B:L,11,FALSE) -> 0
D100: 1176-Procurement & Logistics-Logistics Management-Manage Demand Forecast | E100: =VLOOKUP(D100,'B-Business Capability'!B:H,5,FALSE) -> Procurement & Logistics | F100: =VLOOKUP(D100,'B-Business Capability'!B:H,6,FALSE) -> Logistics Management | G100: =VLOOKUP(D100,'B-Business Capability'!B:H,7,FALSE) -> Manage Demand Forecast | I100: DK10 | J100: Supply Chain | L100: 1 - IFS ERP | M100: =VLOOKUP(L100,'A-Applications'!B:D,3,FALSE) -> IFS ERP | N100: Invest | O100: Business Critical | P100: P11-Operations-SP11.31-Sales and Operations Planning | Q100: =VLOOKUP(KamstrupData[[#This Row],[IdLevel123]],'B-Business Capability'!B:L,10,FALSE) -> Make-to-Delivery (M2D) | R100: =VLOOKUP(KamstrupData[[#This Row],[IdLevel123]],'B-Business Capability'!B:L,11,FALSE) -> 0
D101: 1177-Procurement & Logistics-Logistics Management-Manage Logistic Order | E101: =VLOOKUP(D101,'B-Business Capability'!B:H,5,FALSE) -> Procurement & Logistics | F101: =VLOOKUP(D101,'B-Business Capability'!B:H,6,FALSE) -> Logistics Management | G101: =VLOOKUP(D101,'B-Business Capability'!B:H,7,FALSE) -> Manage Logistic Order | I101: DK10 | J101: Supply Chain | L101: 1 - IFS ERP | M101: =VLOOKUP(L101,'A-Applications'!B:D,3,FALSE) -> IFS ERP | N101: Tolerate | O101: Business Critical | P101: P11-Operations-SP11.35-Warehouse Management | Q101: =VLOOKUP(KamstrupData[[#This Row],[IdLevel123]],'B-Business Capability'!B:L,10,FALSE) -> Make-to-Delivery (M2D) | R101: =VLOOKUP(KamstrupData[[#This Row],[IdLevel123]],'B-Business Capability'!B:L,11,FALSE) -> 0
...

Sheet A-Applications
D1: Name of the application | E1: Application group | F1: Introduction date of application. (Before 1/8-2025 all applications are set to 01-01-2025) | G1: Install Type - On Prem - Cloud - 3 party hosted - Edge Computing - Distributed Applications | H1: The Gartner TIME (Tolerate, Invest, Migrate, Eliminate) framework is the industry standard for planning and executing an application rationalization. It is a proven methodology for maximizing the business value of your application portfolio. | J1: Vendor Kamstrup purchace the application from | L1: Consultancy for the application | M1: The number of users for the application | N1: The current stage of the application | O1: End of life or Phase out date for the application (Format 31-06-2026) | R1: The URL of the application | S1: Business Owner of the application. Used for applications with no cost if handled in business | V1: Owner of the application. From cost sheet or if empty from Business owner | W1: Delete,Superusers of the application | Y1: Delete | Z1: EA Information related to closure of the application | AA1: Not relevant, SLA for the application | AB1: Not relevant, License responsible of the application | AC1: Sub component to applicatoin | AD1: Which applications are supported by the application. Eg. READy, OMNIA, etc | AE1: Primary in relation to cleanup track | AF1: The application contain AI features. If Yes the risk should be evaluated. | AG1: Set to "No" if the application are not used in capability mapping. Used for server licenses and so. | AH1: If the application are part of a Platform chose the platform. | AI1: Note on the application | AJ1: The recomendation for clean up | AK1: Reason for the recommendation | AL1: Workpackage size of the clousure (S, M, Project) | AM1: Security approved application | AN1: Security approved date | AO1: Security debt. Low Medium High (Inveigate are beeing security investigated) | AP1: Is this application seen as a crown jewel
H2: https://www.leanix.net/en/download/applying-the-gartner-time-framework-for-application-rationalization?utm_term=gartner%20time%20model&utm_source=bing&utm_medium=ppc&utm_campaign=EMEA-NORDIC_Application-Rationalization_AR_Search_ENG_B&hsa_acc=9751618594&hsa_cam=590193139&hsa_grp=1136896741662464&hsa_kw=gartner%20time%20model&hsa_mt=e&hsa_net=bing&hsa_src=o&hsa_tgt=kwd-71056741979861:loc-53&hsa_ad=&hsa_ver=3&msclkid=a7b7b4e697911d431c1dd255b34cacf3&utm_content=NORDIC_gartner-time-framework
B3: NoApplication | C3: No | D3: Application | E3: Application Group | F3: Introduction date | G3: Install type | H3: Gartner TIME | I3: Application Type | J3: Software Vendor | K3: ItemNumber | L3: Consultancy | M3: User base | N3: Lifecycle stage status | O3: Expected End-of-Life Year | P3: Replaced by | Q3: Details | R3: URL | S3: Business Owner | T3: Supported by Group IT | U3: Details2 | V3: Owner | W3: Super User | X3: Named users | Y3: OLD-Data integration | Z3: Temp | AA3: SLA | AB3: Licens responsible | AC3: Sub component to | AD3: Supporting applications | AE3: Org | AF3: AI | AG3: Used in capabilitiy mapping | AH3: Platform | AI3: Clean up: Note | AJ3: Clean up: Recomendation | AK3: Clean up: Reason | AL3: Clean up: WP Size | AM3: Security approved | AN3: Security Approved date | AO3: Security debt | AP3: Crown Jewels
B4: =_xlfn.CONCAT(Applications[[#This Row],[No]]," - ",Applications[[#This Row],[Application]]) -> 1 - IFS ERP | C4: 1 | D4: IFS ERP | E4: Enterprise Platforms | F4: 45658 | G4: On Premise | H4: Invest | I4: Standard solutions | J4: IFS AB | L4: IFS | M4: 1000-> | N4: 1-Strategic | O4: 46813 | Q4: IFS Apps 10 has End of life 1-3-2028. Transsition for new version are projected. | T4: X | U4: Ny licensaftale, generel prisstigning | V4: =_xlfn.XLOOKUP(Applications[[#This Row],[NoApplication]],#REF!,#REF!,Applications[[#This Row],[Business Owner]],0,1) -> #REF! | AB4: KRTI | AE4: Finans, Project | AH4: IFS | AI4: Note for cleanup | AJ4: Keep as strategic | AK4: It is our ERP system | AM4: Yes | AN4: 45658 | AO4: Low | AP4: Crown Jewel_1
B5: =_xlfn.CONCAT(Applications[[#This Row],[No]]," - ",Applications[[#This Row],[Application]]) -> 2 - QAD ERP | C5: 2 | D5: QAD ERP | E5: Business | F5: 45658 | G5: On Premise | H5: Eliminate | I5: Standard solutions | J5: QAD Inc. | L5: Kamstrup | M5: 50-99 | N5: 8-Phase out | O5: 47484 | P5: IFS ERP | Q5: QAD ERP: QAD ERP is a cloud-based enterprise resource planning solution designed specifically for manufacturers. It offers comprehensive solutions for supply chain management, production planning, inventory control, quality management, and regulatory compliance | T5: X | U5: Old ERP system, are only used for viewing of old data. Serial no., Sales invoice, Purchase invoice. Comment 20/11-2024 Ole F har talt lidt med div. I Service vedr. deres aktuelle brug af systemet. Det lyder til (og der kommer en opfølgning på det) at der er brug for meget lidt data. Så jeg vil foreslå at vi laver en analyse / export af disse data til et Excel ark, og derefter officielt lukker systemet 😊 /Ole | V5: =_xlfn.XLOOKUP(Applications[[#This Row],[NoApplication]],#REF!,#REF!,Applications[[#This Row],[Business Owner]],0,1) -> #REF! | AB5: KRTI | AE5: Supply Chain | AH5: QAD | AI5: Jf. bogføringsloven skal noget data gemmes i 5 år (sidste fakturering i 2021). Fra Ole: Jeg tænker det betyder at MFG (som er endnu ældre - data fra 1997 .. 2011) også skal med. Blot til info: - Tænker det er et projekt o Vi skal have information om vores serienumre i mindst 20 år så vidt jeg ved. o Og mere detaljeret i ca 10 år o Begge dele må kunne gemmes i BI på en eller anden måde o Det vil også kræve ændringer i Integration – da de så vil skulle lave serial lookup i BI istedet for i QAD/MFG - En anden udfordring er nok at jeg er den eneste med QAD/MFG viden i Kamstrup. Ole | AL5: M
B6: =_xlfn.CONCAT(Applications[[#This Row],[No]]," - ",Applications[[#This Row],[Application]]) -> 3 - Aras Innovator PLM | C6: 3 | D6: Aras Innovator PLM | E6: Business | F6: 45658 | G6: On Premise | I6: Standard solutions | J6: Aras Corporation | L6: Aras | M6: 100-499 | N6: 1-Strategic | O6: 54788 | Q6: Aras Innovator PLM: Aras Innovator PLM is a flexible, scalable, and upgradeable product lifecycle management software. It supports manufacturers of complex, connected products in digitally transforming their engineering business. It includes features like parts management, change management, document management, and quality management | T6: X | U6: non-standard / potentiale for forbedring | V6: =_xlfn.XLOOKUP(Applications[[#This Row],[NoApplication]],#REF!,#REF!,Applications[[#This Row],[Business Owner]],0,1) -> #REF! | X6: JES, AOE, FHB | AB6: FRFS | AE6: Supply Chain | AH6: Aras Innovator
B7: =_xlfn.CONCAT(Applications[[#This Row],[No]]," - ",Applications[[#This Row],[Application]]) -> 4 - Microsoft Dynamics 365 CE (Sales) | C7: 4 | D7: Microsoft Dynamics 365 CE (Sales) | E7: Enterprise Platforms | F7: 45658 | G7: Cloud | I7: Standard solutions | J7: Microsoft | K7: DGP-00003 | L7: Netcompany | M7: 100-499 | N7: 1-Strategic | O7: 54788 | Q7: Microsoft Dynamics 365 CE (Sales): Microsoft Dynamics 365 Customer Engagement (CE) Sales is a customer relationship management (CRM) solution that helps sales teams build strong relationships with customers, take actions based on insights, and close deals faster. It includes features like account and contact management, lead and opportunity management, and sales forecasting | R7: https://kamstrup.crm4.dynamics.com/ | S7: MIBN | T7: X | V7: =_xlfn.XLOOKUP(Applications[[#This Row],[NoApplication]],#REF!,#REF!,Applications[[#This Row],[Business Owner]],0,1) -> #REF! | AA7: SLA | AB7: Susanne, JTBN | AE7: Sales & Marketing | AF7: Yes | AH7: Dynamics 365
B8: =_xlfn.CONCAT(Applications[[#This Row],[No]]," - ",Applications[[#This Row],[Application]]) -> 5 - Oracle CPQ | C8: 5 | D8: Oracle CPQ | E8: Enterprise Platforms | F8: 45658 | I8: Standard solutions | J8: Oracle Corporation | L8: Solutionspace | N8: 1-Strategic | O8: 54788 | Q8: Oracle CPQ: Oracle Configure, Price, Quote (CPQ) is a cloud-based application that helps sellers configure the right mix of products or services and create accurate, professional quotes to quickly meet their customers’ pricing needs. It streamlines the entire opportunity-to-quote-to-order process | T8: X | U8: General stigning | V8: =_xlfn.XLOOKUP(Applications[[#This Row],[NoApplication]],#REF!,#REF!,Applications[[#This Row],[Business Owner]],0,1) -> #REF! | AB8: JTBN | AE8: Sales & Marketing | AH8: Oracle
B9: =_xlfn.CONCAT(Applications[[#This Row],[No]]," - ",Applications[[#This Row],[Application]]) -> 6 - ServiceNow | C9: 6 | D9: ServiceNow | E9: Business | F9: 45658 | G9: Cloud | H9: Invest | I9: Standard solutions | J9: ServiceNow Inc. | L9: Devoteam | M9: 1000-> | N9: 1-Strategic | O9: 54788 | Q9: ServiceNow: ServiceNow is a cloud-based enterprise workflow automation platform delivered as Software-as-a-Service (SaaS). It automates various business processes, including IT service management, customer service management, and project approvals, on a single, centralized platform | T9: X | U9: ITSM, Web portal | V9: =_xlfn.XLOOKUP(Applications[[#This Row],[NoApplication]],#REF!,#REF!,Applications[[#This Row],[Business Owner]],0,1) -> #REF! | AB9: JEHT | AE9: Supply Chain | AF9: Yes - Minimal Risk | AH9: ServiceNow
B10: =_xlfn.CONCAT(Applications[[#This Row],[No]]," - ",Applications[[#This Row],[Application]]) -> 7 - Reliance | C10: 7 | D10: Reliance | E10: Quality Management System | F10: 45658 | G10: Cloud | I10: Standard solutions | J10: Reliance Industries Limited | L10: ETQ | N10: 8-Phase out | O10: 46477 | Q10: Reliance: Reliance is a governance, risk, and compliance (GRC) software solution that helps organizations streamline their risk management processes, ensure regulatory compliance, and enhance overall operational efficiency | T10: X | U10: QMS - Quality Management System | V10: =_xlfn.XLOOKUP(Applications[[#This Row],[NoApplication]],#REF!,#REF!,Applications[[#This Row],[Business Owner]],0,1) -> #REF! | AE10: Quality | AI10: Phase out and move to IFS, ServiceNow and IPW. Info on phase out from KRNO. | AL10: Project-initiated
B11: =_xlfn.CONCAT(Applications[[#This Row],[No]]," - ",Applications[[#This Row],[Application]]) -> 8 - Neuron | C11: 8 | D11: Neuron | E11: Integration Platforms | F11: 45658 | I11: Standard solutions | J11: Neuron ESB | L11: Integrator | N11: 8-Phase out | O11: 46387 | P11: Azure | Q11: Neuron: Neuron is a simulation environment for modeling individual neurons and networks of neurons. It provides tools for building, managing, and using models in a way that is numerically sound and computationally efficient | T11: Yes | U11: Integration | V11: =_xlfn.XLOOKUP(Applications[[#This Row],[NoApplication]],#REF!,#REF!,Applications[[#This Row],[Business Owner]],0,1) -> #REF! | AB11: FFM | AC11: 8 - Neuron | AE11: Digitalization | AI11: Project of phase out are started with Jeyant in integration team | AL11: Project-initiated
B12: =_xlfn.CONCAT(Applications[[#This Row],[No]]," - ",Applications[[#This Row],[Application]]) -> 9 - Orbit | C12: 9 | D12: Orbit | E12: Communication | F12: 45658 | G12: Cloud | I12: Standard solutions | J12: Secoya A/S, Orbit Online A/S | L12: Secoya A/S | M12: 50-99 | N12: 7-Potential for phase out | O12: 54788 | Q12: Orbit: Orbit is a reporting and analytics solution suitable for businesses of any size. It includes features like automated reporting, report exporting, and interactive dashboards to monitor business metrics and KPIs in real-time | T12: X | U12: Project Sales, replaces Sharepoint 2003 site | V12: =_xlfn.XLOOKUP(Applications[[#This Row],[NoApplication]],#REF!,#REF!,Applications[[#This Row],[Business Owner]],0,1) -> #REF! | AB12: FRFS | AE12: Supply Chain, Project | AI12: Close | AL12: Project-initiated
B13: =_xlfn.CONCAT(Applications[[#This Row],[No]]," - ",Applications[[#This Row],[Application]]) -> 10 - Encryption Key Service (EKS) | C13: 10 | D13: Encryption Key Service (EKS) | E13: Kamstrup - Customer Software | F13: 45658 | I13: Customer Experience | J13: Kamstrup | N13: 3-Kamstrup application | O13: 54788 | Q13: Encryption Key Service (EKS): EKS is a service that provides encryption key management for securing sensitive data. It integrates with various applications to ensure data is encrypted and protected throughout its lifecycle. Consist of many services | V13: =_xlfn.XLOOKUP(Applications[[#This Row],[NoApplication]],#REF!,#REF!,Applications[[#This Row],[Business Owner]],0,1) -> #REF! | AP13: Crown Jewel_1
B14: =_xlfn.CONCAT(Applications[[#This Row],[No]]," - ",Applications[[#This Row],[Application]]) -> 12 - My Kamstrup | C14: 12 | D14: My Kamstrup | E14: Business | F14: 45658 | I14: Customer Experience | J14: Kamstrup | M14: 1000-> | N14: 2-Important application | O14: 54788 | Q14: My Kamstrup: My Kamstrup is a customer portal platform that provides access to various Kamstrup applications and services. It includes features like user administration, encryption key management, subscription management, and case creation | U14: FRFS info from US: MyKamstrup virker ikke ordentligt, aktiveringsmail ryger i spam ofte. Her burde man virkelig ændre på customer experience. | V14: =_xlfn.XLOOKUP(Applications[[#This Row],[NoApplication]],#REF!,#REF!,Applications[[#This Row],[Business Owner]],0,1) -> #REF! | AE14: Sales & Marketing
B15: =_xlfn.CONCAT(Applications[[#This Row],[No]]," - ",Applications[[#This Row],[Application]]) -> 15 - JIRA | C15: 15 | D15: JIRA | E15: Business | F15: 45658 | G15: Cloud | I15: Development Tools | J15: Atlassian | L15: Atlassian, Eficode A/S | M15: 500-999 | N15: 1-Strategic | O15: 54788 | Q15: JIRA: JIRA is a project management and issue-tracking software developed by Atlassian. It is used for bug tracking, issue tracking, and project management, and is widely used by software development teams. | U15: Bitbucket is mostly used for code and code review | V15: =_xlfn.XLOOKUP(Applications[[#This Row],[NoApplication]],#REF!,#REF!,Applications[[#This Row],[Business Owner]],0,1) -> #REF! | AB15: FRFS | AE15: Software, Hardware Departments | AH15: Atlassian | AK15: Strategic decision to use it
B16: =_xlfn.CONCAT(Applications[[#This Row],[No]]," - ",Applications[[#This Row],[Application]]) -> 16 - BitBucket | C16: 16 | D16: BitBucket | E16: Development and Programming | F16: 45658 | G16: Cloud | I16: Development Tools | J16: Atlassian | N16: 5-Investigate | O16: 54788 | Q16: BitBucket: BitBucket is a web-based version control repository hosting service owned by Atlassian. It supports Git and Mercurial version control systems and is used for source code management and collaboration. | S16: LAAG | U16: Jira is used for issue tracking and project management | V16: =_xlfn.XLOOKUP(Applications[[#This Row],[NoApplication]],#REF!,#REF!,Applications[[#This Row],[Business Owner]],0,1) -> #REF! | AH16: Atlassian
B17: =_xlfn.CONCAT(Applications[[#This Row],[No]]," - ",Applications[[#This Row],[Application]]) -> 17 - TFS | C17: 17 | D17: TFS | E17: Development and Programming | F17: 45658 | I17: Development Tools | J17: Microsoft | N17: 5-Investigate | O17: 54788 | Q17: TFS: Team Foundation Server (TFS) is a Microsoft product that provides source code management, project management, and build automation for software development projects. It supports version control, work item tracking, and continuous integration. | V17: =_xlfn.XLOOKUP(Applications[[#This Row],[NoApplication]],#REF!,#REF!,Applications[[#This Row],[Business Owner]],0,1) -> #REF!
B18: =_xlfn.CONCAT(Applications[[#This Row],[No]]," - ",Applications[[#This Row],[Application]]) -> 18 - Microsoft Visual Studio Pro MSDN | C18: 18 | D18: Microsoft Visual Studio Pro MSDN | E18: Development and Programming | F18: 45658 | G18: Distributed Applications | I18: Development Tools | J18: Microsoft | K18: 77D-00111 | M18: 50-99 | N18: 1-Strategic | O18: 54788 | Q18: Microsoft Visual Studio: Microsoft Visual Studio is an integrated development environment (IDE) used for developing applications, websites, and services. It supports various programming languages and includes features like code editing, debugging, and testing. | V18: =_xlfn.XLOOKUP(Applications[[#This Row],[NoApplication]],#REF!,#REF!,Applications[[#This Row],[Business Owner]],0,1) -> #REF! | AB18: Susanne | AD18: IDE | AE18: Software, Hardware Departments | AH18: Microsoft Developper | AJ18: Tolerate/Invest | AK18: Widely used for .NET development
B19: =_xlfn.CONCAT(Applications[[#This Row],[No]]," - ",Applications[[#This Row],[Application]]) -> 19 - TMS | C19: 19 | D19: TMS | E19: Utilities and Miscellaneous | F19: 45658 | I19: ERP Integrated Solutions | J19: Transporeon | N19: 4-Saved for now | O19: 54788 | Q19: TMS: Transportation Management System (TMS) is a software solution that helps organizations manage and optimize their transportation operations. It includes features like route planning, carrier selection, shipment tracking, and freight payment. | S19: KRNO | V19: =_xlfn.XLOOKUP(Applications[[#This Row],[NoApplication]],#REF!,#REF!,Applications[[#This Row],[Business Owner]],0,1) -> #REF! | AE19: Supply Chain
B20: =_xlfn.CONCAT(Applications[[#This Row],[No]]," - ",Applications[[#This Row],[Application]]) -> 21 - Subscription Manager | C20: 21 | D20: Subscription Manager | E20: Utilities and Miscellaneous | F20: 45658 | I20: ERP Integrated Solutions | J20: Flexera Software | N20: 5-Investigate | O20: 54788 | Q20: Subscription Manager: Subscription Manager is a software solution that helps organizations manage their subscription-based services. It includes features like subscription billing, customer management, and analytics. | V20: =_xlfn.XLOOKUP(Applications[[#This Row],[NoApplication]],#REF!,#REF!,Applications[[#This Row],[Business Owner]],0,1) -> #REF!
B21: =_xlfn.CONCAT(Applications[[#This Row],[No]]," - ",Applications[[#This Row],[Application]]) -> 23 - Readsoft | C21: 23 | D21: Readsoft | E21: Business | F21: 45658 | I21: ERP Integrated Solutions | J21: Kofax | M21: 10-49 | N21: 4-Saved for now | O21: 54788 | Q21: Readsoft: Readsoft is a software solution for automating document processing. It includes features like optical character recognition (OCR), data extraction, and workflow automation to streamline document management processes. | V21: =_xlfn.XLOOKUP(Applications[[#This Row],[NoApplication]],#REF!,#REF!,Applications[[#This Row],[Business Owner]],0,1) -> #REF! | AB21: KRTI | AE21: Finans | AI21: Set to Save for now with KRTI
B22: =_xlfn.CONCAT(Applications[[#This Row],[No]]," - ",Applications[[#This Row],[Application]]) -> 24 - Pipechain | C22: 24 | D22: Pipechain | E22: Utilities and Miscellaneous | F22: 45658 | I22: ERP Integrated Solutions | J22: Pipechain, Inc. | N22: 5-Investigate | O22: 54788 | V22: =_xlfn.XLOOKUP(Applications[[#This Row],[NoApplication]],#REF!,#REF!,Applications[[#This Row],[Business Owner]],0,1) -> #REF!
B23: =_xlfn.CONCAT(Applications[[#This Row],[No]]," - ",Applications[[#This Row],[Application]]) -> 25 - PJD 3P | C23: 25 | D23: PJD 3P | E23: Utilities and Miscellaneous | F23: 45658 | I23: Production IT | J23: PJD Group | N23: 5-Investigate | O23: 54788 | V23: =_xlfn.XLOOKUP(Applications[[#This Row],[NoApplication]],#REF!,#REF!,Applications[[#This Row],[Business Owner]],0,1) -> #REF!
B24: =_xlfn.CONCAT(Applications[[#This Row],[No]]," - ",Applications[[#This Row],[Application]]) -> 30 - Billing Com | C24: 30 | D24: Billing Com | E24: Utilities and Miscellaneous | F24: 45658 | I24: Service Tools | J24: Amdocs | N24: 5-Investigate | O24: 54788 | V24: =_xlfn.XLOOKUP(Applications[[#This Row],[NoApplication]],#REF!,#REF!,Applications[[#This Row],[Business Owner]],0,1) -> #REF! | AE24: Supply Chain
B25: =_xlfn.CONCAT(Applications[[#This Row],[No]]," - ",Applications[[#This Row],[Application]]) -> 31 - SIM Service | C25: 31 | D25: SIM Service | E25: Utilities and Miscellaneous | F25: 45658 | I25: Service Tools | J25: SIM Service. | N25: 5-Investigate | O25: 54788 | V25: =_xlfn.XLOOKUP(Applications[[#This Row],[NoApplication]],#REF!,#REF!,Applications[[#This Row],[Business Owner]],0,1) -> #REF!
B26: =_xlfn.CONCAT(Applications[[#This Row],[No]]," - ",Applications[[#This Row],[Application]]) -> 33 - TLF Service | C26: 33 | D26: TLF Service | E26: Utilities and Miscellaneous | F26: 45658 | I26: Service Tools | J26: The Software Vendor for the application TLF Service is TLF Technology. | N26: 5-Investigate | O26: 54788 | V26: =_xlfn.XLOOKUP(Applications[[#This Row],[NoApplication]],#REF!,#REF!,Applications[[#This Row],[Business Owner]],0,1) -> #REF!
B27: =_xlfn.CONCAT(Applications[[#This Row],[No]]," - ",Applications[[#This Row],[Application]]) -> 34 - Custom SIM | C27: 34 | D27: Custom SIM | E27: Utilities and Miscellaneous | F27: 45658 | I27: Service Tools | J27: Custom SIM Technologies | N27: 5-Investigate | O27: 54788 | V27: =_xlfn.XLOOKUP(Applications[[#This Row],[NoApplication]],#REF!,#REF!,Applications[[#This Row],[Business Owner]],0,1) -> #REF!
B28: =_xlfn.CONCAT(Applications[[#This Row],[No]]," - ",Applications[[#This Row],[Application]]) -> 35 - Lessor PM | C28: 35 | D28: Lessor PM | E28: Business | F28: 45658 | G28: Cloud | I28: Other Tools | J28: Lessor PM is developed by Lessor. | N28: 1-Strategic | O28: 54788 | Q28: OBS - High spend - could be renigosiated | S28: HAA | V28: =_xlfn.XLOOKUP(Applications[[#This Row],[NoApplication]],#REF!,#REF!,Applications[[#This Row],[Business Owner]],0,1) -> #REF! | AB28: KRTI | AE28: People | AI28: We are investigating if we can upgrade to LessorLøn - a cloud based replacement from same company (Paychex Europe) | AJ28: Handles all Danish payroll and payslips. | AL28: Project
B29: =_xlfn.CONCAT(Applications[[#This Row],[No]]," - ",Applications[[#This Row],[Application]]) -> 36 - Concur | C29: 36 | D29: Concur | E29: Business | F29: 45658 | G29: Cloud | I29: Other Tools | J29: SAP Concur | M29: 1000-> | N29: 7-Potential for phase out | O29: 54788 | U29: FIN | V29: =_xlfn.XLOOKUP(Applications[[#This Row],[NoApplication]],#REF!,#REF!,Applications[[#This Row],[Business Owner]],0,1) -> #REF! | AB29: KRTI | AE29: Finans | AH29: SAP | AL29: Project
B30: =_xlfn.CONCAT(Applications[[#This Row],[No]]," - ",Applications[[#This Row],[Application]]) -> 37 - OpenLM | C30: 37 | D30: OpenLM | E30: Utilities and Miscellaneous | F30: 45658 | G30: Cloud | I30: Other Tools | J30: OpenLM. | M30: 0-9 | N30: 4-Saved for now | O30: 54788 | Q30: FRFS: Look on if this can be used in general license use in Kamstrup | R30: License Management Services | OpenLM | V30: =_xlfn.XLOOKUP(Applications[[#This Row],[NoApplication]],#REF!,#REF!,Applications[[#This Row],[Business Owner]],0,1) -> #REF! | AE30: Hardware Departments
B31: =_xlfn.CONCAT(Applications[[#This Row],[No]]," - ",Applications[[#This Row],[Application]]) -> 38 - SP TID | C31: 38 | D31: SP TID | E31: Utilities and Miscellaneous | F31: 45658 | I31: Other Tools | J31: SAP | N31: 5-Investigate | O31: 54788 | V31: =_xlfn.XLOOKUP(Applications[[#This Row],[NoApplication]],#REF!,#REF!,Applications[[#This Row],[Business Owner]],0,1) -> #REF!
B32: =_xlfn.CONCAT(Applications[[#This Row],[No]]," - ",Applications[[#This Row],[Application]]) -> 39 - EPOS | C32: 39 | D32: EPOS | E32: Utilities and Miscellaneous | F32: 45658 | I32: Other Tools | J32: NCR Corporation | N32: 5-Investigate | O32: 54788 | V32: =_xlfn.XLOOKUP(Applications[[#This Row],[NoApplication]],#REF!,#REF!,Applications[[#This Row],[Business Owner]],0,1) -> #REF!
B33: =_xlfn.CONCAT(Applications[[#This Row],[No]]," - ",Applications[[#This Row],[Application]]) -> 40 - Omnia | C33: 40 | D33: Omnia | E33: Kamstrup - Customer Software | F33: 45658 | I33: Kamstrup Software | J33: Kamstrup | N33: 3-Kamstrup application | O33: 54788 | Q33: Custom software and hardware solutions | S33: MIA | V33: =_xlfn.XLOOKUP(Applications[[#This Row],[NoApplication]],#REF!,#REF!,Applications[[#This Row],[Business Owner]],0,1) -> #REF! | AE33: Software Departments | AP33: Crown Jewel_1
B34: =_xlfn.CONCAT(Applications[[#This Row],[No]]," - ",Applications[[#This Row],[Application]]) -> 41 - READy | C34: 41 | D34: READy | E34: Kamstrup - Customer Software | F34: 45658 | I34: Kamstrup Software | J34: Kamstrup | N34: 3-Kamstrup application | O34: 54788 | Q34: Visualisation of meters and reading data, heat reports, alarm notification, meter exchange, data export mm. FRFS Rename to READY Manager | S34: JEMR | U34: Remote reading tool for water and heat meters | V34: =_xlfn.XLOOKUP(Applications[[#This Row],[NoApplication]],#REF!,#REF!,Applications[[#This Row],[Business Owner]],0,1) -> #REF! | AE34: Supply Chain | AP34: Crown Jewel_1
B35: =_xlfn.CONCAT(Applications[[#This Row],[No]]," - ",Applications[[#This Row],[Application]]) -> 43 - Ceedling | C35: 43 | D35: Ceedling | E35: Development and Programming | F35: 45658 | G35: Distributed Applications | J35: ThrowTheSwitch, LLC | N35: 2-Important application | O35: 54788 | Q35: Test tool for 'c language' programming. Ceedling is primarily targeted at Test-Driven Development | U35: Test tool (unit test) | V35: =_xlfn.XLOOKUP(Applications[[#This Row],[NoApplication]],#REF!,#REF!,Applications[[#This Row],[Business Owner]],0,1) -> #REF! | W35: RUP | X35: Fra egen afd: JDP,AGR,SAS,TPT,JKI,JML,MTR,RUP,DGG,CKS,KSC,TRL,ACP | Y35: GCC, IAR, (Ruby) | AA35: Opensource | AB35: Opensource | AE35: Hardware Departments | AI35: Test framework for C based tools. | AJ35: Subcomponent for C | AK35: CLI tool used to test C code. | AO35: Investigate
B36: =_xlfn.CONCAT(Applications[[#This Row],[No]]," - ",Applications[[#This Row],[Application]]) -> 44 - C-Spy | C36: 44 | D36: C-Spy | E36: Development and Programming | F36: 45658 | J36: ELM Technology. | N36: 5-Investigate | O36: 54788 | U36: Debugger | V36: =_xlfn.XLOOKUP(Applications[[#This Row],[NoApplication]],#REF!,#REF!,Applications[[#This Row],[Business Owner]],0,1) -> #REF! | W36: KER | X36: Fra egen afd: LTS,JDP,AGR,SAS,TPT,JKI,JML,MTR,RUP,DGG,CKS,KSC,TRL,ACP | Y36: IAR | AA36: IAR | AB36: KER
B37: =_xlfn.CONCAT(Applications[[#This Row],[No]]," - ",Applications[[#This Row],[Application]]) -> 45 - DockLight | C37: 45 | D37: DockLight | E37: Development and Programming | F37: 45658 | G37: Distributed Applications | J37: DockLight Software | N37: 5-Investigate | O37: 54788 | Q37: Docklight is a testing, analysis and simulation tool for serial communication protocols. | U37: Serial script/trace | V37: =_xlfn.XLOOKUP(Applications[[#This Row],[NoApplication]],#REF!,#REF!,Applications[[#This Row],[Business Owner]],0,1) -> #REF! | W37: Ved ikke | X37: Fra egen afd: LTS,JDP,AGR,SAS,TPT,JKI,JML,MTR,RUP,DGG,CKS,KSC,TRL,ACP | AA37: Købt licens + x antal gratis | AB37: Ved ikke | AE37: Hardware Departments | AF37: No | AI37: Test, analysis and simulation tool for hardware. | AJ37: Tolerate | AK37: Investigate usage
B38: =_xlfn.CONCAT(Applications[[#This Row],[No]]," - ",Applications[[#This Row],[Application]]) -> 46 - Doxygen | C38: 46 | D38: Doxygen | E38: Development and Programming | F38: 45658 | J38: Affero, Inc. | N38: 4-Saved for now | O38: 54788 | Q38: dokumentere software ud fra kildekoden | U38: Kodedokumentationsprogram til dokumentation | V38: =_xlfn.XLOOKUP(Applications[[#This Row],[NoApplication]],#REF!,#REF!,Applications[[#This Row],[Business Owner]],0,1) -> #REF! | W38: Ved ikke | X38: Fra egen afd: LTS,JDP,AGR,SAS,TPT,JKI,KKA,BTH,JML,STK,MTR,LAA,ARO,RUP,DGG,CKS,KSC,TRL,ACP; PMB | AA38: Opensource | AB38: Opensource | AE38: Hardware Departments | AI38: Free and automated documentation software. | AJ38: Tolerate/migrate | AK38: Free and open source client system
B39: =_xlfn.CONCAT(Applications[[#This Row],[No]]," - ",Applications[[#This Row],[Application]]) -> 47 - FABric | C39: 47 | D39: FABric | E39: Utilities and Miscellaneous | F39: 45658 | J39: FABric is developed by the company Fabric Software. | N39: 5-Investigate | O39: 54788 | Q39: Fabric is a platform that helps your mobile team build better apps, understand your users, and grow your business. | U39: Python framework - Vedligeholdes internt i R&D | V39: =_xlfn.XLOOKUP(Applications[[#This Row],[NoApplication]],#REF!,#REF!,Applications[[#This Row],[Business Owner]],0,1) -> #REF! | W39: Individuelt pr. bruger | X39: Fra egen afd: LTS,KKA,BTH,STK,MTR,LAA, | AA39: Ved ikke | AB39: Ved ikke
B40: =_xlfn.CONCAT(Applications[[#This Row],[No]]," - ",Applications[[#This Row],[Application]]) -> 48 - FreeRTOS | C40: 48 | D40: FreeRTOS | E40: Development and Programming | F40: 45658 | J40: Amazon Web Services, Inc. | N40: 5-Investigate | O40: 54788 | Q40: MIT Licens, FreeRTOS er blevet porteret til 31 forskellige microcontrollerfamilier, kodning | U40: Development/support to development | V40: =_xlfn.XLOOKUP(Applications[[#This Row],[NoApplication]],#REF!,#REF!,Applications[[#This Row],[Business Owner]],0,1) -> #REF! | W40: Ved ikke | X40: Fra egen afd: JDP,JKI,RUP,DGG,TRL | Y40: IAR, GCC | AA40: Opensource | AB40: Opensource
B41: =_xlfn.CONCAT(Applications[[#This Row],[No]]," - ",Applications[[#This Row],[Application]]) -> 49 - GCC | C41: 49 | D41: GCC | E41: Development and Programming | F41: 45658 | N41: 5-Investigate | O41: 54788 | U41: Compiler - Vedligeholdes internt i R&D | V41: =_xlfn.XLOOKUP(Applications[[#This Row],[NoApplication]],#REF!,#REF!,Applications[[#This Row],[Business Owner]],0,1) -> #REF! | W41: Ved ikke | X41: Fra egen afd: LTS,JDP,AGR,SAS,TPT,JKI,KKA,BTH,JML,STK,MTR,LAA,ARO,RUP,DGG,CKS,KSC,TRL,ACP | Y41: Ceedling | AA41: Opensource | AB41: Opensource
B42: =_xlfn.CONCAT(Applications[[#This Row],[No]]," - ",Applications[[#This Row],[Application]]) -> 50 - GDB | C42: 50 | D42: GDB | E42: Development and Programming | F42: 45658 | J42: GNU | N42: 5-Investigate | O42: 54788 | U42: Debugger Linux | V42: =_xlfn.XLOOKUP(Applications[[#This Row],[NoApplication]],#REF!,#REF!,Applications[[#This Row],[Business Owner]],0,1) -> #REF! | W42: Individuelt | X42: Fra egen afd: LTS,KKA,BTH,STK,MTR,LAA, | AA42: Opensource | AB42: Opensource
B43: =_xlfn.CONCAT(Applications[[#This Row],[No]]," - ",Applications[[#This Row],[Application]]) -> 51 - NEC Compiler | C43: 51 | D43: NEC Compiler | E43: Development and Programming | F43: 45658 | G43: Distributed Applications | J43: NEC Corporation | M43: 0-9 | N43: 4-Saved for now | O43: 47118 | Q43: Not used anymore, but need to be availabel for HC Technologi Hardware Ref. JESP | U43: Compiler (MSP, EFM, NEC) - No support but continued access to compiler | V43: =_xlfn.XLOOKUP(Applications[[#This Row],[NoApplication]],#REF!,#REF!,Applications[[#This Row],[Business Owner]],0,1) -> #REF! | W43: KER | X43: Fra egen afd: LTS,JDP,AGR,SAS,TPT,JKI,JML,MTR,RUP,DGG,CKS,KSC,TRL,ACP | Y43: Teamcity, Jenkins | AA43: Ved ikke | AB43: KER | AE43: Hardware Departments | AJ43: ? | AK43: ?
B44: =_xlfn.CONCAT(Applications[[#This Row],[No]]," - ",Applications[[#This Row],[Application]]) -> 52 - Orcad | C44: 52 | D44: Orcad | E44: Simulations and Engineering | F44: 45658 | G44: Distributed Applications | I44: Development Tools | J44: Cadence Design Systems | N44: 1-Strategic | O44: 54788 | Q44: The OrCAD suite is the central part of en electronics engineers daily life. OrCAD suite is integrated to the PLM system from which information about partnumbers, descriptions, partstatuses and more is grapped. | U44: PCB Layout - Har du inputs via afd. 0144 (JLU)? | V44: =_xlfn.XLOOKUP(Applications[[#This Row],[NoApplication]],#REF!,#REF!,Applications[[#This Row],[Business Owner]],0,1) -> #REF! | W44: JLU | X44: Fra egen afd: PPH;JLU;BHR;CLR | AA44: Nordcad | AB44: JHD | AE44: Hardware Departments | AH44: Cadance
B45: =_xlfn.CONCAT(Applications[[#This Row],[No]]," - ",Applications[[#This Row],[Application]]) -> 53 - OSELAS | C45: 53 | D45: OSELAS | E45: Utilities and Miscellaneous | F45: 45658 | J45: OSELAS Technologies GmbH | N45: 5-Investigate | O45: 54788 | Q45: The OSELAS.Toolchain() project provides cross development tools for embedded Linux projects: GCC, GNU binutils, GDB and glibc. | U45: Compiler C++, Linux Toolchain - Vedligeholdes internt i R&D | V45: =_xlfn.XLOOKUP(Applications[[#This Row],[NoApplication]],#REF!,#REF!,Applications[[#This Row],[Business Owner]],0,1) -> #REF! | W45: BTH | X45: Fra egen afd: LTS,KKA,BTH,STK,MTR,LAA, | AA45: Opensource | AB45: Opensource
B46: =_xlfn.CONCAT(Applications[[#This Row],[No]]," - ",Applications[[#This Row],[Application]]) -> 55 - QT Creator | C46: 55 | D46: QT Creator | E46: Development and Programming | F46: 45658 | J46: The Qt Company | N46: 5-Investigate | O46: 54788 | Q46: Qt Creator er et platforms C ++, JavaScript og QML integreret udviklingsmiljø, som er en del af SDK for Qt GUI applikationsudviklingsrammen. Den indeholder en visuel debugger og et integreret GUI layout og form designer | U46: IDE - Vedligeholdes internt i R&D | V46: =_xlfn.XLOOKUP(Applications[[#This Row],[NoApplication]],#REF!,#REF!,Applications[[#This Row],[Business Owner]],0,1) -> #REF! | W46: BTH | X46: Fra egen afd: LTS,KKA,BTH,STK,MTR,LAA, | AA46: Opensource | AB46: Opensource
B47: =_xlfn.CONCAT(Applications[[#This Row],[No]]," - ",Applications[[#This Row],[Application]]) -> 56 - QT Unit | C47: 56 | D47: QT Unit | E47: Development and Programming | F47: 45658 | J47: The Qt Company | N47: 5-Investigate | O47: 54788 | U47: Test tool (unit test) Linux - Vedligeholdes internt i R&D | V47: =_xlfn.XLOOKUP(Applications[[#This Row],[NoApplication]],#REF!,#REF!,Applications[[#This Row],[Business Owner]],0,1) -> #REF! | W47: Individuelt pr. bruger | X47: Fra egen afd: LTS,KKA,BTH,STK,MTR,LAA, | AA47: Ved ikke | AB47: Ved ikke
B48: =_xlfn.CONCAT(Applications[[#This Row],[No]]," - ",Applications[[#This Row],[Application]]) -> 57 - SMX | C48: 57 | D48: SMX | E48: Utilities and Miscellaneous | F48: 45658 | J48: SMX Corporation | N48: 5-Investigate | O48: 54788 | U48: Realtids operativ system | V48: =_xlfn.XLOOKUP(Applications[[#This Row],[NoApplication]],#REF!,#REF!,Applications[[#This Row],[Business Owner]],0,1) -> #REF! | W48: Ved ikke En eller anden fra HFR's afd… | X48: AGR,SAS,TPT,JML,CKS,KSC,ACP | AA48: Ved ikke | AB48: Ved ikke
B49: =_xlfn.CONCAT(Applications[[#This Row],[No]]," - ",Applications[[#This Row],[Application]]) -> 58 - GitKraken | C49: 58 | D49: GitKraken | E49: Development and Programming | F49: 45658 | G49: Distributed Applications | J49: Axosoft | M49: 10-49 | N49: 2-Important application | O49: 54788 | Q49: ERC: Bruges på tværs. Alle licenser er i brug (must have) Det bør undersøges om netværkslicens er en mulighed | U49: Git GUI klient. Tool til visualisering og håndtering af source control via Git. | V49: =_xlfn.XLOOKUP(Applications[[#This Row],[NoApplication]],#REF!,#REF!,Applications[[#This Row],[Business Owner]],0,1) -> #REF! | W49: CKS, DGG | X49: DGG, CKS, RUP, TPT, KSC, ACP, AGR, MBD, JML, TRL, JKI | AA49: Licens købes til 25 brugere, et år af gangen. (ikke flydende). | AE49: Hardware Departments
B50: =_xlfn.CONCAT(Applications[[#This Row],[No]]," - ",Applications[[#This Row],[Application]]) -> 59 - Advanced Serial Port Monitor | C50: 59 | D50: Advanced Serial Port Monitor | E50: Utilities and Miscellaneous | F50: 45658 | J50: Fabula Tech | N50: 5-Investigate | O50: 54788 | U50: Analyserer data på computerens comport - Vi har 10 Licenser | V50: =_xlfn.XLOOKUP(Applications[[#This Row],[NoApplication]],#REF!,#REF!,Applications[[#This Row],[Business Owner]],0,1) -> #REF! | W50: KER | X50: CSS, MVN, KRF, IBV, NCJ, GEK, RNY, RMK, MAT | AA50: Licensen købes pr. versionpr. Bruger. Ved ny version eller ny bruger, skal der købes ny licnes. | AB50: KER | AE50: Hardware Departments
B51: =_xlfn.CONCAT(Applications[[#This Row],[No]]," - ",Applications[[#This Row],[Application]]) -> 60 - Astah professional | C51: 60 | D51: Astah professional | E51: Simulations and Engineering | F51: 45658 | J51: Change Vision Inc. | N51: 5-Investigate | O51: 54788 | U51: Tegneprogram til kode design (Vi bruger det kun til C kode). | V51: =_xlfn.XLOOKUP(Applications[[#This Row],[NoApplication]],#REF!,#REF!,Applications[[#This Row],[Business Owner]],0,1) -> #REF! | W51: MLW; MVN; CSS; GEK | X51: CSS;MLW;HSS;ANG;MVN;KRF;IBV;JAJ;NCJ;MAT;RMK;GEK;RNY | AA51: Licensen købes en gang om året. Snak med KER omkring antal. | AB51: KER
B52: =_xlfn.CONCAT(Applications[[#This Row],[No]]," - ",Applications[[#This Row],[Application]]) -> 61 - Conformance Test Tool 3.0 | C52: 61 | D52: Conformance Test Tool 3.0 | E52: Quality Management System | F52: 45658 | J52: Siemens | N52: 5-Investigate | O52: 54788 | U52: Officielt tool til conformance test og godkendelse af DLMS protokol implementeringen - 3 licenser | V52: =_xlfn.XLOOKUP(Applications[[#This Row],[NoApplication]],#REF!,#REF!,Applications[[#This Row],[Business Owner]],0,1) -> #REF! | W52: MLW, MVN, CSS | X52: ANG, MLW, CSS, MVN, KRF, JAJ, IBV, NCJ, GEK, RNY, RMK, MAT | AA52: Licensen købes pr. major version. Ved ny major version, skal der normalt købes ny licnes.Der medfølger 3 licenser | AB52: Licens installeret hos IT på License1
B53: =_xlfn.CONCAT(Applications[[#This Row],[No]]," - ",Applications[[#This Row],[Application]]) -> 62 - Eclipse | C53: 62 | D53: Eclipse | E53: Development and Programming | F53: 45658 | J53: Eclipse Foundation | N53: 4-Saved for now | O53: 54788 | Q53: JDP, Cool editor for development, alternative to Notepad | U53: Et IDE (Integrated Development Environment). Bliver benyttet af ca. 60% af alle el-meter firmware udviklere - Bliver primært brugt for at kunne benytte parasoft | V53: =_xlfn.XLOOKUP(Applications[[#This Row],[NoApplication]],#REF!,#REF!,Applications[[#This Row],[Business Owner]],0,1) -> #REF! | X53: MLW, CSS, MVN, ANG, HSS (konsulet), RNY, MAT, GEK, RMK, TPT, AGR, RUP, DAG; MAJ,TLC,KHB,HRJ;PMB;AHG;DGG;AHG;LTS,JDP,AGR,SAS,TPT,JKI,JML,MTR,RUP,DGG,CKS,KSC,TRL,ACP;JLY | Y53: DATA FROM: Ja, IAR's compiler/linker iccarm, icclink;Parasoft; Java JDK, DATA TO:Ja, FW releases produceres med dette system. IAR, Parasoft | AA53: Ingen, freeware. Der kommer dog nyt release hver 6. måned | AB53: Freeware | AC53: 190 - Parasoft | AD53: IDE | AE53: Hardware Departments | AI53: General Purpose Editor FRFS: Set to potential for phase out based on info from business of MIGRATE | AJ53: Tolerate/migrate | AK53: Free and open source client system
B54: =_xlfn.CONCAT(Applications[[#This Row],[No]]," - ",Applications[[#This Row],[Application]]) -> 63 - ElDevScripts | C54: 63 | D54: ElDevScripts | E54: Development and Programming | F54: 45658 | J54: ElDevScripts | N54: 5-Investigate | O54: 54788 | U54: En samling scripts der automatiserer at lave releases, og som letter byrden med at lave logiske branches betydeligt. - Grupper der har svn:externals i deres SW-udtræk vil kunne have glæde af ElDevScripts | V54: =_xlfn.XLOOKUP(Applications[[#This Row],[NoApplication]],#REF!,#REF!,Applications[[#This Row],[Business Owner]],0,1) -> #REF! | W54: Alle der kan checke ElDevScripts ud fra VisualSVN på el-svn | X54: MLW, CSS, MVN, ANG, IBV, KRF, JAJ, NCJ, HSS (konsulet), RNY, MAT, GEK, RMK, TPT, AGR, RUP (måske) | Y54: SVN på "standard" Kamstrup SVN leverer sådan set de "rå-data" som ElDevScripts opererer på | AA54: Ingen, det er en flok internt udviklede scripts | AB54: Internt udviklet freeware
B55: =_xlfn.CONCAT(Applications[[#This Row],[No]]," - ",Applications[[#This Row],[Application]]) -> 66 - KEMA Test Facility Generic | C55: 66 | D55: KEMA Test Facility Generic | E55: Development and Programming | F55: 45658 | N55: 5-Investigate | O55: 54788 | U55: Test program til at teste DLMS protokollen i målere - License WebAdmin. http://license1:22350/ | V55: =_xlfn.XLOOKUP(Applications[[#This Row],[NoApplication]],#REF!,#REF!,Applications[[#This Row],[Business Owner]],0,1) -> #REF! | W55: NCJ, CSS | X55: ANG, MLW, CSS, MVN, KRF, JAJ, IBV, NCJ, GEK, RNY, RMK, MAT | AA55: Licens købt pr bruger. Support & Upgrade aftale forlænges med et år ad gangen | AB55: Flydende licens på License1. Hardware Dongle hos IT.
B56: =_xlfn.CONCAT(Applications[[#This Row],[No]]," - ",Applications[[#This Row],[Application]]) -> 67 - Mathcad | C56: 67 | D56: Mathcad | E56: Simulations and Engineering | F56: 45658 | J56: PTC Inc. | M56: 0-9 | N56: 4-Saved for now | O56: 54788 | U56: Regneprogram som kan sidestilles med en avanceret lommeregner | V56: =_xlfn.XLOOKUP(Applications[[#This Row],[NoApplication]],#REF!,#REF!,Applications[[#This Row],[Business Owner]],0,1) -> #REF! | W56: JPN, BRI | X56: BRI, UCH, GBH, DKI, SLH;JPN, MTM, JJS | AA56: Vi har en flydende licens. BRI og JPN individuelle licenser. Desuden har afdelingen en meget gammel udgave af Mathcad (2001) hvor licensforholdet ikke kendes./ 1 flydende licens (en gangs) + to faste licenser Alfasoft | AB56: JPN eller IT? | AE56: Hardware Departments
B57: =_xlfn.CONCAT(Applications[[#This Row],[No]]," - ",Applications[[#This Row],[Application]]) -> 68 - ModelSim | C57: 68 | D57: ModelSim | E57: Development and Programming | F57: 45658 | G57: Distributed Applications | J57: Innofour. | M57: 0-9 | N57: 5-Investigate | O57: 54788 | Q57: JESP: Nødvendig for vores FPGA kerne på SDR produkter (MIDI/READy Concentrator MKII etc) | U57: PADS består af 2 programmer. PADS Layout, program til at designe pcb. PADS Logic, program til at lave schematic. PCB Layout program + PADS Logic til at lave schematic - Til info.Vi har 6 PADS layout licenser og 2 PADS logic licenser. PADS bruges i dag kun til vedligehold af eksisterende pcb design, små ændringer på et pcb laves i PADS. Ved nye design / størrer ændringer laves det i OrCAD. OrCad blev indført sidste år. | V57: =_xlfn.XLOOKUP(Applications[[#This Row],[NoApplication]],#REF!,#REF!,Applications[[#This Row],[Business Owner]],0,1) -> #REF! | W57: PPH, JLU, BRH, CLR | X57: UCH, SLH, BRI, DKI, CSK, GBH, MHO, JJS, MTM, SAR, JBR, TES, CJO; JPN, JJS, MTM, SAR, JBR | Y57: PADS Logic | AA57: www.innofour.com | AB57: PPH | AE57: Hardware Departments | AJ57: Tolerate | AK57: Investigate usage
B58: =_xlfn.CONCAT(Applications[[#This Row],[No]]," - ",Applications[[#This Row],[Application]]) -> 69 - Seqzap fra CIM Software Testing | C58: 69 | D58: Seqzap fra CIM Software Testing | E58: Quality Management System | F58: 45658 | J58: CIM Software Testing | M58: 0-9 | N58: 5-Investigate | O58: 54788 | U58: Windows program til at udvikle og afvikle scripts til automatiseret test af elmåleren | V58: =_xlfn.XLOOKUP(Applications[[#This Row],[NoApplication]],#REF!,#REF!,Applications[[#This Row],[Business Owner]],0,1) -> #REF! | W58: RNY; JAJ | X58: CSS;MLW;HSS;ANG;MVN;KRF;IBV;JAJ;NCJ;MAT;RMK;GEK;RNY | Y58: Kamstrup Firmwaremodeller (5098-1221) | AA58: CIM Software Testing, Business Park Nord, Østre Allé 6, 9530 Støvring. Vi har pt. 7 flydende licenser, der betales support, service og opdateringsaftale for en gang om året. | AB58: RNY | AE58: Hardware Departments
B59: =_xlfn.CONCAT(Applications[[#This Row],[No]]," - ",Applications[[#This Row],[Application]]) -> 70 - WikiMedia | C59: 70 | D59: WikiMedia | E59: Utilities and Miscellaneous | F59: 45658 | J59: Unknown | N59: 8-Phase out | O59: 46023 | Q59: Info of Phase out from meeting with MLNN the 17/1-2025 | R59: http://wiki.kamstrup.dk | U59: Wiki for Elmåler-, NetworkManager- og Concentrator-gruppen | V59: =_xlfn.XLOOKUP(Applications[[#This Row],[NoApplication]],#REF!,#REF!,Applications[[#This Row],[Business Owner]],0,1) -> #REF! | W59: SMB; RNY | X59: CSS;MLW;HSS;ANG;MVN;KRF;IBV;JAJ;NCJ;MAT;RMK;GEK;RNY | AA59: Opensource | AE59: Software Departments | AI59: Remember to ask Electricity if they are still using it. Used for wiki.kamstrup.dk | AJ59: FRFS: moved from 31-12-2025 to 01-01-2026 for reporting | AL59: M
B60: =_xlfn.CONCAT(Applications[[#This Row],[No]]," - ",Applications[[#This Row],[Application]]) -> 71 - AD Link | C60: 71 | D60: AD Link | E60: Development and Programming | F60: 45658 | N60: 5-Investigate | O60: 54788 | U60: SW til A/D og I/O kort i PC | V60: =_xlfn.XLOOKUP(Applications[[#This Row],[NoApplication]],#REF!,#REF!,Applications[[#This Row],[Business Owner]],0,1) -> #REF! | X60: LHB | AB60: Leveres sammen med HW
B61: =_xlfn.CONCAT(Applications[[#This Row],[No]]," - ",Applications[[#This Row],[Application]]) -> 72 - APEX SQL | C61: 72 | D61: APEX SQL | E61: Data and Analytics | F61: 45658 | J61: APEX SQL, Inc. | N61: 5-Investigate | O61: 54788 | U61: Database værktøj | V61: =_xlfn.XLOOKUP(Applications[[#This Row],[NoApplication]],#REF!,#REF!,Applications[[#This Row],[Business Owner]],0,1) -> #REF! | X61: klu | AB61: klu
B62: =_xlfn.CONCAT(Applications[[#This Row],[No]]," - ",Applications[[#This Row],[Application]]) -> 73 - ApexSQL Edit | C62: 73 | D62: ApexSQL Edit | E62: Development and Programming | F62: 45658 | J62: ApexSQL | N62: 5-Investigate | O62: 54788 | U62: Database designer - PTA software har nogle licenser | V62: =_xlfn.XLOOKUP(Applications[[#This Row],[NoApplication]],#REF!,#REF!,Applications[[#This Row],[Business Owner]],0,1) -> #REF! | X62: klu | AB62: Licensen købes pr. bruger
B63: =_xlfn.CONCAT(Applications[[#This Row],[No]]," - ",Applications[[#This Row],[Application]]) -> 74 - AppFabric | C63: 74 | D63: AppFabric | E63: Development and Programming | F63: 45658 | J63: Microsoft | N63: 5-Investigate | O63: 54788 | U63: Hosting container til WCF services | V63: =_xlfn.XLOOKUP(Applications[[#This Row],[NoApplication]],#REF!,#REF!,Applications[[#This Row],[Business Owner]],0,1) -> #REF! | W63: EMG | X63: EMG | AB63: Gratis addon til Windows Server
B64: =_xlfn.CONCAT(Applications[[#This Row],[No]]," - ",Applications[[#This Row],[Application]]) -> 75 - Blend | C64: 75 | D64: Blend | E64: Development and Programming | F64: 45658 | J64: Blend Labs, Inc. | N64: 5-Investigate | O64: 54788 | U64: GUI design værktøj for Visual Studio | V64: =_xlfn.XLOOKUP(Applications[[#This Row],[NoApplication]],#REF!,#REF!,Applications[[#This Row],[Business Owner]],0,1) -> #REF! | X64: MCF, MEV | AA64: MSDN | AB64: IT
B65: =_xlfn.CONCAT(Applications[[#This Row],[No]]," - ",Applications[[#This Row],[Application]]) -> 79 - Code::Blocks (www.codeblocks.org) | C65: 79 | D65: Code::Blocks (www.codeblocks.org) | E65: Development and Programming | F65: 45658 | J65: The Code::Blocks application is developed by Code::Blocks Team. | N65: 5-Investigate | O65: 54788 | U65: Open source IDE til C/C++. Kan anvendes sammen med en række compilere. | V65: =_xlfn.XLOOKUP(Applications[[#This Row],[NoApplication]],#REF!,#REF!,Applications[[#This Row],[Business Owner]],0,1) -> #REF! | W65: EMG | X65: EMG | AB65: Freeware
B66: =_xlfn.CONCAT(Applications[[#This Row],[No]]," - ",Applications[[#This Row],[Application]]) -> 82 - Crystal Reports | C66: 82 | D66: Crystal Reports | E66: Data and Analytics | F66: 45658 | J66: SAP | N66: 7-Potential for phase out | O66: 54788 | U66: Designprogram til bl.a. dagsrapporter | V66: =_xlfn.XLOOKUP(Applications[[#This Row],[NoApplication]],#REF!,#REF!,Applications[[#This Row],[Business Owner]],0,1) -> #REF! | X66: KLU;LSH;JJB, KLU, KLU, JJB | AA66: Licensen købes pr. versionpr. Bruger. Ved ny version eller ny bruger, skal der købes ny licnes. | AB66: Bruger selv | AE66: Supply Chain | AI66: FRFS: Set to potential for phase out based on info from business of MIGRATE. For software to List and Label and for certificates to PowerBI | AJ66: Phase out/Migrate
B67: =_xlfn.CONCAT(Applications[[#This Row],[No]]," - ",Applications[[#This Row],[Application]]) -> 83 - DOSBox (www.dosbox.com) | C67: 83 | D67: DOSBox (www.dosbox.com) | E67: Utilities and Miscellaneous | F67: 45658 | J67: DOSBox Team | N67: 5-Investigate | O67: 54788 | U67: DOS emulator til Windows. Gør det muligt at afvikle 16-bit DOS programmer på en Windows PC. | V67: =_xlfn.XLOOKUP(Applications[[#This Row],[NoApplication]],#REF!,#REF!,Applications[[#This Row],[Business Owner]],0,1) -> #REF! | W67: EMG | X67: EMG | AB67: Freeware
B68: =_xlfn.CONCAT(Applications[[#This Row],[No]]," - ",Applications[[#This Row],[Application]]) -> 84 - Dr. Memory (http://drmemory.org/) | C68: 84 | D68: Dr. Memory (http://drmemory.org/) | E68: Utilities and Miscellaneous | F68: 45658 | J68: The Dr. Memory application is developed by the company named "University of Hawaii". | N68: 5-Investigate | O68: 54788 | U68: Statisk kodeanalyse af memory management i C kode | V68: =_xlfn.XLOOKUP(Applications[[#This Row],[NoApplication]],#REF!,#REF!,Applications[[#This Row],[Business Owner]],0,1) -> #REF! | W68: EMG | X68: EMG | AB68: LGPL license
B69: =_xlfn.CONCAT(Applications[[#This Row],[No]]," - ",Applications[[#This Row],[Application]]) -> 85 - Eltima Serial Port Monitor (www.eltima.com) | C69: 85 | D69: Eltima Serial Port Monitor (www.eltima.com) | E69: Utilities and Miscellaneous | F69: 45658 | J69: Eltima Software | N69: 7-Potential for phase out | O69: 46173 | U69: COMPort analyse værktøj; til RS232 kommunikation | V69: =_xlfn.XLOOKUP(Applications[[#This Row],[NoApplication]],#REF!,#REF!,Applications[[#This Row],[Business Owner]],0,1) -> #REF! | X69: EMG, klu, hlb, jax;KLU | AB69: klu | AE69: Hardware Departments
B70: =_xlfn.CONCAT(Applications[[#This Row],[No]]," - ",Applications[[#This Row],[Application]]) -> 86 - ExactFile | C70: 86 | D70: ExactFile | E70: Utilities and Miscellaneous | F70: 45658 | J70: ExactFile, Inc. | N70: 5-Investigate | O70: 54788 | U70: Tool til beregning af checksum | V70: =_xlfn.XLOOKUP(Applications[[#This Row],[NoApplication]],#REF!,#REF!,Applications[[#This Row],[Business Owner]],0,1) -> #REF! | X70: EMG | AB70: Freeware
B71: =_xlfn.CONCAT(Applications[[#This Row],[No]]," - ",Applications[[#This Row],[Application]]) -> 88 - KEPWare | C71: 88 | D71: KEPWare | E71: Utilities and Miscellaneous | F71: 45658 | J71: Parker Hannifin Corporation | N71: 5-Investigate | O71: 54788 | U71: OPC værktøj | V71: =_xlfn.XLOOKUP(Applications[[#This Row],[NoApplication]],#REF!,#REF!,Applications[[#This Row],[Business Owner]],0,1) -> #REF! | X71: klu | AB71: klu
B72: =_xlfn.CONCAT(Applications[[#This Row],[No]]," - ",Applications[[#This Row],[Application]]) -> 89 - Kepware KEPServerEX | C72: 89 | D72: Kepware KEPServerEX | E72: Development and Programming | F72: 45658 | N72: 5-Investigate | O72: 54788 | U72: OPC server til kommunikation til PLCer | V72: =_xlfn.XLOOKUP(Applications[[#This Row],[NoApplication]],#REF!,#REF!,Applications[[#This Row],[Business Owner]],0,1) -> #REF! | X72: klu, lhb | AB72: 2 timers demo mode.
B73: =_xlfn.CONCAT(Applications[[#This Row],[No]]," - ",Applications[[#This Row],[Application]]) -> 90 - Microsoft FX Cops | C73: 90 | D73: Microsoft FX Cops | E73: Quality Management System | F73: 45658 | J73: Microsoft | N73: 5-Investigate | O73: 54788 | U73: Kode analyse værktøj | V73: =_xlfn.XLOOKUP(Applications[[#This Row],[NoApplication]],#REF!,#REF!,Applications[[#This Row],[Business Owner]],0,1) -> #REF! | X73: JLM, MEV | AB73: Freeware
B74: =_xlfn.CONCAT(Applications[[#This Row],[No]]," - ",Applications[[#This Row],[Application]]) -> 91 - Microsoft SQL server Standard | C74: 91 | D74: Microsoft SQL server Standard | E74: Data and Analytics | F74: 45658 | J74: Microsoft | K74: 7NQ-00292 | N74: 1-Strategic | O74: 54788 | U74: Databaser | V74: =_xlfn.XLOOKUP(Applications[[#This Row],[NoApplication]],#REF!,#REF!,Applications[[#This Row],[Business Owner]],0,1) -> #REF! | X74: klu | AA74: IT | AB74: Susanne | AE74: Digital workplace | AH74: Microsoft Data Platform
B75: =_xlfn.CONCAT(Applications[[#This Row],[No]]," - ",Applications[[#This Row],[Application]]) -> 96 - Microsoft team Foundation server | C75: 96 | D75: Microsoft team Foundation server | E75: Development and Programming | F75: 45658 | J75: Microsoft | N75: 9-End of Life | O75: 46023 | U75: Source safe værktøj | V75: =_xlfn.XLOOKUP(Applications[[#This Row],[NoApplication]],#REF!,#REF!,Applications[[#This Row],[Business Owner]],0,1) -> #REF! | W75: JAX;LHB | X75: mailgrupper: pta sw hcw, technology heat | AB75: MSDN Abonnement | AE75: Software Departments | AJ75: FRFS: moved from 15-09-2025 to 01-01-2026 for reporting | AL75: S
B76: =_xlfn.CONCAT(Applications[[#This Row],[No]]," - ",Applications[[#This Row],[Application]]) -> 102 - Microsoft Windows virtual PC | C76: 102 | D76: Microsoft Windows virtual PC | E76: Utilities and Miscellaneous | F76: 45658 | J76: Microsoft | N76: 5-Investigate | O76: 54788 | U76: Bruges til at oprette og køre virtuelle maskiner | V76: =_xlfn.XLOOKUP(Applications[[#This Row],[NoApplication]],#REF!,#REF!,Applications[[#This Row],[Business Owner]],0,1) -> #REF! | X76: LSH | AA76: MSDN
B77: =_xlfn.CONCAT(Applications[[#This Row],[No]]," - ",Applications[[#This Row],[Application]]) -> 103 - Motorola EMDK for .NET | C77: 103 | D77: Motorola EMDK for .NET | E77: Development and Programming | F77: 45658 | J77: Motorola Solutions | N77: 5-Investigate | O77: 54788 | U77: SDK til Motorola MT2090 scannere | V77: =_xlfn.XLOOKUP(Applications[[#This Row],[NoApplication]],#REF!,#REF!,Applications[[#This Row],[Business Owner]],0,1) -> #REF! | W77: EMG | X77: EMG | AB77: Freeware
B78: =_xlfn.CONCAT(Applications[[#This Row],[No]]," - ",Applications[[#This Row],[Application]]) -> 104 - Open Watcom IDE (www.openwacom.org) | C78: 104 | D78: Open Watcom IDE (www.openwacom.org) | E78: Development and Programming | F78: 45658 | J78: Open Watcom Project | N78: 5-Investigate | O78: 54788 | U78: IDE til Open Watcom compiler. Bruges som Cross Compiler til MS-DOS 6.22 - IDE'et er ikke det mest moderne. Men compileren og de øvrige værktøjer kan med fordel anvendes fra Code::Blocks. | V78: =_xlfn.XLOOKUP(Applications[[#This Row],[NoApplication]],#REF!,#REF!,Applications[[#This Row],[Business Owner]],0,1) -> #REF! | W78: EMG | X78: EMG | AB78: Sybase Open Watcom Public License
B79: =_xlfn.CONCAT(Applications[[#This Row],[No]]," - ",Applications[[#This Row],[Application]]) -> 105 - PhotoFiltre 7 | C79: 105 | D79: PhotoFiltre 7 | E79: Utilities and Miscellaneous | F79: 45658 | J79: PhotoFiltre Studio | N79: 5-Investigate | O79: 54788 | U79: Billede behandling/ tegneprogram | V79: =_xlfn.XLOOKUP(Applications[[#This Row],[NoApplication]],#REF!,#REF!,Applications[[#This Row],[Business Owner]],0,1) -> #REF! | X79: MEV | AB79: Freeware
B80: =_xlfn.CONCAT(Applications[[#This Row],[No]]," - ",Applications[[#This Row],[Application]]) -> 106 - SciChart | C80: 106 | D80: SciChart | E80: Development and Programming-Library | F80: 45658 | J80: SciChart Limited | N80: 4-Saved for now | O80: 54788 | U80: Grafværktøj til Visual Studio. Bruges til visning af data fra målerne. | V80: =_xlfn.XLOOKUP(Applications[[#This Row],[NoApplication]],#REF!,#REF!,Applications[[#This Row],[Business Owner]],0,1) -> #REF! | X80: mfc | Y80: DATA TO:LogView og LabTool, JAX have info of this | AA80: Licensen købes pr. versionpr. Bruger. Ved ny version eller ny bruger, skal der købes ny licnes. | AD80: READy | AE80: Software Departments | AJ80: Will be expensive to remove. Used extensively in READy | AK80: Is a library | AO80: Investigate
B81: =_xlfn.CONCAT(Applications[[#This Row],[No]]," - ",Applications[[#This Row],[Application]]) -> 107 - Serial port monitor 5.0 | C81: 107 | D81: Serial port monitor 5.0 | E81: Utilities and Miscellaneous | F81: 45658 | J81: Roma Software. | N81: 5-Investigate | O81: 54788 | U81: Overvågning/snifning af seriel port | V81: =_xlfn.XLOOKUP(Applications[[#This Row],[NoApplication]],#REF!,#REF!,Applications[[#This Row],[Business Owner]],0,1) -> #REF! | X81: LSH | AA81: Licensen købes pr. versionpr. Bruger. Ved ny version eller ny bruger, skal der købes ny licnes.
B82: =_xlfn.CONCAT(Applications[[#This Row],[No]]," - ",Applications[[#This Row],[Application]]) -> 108 - Snoop | C82: 108 | D82: Snoop | E82: Utilities and Miscellaneous | F82: 45658 | J82: Snoop Software Ltd. | N82: 5-Investigate | O82: 54788 | R82: https://snoopwpf.codeplex.com | U82: WPF spy | V82: =_xlfn.XLOOKUP(Applications[[#This Row],[NoApplication]],#REF!,#REF!,Applications[[#This Row],[Business Owner]],0,1) -> #REF! | X82: EMG | AB82: Ms-PL (Microsoft Public License)
B83: =_xlfn.CONCAT(Applications[[#This Row],[No]]," - ",Applications[[#This Row],[Application]]) -> 109 - SonicMQ .NET | C83: 109 | D83: SonicMQ .NET | E83: Development and Programming | F83: 45658 | J83: Progress Software Corporation | N83: 5-Investigate | O83: 54788 | U83: Klient til SonicMQ integration mod QAD | V83: =_xlfn.XLOOKUP(Applications[[#This Row],[NoApplication]],#REF!,#REF!,Applications[[#This Row],[Business Owner]],0,1) -> #REF! | X83: EMG | AB83: IT
B84: =_xlfn.CONCAT(Applications[[#This Row],[No]]," - ",Applications[[#This Row],[Application]]) -> 110 - SQLDigger | C84: 110 | D84: SQLDigger | E84: Data and Analytics | F84: 45658 | J84: SQLDigger is developed by**SQLDigger, Inc.** | N84: 5-Investigate | O84: 54788 | U84: Reverse engernering. Søge program til SQL server | V84: =_xlfn.XLOOKUP(Applications[[#This Row],[NoApplication]],#REF!,#REF!,Applications[[#This Row],[Business Owner]],0,1) -> #REF! | X84: JLM | AB84: Ældre freeware
B85: =_xlfn.CONCAT(Applications[[#This Row],[No]]," - ",Applications[[#This Row],[Application]]) -> 111 - WinMerge | C85: 111 | D85: WinMerge | E85: Utilities and Miscellaneous | F85: 45658 | G85: Distributed Applications | J85: WinMerge is developed by WinMerge.org. | N85: 2-Important application | O85: 54788 | Q85: Filecomparison / merge | U85: Værktøj til sammenligning af filer/biblioteker | V85: =_xlfn.XLOOKUP(Applications[[#This Row],[NoApplication]],#REF!,#REF!,Applications[[#This Row],[Business Owner]],0,1) -> #REF! | X85: LHB | AB85: Freeware | AE85: Hardware Departments
B86: =_xlfn.CONCAT(Applications[[#This Row],[No]]," - ",Applications[[#This Row],[Application]]) -> 113 - Keysight ADS | C86: 113 | D86: Keysight ADS | E86: Simulations and Engineering | F86: 45658 | G86: Distributed Applications | J86: Keysight Technologies | N86: 7-Potential for phase out | O86: 46173 | Q86: ADS Core, Layout, Harmonic Balance,Momentum G2 bundled license JESP: Nødvendigt til RF Hardware design og RF simulering under udvikling | U86: RF Simulering | V86: =_xlfn.XLOOKUP(Applications[[#This Row],[NoApplication]],#REF!,#REF!,Applications[[#This Row],[Business Owner]],0,1) -> #REF! | W86: MTM, JFB | X86: TES, JFB, BOR, LAZ, CJO, PEM, KAR, JCS | AA86: Floating license | AE86: Hardware Departments
B87: =_xlfn.CONCAT(Applications[[#This Row],[No]]," - ",Applications[[#This Row],[Application]]) -> 114 - Labview | C87: 114 | D87: Labview | E87: Simulations and Engineering | F87: 45658 | J87: National Instruments | N87: 5-Investigate | O87: 54788 | U87: Test | V87: =_xlfn.XLOOKUP(Applications[[#This Row],[NoApplication]],#REF!,#REF!,Applications[[#This Row],[Business Owner]],0,1) -> #REF! | X87: TES | AA87: Single license | AB87: TES
B88: =_xlfn.CONCAT(Applications[[#This Row],[No]]," - ",Applications[[#This Row],[Application]]) -> 116 - Orcad / Cadence | C88: 116 | D88: Orcad / Cadence | E88: Simulations and Engineering | F88: 45658 | G88: Distributed Applications | J88: Cadence Design Systems | N88: 1-Strategic | O88: 54788 | U88: Diagram tegning og Print udlægning | V88: =_xlfn.XLOOKUP(Applications[[#This Row],[NoApplication]],#REF!,#REF!,Applications[[#This Row],[Business Owner]],0,1) -> #REF! | W88: JLU | X88: LBU, JLU, TES, JFB, BOR, LAZ, CJO, PEM, KAR, JCS | AA88: Floating license | AE88: Hardware Departments | AH88: Cadance
B89: =_xlfn.CONCAT(Applications[[#This Row],[No]]," - ",Applications[[#This Row],[Application]]) -> 117 - Pads | C89: 117 | D89: Pads | E89: Utilities and Miscellaneous | F89: 45658 | G89: Distributed Applications | J89: PADS Software | N89: 7-Potential for phase out | O89: 46173 | U89: Diagram tegning og Print udlægning | V89: =_xlfn.XLOOKUP(Applications[[#This Row],[NoApplication]],#REF!,#REF!,Applications[[#This Row],[Business Owner]],0,1) -> #REF! | X89: LBU, JLU, TES, JFB, BOR, LAZ, CJO, PEM, KAR, JCS | AA89: Dongle | AE89: Hardware Departments | AI89: FRFS: Set to potential for phase out based on info from business of ELIMINATE | AJ89: Eliminate | AO89: Investigate
B90: =_xlfn.CONCAT(Applications[[#This Row],[No]]," - ",Applications[[#This Row],[Application]]) -> 118 - Python | C90: 118 | D90: Python | E90: Development and Programming | F90: 45658 | G90: Distributed Applications | J90: Python Software Foundation | N90: 1-Strategic | O90: 54788 | U90: Scripting | V90: =_xlfn.XLOOKUP(Applications[[#This Row],[NoApplication]],#REF!,#REF!,Applications[[#This Row],[Business Owner]],0,1) -> #REF! | X90: LBU, JLU, TES, JFB, BOR, LAZ, CJO, PEM, KAR, JCS | AB90: Freeware | AE90: Software, Hardware Departments | AH90: Python | AJ90: Tolerate/Invest
B91: =_xlfn.CONCAT(Applications[[#This Row],[No]]," - ",Applications[[#This Row],[Application]]) -> 119 - R&S EMC32 | C91: 119 | D91: R&S EMC32 | E91: Simulations and Engineering | F91: 45658 | J91: Rohde & Schwarz | M91: 0-9 | N91: 5-Investigate | O91: 54788 | U91: Test - EMC kammer | V91: =_xlfn.XLOOKUP(Applications[[#This Row],[NoApplication]],#REF!,#REF!,Applications[[#This Row],[Business Owner]],0,1) -> #REF! | W91: JLK | X91: TES, JFB, BOR, LAZ, CJO, PEM, KAR, JCS | AA91: 2xDongle
B92: =_xlfn.CONCAT(Applications[[#This Row],[No]]," - ",Applications[[#This Row],[Application]]) -> 120 - SolidWorks | C92: 120 | D92: SolidWorks | E92: Simulations and Engineering | F92: 45658 | G92: Distributed Applications | J92: Dassault Systèmes | N92: 5-Investigate | O92: 54788 | Q92: 3D tegneprogram.Mekanisk konstruktion | U92: 3D tegneprogram.Mekanisk konstruktion | V92: =_xlfn.XLOOKUP(Applications[[#This Row],[NoApplication]],#REF!,#REF!,Applications[[#This Row],[Business Owner]],0,1) -> #REF! | X92: BOR, JLU, NAN, LPI, JES,LAM;IRA | AA92: No yearly licens | AE92: Hardware Departments
B93: =_xlfn.CONCAT(Applications[[#This Row],[No]]," - ",Applications[[#This Row],[Application]]) -> 121 - Balsamiq Mockups | C93: 121 | D93: Balsamiq Mockups | E93: Productivity | F93: 45658 | J93: Balsamiq Studios, LLC | N93: 5-Investigate | O93: 54788 | U93: GUI Prototyping - Vi har ikke nyeste versioner | V93: =_xlfn.XLOOKUP(Applications[[#This Row],[NoApplication]],#REF!,#REF!,Applications[[#This Row],[Business Owner]],0,1) -> #REF! | W93: JLY | X93: JLY;KAK | AB93: Egne personlige licenser
B94: =_xlfn.CONCAT(Applications[[#This Row],[No]]," - ",Applications[[#This Row],[Application]]) -> 122 - List&Label | C94: 122 | D94: List&Label | E94: Business | F94: 45658 | J94: Combit GmbH | M94: 0-9 | N94: 4-Saved for now | O94: 54788 | R94: Software für Entwicklung und Kontaktmanagement von combit | U94: Label / rapport Design/Udskrivning | V94: =_xlfn.XLOOKUP(Applications[[#This Row],[NoApplication]],#REF!,#REF!,Applications[[#This Row],[Business Owner]],0,1) -> #REF! | W94: JLY;RBA;KAK;MDA | X94: JLY;RBA;KAK;MDA;KLU | Y94: DATA TO:All main products. KAMES, Integration owner JAX | AB94: KJN | AE94: Supply Chain
B95: =_xlfn.CONCAT(Applications[[#This Row],[No]]," - ",Applications[[#This Row],[Application]]) -> 124 - Pluralsight Skills | C95: 124 | D95: Pluralsight Skills | E95: Productivity | F95: 45658 | J95: Pluralsight, Inc. | N95: 5-Investigate | O95: 54788 | Q95: Learning platform | U95: Online kursusmatriale til bla. udviklingsmetoder og værktøjer - Vi deler en licens | V95: =_xlfn.XLOOKUP(Applications[[#This Row],[NoApplication]],#REF!,#REF!,Applications[[#This Row],[Business Owner]],0,1) -> #REF! | X95: JLY;MCR;RBA;MDA;KAK;KJN | AB95: KAK | AE95: Supply Chain
B96: =_xlfn.CONCAT(Applications[[#This Row],[No]]," - ",Applications[[#This Row],[Application]]) -> 125 - Raylase Weldmark | C96: 125 | D96: Raylase Weldmark | E96: Simulations and Engineering | F96: 45658 | J96: Raylase GmbH | N96: 5-Investigate | O96: 54788 | U96: Laser markerings program | V96: =_xlfn.XLOOKUP(Applications[[#This Row],[NoApplication]],#REF!,#REF!,Applications[[#This Row],[Business Owner]],0,1) -> #REF! | X96: KAK;KJN;kamstrup-pta3 | AA96: Raylase | AB96: KJN via dongels
B97: =_xlfn.CONCAT(Applications[[#This Row],[No]]," - ",Applications[[#This Row],[Application]]) -> 126 - Renorex | C97: 126 | D97: Renorex | E97: Quality Management System | F97: 45658 | J97: Renuex GmbH | N97: 5-Investigate | O97: 54788 | U97: Visual test automatisering | V97: =_xlfn.XLOOKUP(Applications[[#This Row],[NoApplication]],#REF!,#REF!,Applications[[#This Row],[Business Owner]],0,1) -> #REF! | X97: JHL;KJN | AA97: Renorex via dansk forhandler | AB97: KJN
B98: =_xlfn.CONCAT(Applications[[#This Row],[No]]," - ",Applications[[#This Row],[Application]]) -> 128 - AnkSVN | C98: 128 | D98: AnkSVN | E98: Development and Programming | F98: 45658 | J98: AnkSVN is developed by Ank God. | N98: 5-Investigate | O98: 54788 | V98: =_xlfn.XLOOKUP(Applications[[#This Row],[NoApplication]],#REF!,#REF!,Applications[[#This Row],[Business Owner]],0,1) -> #REF! | X98: SHG;BBH;ARD;LAO;MRE; | AB98: Freeware
B99: =_xlfn.CONCAT(Applications[[#This Row],[No]]," - ",Applications[[#This Row],[Application]]) -> 129 - Chocolatey | C99: 129 | D99: Chocolatey | E99: Utilities and Miscellaneous | F99: 45658 | J99: Chocolatey Software, Inc. | N99: 4-Saved for now | O99: 54788 | U99: NuGet pakke manager | V99: =_xlfn.XLOOKUP(Applications[[#This Row],[NoApplication]],#REF!,#REF!,Applications[[#This Row],[Business Owner]],0,1) -> #REF! | W99: ARD;KMO; | X99: SHG;MBM;ARD;KMO;MAH; | AB99: Freeware | AE99: Software, Hardware Departments | AI99: Used in OMNIA build pipelines. Could possibly be removed from our client PC.s | AJ99: A significant time-investment is needed to remove this.
B100: =_xlfn.CONCAT(Applications[[#This Row],[No]]," - ",Applications[[#This Row],[Application]]) -> 130 - Emacs | C100: 130 | D100: Emacs | E100: Development and Programming | F100: 45658 | G100: Distributed Applications | J100: GNU Project | N100: 4-Saved for now | O100: 54788 | U100: Editor og med det rette plugin alt hvad de andre programmer på listen kan. | V100: =_xlfn.XLOOKUP(Applications[[#This Row],[NoApplication]],#REF!,#REF!,Applications[[#This Row],[Business Owner]],0,1) -> #REF! | X100: TLJ; | AB100: Freeware | AD100: IDE | AE100: Hardware Departments | AI100: Editor | AJ100: Tolerate/migrate | AK100: Free and open source client system
...

Sheet A-Application_Approval
B1: Chose the application | R1: Auto fill from A-Applications
C2: ECS | F2: Legal
B3: NoApplication | C3: ECS approved | D3: ECS Approval date | E3: ECS Approved by | F3: Legal approved | G3: Legal Approval date | H3: Legal Approved by
B4: kljæk | C4: Yes | D4: 45667 | G4: 45659
B5: øklæø | C5: No | D5: 45672 | G5: 45713
B6: klæj | C6: Under evaluation

Sheet A-Application_Budget
B4: Description | C4: Date | D4: Type | E4: Amount
B5: Azure | C5: 45292 | D5: Budget | E5: 24623000
B6: Licenses | C6: 45292 | D6: Budget | E6: 82277000
B7: Azure | C7: 45291 | D7: Actual | E7: 22385000
B8: Licenses | C8: 45291 | D8: Actual | E8: 52605000
B9: Azure | C9: 45658 | D9: Budget | E9: 36000000
B10: Licenses | C10: 45658 | D10: Budget | E10: 81455000

Sheet B-Business Capability
F2: Level 1 of the business capability | G2: Level 2 of the business capability | H2: Level 3 of the business capability | I2: Gartner Pace Layer strategy as classification. Strategic value for the business | J2: Description of the capability | K2: Value Stream applying to the capability | L2: Value Stream order applying to the Value stream | M2: NIS2 - Criticality | N2: Date of update with business | O2: Initials of business responsabel from the business | P2: Comments
B5: IdLevel123 | C5: Column1 | D5: Type | E5: Level 0 | F5: Level 1 | G5: Level 2 | H5: Level 3 | I5: Pace Layer | J5: Description | K5: Value Stream | L5: Value stream order | M5: NIS2 - Criticality | N5: Updated | O5: Business Responsibel | P5: Comment | Q5: __PowerAppsId__
B6: =_xlfn.CONCAT(Capabilities[[#This Row],[Column1]],"-",Capabilities[[#This Row],[Level 1]],"-",Capabilities[[#This Row],[Level 2]],"-",Capabilities[[#This Row],[Level 3]]) -> 999-All-- | C6: 999 | E6: All | F6: All | K6: N/A | Q6: 21541184-493d-479c-8c0c-6b71625ef1a4
B7: =_xlfn.CONCAT(Capabilities[[#This Row],[Column1]],"-",Capabilities[[#This Row],[Level 1]],"-",Capabilities[[#This Row],[Level 2]],"-",Capabilities[[#This Row],[Level 3]]) -> 1000-Customer Relationship-- | C7: 1000 | D7: BusinessCapability | E7: Sales | F7: Customer Relationship | J7: A robust system designed to manage interactions and relationships with a large customer base effectively and efficiently. | K7: Customer Service and Support | Q7: 1f2d6dcb-b2bf-4dac-92ad-daa3c02c7e9e
B8: =_xlfn.CONCAT(Capabilities[[#This Row],[Column1]],"-",Capabilities[[#This Row],[Level 1]],"-",Capabilities[[#This Row],[Level 2]],"-",Capabilities[[#This Row],[Level 3]]) -> 1008-Customer Relationship-Contact Management- | C8: 1008 | D8: BusinessCapability | E8: Sales | F8: Customer Relationship | G8: Contact Management | J8: Facilitates efficient communication and organization of customer interactions to enhance satisfaction and loyalty. | K8: Customer Service and Support | Q8: e7705fd4-7ec5-4702-8f12-be14c6197fd2
B9: =_xlfn.CONCAT(Capabilities[[#This Row],[Column1]],"-",Capabilities[[#This Row],[Level 1]],"-",Capabilities[[#This Row],[Level 2]],"-",Capabilities[[#This Row],[Level 3]]) -> 1062-Customer Relationship-Contact Management-Classify Demand | C9: 1062 | D9: BusinessCapability | E9: Sales | F9: Customer Relationship | G9: Contact Management | H9: Classify Demand | J9: Organizes and prioritizes customer interactions to enhance relationship management and streamline communication strategies effectively. | K9: Customer Service and Support | Q9: e3055f01-8611-499f-b008-9535fc5ccc8f
B10: =_xlfn.CONCAT(Capabilities[[#This Row],[Column1]],"-",Capabilities[[#This Row],[Level 1]],"-",Capabilities[[#This Row],[Level 2]],"-",Capabilities[[#This Row],[Level 3]]) -> 1063-Customer Relationship-Contact Management-Contact Interaction | C10: 1063 | D10: BusinessCapability | E10: Sales | F10: Customer Relationship | G10: Contact Management | H10: Contact Interaction | J10: Managing and tracking interactions with clients to enhance relationships and improve service delivery through organized communication records. | K10: Customer Service and Support | Q10: edd10c33-c68a-413e-90d8-dbb7de152f7b
B11: =_xlfn.CONCAT(Capabilities[[#This Row],[Column1]],"-",Capabilities[[#This Row],[Level 1]],"-",Capabilities[[#This Row],[Level 2]],"-",Capabilities[[#This Row],[Level 3]]) -> 1064-Customer Relationship-Contact Management-Inbound Contact | C11: 1064 | D11: BusinessCapability | E11: Sales | F11: Customer Relationship | G11: Contact Management | H11: Inbound Contact | J11: Manages incoming inquiries, ensuring efficient communication and relationship-building with customers through organized tracking and timely responses. | K11: Customer Service and Support | Q11: 9161f33a-ac06-4912-8df1-1619d40fefd6
B12: =_xlfn.CONCAT(Capabilities[[#This Row],[Column1]],"-",Capabilities[[#This Row],[Level 1]],"-",Capabilities[[#This Row],[Level 2]],"-",Capabilities[[#This Row],[Level 3]]) -> 1065-Customer Relationship-Contact Management-Manage Interaction | C12: 1065 | D12: BusinessCapability | E12: Sales | F12: Customer Relationship | G12: Contact Management | H12: Manage Interaction | J12: Facilitates tracking, organizing, and optimizing customer interactions to enhance relationship quality and improve service outcomes. | K12: Customer Service and Support | Q12: de061f70-9b54-4b09-9919-4ce70caa22c1
B13: =_xlfn.CONCAT(Capabilities[[#This Row],[Column1]],"-",Capabilities[[#This Row],[Level 1]],"-",Capabilities[[#This Row],[Level 2]],"-",Capabilities[[#This Row],[Level 3]]) -> 1066-Customer Relationship-Contact Management-Outbound Contact | C13: 1066 | D13: BusinessCapability | E13: Sales | F13: Customer Relationship | G13: Contact Management | H13: Outbound Contact | J13: Managing and optimizing outbound communications with customers to enhance relationships, track interactions, and improve engagement effectiveness. | K13: Customer Service and Support | Q13: 5a08cbd1-4be0-41c8-a653-b97ec8ec6d9e
B14: =_xlfn.CONCAT(Capabilities[[#This Row],[Column1]],"-",Capabilities[[#This Row],[Level 1]],"-",Capabilities[[#This Row],[Level 2]],"-",Capabilities[[#This Row],[Level 3]]) -> 1067-Customer Relationship-Contact Management-Route Contact | C14: 1067 | D14: BusinessCapability | E14: Sales | F14: Customer Relationship | G14: Contact Management | H14: Route Contact | J14: Facilitates efficient tracking and management of customer interactions, enhancing engagement and optimizing communication routes for improved relationships. | K14: Customer Service and Support | Q14: 965628c7-54b6-4663-a1ad-1757aedd0240
B15: =_xlfn.CONCAT(Capabilities[[#This Row],[Column1]],"-",Capabilities[[#This Row],[Level 1]],"-",Capabilities[[#This Row],[Level 2]],"-",Capabilities[[#This Row],[Level 3]]) -> 1070-Customer Relationship-Contract Management-Manage Product Usage | C15: 1070 | D15: BusinessCapability | E15: Sales | F15: Customer Relationship | G15: Contract Management | H15: Manage Product Usage | J15: Oversee and optimize product utilization and compliance within customer contracts, ensuring satisfaction and maximizing value delivered. | K15: Subscribtion-to-Pay (S2P) | L15: 600 | O15: KBO | Q15: f8eec740-49b3-4ea4-8651-f2e00b2e2ef9
B16: =_xlfn.CONCAT(Capabilities[[#This Row],[Column1]],"-",Capabilities[[#This Row],[Level 1]],"-",Capabilities[[#This Row],[Level 2]],"-",Capabilities[[#This Row],[Level 3]]) -> 1009-Customer Relationship-Contract Management- | C16: 1009 | D16: BusinessCapability | E16: Sales | F16: Customer Relationship | G16: Contract Management | J16: Facilitates effective management of customer contracts, ensuring compliance, tracking obligations, and enhancing relationship longevity through streamlined processes. | K16: N/A | Q16: c55bc51e-6f6e-4c8d-a674-b8ccfc4e9886
B17: =_xlfn.CONCAT(Capabilities[[#This Row],[Column1]],"-",Capabilities[[#This Row],[Level 1]],"-",Capabilities[[#This Row],[Level 2]],"-",Capabilities[[#This Row],[Level 3]]) -> 1068-Customer Relationship-Contract Management-Manage Contract | C17: 1068 | D17: BusinessCapability | E17: Sales | F17: Customer Relationship | G17: Contract Management | H17: Manage Contract | J17: Oversee contractual agreements, ensuring compliance, tracking obligations, and fostering positive relationships between involved parties for successful outcomes. | K17: N/A | Q17: 7daf00b4-db21-44a3-a4f1-28ce3dc3e6cf
B18: =_xlfn.CONCAT(Capabilities[[#This Row],[Column1]],"-",Capabilities[[#This Row],[Level 1]],"-",Capabilities[[#This Row],[Level 2]],"-",Capabilities[[#This Row],[Level 3]]) -> 1069-Customer Relationship-Contract Management-Manage Frame-Contract | C18: 1069 | D18: BusinessCapability | E18: Sales | F18: Customer Relationship | G18: Contract Management | H18: Manage Frame-Contract | J18: Oversee contractual agreements, ensuring compliance, performance tracking, and fostering strong customer relationships throughout the contract lifecycle. | K18: N/A | Q18: d4876128-c6ab-48df-98c8-88b0c8e77d74
B19: =_xlfn.CONCAT(Capabilities[[#This Row],[Column1]],"-",Capabilities[[#This Row],[Level 1]],"-",Capabilities[[#This Row],[Level 2]],"-",Capabilities[[#This Row],[Level 3]]) -> 1071-Customer Relationship-Contract Management-Negotiate Contract | C19: 1071 | D19: BusinessCapability | E19: Sales | F19: Customer Relationship | G19: Contract Management | H19: Negotiate Contract | J19: Facilitates effective negotiation strategies to enhance partnerships, ensuring mutually beneficial terms and compliance for all stakeholders involved. | K19: N/A | Q19: 1957a254-b251-4395-8057-1aa5a23330db
B20: =_xlfn.CONCAT(Capabilities[[#This Row],[Column1]],"-",Capabilities[[#This Row],[Level 1]],"-",Capabilities[[#This Row],[Level 2]],"-",Capabilities[[#This Row],[Level 3]]) -> 1010-Customer Relationship-Customer Management- | C20: 1010 | D20: BusinessCapability | E20: Sales | F20: Customer Relationship | G20: Customer Management | J20: Managing interactions and relationships with customers to enhance satisfaction, loyalty, and retention through effective communication and personalized service. | K20: Customer Service and Support | Q20: 36c1a040-6db8-497e-acbe-00760b35c5c9
B21: =_xlfn.CONCAT(Capabilities[[#This Row],[Column1]],"-",Capabilities[[#This Row],[Level 1]],"-",Capabilities[[#This Row],[Level 2]],"-",Capabilities[[#This Row],[Level 3]]) -> 1072-Customer Relationship-Customer Management-Identify Customer | C21: 1072 | D21: BusinessCapability | E21: Sales | F21: Customer Relationship | G21: Customer Management | H21: Identify Customer | J21: Ability to recognize and profile clients to enhance engagement and tailor services for improved satisfaction. | K21: Customer Service and Support | Q21: 03186182-8faa-4856-b9aa-136dbc194bd5
B22: =_xlfn.CONCAT(Capabilities[[#This Row],[Column1]],"-",Capabilities[[#This Row],[Level 1]],"-",Capabilities[[#This Row],[Level 2]],"-",Capabilities[[#This Row],[Level 3]]) -> 1073-Customer Relationship-Customer Management-Manage Community | C22: 1073 | D22: BusinessCapability | E22: Sales | F22: Customer Relationship | G22: Customer Management | H22: Manage Community | J22: Facilitates engagement and interaction with customers, enhancing loyalty and community through targeted communication and support strategies. | K22: N/A | Q22: 060ada05-9c68-4da9-b7f3-4747607e9266
B23: =_xlfn.CONCAT(Capabilities[[#This Row],[Column1]],"-",Capabilities[[#This Row],[Level 1]],"-",Capabilities[[#This Row],[Level 2]],"-",Capabilities[[#This Row],[Level 3]]) -> 1074-Customer Relationship-Customer Management-Manage Customer | C23: 1074 | D23: BusinessCapability | E23: Sales | F23: Customer Relationship | G23: Customer Management | H23: Manage Customer | J23: Efficiently oversee customer interactions to enhance satisfaction, loyalty, and retention through personalized communication and service strategies. | K23: Customer Service and Support | O23: THG | Q23: 58b1d38e-08d9-4f79-baa4-538a3dac4ab9
B24: =_xlfn.CONCAT(Capabilities[[#This Row],[Column1]],"-",Capabilities[[#This Row],[Level 1]],"-",Capabilities[[#This Row],[Level 2]],"-",Capabilities[[#This Row],[Level 3]]) -> 1075-Customer Relationship-Customer Management-Manage Customer Hierarchy | C24: 1075 | D24: BusinessCapability | E24: Sales | F24: Customer Relationship | G24: Customer Management | H24: Manage Customer Hierarchy | J24: Organizes customer relationships by establishing tiers and connections, enabling personalized interactions and efficient account management strategies. | K24: Customer Service and Support | Q24: 99970d67-2d2b-41eb-a0c2-c61485e5df14
B25: =_xlfn.CONCAT(Capabilities[[#This Row],[Column1]],"-",Capabilities[[#This Row],[Level 1]],"-",Capabilities[[#This Row],[Level 2]],"-",Capabilities[[#This Row],[Level 3]]) -> 1076-Customer Relationship-Customer Management-Manage Org. Context | C25: 1076 | D25: BusinessCapability | E25: Sales | F25: Customer Relationship | G25: Customer Management | H25: Manage Org. Context | J25: Effectively oversee organizational context to enhance customer engagement, streamline interactions, and optimize overall relationship management processes. | K25: Customer Service and Support | Q25: 98ada6a8-8ff4-44ab-af3c-a998d12338c9
B26: =_xlfn.CONCAT(Capabilities[[#This Row],[Column1]],"-",Capabilities[[#This Row],[Level 1]],"-",Capabilities[[#This Row],[Level 2]],"-",Capabilities[[#This Row],[Level 3]]) -> 1011-Customer Relationship-Customer Scoring- | C26: 1011 | D26: BusinessCapability | E26: Sales | F26: Customer Relationship | G26: Customer Scoring | J26: Evaluates customer interactions and behaviors to prioritize engagement strategies and enhance relationship management effectively. | K26: Customer Service and Support | Q26: 924efce8-b87d-4a36-91e2-0a4d1e8970b0
B27: =_xlfn.CONCAT(Capabilities[[#This Row],[Column1]],"-",Capabilities[[#This Row],[Level 1]],"-",Capabilities[[#This Row],[Level 2]],"-",Capabilities[[#This Row],[Level 3]]) -> 1077-Customer Relationship-Customer Scoring-Check Credit-Worthiness | C27: 1077 | D27: BusinessCapability | E27: Sales | F27: Customer Relationship | G27: Customer Scoring | H27: Check Credit-Worthiness | J27: Evaluates customer credit risk and financial reliability to inform decision-making and enhance relationship management strategies. | K27: N/A | Q27: bf0c1e55-16c9-4b9e-a439-d208d6e30420
B28: =_xlfn.CONCAT(Capabilities[[#This Row],[Column1]],"-",Capabilities[[#This Row],[Level 1]],"-",Capabilities[[#This Row],[Level 2]],"-",Capabilities[[#This Row],[Level 3]]) -> 1078-Customer Relationship-Customer Scoring-Define Customer Risks | C28: 1078 | D28: BusinessCapability | E28: Sales | F28: Customer Relationship | G28: Customer Scoring | H28: Define Customer Risks | J28: Evaluate customer profiles to identify potential risks, enhancing relationship management and targeted strategies for improved customer engagement. | K28: N/A | Q28: 140bf481-09cb-42bd-9c85-8d95bb458ac9
B29: =_xlfn.CONCAT(Capabilities[[#This Row],[Column1]],"-",Capabilities[[#This Row],[Level 1]],"-",Capabilities[[#This Row],[Level 2]],"-",Capabilities[[#This Row],[Level 3]]) -> 1079-Customer Relationship-Customer Scoring-Manage Customer Risks | C29: 1079 | D29: BusinessCapability | E29: Sales | F29: Customer Relationship | G29: Customer Scoring | H29: Manage Customer Risks | J29: Assess and prioritize customer relationships by analyzing risk factors to enhance engagement and retention strategies effectively. | K29: N/A | Q29: f55bc9d4-e3e5-4c0b-b0d9-6b7eba0f1e48
B30: =_xlfn.CONCAT(Capabilities[[#This Row],[Column1]],"-",Capabilities[[#This Row],[Level 1]],"-",Capabilities[[#This Row],[Level 2]],"-",Capabilities[[#This Row],[Level 3]]) -> 1012-Customer Relationship-Order Management- | C30: 1012 | D30: BusinessCapability | E30: Sales | F30: Customer Relationship | G30: Order Management | J30: Streamlines the process of managing customer orders, enhancing satisfaction through efficient tracking, processing, and communication. | K30: Order-to-Cash (O2C) | L30: 150 | Q30: 86c7cdee-0271-4321-a8c6-147d323f683b
B31: =_xlfn.CONCAT(Capabilities[[#This Row],[Column1]],"-",Capabilities[[#This Row],[Level 1]],"-",Capabilities[[#This Row],[Level 2]],"-",Capabilities[[#This Row],[Level 3]]) -> 1080-Customer Relationship-Order Management-Bundle Order | C31: 1080 | D31: BusinessCapability | E31: Sales | F31: Customer Relationship | G31: Order Management | H31: Bundle Order | J31: Facilitates the management and processing of bundled customer orders, ensuring efficient tracking and fulfillment for enhanced satisfaction. | K31: Order-to-Cash (O2C) | L31: 155 | Q31: 9b58eb22-6c27-4beb-8c01-d4e68900fea1
B32: =_xlfn.CONCAT(Capabilities[[#This Row],[Column1]],"-",Capabilities[[#This Row],[Level 1]],"-",Capabilities[[#This Row],[Level 2]],"-",Capabilities[[#This Row],[Level 3]]) -> 1084-Customer Relationship-Order Management-Validate Order | C32: 1084 | D32: BusinessCapability | E32: Sales | F32: Customer Relationship | G32: Order Management | H32: Validate Order | J32: Ensures accurate verification of customer orders, confirming details and compliance before processing for fulfillment and shipping. | K32: Order-to-Cash (O2C) | L32: 160 | Q32: 73e37d24-01db-441b-b609-128c02bb0e6c
B33: =_xlfn.CONCAT(Capabilities[[#This Row],[Column1]],"-",Capabilities[[#This Row],[Level 1]],"-",Capabilities[[#This Row],[Level 2]],"-",Capabilities[[#This Row],[Level 3]]) -> 1081-Customer Relationship-Order Management-Cancel Order | C33: 1081 | D33: BusinessCapability | E33: Sales | F33: Customer Relationship | G33: Order Management | H33: Cancel Order | J33: Facilitates the process of canceling customer orders efficiently while maintaining accurate records and communication. | K33: Order-to-Cash (O2C) | L33: 165 | Q33: 1865a63f-12b9-4391-b766-fdb60f03aa6a
B34: =_xlfn.CONCAT(Capabilities[[#This Row],[Column1]],"-",Capabilities[[#This Row],[Level 1]],"-",Capabilities[[#This Row],[Level 2]],"-",Capabilities[[#This Row],[Level 3]]) -> 1082-Customer Relationship-Order Management-Steer Order | C34: 1082 | D34: BusinessCapability | E34: Sales | F34: Customer Relationship | G34: Order Management | H34: Steer Order | J34: Facilitates effective order handling and management, ensuring timely processing, customer satisfaction, and streamlined operations throughout the order lifecycle. | K34: Order-to-Cash (O2C) | L34: 170 | Q34: f08caa22-4fa4-4eed-b193-b26f613c6f32
B35: =_xlfn.CONCAT(Capabilities[[#This Row],[Column1]],"-",Capabilities[[#This Row],[Level 1]],"-",Capabilities[[#This Row],[Level 2]],"-",Capabilities[[#This Row],[Level 3]]) -> 1083-Customer Relationship-Order Management-Track Order | C35: 1083 | D35: BusinessCapability | E35: Sales | F35: Customer Relationship | G35: Order Management | H35: Track Order | J35: Enables monitoring of customer orders throughout the fulfillment process, ensuring timely delivery and enhancing customer satisfaction. | K35: Order-to-Cash (O2C) | L35: 175 | Q35: 2d9d537f-6189-4dd8-a4f6-4a6d5b583407
B36: =_xlfn.CONCAT(Capabilities[[#This Row],[Column1]],"-",Capabilities[[#This Row],[Level 1]],"-",Capabilities[[#This Row],[Level 2]],"-",Capabilities[[#This Row],[Level 3]]) -> 1013-Customer Relationship-SLA Management- | C36: 1013 | D36: BusinessCapability | E36: Sales | F36: Customer Relationship | G36: SLA Management | J36: Ensures timely service delivery, maintains customer satisfaction, and monitors performance against agreed service levels for optimal support. | K36: Customer Service and Support | Q36: 406b7a2f-3c07-4562-af18-198eead58a1f
B37: =_xlfn.CONCAT(Capabilities[[#This Row],[Column1]],"-",Capabilities[[#This Row],[Level 1]],"-",Capabilities[[#This Row],[Level 2]],"-",Capabilities[[#This Row],[Level 3]]) -> 1085-Customer Relationship-SLA Management-Manage SLA Violations | C37: 1085 | D37: BusinessCapability | E37: Sales | F37: Customer Relationship | G37: SLA Management | H37: Manage SLA Violations | J37: Identify, track, and resolve service level agreement breaches to ensure compliance and enhance customer satisfaction. | K37: Customer Service and Support | P37: P13.3 | Q37: 69589442-7aab-4559-9cc6-cadfa6be559f
B38: =_xlfn.CONCAT(Capabilities[[#This Row],[Column1]],"-",Capabilities[[#This Row],[Level 1]],"-",Capabilities[[#This Row],[Level 2]],"-",Capabilities[[#This Row],[Level 3]]) -> 1086-Customer Relationship-SLA Management-Track & Report SLA Breaches | C38: 1086 | D38: BusinessCapability | E38: Sales | F38: Customer Relationship | G38: SLA Management | H38: Track & Report SLA Breaches | J38: Monitor, analyze, and document service level agreement violations to ensure accountability and improve customer satisfaction. | K38: Customer Service and Support | P38: P13.3 | Q38: 93ba48d2-2412-4476-84bd-b7348bdf3ee2
B39: =_xlfn.CONCAT(Capabilities[[#This Row],[Column1]],"-",Capabilities[[#This Row],[Level 1]],"-",Capabilities[[#This Row],[Level 2]],"-",Capabilities[[#This Row],[Level 3]]) -> 4230-Customer Service-Customer Project Management- | C39: 4230 | D39: BusinessCapability | E39: Service | F39: Customer Service | G39: Customer Project Management | K39: Order-to-Cash (O2C) | O39: THB | Q39: 55b0a755-e2c2-42a2-a6ef-f64844c8db86
B40: =_xlfn.CONCAT(Capabilities[[#This Row],[Column1]],"-",Capabilities[[#This Row],[Level 1]],"-",Capabilities[[#This Row],[Level 2]],"-",Capabilities[[#This Row],[Level 3]]) -> 4231-Customer Service-Customer Project Management-Ressource Management | C40: 4231 | D40: BusinessCapability | E40: Service | F40: Customer Service | G40: Customer Project Management | H40: Ressource Management | K40: Order-to-Cash (O2C) | O40: THB | Q40: 3c297db6-0f76-4dd7-8565-cd6f8f1ca303
B41: =_xlfn.CONCAT(Capabilities[[#This Row],[Column1]],"-",Capabilities[[#This Row],[Level 1]],"-",Capabilities[[#This Row],[Level 2]],"-",Capabilities[[#This Row],[Level 3]]) -> 4232-Customer Service-Customer Project Management-Financial Analytics and Management | C41: 4232 | D41: BusinessCapability | E41: Service | F41: Customer Service | G41: Customer Project Management | H41: Financial Analytics and Management | K41: Order-to-Cash (O2C) | O41: THB | Q41: 60db7c1f-84a3-4b8a-b293-3b3f1dae6be6
B42: =_xlfn.CONCAT(Capabilities[[#This Row],[Column1]],"-",Capabilities[[#This Row],[Level 1]],"-",Capabilities[[#This Row],[Level 2]],"-",Capabilities[[#This Row],[Level 3]]) -> 4233-Customer Service-Customer Project Management-Project Management | C42: 4233 | D42: BusinessCapability | E42: Service | F42: Customer Service | G42: Customer Project Management | H42: Project Management | K42: Order-to-Cash (O2C) | O42: THB, ALMO | Q42: 113f9fe9-b4ee-4953-86e4-d3e4bfb28702
B43: =_xlfn.CONCAT(Capabilities[[#This Row],[Column1]],"-",Capabilities[[#This Row],[Level 1]],"-",Capabilities[[#This Row],[Level 2]],"-",Capabilities[[#This Row],[Level 3]]) -> 4235-Customer Service-Customer Project Management-Test Management | C43: 4235 | D43: BusinessCapability | E43: Service | F43: Customer Service | G43: Customer Project Management | H43: Test Management | K43: Order-to-Cash (O2C) | O43: THB | Q43: b035d121-ebf8-48d6-835d-26d7c1588e2d
B44: =_xlfn.CONCAT(Capabilities[[#This Row],[Column1]],"-",Capabilities[[#This Row],[Level 1]],"-",Capabilities[[#This Row],[Level 2]],"-",Capabilities[[#This Row],[Level 3]]) -> 4201-Customer Service-Customer Service and Support- | C44: 4201 | D44: BusinessCapability | E44: Service | F44: Customer Service | G44: Customer Service and Support | J44: Provides assistance and solutions to users, ensuring satisfaction through effective communication and problem resolution. | K44: Customer Service and Support | O44: THB, ALMO | Q44: 984d37ed-27ac-44d8-a756-6e395159c06b
B45: =_xlfn.CONCAT(Capabilities[[#This Row],[Column1]],"-",Capabilities[[#This Row],[Level 1]],"-",Capabilities[[#This Row],[Level 2]],"-",Capabilities[[#This Row],[Level 3]]) -> 4203-Customer Service-Customer Service and Support-Service Request Management | C45: 4203 | D45: BusinessCapability | E45: Service | F45: Customer Service | G45: Customer Service and Support | H45: Service Request Management | I45: Systems of Commodity | J45: Streamlines the process of handling customer requests, ensuring timely responses and effective resolution of issues and inquiries. | K45: Customer Service and Support | O45: THG, THB | Q45: 8c0585dd-bdaa-418f-9b02-fb9e4c1f237e
B46: =_xlfn.CONCAT(Capabilities[[#This Row],[Column1]],"-",Capabilities[[#This Row],[Level 1]],"-",Capabilities[[#This Row],[Level 2]],"-",Capabilities[[#This Row],[Level 3]]) -> 4204-Customer Service-Customer Service and Support-Complaints Management | C46: 4204 | D46: BusinessCapability | E46: Service | F46: Customer Service | G46: Customer Service and Support | H46: Complaints Management | I46: Systems of Commodity | J46: Efficiently manage and resolve customer complaints, ensuring satisfaction and improving service processes through effective communication and follow-up. | K46: Customer Service and Support | O46: THG, THB | Q46: 54e87481-c448-48be-bd7f-61e2cc018bce
B47: =_xlfn.CONCAT(Capabilities[[#This Row],[Column1]],"-",Capabilities[[#This Row],[Level 1]],"-",Capabilities[[#This Row],[Level 2]],"-",Capabilities[[#This Row],[Level 3]]) -> 4205-Customer Service-Customer Service and Support-Customer Claims Management | C47: 4205 | D47: BusinessCapability | E47: Service | F47: Customer Service | G47: Customer Service and Support | H47: Customer Claims Management | I47: Systems of Commodity | J47: Effectively manage customer claims through timely responses, issue resolution, and supportive communication to enhance customer satisfaction and loyalty. | K47: Customer Service and Support | O47: THG, THB | Q47: 8599668d-7c98-4e74-a143-cd5f17572d7d
B48: =_xlfn.CONCAT(Capabilities[[#This Row],[Column1]],"-",Capabilities[[#This Row],[Level 1]],"-",Capabilities[[#This Row],[Level 2]],"-",Capabilities[[#This Row],[Level 3]]) -> 4206-Customer Service-Customer Service and Support-Customer Returns Management | C48: 4206 | D48: BusinessCapability | E48: Service | F48: Customer Service | G48: Customer Service and Support | H48: Customer Returns Management | I48: Systems of Commodity | J48: Manages returned products efficiently, ensuring efficient processing, refunds, and customer satisfaction throughout the returns process. | K48: Customer Service and Support | O48: THG, THB? | Q48: d650b794-bcc8-4e83-83ab-212fc0b306a9
B49: =_xlfn.CONCAT(Capabilities[[#This Row],[Column1]],"-",Capabilities[[#This Row],[Level 1]],"-",Capabilities[[#This Row],[Level 2]],"-",Capabilities[[#This Row],[Level 3]]) -> 4207-Customer Service-Customer Service and Support-Customer Warranty Claim Processing | C49: 4207 | D49: BusinessCapability | E49: Service | F49: Customer Service | G49: Customer Service and Support | H49: Customer Warranty Claim Processing | I49: Systems of Commodity | J49: Efficiently manages customer warranty claims, ensuring prompt resolution and effective communication to enhance customer satisfaction and loyalty. | K49: Customer Service and Support | O49: THG, THB? | Q49: 9511b8f9-cf7d-49cc-88b0-a844e37c3899
B50: =_xlfn.CONCAT(Capabilities[[#This Row],[Column1]],"-",Capabilities[[#This Row],[Level 1]],"-",Capabilities[[#This Row],[Level 2]],"-",Capabilities[[#This Row],[Level 3]]) -> 4208-Customer Service-Customer Service and Support-Inquiry Management | C50: 4208 | D50: BusinessCapability | E50: Service | F50: Customer Service | G50: Customer Service and Support | H50: Inquiry Management | I50: Systems of Commodity | J50: Efficiently handles customer inquiries, providing timely resolutions and support to enhance satisfaction and maintain positive relationships. | K50: Customer Service and Support | O50: THG, THB | Q50: dcf212b2-de8e-4e0a-8b31-fc8408c01cf8
B51: =_xlfn.CONCAT(Capabilities[[#This Row],[Column1]],"-",Capabilities[[#This Row],[Level 1]],"-",Capabilities[[#This Row],[Level 2]],"-",Capabilities[[#This Row],[Level 3]]) -> 4209-Customer Service-Customer Service and Support-Omnichannel Customer Engagement | C51: 4209 | D51: BusinessCapability | E51: Service | F51: Customer Service | G51: Customer Service and Support | H51: Omnichannel Customer Engagement | J51: Seamlessly integrates multiple communication channels to enhance customer experience and provide consistent support across platforms. | K51: Customer Service and Support | O51: THB? | Q51: 6398f0c9-283b-4f3c-a084-faecb29a43d4
B52: =_xlfn.CONCAT(Capabilities[[#This Row],[Column1]],"-",Capabilities[[#This Row],[Level 1]],"-",Capabilities[[#This Row],[Level 2]],"-",Capabilities[[#This Row],[Level 3]]) -> 4210-Customer Service-Customer Service and Support-Recall Management | C52: 4210 | D52: BusinessCapability | E52: Service | F52: Customer Service | G52: Customer Service and Support | H52: Recall Management | I52: Systems of Commodity | J52: Manages product recalls efficiently, ensuring timely communication and support to affected customers for safety and compliance. | K52: Customer Service and Support | O52: THG, THB | Q52: 4b7da6b1-7fd5-4bde-b426-e3ee599cfcdc
B53: =_xlfn.CONCAT(Capabilities[[#This Row],[Column1]],"-",Capabilities[[#This Row],[Level 1]],"-",Capabilities[[#This Row],[Level 2]],"-",Capabilities[[#This Row],[Level 3]]) -> 4211-Customer Service-Customer Service and Support-Self-Service Engagement | C53: 4211 | D53: BusinessCapability | E53: Service | F53: Customer Service | G53: Customer Service and Support | H53: Self-Service Engagement | I53: Systems of Commodity | J53: Empowering users to independently resolve issues through accessible resources, enhancing satisfaction and reducing support workload. | K53: Customer Service and Support | O53: THG, THB | Q53: 35508a57-8609-43ad-a850-0f887285cdb8
B54: =_xlfn.CONCAT(Capabilities[[#This Row],[Column1]],"-",Capabilities[[#This Row],[Level 1]],"-",Capabilities[[#This Row],[Level 2]],"-",Capabilities[[#This Row],[Level 3]]) -> 4212-Customer Service-Customer Service and Support-Service Knowledge Base Management | C54: 4212 | D54: BusinessCapability | E54: Service | F54: Customer Service | G54: Customer Service and Support | H54: Service Knowledge Base Management | I54: Systems of Commodity | J54: Management of centralized information resources to enhance support efficiency and customer satisfaction through accessible service knowledge. | K54: Customer Service and Support | O54: THG, THB | Q54: 442a313a-d1a7-4262-b676-30a6e0b492fd
B55: =_xlfn.CONCAT(Capabilities[[#This Row],[Column1]],"-",Capabilities[[#This Row],[Level 1]],"-",Capabilities[[#This Row],[Level 2]],"-",Capabilities[[#This Row],[Level 3]]) -> 4213-Customer Service-Customer Service and Support-Service Level Management | C55: 4213 | D55: BusinessCapability | E55: Service | F55: Customer Service | G55: Customer Service and Support | H55: Service Level Management | I55: Systems of Commodity | J55: Ensures timely and effective support delivery, aligning services with customer needs and expectations to enhance satisfaction and performance. | K55: Customer Service and Support | O55: THG, THB | Q55: fbae318b-5dde-47f9-9c88-b5c95db18b9a
B56: =_xlfn.CONCAT(Capabilities[[#This Row],[Column1]],"-",Capabilities[[#This Row],[Level 1]],"-",Capabilities[[#This Row],[Level 2]],"-",Capabilities[[#This Row],[Level 3]]) -> 4234-Customer Service-Customer Service and Support-Customer Operations | C56: 4234 | D56: BusinessCapability | E56: Service | F56: Customer Service | G56: Customer Service and Support | H56: Customer Operations | K56: Order-to-Cash (O2C) | O56: THB | Q56: 5cf23d09-5d76-4de9-87f4-9ff08fd96677
B57: =_xlfn.CONCAT(Capabilities[[#This Row],[Column1]],"-",Capabilities[[#This Row],[Level 1]],"-",Capabilities[[#This Row],[Level 2]],"-",Capabilities[[#This Row],[Level 3]]) -> 4202-Customer Service-Customer Service Strategy and Planning- | C57: 4202 | D57: BusinessCapability | E57: Service | F57: Customer Service | G57: Customer Service Strategy and Planning | J57: Developing and implementing tactics to enhance customer satisfaction, communication, and support processes for improved service delivery. | K57: Customer Service and Support | O57: THB, ALMO | Q57: 1334f529-1890-491a-90ac-ec91711d6427
B58: =_xlfn.CONCAT(Capabilities[[#This Row],[Column1]],"-",Capabilities[[#This Row],[Level 1]],"-",Capabilities[[#This Row],[Level 2]],"-",Capabilities[[#This Row],[Level 3]]) -> 4214-Customer Service-Customer Service Strategy and Planning-Customer Service Analytics | C58: 4214 | D58: BusinessCapability | E58: Service | F58: Customer Service | G58: Customer Service Strategy and Planning | H58: Customer Service Analytics | I58: Systems of Commodity | J58: Utilizes data-driven insights to enhance service delivery, optimize resources, and improve overall customer satisfaction and engagement. | K58: Customer Service and Support | O58: THG, THB | Q58: 9ae96f4a-e636-4c13-ba13-c5d373bdd3db
B59: =_xlfn.CONCAT(Capabilities[[#This Row],[Column1]],"-",Capabilities[[#This Row],[Level 1]],"-",Capabilities[[#This Row],[Level 2]],"-",Capabilities[[#This Row],[Level 3]]) -> 4215-Customer Service-Customer Service Strategy and Planning-Customer Service Planning and Forecasting | C59: 4215 | D59: BusinessCapability | E59: Service | F59: Customer Service | G59: Customer Service Strategy and Planning | H59: Customer Service Planning and Forecasting | I59: Systems of Commodity | J59: Developing systematic approaches for anticipating customer needs and optimizing resources to enhance service delivery and satisfaction. | K59: Customer Service and Support | O59: THG, THB | Q59: 84cd4380-d295-4220-8d54-97b5a1c23e1f
B60: =_xlfn.CONCAT(Capabilities[[#This Row],[Column1]],"-",Capabilities[[#This Row],[Level 1]],"-",Capabilities[[#This Row],[Level 2]],"-",Capabilities[[#This Row],[Level 3]]) -> 4216-Customer Service-Customer Service Strategy and Planning-Customer Service Strategy Management | C60: 4216 | D60: BusinessCapability | E60: Service | F60: Customer Service | G60: Customer Service Strategy and Planning | H60: Customer Service Strategy Management | I60: Systems of Commodity | J60: Develops and implements strategic frameworks to enhance customer service effectiveness and align it with organizational goals. | K60: Customer Service and Support | O60: THG, THB | Q60: ec1afd7b-a87e-4a96-9589-df7c0d551ddd
B61: =_xlfn.CONCAT(Capabilities[[#This Row],[Column1]],"-",Capabilities[[#This Row],[Level 1]],"-",Capabilities[[#This Row],[Level 2]],"-",Capabilities[[#This Row],[Level 3]]) -> 4200-Customer Service-- | C61: 4200 | D61: BusinessCapability | E61: Service | F61: Customer Service | J61: Focused on delivering effective support, resolving issues, and enhancing client satisfaction through timely communication and problem-solving strategies. | K61: Customer Service and Support | Q61: cc324013-3f8d-4d21-8b27-27436540dd0c
B62: =_xlfn.CONCAT(Capabilities[[#This Row],[Column1]],"-",Capabilities[[#This Row],[Level 1]],"-",Capabilities[[#This Row],[Level 2]],"-",Capabilities[[#This Row],[Level 3]]) -> 1106-Digital Management-IT Strategy & Transformation-Enterprise Architecture | C62: 1106 | D62: BusinessCapability-Kamstrup | E62: Corporate Services | F62: Digital Management | G62: IT Strategy & Transformation | H62: Enterprise Architecture | I62: Systems of Commodity | J62: Facilitates alignment of IT infrastructure with business goals, ensuring optimal performance and strategic planning for future technology integration. | K62: N/A | O62: FRFS | Q62: a6e0346d-f945-492a-90d8-01952be4baca
B63: =_xlfn.CONCAT(Capabilities[[#This Row],[Column1]],"-",Capabilities[[#This Row],[Level 1]],"-",Capabilities[[#This Row],[Level 2]],"-",Capabilities[[#This Row],[Level 3]]) -> 1107-Digital Management-IT Strategy & Transformation-IT Project Management | C63: 1107 | D63: BusinessCapability-Kamstrup | E63: Corporate Services | F63: Digital Management | G63: IT Strategy & Transformation | H63: IT Project Management | I63: Systems of Commodity | J63: Oversees planning, execution, and monitoring of IT projects to ensure alignment with business objectives and efficient resource utilization. | K63: N/A | O63: BCAR | Q63: 2823b60b-e7f9-42ac-9104-f6a168ffbb72
B64: =_xlfn.CONCAT(Capabilities[[#This Row],[Column1]],"-",Capabilities[[#This Row],[Level 1]],"-",Capabilities[[#This Row],[Level 2]],"-",Capabilities[[#This Row],[Level 3]]) -> 1109-Digital Management-IT Strategy & Transformation-IT Strategy | C64: 1109 | D64: BusinessCapability-Kamstrup | E64: Corporate Services | F64: Digital Management | G64: IT Strategy & Transformation | H64: IT Strategy | I64: Systems of Differentiation | J64: Develops and aligns IT strategies with business goals, optimizing resource allocation and enhancing organizational efficiency for sustainable growth. | K64: N/A | O64: BCAR | Q64: 4192274b-e6bc-4b9b-bb1a-3106fb3ee8d9
B65: =_xlfn.CONCAT(Capabilities[[#This Row],[Column1]],"-",Capabilities[[#This Row],[Level 1]],"-",Capabilities[[#This Row],[Level 2]],"-",Capabilities[[#This Row],[Level 3]]) -> 4504-Digital Management-IT Strategy & Transformation- | C65: 4504 | D65: BusinessCapability-Kamstrup | E65: Corporate Services | F65: Digital Management | G65: IT Strategy & Transformation | K65: N/A | Q65: f41d6919-b965-49b3-8866-91d5207eacd7
B66: =_xlfn.CONCAT(Capabilities[[#This Row],[Column1]],"-",Capabilities[[#This Row],[Level 1]],"-",Capabilities[[#This Row],[Level 2]],"-",Capabilities[[#This Row],[Level 3]]) -> 4500-Digital Management-- | C66: 4500 | D66: BusinessCapability-Kamstrup | E66: Corporate Services | F66: Digital Management | J66: Facilitates strategic alignment of IT resources with business objectives, ensuring efficient operation and optimizing technology investments. | K66: N/A | Q66: 678c2af0-3242-4875-a6b4-a84106ba4640
B67: =_xlfn.CONCAT(Capabilities[[#This Row],[Column1]],"-",Capabilities[[#This Row],[Level 1]],"-",Capabilities[[#This Row],[Level 2]],"-",Capabilities[[#This Row],[Level 3]]) -> 4507-Digital Management -Business Engagement- | C67: 4507 | D67: BusinessCapability-Kamstrup | E67: Corporate Services | F67: Digital Management | G67: Business Engagement | I67: Systems of Commodity | J67: Facilitate collaboration between IT and business functions. | K67: N/A | Q67: c4994766-8d0e-4f0b-b843-cea09e811391
B68: =_xlfn.CONCAT(Capabilities[[#This Row],[Column1]],"-",Capabilities[[#This Row],[Level 1]],"-",Capabilities[[#This Row],[Level 2]],"-",Capabilities[[#This Row],[Level 3]]) -> 4508-Digital Management -Business Engagement-(IT) Business Change Management | C68: 4508 | D68: BusinessCapability-Kamstrup | E68: Corporate Services | F68: Digital Management | G68: Business Engagement | H68: (IT) Business Change Management | I68: Systems of Commodity | J68: Support change initiatives through communication, training, and adoption planning. | K68: N/A | Q68: cf0c088e-7fe1-4f69-8333-2f3a17bbd3d7
B69: =_xlfn.CONCAT(Capabilities[[#This Row],[Column1]],"-",Capabilities[[#This Row],[Level 1]],"-",Capabilities[[#This Row],[Level 2]],"-",Capabilities[[#This Row],[Level 3]]) -> 4509-Digital Management -Business Engagement-(IT) Business Continuity Management | C69: 4509 | D69: BusinessCapability-Kamstrup | E69: Corporate Services | F69: Digital Management | G69: Business Engagement | H69: (IT) Business Continuity Management | I69: Systems of Commodity | J69: Ensure critical IT services can continue during disruptions. | K69: N/A | Q69: c10a0f2d-26e5-4a94-b0ce-ba341826cf88
B70: =_xlfn.CONCAT(Capabilities[[#This Row],[Column1]],"-",Capabilities[[#This Row],[Level 1]],"-",Capabilities[[#This Row],[Level 2]],"-",Capabilities[[#This Row],[Level 3]]) -> 4510-Digital Management -Business Engagement-Business Relationship Management | C70: 4510 | D70: BusinessCapability-Kamstrup | E70: Corporate Services | F70: Digital Management | G70: Business Engagement | H70: Business Relationship Management | I70: Systems of Commodity | J70: Manage relationships with business units to align IT services. | K70: N/A | Q70: 40352706-22d3-4f03-bb10-43db1fe9b4b0
B71: =_xlfn.CONCAT(Capabilities[[#This Row],[Column1]],"-",Capabilities[[#This Row],[Level 1]],"-",Capabilities[[#This Row],[Level 2]],"-",Capabilities[[#This Row],[Level 3]]) -> 4511-Digital Management -Business Engagement-Customer insights (new) | C71: 4511 | D71: BusinessCapability-Kamstrup | E71: Corporate Services | F71: Digital Management | G71: Business Engagement | H71: Customer insights (new) | I71: Systems of Commodity | J71: Capture and analyze end-user feedback to inform IT and product decisions. | K71: N/A | Q71: c664487d-75aa-482b-91ab-9a50ddb278a4
B72: =_xlfn.CONCAT(Capabilities[[#This Row],[Column1]],"-",Capabilities[[#This Row],[Level 1]],"-",Capabilities[[#This Row],[Level 2]],"-",Capabilities[[#This Row],[Level 3]]) -> 4512-Digital Management -Business Engagement-Product Adoption & Training | C72: 4512 | D72: BusinessCapability-Kamstrup | E72: Corporate Services | F72: Digital Management | G72: Business Engagement | H72: Product Adoption & Training | I72: Systems of Commodity | J72: Drive user adoption through onboarding and education. | K72: N/A | Q72: 0ddd98a5-cfeb-45d7-bad4-887947fea6d4
B73: =_xlfn.CONCAT(Capabilities[[#This Row],[Column1]],"-",Capabilities[[#This Row],[Level 1]],"-",Capabilities[[#This Row],[Level 2]],"-",Capabilities[[#This Row],[Level 3]]) -> 4513-Digital Management -Business Engagement-Product Design | C73: 4513 | D73: BusinessCapability-Kamstrup | E73: Corporate Services | F73: Digital Management | G73: Business Engagement | H73: Product Design | I73: Systems of Commodity | J73: Collaborate with stakeholders to define user-centric IT solutions. | K73: N/A | Q73: 0c01311a-bf81-48da-a9a9-2e65f468f67f
B74: =_xlfn.CONCAT(Capabilities[[#This Row],[Column1]],"-",Capabilities[[#This Row],[Level 1]],"-",Capabilities[[#This Row],[Level 2]],"-",Capabilities[[#This Row],[Level 3]]) -> 4514-Digital Management -Business Engagement-Product management | C74: 4514 | D74: BusinessCapability-Kamstrup | E74: Corporate Services | F74: Digital Management | G74: Business Engagement | H74: Product management | I74: Systems of Commodity | J74: Oversee the lifecycle, performance, and roadmap of IT products. | K74: N/A | Q74: 787ebe18-0e09-41e9-8659-79349506c35f
B75: =_xlfn.CONCAT(Capabilities[[#This Row],[Column1]],"-",Capabilities[[#This Row],[Level 1]],"-",Capabilities[[#This Row],[Level 2]],"-",Capabilities[[#This Row],[Level 3]]) -> 4522-Digital Management -Information Security- | C75: 4522 | D75: BusinessCapability-Kamstrup | E75: Corporate Services | F75: Digital Management | G75: Information Security | I75: Systems of Commodity | J75: Protect the organization's information assets against threats. Ensures alignment of security policies, risk management, and regulatory compliance to protect data and privacy effectively. | K75: N/A | O75: PEDN | Q75: 18923300-7cbb-4c5e-b485-d7f3aac4a194
B76: =_xlfn.CONCAT(Capabilities[[#This Row],[Column1]],"-",Capabilities[[#This Row],[Level 1]],"-",Capabilities[[#This Row],[Level 2]],"-",Capabilities[[#This Row],[Level 3]]) -> 4523-Digital Management -Information Security-Cyber Security | C76: 4523 | D76: BusinessCapability-Kamstrup | E76: Corporate Services | F76: Digital Management | G76: Information Security | H76: Cyber Security | I76: Systems of Commodity | J76: Defend digital infrastructure from cyberattacks. This capability ensures organizations manage cybersecurity risks, protect data, and comply with privacy regulations effectively and efficiently. | K76: N/A | O76: PEDN | Q76: 4ba14386-0bce-4124-9b3b-256db6575869
B77: =_xlfn.CONCAT(Capabilities[[#This Row],[Column1]],"-",Capabilities[[#This Row],[Level 1]],"-",Capabilities[[#This Row],[Level 2]],"-",Capabilities[[#This Row],[Level 3]]) -> 4524-Digital Management -Information Security-Information Security Management System | C77: 4524 | D77: BusinessCapability-Kamstrup | E77: Corporate Services | F77: Digital Management | G77: Information Security | H77: Information Security Management System | I77: Systems of Commodity | J77: Govern security policies, standards, and practices. | K77: N/A | O77: PEDN | Q77: b9d0bfa5-ec7c-42da-a550-3c3e325ee1f9
B78: =_xlfn.CONCAT(Capabilities[[#This Row],[Column1]],"-",Capabilities[[#This Row],[Level 1]],"-",Capabilities[[#This Row],[Level 2]],"-",Capabilities[[#This Row],[Level 3]]) -> 4525-Digital Management -Information Security-Risk Management | C78: 4525 | D78: BusinessCapability-Kamstrup | E78: Corporate Services | F78: Digital Management | G78: Information Security | H78: Risk Management | I78: Systems of Commodity | J78: Identify, assess, and mitigate information security risks. | K78: N/A | O78: PEDN | Q78: 82a50809-4081-433d-bc7f-a798c5f4365a
B79: =_xlfn.CONCAT(Capabilities[[#This Row],[Column1]],"-",Capabilities[[#This Row],[Level 1]],"-",Capabilities[[#This Row],[Level 2]],"-",Capabilities[[#This Row],[Level 3]]) -> 4526-Digital Management -Information Security-Security Architecture | C79: 4526 | D79: BusinessCapability-Kamstrup | E79: Corporate Services | F79: Digital Management | G79: Information Security | H79: Security Architecture | I79: Systems of Commodity | J79: Design secure IT systems and networks. | K79: N/A | O79: PEDN | Q79: 27c5ea99-3621-46fc-8a8f-bc672dcb5b9d
B80: =_xlfn.CONCAT(Capabilities[[#This Row],[Column1]],"-",Capabilities[[#This Row],[Level 1]],"-",Capabilities[[#This Row],[Level 2]],"-",Capabilities[[#This Row],[Level 3]]) -> 4527-Digital Management -Information Security-Security Awareness | C80: 4527 | D80: BusinessCapability-Kamstrup | E80: Corporate Services | F80: Digital Management | G80: Information Security | H80: Security Awareness | I80: Systems of Commodity | J80: Educate employees on security best practices and threats. | K80: N/A | O80: PEDN | Q80: 2a07d15f-ea4f-4459-b172-639dfc351f09
B81: =_xlfn.CONCAT(Capabilities[[#This Row],[Column1]],"-",Capabilities[[#This Row],[Level 1]],"-",Capabilities[[#This Row],[Level 2]],"-",Capabilities[[#This Row],[Level 3]]) -> 4528-Digital Management -Information Security-Threat & Vunerability Management | C81: 4528 | D81: BusinessCapability-Kamstrup | E81: Corporate Services | F81: Digital Management | G81: Information Security | H81: Threat & Vunerability Management | I81: Systems of Commodity | J81: Identify and remediate security weaknesses. | K81: N/A | O81: PEDN | Q81: 39256722-00c6-4d59-84cf-4e6c6d889133
B82: =_xlfn.CONCAT(Capabilities[[#This Row],[Column1]],"-",Capabilities[[#This Row],[Level 1]],"-",Capabilities[[#This Row],[Level 2]],"-",Capabilities[[#This Row],[Level 3]]) -> 4515-Digital Management -IT Strategy & Transformation-FinOps | C82: 4515 | D82: BusinessCapability-Kamstrup | E82: Corporate Services | F82: Digital Management | G82: IT Strategy & Transformation | H82: FinOps | I82: Systems of Commodity | J82: Optimize cloud financial operations and value realization. | K82: N/A | Q82: 6481fcc5-0b16-4907-bd7b-041cc41673a6
B83: =_xlfn.CONCAT(Capabilities[[#This Row],[Column1]],"-",Capabilities[[#This Row],[Level 1]],"-",Capabilities[[#This Row],[Level 2]],"-",Capabilities[[#This Row],[Level 3]]) -> 4516-Digital Management -IT Strategy & Transformation-IT Financial Management | C83: 4516 | D83: BusinessCapability-Kamstrup | E83: Corporate Services | F83: Digital Management | G83: IT Strategy & Transformation | H83: IT Financial Management | I83: Systems of Commodity | J83: Budget, monitor, and control IT expenditures and ROI. | K83: N/A | Q83: f31900ab-cb24-4008-b46e-0e24de109a10
B84: =_xlfn.CONCAT(Capabilities[[#This Row],[Column1]],"-",Capabilities[[#This Row],[Level 1]],"-",Capabilities[[#This Row],[Level 2]],"-",Capabilities[[#This Row],[Level 3]]) -> 4517-Digital Management -IT Strategy & Transformation-IT Governance | C84: 4517 | D84: BusinessCapability-Kamstrup | E84: Corporate Services | F84: Digital Management | G84: IT Strategy & Transformation | H84: IT Governance | I84: Systems of Commodity | J84: Establish IT policies, controls, and compliance mechanisms. | K84: N/A | Q84: e24ced8c-adb6-4c6c-b68d-0e1ef365a0c6
B85: =_xlfn.CONCAT(Capabilities[[#This Row],[Column1]],"-",Capabilities[[#This Row],[Level 1]],"-",Capabilities[[#This Row],[Level 2]],"-",Capabilities[[#This Row],[Level 3]]) -> 4518-Digital Management -IT Strategy & Transformation-IT M&A | C85: 4518 | D85: BusinessCapability-Kamstrup | E85: Corporate Services | F85: Digital Management | G85: IT Strategy & Transformation | H85: IT M&A | I85: Systems of Commodity | J85: Manage technology aspects of mergers, acquisitions, and divestitures. | K85: N/A | Q85: 9aedab8b-a9c7-4bcd-ab13-e10cea19b0f7
B86: =_xlfn.CONCAT(Capabilities[[#This Row],[Column1]],"-",Capabilities[[#This Row],[Level 1]],"-",Capabilities[[#This Row],[Level 2]],"-",Capabilities[[#This Row],[Level 3]]) -> 4519-Digital Management -IT Strategy & Transformation-IT Performance Management | C86: 4519 | D86: BusinessCapability-Kamstrup | E86: Corporate Services | F86: Digital Management | G86: IT Strategy & Transformation | H86: IT Performance Management | I86: Systems of Commodity | J86: Track and optimize IT performance metrics and outcomes. | K86: N/A | Q86: 8c24fa55-0e7e-47db-91a7-da06ea880c80
B87: =_xlfn.CONCAT(Capabilities[[#This Row],[Column1]],"-",Capabilities[[#This Row],[Level 1]],"-",Capabilities[[#This Row],[Level 2]],"-",Capabilities[[#This Row],[Level 3]]) -> 4520-Digital Management -IT Strategy & Transformation-IT Portfolio Management | C87: 4520 | D87: BusinessCapability-Kamstrup | E87: Corporate Services | F87: Digital Management | G87: IT Strategy & Transformation | H87: IT Portfolio Management | I87: Systems of Commodity | J87: Oversee and prioritize the full portfolio of IT initiatives and assets. | K87: N/A | Q87: 95dc9d7f-62ee-4ab2-bc95-529c9f131652
B88: =_xlfn.CONCAT(Capabilities[[#This Row],[Column1]],"-",Capabilities[[#This Row],[Level 1]],"-",Capabilities[[#This Row],[Level 2]],"-",Capabilities[[#This Row],[Level 3]]) -> 4547-Digital Platform and Operations-AI, Data & Analytics- | C88: 4547 | D88: BusinessCapability-Kamstrup | E88: Corporate Services | F88: Digital Platform and Operations | G88: AI, Data & Analytics | I88: Systems of Commodity | J88: Enable data-driven decisions and automation through structured data use and AI. | K88: N/A | Q88: 046043f5-a0f6-488e-a959-678e1e9d6d67
B89: =_xlfn.CONCAT(Capabilities[[#This Row],[Column1]],"-",Capabilities[[#This Row],[Level 1]],"-",Capabilities[[#This Row],[Level 2]],"-",Capabilities[[#This Row],[Level 3]]) -> 4548-Digital Platform and Operations-AI, Data & Analytics-AI | C89: 4548 | D89: BusinessCapability-Kamstrup | E89: Corporate Services | F89: Digital Platform and Operations | G89: AI, Data & Analytics | H89: AI | I89: Systems of Differentiation | J89: Develop and deploy artificial intelligence solutions to automate and enhance operations. | K89: N/A | Q89: 3f881860-1b40-44b0-983f-e83795e00e54
B90: =_xlfn.CONCAT(Capabilities[[#This Row],[Column1]],"-",Capabilities[[#This Row],[Level 1]],"-",Capabilities[[#This Row],[Level 2]],"-",Capabilities[[#This Row],[Level 3]]) -> 4549-Digital Platform and Operations-AI, Data & Analytics-BI Enablement | C90: 4549 | D90: BusinessCapability-Kamstrup | E90: Corporate Services | F90: Digital Platform and Operations | G90: AI, Data & Analytics | H90: BI Enablement | I90: Systems of Differentiation | J90: Provide tools and platforms for business intelligence and reporting. Establish criteria for key performance indicators and generate insightful reports to guide data-driven decision-making. | K90: N/A | Q90: a360e238-8377-450b-a8fb-30f7097ed38d
B91: =_xlfn.CONCAT(Capabilities[[#This Row],[Column1]],"-",Capabilities[[#This Row],[Level 1]],"-",Capabilities[[#This Row],[Level 2]],"-",Capabilities[[#This Row],[Level 3]]) -> 4550-Digital Platform and Operations-AI, Data & Analytics-Data Architecture | C91: 4550 | D91: BusinessCapability-Kamstrup | E91: Corporate Services | F91: Digital Platform and Operations | G91: AI, Data & Analytics | H91: Data Architecture | I91: Systems of Commodity | J91: Design how data is structured, stored, and accessed across systems. | K91: N/A | Q91: eceb9f70-8c7f-45eb-83dd-5b572d6c1454
B92: =_xlfn.CONCAT(Capabilities[[#This Row],[Column1]],"-",Capabilities[[#This Row],[Level 1]],"-",Capabilities[[#This Row],[Level 2]],"-",Capabilities[[#This Row],[Level 3]]) -> 4551-Digital Platform and Operations-AI, Data & Analytics-Data Governance | C92: 4551 | D92: BusinessCapability-Kamstrup | E92: Corporate Services | F92: Digital Platform and Operations | G92: AI, Data & Analytics | H92: Data Governance | I92: Systems of Commodity | J92: Ensures data quality, compliance, and accessibility through structured policies, processes, and roles for effective data handling and stewardship. | K92: N/A | Q92: 107ec7e5-c439-4059-903d-ec8fa6e52c2d
B93: =_xlfn.CONCAT(Capabilities[[#This Row],[Column1]],"-",Capabilities[[#This Row],[Level 1]],"-",Capabilities[[#This Row],[Level 2]],"-",Capabilities[[#This Row],[Level 3]]) -> 4552-Digital Platform and Operations-AI, Data & Analytics-Data Management | C93: 4552 | D93: BusinessCapability-Kamstrup | E93: Corporate Services | F93: Digital Platform and Operations | G93: AI, Data & Analytics | H93: Data Management | I93: Systems of Commodity | J93: Control the lifecycle of data from creation to deletion. Ensure effective data storage, retrieval, integration, and governance to support organizational decision-making and enhance operational efficiency. | K93: N/A | Q93: 431926e8-a29b-46d9-b4b1-0f53ddec4cdd
B94: =_xlfn.CONCAT(Capabilities[[#This Row],[Column1]],"-",Capabilities[[#This Row],[Level 1]],"-",Capabilities[[#This Row],[Level 2]],"-",Capabilities[[#This Row],[Level 3]]) -> 4553-Digital Platform and Operations-AI, Data & Analytics-Data Processing & Modeling | C94: 4553 | D94: BusinessCapability-Kamstrup | E94: Corporate Services | F94: Digital Platform and Operations | G94: AI, Data & Analytics | H94: Data Processing & Modeling | I94: Systems of Commodity | J94: Clean, transform, and model data for analysis and use in systems and ensure compliance with regulatory standards. | K94: N/A | Q94: ecea4609-60da-4df3-bc6d-dd75f5bd6989
B95: =_xlfn.CONCAT(Capabilities[[#This Row],[Column1]],"-",Capabilities[[#This Row],[Level 1]],"-",Capabilities[[#This Row],[Level 2]],"-",Capabilities[[#This Row],[Level 3]]) -> 4554-Digital Platform and Operations-AI, Data & Analytics-Data Privacy & Compliance | C95: 4554 | D95: BusinessCapability-Kamstrup | E95: Corporate Services | F95: Digital Platform and Operations | G95: AI, Data & Analytics | H95: Data Privacy & Compliance | I95: Systems of Commodity | J95: Ensure compliance with data protection laws (e.g., GDPR). | K95: N/A | Q95: 1e8286bd-00ca-4bf5-b4ab-72372d58198e
B96: =_xlfn.CONCAT(Capabilities[[#This Row],[Column1]],"-",Capabilities[[#This Row],[Level 1]],"-",Capabilities[[#This Row],[Level 2]],"-",Capabilities[[#This Row],[Level 3]]) -> 4555-Digital Platform and Operations-AI, Data & Analytics-Data Analytics | C96: 4555 | D96: BusinessCapability-Kamstrup | E96: Corporate Services | F96: Digital Platform and Operations | G96: AI, Data & Analytics | H96: Data Analytics | I96: Systems of Differentiation | J96: Analyze data to generate insights for strategic and operational decisions. | K96: N/A | Q96: fc5a36db-ab09-41df-b186-0b545e46c696
B97: =_xlfn.CONCAT(Capabilities[[#This Row],[Column1]],"-",Capabilities[[#This Row],[Level 1]],"-",Capabilities[[#This Row],[Level 2]],"-",Capabilities[[#This Row],[Level 3]]) -> 4556-Digital Platform and Operations-AI, Data & Analytics-Master Data Management | C97: 4556 | D97: BusinessCapability-Kamstrup | E97: Corporate Services | F97: Digital Platform and Operations | G97: AI, Data & Analytics | H97: Master Data Management | I97: Systems of Commodity | J97: Ensure consistent and accurate master data across systems and functions. | K97: N/A | Q97: 669a9bbe-7d63-4ba1-bc1c-0c3abfe324c5
B98: =_xlfn.CONCAT(Capabilities[[#This Row],[Column1]],"-",Capabilities[[#This Row],[Level 1]],"-",Capabilities[[#This Row],[Level 2]],"-",Capabilities[[#This Row],[Level 3]]) -> 1101-Digital Platform and Operations-AI, Data & Analytics-Gather Data | C98: 1101 | D98: BusinessCapability-Kamstrup | E98: Corporate Services | F98: Digital Platform and Operations | G98: AI, Data & Analytics | H98: Gather Data | I98: Systems of Commodity | J98: Collect and organize data from various sources to facilitate informed decision-making and enhance organizational efficiency. | K98: N/A | Q98: ce0671ee-d2a8-477c-9dc4-87a88d0a4381
B99: =_xlfn.CONCAT(Capabilities[[#This Row],[Column1]],"-",Capabilities[[#This Row],[Level 1]],"-",Capabilities[[#This Row],[Level 2]],"-",Capabilities[[#This Row],[Level 3]]) -> 4557-Digital Platform and Operations-Digital Workplace & Infrastructure Development- | C99: 4557 | D99: BusinessCapability-Kamstrup | E99: Corporate Services | F99: Digital Platform and Operations | G99: Digital Workplace & Infrastructure Development | I99: Systems of Commodity | J99: Build and maintain the IT foundation and tools that support employee productivity. | K99: N/A | Q99: 43c87b35-bec2-44f1-938a-6cf29709372c
B100: =_xlfn.CONCAT(Capabilities[[#This Row],[Column1]],"-",Capabilities[[#This Row],[Level 1]],"-",Capabilities[[#This Row],[Level 2]],"-",Capabilities[[#This Row],[Level 3]]) -> 4558-Digital Platform and Operations-Digital Workplace & Infrastructure Development-Communication & Collaboration | C100: 4558 | D100: BusinessCapability-Kamstrup | E100: Corporate Services | F100: Digital Platform and Operations | G100: Digital Workplace & Infrastructure Development | H100: Communication & Collaboration | I100: Systems of Commodity | J100: Provide tools and platforms for messaging, conferencing, and teamwork. | K100: N/A | Q100: cd56ec16-10b5-4b68-aab1-52175dbfb58b
B101: =_xlfn.CONCAT(Capabilities[[#This Row],[Column1]],"-",Capabilities[[#This Row],[Level 1]],"-",Capabilities[[#This Row],[Level 2]],"-",Capabilities[[#This Row],[Level 3]]) -> 4559-Digital Platform and Operations-Digital Workplace & Infrastructure Development-Devices & Print | C101: 4559 | D101: BusinessCapability-Kamstrup | E101: Corporate Services | F101: Digital Platform and Operations | G101: Digital Workplace & Infrastructure Development | H101: Devices & Print | I101: Systems of Commodity | J101: Manage endpoints, print services, and user equipment lifecycle. | K101: N/A | Q101: efd1a5ee-503c-4dcf-a40d-76762246dc45
B102: =_xlfn.CONCAT(Capabilities[[#This Row],[Column1]],"-",Capabilities[[#This Row],[Level 1]],"-",Capabilities[[#This Row],[Level 2]],"-",Capabilities[[#This Row],[Level 3]]) -> 4561-Digital Platform and Operations-Digital Workplace & Infrastructure Development-Infrastructure Architecture | C102: 4561 | D102: BusinessCapability-Kamstrup | E102: Corporate Services | F102: Digital Platform and Operations | G102: Digital Workplace & Infrastructure Development | H102: Infrastructure Architecture | I102: Systems of Commodity | J102: Design infrastructure solutions (on-prem, cloud, hybrid) to support business applications. | K102: N/A | Q102: 76ad8e2f-9a04-43fa-be28-2668ac9b1df7
B103: =_xlfn.CONCAT(Capabilities[[#This Row],[Column1]],"-",Capabilities[[#This Row],[Level 1]],"-",Capabilities[[#This Row],[Level 2]],"-",Capabilities[[#This Row],[Level 3]]) -> 4562-Digital Platform and Operations-Digital Workplace & Infrastructure Development-Infrastructure Development | C103: 4562 | D103: BusinessCapability-Kamstrup | E103: Corporate Services | F103: Digital Platform and Operations | G103: Digital Workplace & Infrastructure Development | H103: Infrastructure Development | I103: Systems of Commodity | J103: Build, deploy, and scale foundational IT infrastructure. | K103: N/A | Q103: ae39589f-e7d6-42fa-90af-e6d570626ee2
...

Sheet O-Organization
B1: Level 2 | C1: Level 3 | D1: Level 1 | E1: Level 4 - Kan ikke anvendes i denne model pga. Key
B2: Organization | C2: Business Area | D2: Country | E2: Team | I2: CountryCode | J2: Country | N2: DepartmentTeam
B3: Sales & Marketing | C3: Sales & Marketing | D3: Denmark | I3: AT10 | J3: Austria | N3: Business Development
B4: Sales & Marketing | C4: CH_Sales & Marketing | D4: Switzerland | I4: CA10 | J4: Canada | N4: Project Management
B5: Customer Service | C5: CH_Customer Services (Project & Support) | D5: Switzerland | I5: CH10 | J5: Switzerland | N5: H/C Meters
B6: Sales & Marketing | C6: ES_Sales & Marketing | D6: Spain | I6: CN10 | J6: China | N6: Concentrators
B7: Customer Service | C7: ES_Customer Service | D7: Spain | I7: DE10 | J7: Germany | N7: Tech. Lead
B8: Sales & Marketing | C8: FR_Sales & Marketing | D8: France | I8: DK10 | J8: Denmark | N8: Embeded Software
B9: Sales & Marketing | C9: NL_Sales & Marketing | D9: Netherlands | I9: ES10 | J9: Spain | N9: Hardware
B10: Sales & Marketing | C10: NO_Sales & Marketing | D10: Norway | I10: FI10 | J10: Finland | N10: FW
B11: Sales & Marketing | C11: SE_Sales & Marketing | D11: Sweden | G11: Create only Level2 | I11: FR10 | J11: France | N11: Tech
B12: Customer Service | C12: NO_Customer Service | D12: Norway | G12: Create only Level2 | I12: FR10_2 | J12: France (FR network) | N12: Mech
B13: Supply Chain | C13: Supply Chain | D13: Denmark | G13: Create only Level2 | I13: IT10 | J13: Italy | N13: Tools & Apps
B14: Digitalization | C14: DK_Digitalization_Customer Operations | D14: Denmark | G14: Create only Level2 | I14: MY10 | J14: Malaysia | N14: TPM
B15: Digitalization | C15: DK_Digitalization_ Digital Business Development & Transformation | D15: Denmark | G15: Create only Level2 | I15: NL10 | J15: Netherlands | N15: Compliance
B16: Digitalization | C16: DK_Digitalization_EA, Infrastructure and Platforms | D16: Denmark | G16: Create only Level2 | I16: NO10 | J16: Norway | N16: MPM
B17: Digitalization | C17: DK_Digitalization_ECS | D17: Denmark | G17: Create only Level2 | I17: PL10 | J17: Poland | N17: PPM
B18: Digitalization | C18: DK_Digitalization_Kamstrup Solutions | D18: Denmark | G18: Create only Level2 | I18: SE10 | J18: Sweden | N18: DSI
B19: Digitalization | C19: DK_Digitalization_Digitalization | D19: Denmark | G19: Create only Level2 | I19: US10 | J19: United States | N19: BA
B20: Digitalization | C20: FR_Digitalization | D20: France | G20: Create only Level2 | I20: All | J20: All | N20: IOT Solutions
B21: Digitalization | C21: ES_Digitalization | D21: Spain | G21: Create only Level2 | N21: Product Service
B22: Digitalization | C22: SE_Digitalization | D22: Sweden | G22: Create only Level2 | N22: Sourcing
B23: Digitalization | C23: US_Digitalization | D23: United States | G23: Create only Level2 | N23: Manufactoring Software
B24: Executive Management office | C24: DK_Executive Management office_Executive Management office | D24: Denmark | G24: Create only Level2 | N24: Software
B25: Facility | C25: DK_Facility | D25: Denmark | G25: Create only Level2 | N25: Data Sceince
B26: Facility | C26: US_Facility | D26: United States | G26: Create only Level2 | N26: Sales
B27: Finance | C27: DK_Finance | D27: Denmark | G27: Create only Level2 | N27: Internal Sales
B28: Finance | C28: MY_Finance | D28: Malaysia | G28: Create only Level2 | N28: Sales Operation
B29: Finance | C29: NL_Finance | D29: Netherlands | G29: Create only Level2 | N29: Customer Service
B30: Finance | C30: NO_Finance | D30: Norway | G30: Create only Level2 | N30: Customer Service/Project Management
B31: Finance | C31: PL_Finance | D31: Poland | G31: Create only Level2 | N31: Marketing
B32: Finance | C32: SE_Finance | D32: Sweden | G32: Create only Level2 | N32: Metrology, Accreditation & Calibration
B33: Finance | C33: US_Finance | D33: United States | G33: Create only Level2 | N33: Quality
B34: Finance | C34: AT_Finance | D34: Austria | N34: Support
B35: Finance | C35: CA_Finance | D35: Canada | N35: Solutions
B36: Finance | C36: CH_Finance | D36: Switzerland | N36: Services
B37: Finance | C37: CN_Finance | D37: China | N37: Sustainability & Environment
B38: Finance | C38: DE_Finance | D38: Germany | N38: DK_Finance_ESG
B39: Finance | C39: ES_Finance | D39: Spain | N39: Production
B40: Finance | C40: FI_Finance | D40: Finland | N40: Bid Management
B41: Finance | C41: FR_Finance | D41: France | N41: Training
B42: Finance | C42: IT_Finance | D42: Italy | N42: Solution Management
B43: Commercial & Legal Services | C43: Commercial & Legal Services | D43: Denmark | N43: DK_Executive Management office_Executive Management office_Reception
B44: People & Culture | C44: DK_People & Culture | D44: Denmark | N44: DK_Digitalization_ECS_SEC OPS
B45: People & Culture | C45: ES_People & Culture | D45: Spain | N45: DK_Digitalization_ECS_Expert Service
... B68: Electricity | C68: Austria-Electricity-Electricity | D68: Austria | N68: ES_Digitalization_EA, Infrastructure and Platforms_Cloud and Platforms
B69: Electricity | C69: Sweden-Electricity-Electricity | D69: Sweden
B70: Electricity | C70: Electricity - Product Management | D70: Denmark
