Workbook

Sheet KamstrupData
B1: Active from date | C1: End date | D1: Chose the capability | E1: Auto fill Level 1 | F1: Auto fill Level 2 | G1: Auto fill Level 3 | H1: Not used | I1: Country code | J1: Business Area using/doing the capability | K1: Department or Team using/doing the capability | L1: Chose the application | M1: Auto fill application | N1: Evaluation of Gartner TIME for the application only in relation to this Capability | O1: Classifications for Business Criticality: Administrative Service Business Operational Business Critical Mission Critical. | P1: Business process applying to the capability | Q1: Value Stream applying to the process and application | R1: Value Stream order | S1: Projects involving the current Capability, Process and Application | T1: Comment reletad to the current row | U1: AUTO CALCULATION | V1: AUTO CALCULATION Link to organisation
B2: Dates | D2: B-Business Capability | I2: O-Organization | L2: A-Applications | P2: C-Business Context | S2: I-Initiative | T2: Comment | U2: Organisation
B4: FromDate | C4: EndDate | D4: IdLevel123 | E4: Capbility level 1 | F4: Capbility level 2 | G4: Capbility level 3 | H4: Capbility level 4 | I4: CountryCode | J4: Business Area | K4: DepartmentTeam | L4: NoApplication | M4: Application | N4: Gartner TIME | O4: Business Criticality | P4: NoProcess | Q4: Value Stream | R4: Value Stream Order | S4: Projects | T4: Comment | U4: ORG_Concat | V4: IdOrg
D5: 999-All-- | E5: =VLOOKUP(D5,'B-Business Capability'!B:H,5,FALSE) -> All | F5: =VLOOKUP(D5,'B-Business Capability'!B:H,6,FALSE) -> 0 | G5: =VLOOKUP(D5,'B-Business Capability'!B:H,7,FALSE) -> 0 | I5: AT10 | J5: All | L5: 299 - Microsoft Teams | M5: =VLOOKUP(L5,'A-Applications'!B:D,3,FALSE) -> Microsoft Teams | N5: Tolerate | O5: Business Operational | P5: P00-All-- | Q5: =VLOOKUP(KamstrupData[[#This Row],[IdLevel123]],'B-Business Capability'!B:L,10,FALSE) -> N/A | R5: =VLOOKUP(KamstrupData[[#This Row],[IdLevel123]],'B-Business Capability'!B:L,11,FALSE) -> 0 | U5: =_xlfn.CONCAT(KamstrupData[[#This Row],[CountryCode]],"_",KamstrupData[[#This Row],[Business Area]],"_",KamstrupData[[#This Row],[DepartmentTeam]]) -> AT10_All_ | V5: =VLOOKUP(KamstrupData[[#This Row],[ORG_Concat]],'O-Organization'!F:H,3,FALSE) -> 11147_AT10_All_All_
D6: 999-All-- | E6: =VLOOKUP(D6,'B-Business Capability'!B:H,5,FALSE) -> All | F6: =VLOOKUP(D6,'B-Business Capability'!B:H,6,FALSE) -> 0 | G6: =VLOOKUP(D6,'B-Business Capability'!B:H,7,FALSE) -> 0 | I6: AT10 | J6: All | L6: 308 - OneDrive | M6: =VLOOKUP(L6,'A-Applications'!B:D,3,FALSE) -> OneDrive | N6: Tolerate | O6: Business Operational | P6: P00-All-- | Q6: =VLOOKUP(KamstrupData[[#This Row],[IdLevel123]],'B-Business Capability'!B:L,10,FALSE) -> N/A | R6: =VLOOKUP(KamstrupData[[#This Row],[IdLevel123]],'B-Business Capability'!B:L,11,FALSE) -> 0 | U6: =_xlfn.CONCAT(KamstrupData[[#This Row],[CountryCode]],"_",KamstrupData[[#This Row],[Business Area]],"_",KamstrupData[[#This Row],[DepartmentTeam]]) -> AT10_All_ | V6: =VLOOKUP(KamstrupData[[#This Row],[ORG_Concat]],'O-Organization'!F:H,3,FALSE) -> 11147_AT10_All_All_
D7: 999-All-- | E7: =VLOOKUP(D7,'B-Business Capability'!B:H,5,FALSE) -> All | F7: =VLOOKUP(D7,'B-Business Capability'!B:H,6,FALSE) -> 0 | G7: =VLOOKUP(D7,'B-Business Capability'!B:H,7,FALSE) -> 0 | I7: AT10 | J7: All | L7: 428 - Microsoft Word | M7: =VLOOKUP(L7,'A-Applications'!B:D,3,FALSE) -> Microsoft Word | N7: Tolerate | O7: Business Operational | P7: P00-All-- | Q7: =VLOOKUP(KamstrupData[[#This Row],[IdLevel123]],'B-Business Capability'!B:L,10,FALSE) -> N/A | R7: =VLOOKUP(KamstrupData[[#This Row],[IdLevel123]],'B-Business Capability'!B:L,11,FALSE) -> 0 | U7: =_xlfn.CONCAT(KamstrupData[[#This Row],[CountryCode]],"_",KamstrupData[[#This Row],[Business Area]],"_",KamstrupData[[#This Row],[DepartmentTeam]]) -> AT10_All_ | V7: =VLOOKUP(KamstrupData[[#This Row],[ORG_Concat]],'O-Organization'!F:H,3,FALSE) -> 11147_AT10_All_All_
D8: 999-All-- | E8: =VLOOKUP(D8,'B-Business Capability'!B:H,5,FALSE) -> All | F8: =VLOOKUP(D8,'B-Business Capability'!B:H,6,FALSE) -> 0 | G8: =VLOOKUP(D8,'B-Business Capability'!B:H,7,FALSE) -> 0 | I8: AT10 | J8: All | L8: 429 - Microsoft Excel | M8: =VLOOKUP(L8,'A-Applications'!B:D,3,FALSE) -> Microsoft Excel | N8: Tolerate | O8: Business Operational | P8: P00-All-- | Q8: =VLOOKUP(KamstrupData[[#This Row],[IdLevel123]],'B-Business Capability'!B:L,10,FALSE) -> N/A | R8: =VLOOKUP(KamstrupData[[#This Row],[IdLevel123]],'B-Business Capability'!B:L,11,FALSE) -> 0 | U8: =_xlfn.CONCAT(KamstrupData[[#This Row],[CountryCode]],"_",KamstrupData[[#This Row],[Business Area]],"_",KamstrupData[[#This Row],[DepartmentTeam]]) -> AT10_All_ | V8: =VLOOKUP(KamstrupData[[#This Row],[ORG_Concat]],'O-Organization'!F:H,3,FALSE) -> 11147_AT10_All_All_
D9: 999-All-- | E9: =VLOOKUP(D9,'B-Business Capability'!B:H,5,FALSE) -> All | F9: =VLOOKUP(D9,'B-Business Capability'!B:H,6,FALSE) -> 0 | G9: =VLOOKUP(D9,'B-Business Capability'!B:H,7,FALSE) -> 0 | I9: AT10 | J9: All | L9: 430 - Microsoft Power Point | M9: =VLOOKUP(L9,'A-Applications'!B:D,3,FALSE) -> Microsoft Power Point | N9: Tolerate | O9: Business Operational | P9: P00-All-- | Q9: =VLOOKUP(KamstrupData[[#This Row],[IdLevel123]],'B-Business Capability'!B:L,10,FALSE) -> N/A | R9: =VLOOKUP(KamstrupData[[#This Row],[IdLevel123]],'B-Business Capability'!B:L,11,FALSE) -> 0 | U9: =_xlfn.CONCAT(KamstrupData[[#This Row],[CountryCode]],"_",KamstrupData[[#This Row],[Business Area]],"_",KamstrupData[[#This Row],[DepartmentTeam]]) -> AT10_All_ | V9: =VLOOKUP(KamstrupData[[#This Row],[ORG_Concat]],'O-Organization'!F:H,3,FALSE) -> 11147_AT10_All_All_
D10: 999-All-- | E10: =VLOOKUP(D10,'B-Business Capability'!B:H,5,FALSE) -> All | F10: =VLOOKUP(D10,'B-Business Capability'!B:H,6,FALSE) -> 0 | G10: =VLOOKUP(D10,'B-Business Capability'!B:H,7,FALSE) -> 0 | I10: AT10 | J10: All | L10: 431 - Microsoft Outlook | M10: =VLOOKUP(L10,'A-Applications'!B:D,3,FALSE) -> Microsoft Outlook | N10: Tolerate | O10: Business Operational | P10: P00-All-- | Q10: =VLOOKUP(KamstrupData[[#This Row],[IdLevel123]],'B-Business Capability'!B:L,10,FALSE) -> N/A | R10: =VLOOKUP(KamstrupData[[#This Row],[IdLevel123]],'B-Business Capability'!B:L,11,FALSE) -> 0 | U10: =_xlfn.CONCAT(KamstrupData[[#This Row],[CountryCode]],"_",KamstrupData[[#This Row],[Business Area]],"_",KamstrupData[[#This Row],[DepartmentTeam]]) -> AT10_All_ | V10: =VLOOKUP(KamstrupData[[#This Row],[ORG_Concat]],'O-Organization'!F:H,3,FALSE) -> 11147_AT10_All_All_
D11: 999-All-- | E11: =VLOOKUP(D11,'B-Business Capability'!B:H,5,FALSE) -> All | F11: =VLOOKUP(D11,'B-Business Capability'!B:H,6,FALSE) -> 0 | G11: =VLOOKUP(D11,'B-Business Capability'!B:H,7,FALSE) -> 0 | I11: AT10 | J11: All | L11: 483 - Microsoft OneNote | M11: =VLOOKUP(L11,'A-Applications'!B:D,3,FALSE) -> Microsoft OneNote | N11: Tolerate | O11: Administrative Service | P11: P00-All-- | Q11: =VLOOKUP(KamstrupData[[#This Row],[IdLevel123]],'B-Business Capability'!B:L,10,FALSE) -> N/A | R11: =VLOOKUP(KamstrupData[[#This Row],[IdLevel123]],'B-Business Capability'!B:L,11,FALSE) -> 0 | U11: =_xlfn.CONCAT(KamstrupData[[#This Row],[CountryCode]],"_",KamstrupData[[#This Row],[Business Area]],"_",KamstrupData[[#This Row],[DepartmentTeam]]) -> AT10_All_ | V11: =VLOOKUP(KamstrupData[[#This Row],[ORG_Concat]],'O-Organization'!F:H,3,FALSE) -> 11147_AT10_All_All_
D12: 1132-Finance-Financial Planning & Analysis-Cost Accounting_Plan | E12: =VLOOKUP(D12,'B-Business Capability'!B:H,5,FALSE) -> Finance | F12: =VLOOKUP(D12,'B-Business Capability'!B:H,6,FALSE) -> Financial Planning & Analysis | G12: =VLOOKUP(D12,'B-Business Capability'!B:H,7,FALSE) -> Cost Accounting_Plan | I12: AT10 | J12: AT_Customer Service | L12: 1 - IFS ERP | M12: =VLOOKUP(L12,'A-Applications'!B:D,3,FALSE) -> IFS ERP | N12: Tolerate | O12: Business Critical | P12: P18-Budget-- | Q12: =VLOOKUP(KamstrupData[[#This Row],[IdLevel123]],'B-Business Capability'!B:L,10,FALSE) -> N/A | R12: =VLOOKUP(KamstrupData[[#This Row],[IdLevel123]],'B-Business Capability'!B:L,11,FALSE) -> 0 | U12: =_xlfn.CONCAT(KamstrupData[[#This Row],[CountryCode]],"_",KamstrupData[[#This Row],[Business Area]],"_",KamstrupData[[#This Row],[DepartmentTeam]]) -> AT10_AT_Customer Service_ | V12: =VLOOKUP(KamstrupData[[#This Row],[ORG_Concat]],'O-Organization'!F:H,3,FALSE) -> 11025_AT10_Customer Service_AT_Customer Service_
D13: 1137-Finance-Settlements & Payments-Account Payables | E13: =VLOOKUP(D13,'B-Business Capability'!B:H,5,FALSE) -> Finance | F13: =VLOOKUP(D13,'B-Business Capability'!B:H,6,FALSE) -> Settlements & Payments | G13: =VLOOKUP(D13,'B-Business Capability'!B:H,7,FALSE) -> Account Payables | I13: AT10 | J13: AT_Finance | L13: 1 - IFS ERP | M13: =VLOOKUP(L13,'A-Applications'!B:D,3,FALSE) -> IFS ERP | N13: Tolerate | O13: Administrative Service | P13: P14-Accounting-SP14.1-Procure to Pay | Q13: =VLOOKUP(KamstrupData[[#This Row],[IdLevel123]],'B-Business Capability'!B:L,10,FALSE) -> Procure-to-Pay (P2P) | R13: =VLOOKUP(KamstrupData[[#This Row],[IdLevel123]],'B-Business Capability'!B:L,11,FALSE) -> 500 | U13: =_xlfn.CONCAT(KamstrupData[[#This Row],[CountryCode]],"_",KamstrupData[[#This Row],[Business Area]],"_",KamstrupData[[#This Row],[DepartmentTeam]]) -> AT10_AT_Finance_ | V13: =VLOOKUP(KamstrupData[[#This Row],[ORG_Concat]],'O-Organization'!F:H,3,FALSE) -> 11063_AT10_Finance_AT_Finance_
D14: 1137-Finance-Settlements & Payments-Account Payables | E14: =VLOOKUP(D14,'B-Business Capability'!B:H,5,FALSE) -> Finance | F14: =VLOOKUP(D14,'B-Business Capability'!B:H,6,FALSE) -> Settlements & Payments | G14: =VLOOKUP(D14,'B-Business Capability'!B:H,7,FALSE) -> Account Payables | I14: AT10 | J14: AT_Finance | L14: 443 - VIES | M14: =VLOOKUP(L14,'A-Applications'!B:D,3,FALSE) -> VIES | N14: Tolerate | P14: P14-Accounting-SP14.1-Procure to Pay | Q14: =VLOOKUP(KamstrupData[[#This Row],[IdLevel123]],'B-Business Capability'!B:L,10,FALSE) -> Procure-to-Pay (P2P) | R14: =VLOOKUP(KamstrupData[[#This Row],[IdLevel123]],'B-Business Capability'!B:L,11,FALSE) -> 500 | U14: =_xlfn.CONCAT(KamstrupData[[#This Row],[CountryCode]],"_",KamstrupData[[#This Row],[Business Area]],"_",KamstrupData[[#This Row],[DepartmentTeam]]) -> AT10_AT_Finance_ | V14: =VLOOKUP(KamstrupData[[#This Row],[ORG_Concat]],'O-Organization'!F:H,3,FALSE) -> 11063_AT10_Finance_AT_Finance_
D15: 3097-Finance-Accounting-Accounts Recievabel | E15: =VLOOKUP(D15,'B-Business Capability'!B:H,5,FALSE) -> Finance | F15: =VLOOKUP(D15,'B-Business Capability'!B:H,6,FALSE) -> Accounting | G15: =VLOOKUP(D15,'B-Business Capability'!B:H,7,FALSE) -> Accounts Recievabel | I15: AT10 | J15: AT_Finance | L15: 443 - VIES | M15: =VLOOKUP(L15,'A-Applications'!B:D,3,FALSE) -> VIES | N15: Tolerate | P15: P14-Accounting-SP14.2-Order to Cash | Q15: =VLOOKUP(KamstrupData[[#This Row],[IdLevel123]],'B-Business Capability'!B:L,10,FALSE) -> N/A | R15: =VLOOKUP(KamstrupData[[#This Row],[IdLevel123]],'B-Business Capability'!B:L,11,FALSE) -> 0 | U15: =_xlfn.CONCAT(KamstrupData[[#This Row],[CountryCode]],"_",KamstrupData[[#This Row],[Business Area]],"_",KamstrupData[[#This Row],[DepartmentTeam]]) -> AT10_AT_Finance_ | V15: =VLOOKUP(KamstrupData[[#This Row],[ORG_Concat]],'O-Organization'!F:H,3,FALSE) -> 11063_AT10_Finance_AT_Finance_
D16: 1291-Strategic Management-Manage Core Business-Manage Projects | E16: =VLOOKUP(D16,'B-Business Capability'!B:H,5,FALSE) -> Strategic Management | F16: =VLOOKUP(D16,'B-Business Capability'!B:H,6,FALSE) -> Manage Core Business | G16: =VLOOKUP(D16,'B-Business Capability'!B:H,7,FALSE) -> Manage Projects | I16: AT10 | J16: AT_Customer Service | L16: 1 - IFS ERP | M16: =VLOOKUP(L16,'A-Applications'!B:D,3,FALSE) -> IFS ERP | N16: Tolerate | O16: Business Critical | P16: P12-Customer Solution Deployment-- | Q16: =VLOOKUP(KamstrupData[[#This Row],[IdLevel123]],'B-Business Capability'!B:L,10,FALSE) -> N/A | R16: =VLOOKUP(KamstrupData[[#This Row],[IdLevel123]],'B-Business Capability'!B:L,11,FALSE) -> 0 | U16: =_xlfn.CONCAT(KamstrupData[[#This Row],[CountryCode]],"_",KamstrupData[[#This Row],[Business Area]],"_",KamstrupData[[#This Row],[DepartmentTeam]]) -> AT10_AT_Customer Service_ | V16: =VLOOKUP(KamstrupData[[#This Row],[ORG_Concat]],'O-Organization'!F:H,3,FALSE) -> 11025_AT10_Customer Service_AT_Customer Service_
D17: 3028-Sales-Sales Operations-Claims, returns and Refund management | E17: =VLOOKUP(D17,'B-Business Capability'!B:H,5,FALSE) -> Sales | F17: =VLOOKUP(D17,'B-Business Capability'!B:H,6,FALSE) -> Sales Operations | G17: =VLOOKUP(D17,'B-Business Capability'!B:H,7,FALSE) -> Claims, returns and Refund management | I17: AT10 | J17: AT_Customer Service | L17: 1 - IFS ERP | M17: =VLOOKUP(L17,'A-Applications'!B:D,3,FALSE) -> IFS ERP | N17: Tolerate | O17: Business Critical | P17: P-Not mapped to process-- | Q17: =VLOOKUP(KamstrupData[[#This Row],[IdLevel123]],'B-Business Capability'!B:L,10,FALSE) -> Order-to-Cash (O2C) | R17: =VLOOKUP(KamstrupData[[#This Row],[IdLevel123]],'B-Business Capability'!B:L,11,FALSE) -> 600 | U17: =_xlfn.CONCAT(KamstrupData[[#This Row],[CountryCode]],"_",KamstrupData[[#This Row],[Business Area]],"_",KamstrupData[[#This Row],[DepartmentTeam]]) -> AT10_AT_Customer Service_ | V17: =VLOOKUP(KamstrupData[[#This Row],[ORG_Concat]],'O-Organization'!F:H,3,FALSE) -> 11025_AT10_Customer Service_AT_Customer Service_
D18: 4203-Customer Service-Customer Service and Support-Service Request Management | E18: =VLOOKUP(D18,'B-Business Capability'!B:H,5,FALSE) -> Customer Service | F18: =VLOOKUP(D18,'B-Business Capability'!B:H,6,FALSE) -> Customer Service and Support | G18: =VLOOKUP(D18,'B-Business Capability'!B:H,7,FALSE) -> Service Request Management | I18: AT10 | J18: AT_Customer Service | L18: 1 - IFS ERP | M18: =VLOOKUP(L18,'A-Applications'!B:D,3,FALSE) -> IFS ERP | N18: Tolerate | O18: Business Critical | P18: P13-Customer Service & Operation-- | Q18: =VLOOKUP(KamstrupData[[#This Row],[IdLevel123]],'B-Business Capability'!B:L,10,FALSE) -> Customer Service and Support | R18: =VLOOKUP(KamstrupData[[#This Row],[IdLevel123]],'B-Business Capability'!B:L,11,FALSE) -> 0 | U18: =_xlfn.CONCAT(KamstrupData[[#This Row],[CountryCode]],"_",KamstrupData[[#This Row],[Business Area]],"_",KamstrupData[[#This Row],[DepartmentTeam]]) -> AT10_AT_Customer Service_ | V18: =VLOOKUP(KamstrupData[[#This Row],[ORG_Concat]],'O-Organization'!F:H,3,FALSE) -> 11025_AT10_Customer Service_AT_Customer Service_
D19: 4207-Customer Service-Customer Service and Support-Customer Warranty Claim Processing | E19: =VLOOKUP(D19,'B-Business Capability'!B:H,5,FALSE) -> Customer Service | F19: =VLOOKUP(D19,'B-Business Capability'!B:H,6,FALSE) -> Customer Service and Support | G19: =VLOOKUP(D19,'B-Business Capability'!B:H,7,FALSE) -> Customer Warranty Claim Processing | I19: AT10 | J19: AT_Customer Service | L19: 1 - IFS ERP | M19: =VLOOKUP(L19,'A-Applications'!B:D,3,FALSE) -> IFS ERP | N19: Tolerate | O19: Business Critical | P19: P13-Customer Service & Operation-- | Q19: =VLOOKUP(KamstrupData[[#This Row],[IdLevel123]],'B-Business Capability'!B:L,10,FALSE) -> Customer Service and Support | R19: =VLOOKUP(KamstrupData[[#This Row],[IdLevel123]],'B-Business Capability'!B:L,11,FALSE) -> 0 | U19: =_xlfn.CONCAT(KamstrupData[[#This Row],[CountryCode]],"_",KamstrupData[[#This Row],[Business Area]],"_",KamstrupData[[#This Row],[DepartmentTeam]]) -> AT10_AT_Customer Service_ | V19: =VLOOKUP(KamstrupData[[#This Row],[ORG_Concat]],'O-Organization'!F:H,3,FALSE) -> 11025_AT10_Customer Service_AT_Customer Service_
D20: 4231-Customer Service-Customer Project Management-Ressource Management | E20: =VLOOKUP(D20,'B-Business Capability'!B:H,5,FALSE) -> Customer Service | F20: =VLOOKUP(D20,'B-Business Capability'!B:H,6,FALSE) -> Customer Project Management | G20: =VLOOKUP(D20,'B-Business Capability'!B:H,7,FALSE) -> Ressource Management | I20: AT10 | J20: AT_Customer Service | L20: 1 - IFS ERP | M20: =VLOOKUP(L20,'A-Applications'!B:D,3,FALSE) -> IFS ERP | N20: Tolerate | O20: Business Critical | P20: P12-Customer Solution Deployment-- | Q20: =VLOOKUP(KamstrupData[[#This Row],[IdLevel123]],'B-Business Capability'!B:L,10,FALSE) -> Order-to-Cash (O2C) | R20: =VLOOKUP(KamstrupData[[#This Row],[IdLevel123]],'B-Business Capability'!B:L,11,FALSE) -> 0 | U20: =_xlfn.CONCAT(KamstrupData[[#This Row],[CountryCode]],"_",KamstrupData[[#This Row],[Business Area]],"_",KamstrupData[[#This Row],[DepartmentTeam]]) -> AT10_AT_Customer Service_ | V20: =VLOOKUP(KamstrupData[[#This Row],[ORG_Concat]],'O-Organization'!F:H,3,FALSE) -> 11025_AT10_Customer Service_AT_Customer Service_
D21: 4231-Customer Service-Customer Project Management-Ressource Management | E21: =VLOOKUP(D21,'B-Business Capability'!B:H,5,FALSE) -> Customer Service | F21: =VLOOKUP(D21,'B-Business Capability'!B:H,6,FALSE) -> Customer Project Management | G21: =VLOOKUP(D21,'B-Business Capability'!B:H,7,FALSE) -> Ressource Management | I21: AT10 | J21: AT_Customer Service | L21: 1 - IFS ERP | M21: =VLOOKUP(L21,'A-Applications'!B:D,3,FALSE) -> IFS ERP | N21: Tolerate | O21: Business Operational | P21: P12-Customer Solution Deployment-- | Q21: =VLOOKUP(KamstrupData[[#This Row],[IdLevel123]],'B-Business Capability'!B:L,10,FALSE) -> Order-to-Cash (O2C) | R21: =VLOOKUP(KamstrupData[[#This Row],[IdLevel123]],'B-Business Capability'!B:L,11,FALSE) -> 0 | U21: =_xlfn.CONCAT(KamstrupData[[#This Row],[CountryCode]],"_",KamstrupData[[#This Row],[Business Area]],"_",KamstrupData[[#This Row],[DepartmentTeam]]) -> AT10_AT_Customer Service_ | V21: =VLOOKUP(KamstrupData[[#This Row],[ORG_Concat]],'O-Organization'!F:H,3,FALSE) -> 11025_AT10_Customer Service_AT_Customer Service_
D22: 4232-Customer Service-Customer Project Management-Financial Analytics and Management | E22: =VLOOKUP(D22,'B-Business Capability'!B:H,5,FALSE) -> Customer Service | F22: =VLOOKUP(D22,'B-Business Capability'!B:H,6,FALSE) -> Customer Project Management | G22: =VLOOKUP(D22,'B-Business Capability'!B:H,7,FALSE) -> Financial Analytics and Management | I22: AT10 | J22: AT_Customer Service | L22: 1 - IFS ERP | M22: =VLOOKUP(L22,'A-Applications'!B:D,3,FALSE) -> IFS ERP | N22: Tolerate | O22: Business Critical | P22: P12-Customer Solution Deployment-- | Q22: =VLOOKUP(KamstrupData[[#This Row],[IdLevel123]],'B-Business Capability'!B:L,10,FALSE) -> Order-to-Cash (O2C) | R22: =VLOOKUP(KamstrupData[[#This Row],[IdLevel123]],'B-Business Capability'!B:L,11,FALSE) -> 0 | U22: =_xlfn.CONCAT(KamstrupData[[#This Row],[CountryCode]],"_",KamstrupData[[#This Row],[Business Area]],"_",KamstrupData[[#This Row],[DepartmentTeam]]) -> AT10_AT_Customer Service_ | V22: =VLOOKUP(KamstrupData[[#This Row],[ORG_Concat]],'O-Organization'!F:H,3,FALSE) -> 11025_AT10_Customer Service_AT_Customer Service_
D23: 4232-Customer Service-Customer Project Management-Financial Analytics and Management | E23: =VLOOKUP(D23,'B-Business Capability'!B:H,5,FALSE) -> Customer Service | F23: =VLOOKUP(D23,'B-Business Capability'!B:H,6,FALSE) -> Customer Project Management | G23: =VLOOKUP(D23,'B-Business Capability'!B:H,7,FALSE) -> Financial Analytics and Management | I23: AT10 | J23: AT_Customer Service | L23: 1 - IFS ERP | M23: =VLOOKUP(L23,'A-Applications'!B:D,3,FALSE) -> IFS ERP | N23: Tolerate | O23: Business Operational | P23: P12-Customer Solution Deployment-- | Q23: =VLOOKUP(KamstrupData[[#This Row],[IdLevel123]],'B-Business Capability'!B:L,10,FALSE) -> Order-to-Cash (O2C) | R23: =VLOOKUP(KamstrupData[[#This Row],[IdLevel123]],'B-Business Capability'!B:L,11,FALSE) -> 0 | U23: =_xlfn.CONCAT(KamstrupData[[#This Row],[CountryCode]],"_",KamstrupData[[#This Row],[Business Area]],"_",KamstrupData[[#This Row],[DepartmentTeam]]) -> AT10_AT_Customer Service_ | V23: =VLOOKUP(KamstrupData[[#This Row],[ORG_Concat]],'O-Organization'!F:H,3,FALSE) -> 11025_AT10_Customer Service_AT_Customer Service_
D24: 4203-Customer Service-Customer Service and Support-Service Request Management | E24: =VLOOKUP(D24,'B-Business Capability'!B:H,5,FALSE) -> Customer Service | F24: =VLOOKUP(D24,'B-Business Capability'!B:H,6,FALSE) -> Customer Service and Support | G24: =VLOOKUP(D24,'B-Business Capability'!B:H,7,FALSE) -> Service Request Management | I24: AT10 | J24: AT_Customer Service | L24: 10 - Encryption Key Service (EKS) | M24: =VLOOKUP(L24,'A-Applications'!B:D,3,FALSE) -> Encryption Key Service (EKS) | N24: Tolerate | O24: Business Critical | P24: P13-Customer Service & Operation-- | Q24: =VLOOKUP(KamstrupData[[#This Row],[IdLevel123]],'B-Business Capability'!B:L,10,FALSE) -> Customer Service and Support | R24: =VLOOKUP(KamstrupData[[#This Row],[IdLevel123]],'B-Business Capability'!B:L,11,FALSE) -> 0 | U24: =_xlfn.CONCAT(KamstrupData[[#This Row],[CountryCode]],"_",KamstrupData[[#This Row],[Business Area]],"_",KamstrupData[[#This Row],[DepartmentTeam]]) -> AT10_AT_Customer Service_ | V24: =VLOOKUP(KamstrupData[[#This Row],[ORG_Concat]],'O-Organization'!F:H,3,FALSE) -> 11025_AT10_Customer Service_AT_Customer Service_
D25: 4709-OT Hosting-OT Operations & Service- | E25: =VLOOKUP(D25,'B-Business Capability'!B:H,5,FALSE) -> OT Hosting | F25: =VLOOKUP(D25,'B-Business Capability'!B:H,6,FALSE) -> OT Operations & Service | G25: =VLOOKUP(D25,'B-Business Capability'!B:H,7,FALSE) -> 0 | I25: AT10 | J25: AT_Customer Service | L25: 10 - Encryption Key Service (EKS) | M25: =VLOOKUP(L25,'A-Applications'!B:D,3,FALSE) -> Encryption Key Service (EKS) | N25: Tolerate | O25: Business Critical | P25: P13-Customer Service & Operation-- | Q25: =VLOOKUP(KamstrupData[[#This Row],[IdLevel123]],'B-Business Capability'!B:L,10,FALSE) -> N/A | R25: =VLOOKUP(KamstrupData[[#This Row],[IdLevel123]],'B-Business Capability'!B:L,11,FALSE) -> 0 | U25: =_xlfn.CONCAT(KamstrupData[[#This Row],[CountryCode]],"_",KamstrupData[[#This Row],[Business Area]],"_",KamstrupData[[#This Row],[DepartmentTeam]]) -> AT10_AT_Customer Service_ | V25: =VLOOKUP(KamstrupData[[#This Row],[ORG_Concat]],'O-Organization'!F:H,3,FALSE) -> 11025_AT10_Customer Service_AT_Customer Service_
D26: 4203-Customer Service-Customer Service and Support-Service Request Management | E26: =VLOOKUP(D26,'B-Business Capability'!B:H,5,FALSE) -> Customer Service | F26: =VLOOKUP(D26,'B-Business Capability'!B:H,6,FALSE) -> Customer Service and Support | G26: =VLOOKUP(D26,'B-Business Capability'!B:H,7,FALSE) -> Service Request Management | I26: AT10 | J26: AT_Customer Service | L26: 1011 - Metertool OMNIA | M26: =VLOOKUP(L26,'A-Applications'!B:D,3,FALSE) -> Metertool OMNIA | N26: Tolerate | O26: Business Operational | P26: P13-Customer Service & Operation-- | Q26: =VLOOKUP(KamstrupData[[#This Row],[IdLevel123]],'B-Business Capability'!B:L,10,FALSE) -> Customer Service and Support | R26: =VLOOKUP(KamstrupData[[#This Row],[IdLevel123]],'B-Business Capability'!B:L,11,FALSE) -> 0 | U26: =_xlfn.CONCAT(KamstrupData[[#This Row],[CountryCode]],"_",KamstrupData[[#This Row],[Business Area]],"_",KamstrupData[[#This Row],[DepartmentTeam]]) -> AT10_AT_Customer Service_ | V26: =VLOOKUP(KamstrupData[[#This Row],[ORG_Concat]],'O-Organization'!F:H,3,FALSE) -> 11025_AT10_Customer Service_AT_Customer Service_
D27: 4203-Customer Service-Customer Service and Support-Service Request Management | E27: =VLOOKUP(D27,'B-Business Capability'!B:H,5,FALSE) -> Customer Service | F27: =VLOOKUP(D27,'B-Business Capability'!B:H,6,FALSE) -> Customer Service and Support | G27: =VLOOKUP(D27,'B-Business Capability'!B:H,7,FALSE) -> Service Request Management | I27: AT10 | J27: AT_Customer Service | L27: 1012 - Glogg | M27: =VLOOKUP(L27,'A-Applications'!B:D,3,FALSE) -> Glogg | P27: P13-Customer Service & Operation-- | Q27: =VLOOKUP(KamstrupData[[#This Row],[IdLevel123]],'B-Business Capability'!B:L,10,FALSE) -> Customer Service and Support | R27: =VLOOKUP(KamstrupData[[#This Row],[IdLevel123]],'B-Business Capability'!B:L,11,FALSE) -> 0 | U27: =_xlfn.CONCAT(KamstrupData[[#This Row],[CountryCode]],"_",KamstrupData[[#This Row],[Business Area]],"_",KamstrupData[[#This Row],[DepartmentTeam]]) -> AT10_AT_Customer Service_ | V27: =VLOOKUP(KamstrupData[[#This Row],[ORG_Concat]],'O-Organization'!F:H,3,FALSE) -> 11025_AT10_Customer Service_AT_Customer Service_
D28: 4203-Customer Service-Customer Service and Support-Service Request Management | E28: =VLOOKUP(D28,'B-Business Capability'!B:H,5,FALSE) -> Customer Service | F28: =VLOOKUP(D28,'B-Business Capability'!B:H,6,FALSE) -> Customer Service and Support | G28: =VLOOKUP(D28,'B-Business Capability'!B:H,7,FALSE) -> Service Request Management | I28: AT10 | J28: AT_Customer Service | L28: 1042 - check.kamstrup.com(concentratorLog) | M28: =VLOOKUP(L28,'A-Applications'!B:D,3,FALSE) -> check.kamstrup.com(concentratorLog) | N28: Tolerate | O28: Business Operational | P28: P13-Customer Service & Operation-- | Q28: =VLOOKUP(KamstrupData[[#This Row],[IdLevel123]],'B-Business Capability'!B:L,10,FALSE) -> Customer Service and Support | R28: =VLOOKUP(KamstrupData[[#This Row],[IdLevel123]],'B-Business Capability'!B:L,11,FALSE) -> 0 | U28: =_xlfn.CONCAT(KamstrupData[[#This Row],[CountryCode]],"_",KamstrupData[[#This Row],[Business Area]],"_",KamstrupData[[#This Row],[DepartmentTeam]]) -> AT10_AT_Customer Service_ | V28: =VLOOKUP(KamstrupData[[#This Row],[ORG_Concat]],'O-Organization'!F:H,3,FALSE) -> 11025_AT10_Customer Service_AT_Customer Service_
D29: 4233-Customer Service-Customer Project Management-Project Management | E29: =VLOOKUP(D29,'B-Business Capability'!B:H,5,FALSE) -> Customer Service | F29: =VLOOKUP(D29,'B-Business Capability'!B:H,6,FALSE) -> Customer Project Management | G29: =VLOOKUP(D29,'B-Business Capability'!B:H,7,FALSE) -> Project Management | I29: AT10 | J29: AT_Customer Service | L29: 1042 - check.kamstrup.com(concentratorLog) | M29: =VLOOKUP(L29,'A-Applications'!B:D,3,FALSE) -> check.kamstrup.com(concentratorLog) | N29: Tolerate | O29: Business Operational | P29: P12-Customer Solution Deployment-- | Q29: =VLOOKUP(KamstrupData[[#This Row],[IdLevel123]],'B-Business Capability'!B:L,10,FALSE) -> Order-to-Cash (O2C) | R29: =VLOOKUP(KamstrupData[[#This Row],[IdLevel123]],'B-Business Capability'!B:L,11,FALSE) -> 0 | U29: =_xlfn.CONCAT(KamstrupData[[#This Row],[CountryCode]],"_",KamstrupData[[#This Row],[Business Area]],"_",KamstrupData[[#This Row],[DepartmentTeam]]) -> AT10_AT_Customer Service_ | V29: =VLOOKUP(KamstrupData[[#This Row],[ORG_Concat]],'O-Organization'!F:H,3,FALSE) -> 11025_AT10_Customer Service_AT_Customer Service_
D30: 4203-Customer Service-Customer Service and Support-Service Request Management | E30: =VLOOKUP(D30,'B-Business Capability'!B:H,5,FALSE) -> Customer Service | F30: =VLOOKUP(D30,'B-Business Capability'!B:H,6,FALSE) -> Customer Service and Support | G30: =VLOOKUP(D30,'B-Business Capability'!B:H,7,FALSE) -> Service Request Management | I30: AT10 | J30: AT_Customer Service | L30: 1043 - Kamstrup ALD | M30: =VLOOKUP(L30,'A-Applications'!B:D,3,FALSE) -> Kamstrup ALD | N30: Tolerate | O30: Business Operational | P30: P13-Customer Service & Operation-- | Q30: =VLOOKUP(KamstrupData[[#This Row],[IdLevel123]],'B-Business Capability'!B:L,10,FALSE) -> Customer Service and Support | R30: =VLOOKUP(KamstrupData[[#This Row],[IdLevel123]],'B-Business Capability'!B:L,11,FALSE) -> 0 | U30: =_xlfn.CONCAT(KamstrupData[[#This Row],[CountryCode]],"_",KamstrupData[[#This Row],[Business Area]],"_",KamstrupData[[#This Row],[DepartmentTeam]]) -> AT10_AT_Customer Service_ | V30: =VLOOKUP(KamstrupData[[#This Row],[ORG_Concat]],'O-Organization'!F:H,3,FALSE) -> 11025_AT10_Customer Service_AT_Customer Service_
D31: 4233-Customer Service-Customer Project Management-Project Management | E31: =VLOOKUP(D31,'B-Business Capability'!B:H,5,FALSE) -> Customer Service | F31: =VLOOKUP(D31,'B-Business Capability'!B:H,6,FALSE) -> Customer Project Management | G31: =VLOOKUP(D31,'B-Business Capability'!B:H,7,FALSE) -> Project Management | I31: AT10 | J31: AT_Customer Service | L31: 1043 - Kamstrup ALD | M31: =VLOOKUP(L31,'A-Applications'!B:D,3,FALSE) -> Kamstrup ALD | N31: Tolerate | O31: Business Operational | P31: P12-Customer Solution Deployment-- | Q31: =VLOOKUP(KamstrupData[[#This Row],[IdLevel123]],'B-Business Capability'!B:L,10,FALSE) -> Order-to-Cash (O2C) | R31: =VLOOKUP(KamstrupData[[#This Row],[IdLevel123]],'B-Business Capability'!B:L,11,FALSE) -> 0 | U31: =_xlfn.CONCAT(KamstrupData[[#This Row],[CountryCode]],"_",KamstrupData[[#This Row],[Business Area]],"_",KamstrupData[[#This Row],[DepartmentTeam]]) -> AT10_AT_Customer Service_ | V31: =VLOOKUP(KamstrupData[[#This Row],[ORG_Concat]],'O-Organization'!F:H,3,FALSE) -> 11025_AT10_Customer Service_AT_Customer Service_
D32: 4201-Customer Service-Customer Service and Support- | E32: =VLOOKUP(D32,'B-Business Capability'!B:H,5,FALSE) -> Customer Service | F32: =VLOOKUP(D32,'B-Business Capability'!B:H,6,FALSE) -> Customer Service and Support | G32: =VLOOKUP(D32,'B-Business Capability'!B:H,7,FALSE) -> 0 | I32: AT10 | J32: AT_Customer Service | L32: 1059 - flonidan | M32: =VLOOKUP(L32,'A-Applications'!B:D,3,FALSE) -> flonidan | P32: P13-Customer Service & Operation-- | Q32: =VLOOKUP(KamstrupData[[#This Row],[IdLevel123]],'B-Business Capability'!B:L,10,FALSE) -> Customer Service and Support | R32: =VLOOKUP(KamstrupData[[#This Row],[IdLevel123]],'B-Business Capability'!B:L,11,FALSE) -> 0 | U32: =_xlfn.CONCAT(KamstrupData[[#This Row],[CountryCode]],"_",KamstrupData[[#This Row],[Business Area]],"_",KamstrupData[[#This Row],[DepartmentTeam]]) -> AT10_AT_Customer Service_ | V32: =VLOOKUP(KamstrupData[[#This Row],[ORG_Concat]],'O-Organization'!F:H,3,FALSE) -> 11025_AT10_Customer Service_AT_Customer Service_
D33: 4209-Customer Service-Customer Service and Support-Omnichannel Customer Engagement | E33: =VLOOKUP(D33,'B-Business Capability'!B:H,5,FALSE) -> Customer Service | F33: =VLOOKUP(D33,'B-Business Capability'!B:H,6,FALSE) -> Customer Service and Support | G33: =VLOOKUP(D33,'B-Business Capability'!B:H,7,FALSE) -> Omnichannel Customer Engagement | I33: AT10 | J33: AT_Customer Service | L33: 12 - My Kamstrup | M33: =VLOOKUP(L33,'A-Applications'!B:D,3,FALSE) -> My Kamstrup | N33: Tolerate | O33: Business Critical | P33: P13-Customer Service & Operation-- | Q33: =VLOOKUP(KamstrupData[[#This Row],[IdLevel123]],'B-Business Capability'!B:L,10,FALSE) -> Customer Service and Support | R33: =VLOOKUP(KamstrupData[[#This Row],[IdLevel123]],'B-Business Capability'!B:L,11,FALSE) -> 0 | U33: =_xlfn.CONCAT(KamstrupData[[#This Row],[CountryCode]],"_",KamstrupData[[#This Row],[Business Area]],"_",KamstrupData[[#This Row],[DepartmentTeam]]) -> AT10_AT_Customer Service_ | V33: =VLOOKUP(KamstrupData[[#This Row],[ORG_Concat]],'O-Organization'!F:H,3,FALSE) -> 11025_AT10_Customer Service_AT_Customer Service_
D34: 4211-Customer Service-Customer Service and Support-Self-Service Engagement | E34: =VLOOKUP(D34,'B-Business Capability'!B:H,5,FALSE) -> Customer Service | F34: =VLOOKUP(D34,'B-Business Capability'!B:H,6,FALSE) -> Customer Service and Support | G34: =VLOOKUP(D34,'B-Business Capability'!B:H,7,FALSE) -> Self-Service Engagement | I34: AT10 | J34: AT_Customer Service | L34: 12 - My Kamstrup | M34: =VLOOKUP(L34,'A-Applications'!B:D,3,FALSE) -> My Kamstrup | N34: Tolerate | O34: Business Critical | P34: P13-Customer Service & Operation-- | Q34: =VLOOKUP(KamstrupData[[#This Row],[IdLevel123]],'B-Business Capability'!B:L,10,FALSE) -> Customer Service and Support | R34: =VLOOKUP(KamstrupData[[#This Row],[IdLevel123]],'B-Business Capability'!B:L,11,FALSE) -> 0 | U34: =_xlfn.CONCAT(KamstrupData[[#This Row],[CountryCode]],"_",KamstrupData[[#This Row],[Business Area]],"_",KamstrupData[[#This Row],[DepartmentTeam]]) -> AT10_AT_Customer Service_ | V34: =VLOOKUP(KamstrupData[[#This Row],[ORG_Concat]],'O-Organization'!F:H,3,FALSE) -> 11025_AT10_Customer Service_AT_Customer Service_
D35: 4211-Customer Service-Customer Service and Support-Self-Service Engagement | E35: =VLOOKUP(D35,'B-Business Capability'!B:H,5,FALSE) -> Customer Service | F35: =VLOOKUP(D35,'B-Business Capability'!B:H,6,FALSE) -> Customer Service and Support | G35: =VLOOKUP(D35,'B-Business Capability'!B:H,7,FALSE) -> Self-Service Engagement | I35: AT10 | J35: AT_Customer Service | L35: 12 - My Kamstrup | M35: =VLOOKUP(L35,'A-Applications'!B:D,3,FALSE) -> My Kamstrup | N35: Tolerate | O35: Business Critical | P35: P13-Customer Service & Operation-- | Q35: =VLOOKUP(KamstrupData[[#This Row],[IdLevel123]],'B-Business Capability'!B:L,10,FALSE) -> Customer Service and Support | R35: =VLOOKUP(KamstrupData[[#This Row],[IdLevel123]],'B-Business Capability'!B:L,11,FALSE) -> 0 | U35: =_xlfn.CONCAT(KamstrupData[[#This Row],[CountryCode]],"_",KamstrupData[[#This Row],[Business Area]],"_",KamstrupData[[#This Row],[DepartmentTeam]]) -> AT10_AT_Customer Service_ | V35: =VLOOKUP(KamstrupData[[#This Row],[ORG_Concat]],'O-Organization'!F:H,3,FALSE) -> 11025_AT10_Customer Service_AT_Customer Service_
D36: 4233-Customer Service-Customer Project Management-Project Management | E36: =VLOOKUP(D36,'B-Business Capability'!B:H,5,FALSE) -> Customer Service | F36: =VLOOKUP(D36,'B-Business Capability'!B:H,6,FALSE) -> Customer Project Management | G36: =VLOOKUP(D36,'B-Business Capability'!B:H,7,FALSE) -> Project Management | I36: AT10 | J36: AT_Customer Service | L36: 12 - My Kamstrup | M36: =VLOOKUP(L36,'A-Applications'!B:D,3,FALSE) -> My Kamstrup | N36: Tolerate | O36: Business Critical | P36: P13-Customer Service & Operation-- | Q36: =VLOOKUP(KamstrupData[[#This Row],[IdLevel123]],'B-Business Capability'!B:L,10,FALSE) -> Order-to-Cash (O2C) | R36: =VLOOKUP(KamstrupData[[#This Row],[IdLevel123]],'B-Business Capability'!B:L,11,FALSE) -> 0 | U36: =_xlfn.CONCAT(KamstrupData[[#This Row],[CountryCode]],"_",KamstrupData[[#This Row],[Business Area]],"_",KamstrupData[[#This Row],[DepartmentTeam]]) -> AT10_AT_Customer Service_ | V36: =VLOOKUP(KamstrupData[[#This Row],[ORG_Concat]],'O-Organization'!F:H,3,FALSE) -> 11025_AT10_Customer Service_AT_Customer Service_
D37: 998-Not mapped to capability-- | E37: =VLOOKUP(D37,'B-Business Capability'!B:H,5,FALSE) -> Not mapped to capability | F37: =VLOOKUP(D37,'B-Business Capability'!B:H,6,FALSE) -> 0 | G37: =VLOOKUP(D37,'B-Business Capability'!B:H,7,FALSE) -> 0 | I37: AT10 | J37: AT_Customer Service | L37: 132 - GreenShot | M37: =VLOOKUP(L37,'A-Applications'!B:D,3,FALSE) -> GreenShot | N37: Tolerate | O37: Administrative Service | P37: No-NoProcess-- | Q37: =VLOOKUP(KamstrupData[[#This Row],[IdLevel123]],'B-Business Capability'!B:L,10,FALSE) -> N/A | R37: =VLOOKUP(KamstrupData[[#This Row],[IdLevel123]],'B-Business Capability'!B:L,11,FALSE) -> 0 | U37: =_xlfn.CONCAT(KamstrupData[[#This Row],[CountryCode]],"_",KamstrupData[[#This Row],[Business Area]],"_",KamstrupData[[#This Row],[DepartmentTeam]]) -> AT10_AT_Customer Service_ | V37: =VLOOKUP(KamstrupData[[#This Row],[ORG_Concat]],'O-Organization'!F:H,3,FALSE) -> 11025_AT10_Customer Service_AT_Customer Service_
D38: 4233-Customer Service-Customer Project Management-Project Management | E38: =VLOOKUP(D38,'B-Business Capability'!B:H,5,FALSE) -> Customer Service | F38: =VLOOKUP(D38,'B-Business Capability'!B:H,6,FALSE) -> Customer Project Management | G38: =VLOOKUP(D38,'B-Business Capability'!B:H,7,FALSE) -> Project Management | I38: AT10 | J38: AT_Customer Service | L38: 142 - Notepad++(https://notepad-plus-plus.org/) | M38: =VLOOKUP(L38,'A-Applications'!B:D,3,FALSE) -> Notepad++(https://notepad-plus-plus.org/) | N38: Tolerate | O38: Business Operational | P38: P12-Customer Solution Deployment-- | Q38: =VLOOKUP(KamstrupData[[#This Row],[IdLevel123]],'B-Business Capability'!B:L,10,FALSE) -> Order-to-Cash (O2C) | R38: =VLOOKUP(KamstrupData[[#This Row],[IdLevel123]],'B-Business Capability'!B:L,11,FALSE) -> 0 | U38: =_xlfn.CONCAT(KamstrupData[[#This Row],[CountryCode]],"_",KamstrupData[[#This Row],[Business Area]],"_",KamstrupData[[#This Row],[DepartmentTeam]]) -> AT10_AT_Customer Service_ | V38: =VLOOKUP(KamstrupData[[#This Row],[ORG_Concat]],'O-Organization'!F:H,3,FALSE) -> 11025_AT10_Customer Service_AT_Customer Service_
D39: 998-Not mapped to capability-- | E39: =VLOOKUP(D39,'B-Business Capability'!B:H,5,FALSE) -> Not mapped to capability | F39: =VLOOKUP(D39,'B-Business Capability'!B:H,6,FALSE) -> 0 | G39: =VLOOKUP(D39,'B-Business Capability'!B:H,7,FALSE) -> 0 | I39: AT10 | J39: AT_Customer Service | L39: 149 - SnagIt | M39: =VLOOKUP(L39,'A-Applications'!B:D,3,FALSE) -> SnagIt | N39: Tolerate | O39: Administrative Service | P39: P12-Customer Solution Deployment-- | Q39: =VLOOKUP(KamstrupData[[#This Row],[IdLevel123]],'B-Business Capability'!B:L,10,FALSE) -> N/A | R39: =VLOOKUP(KamstrupData[[#This Row],[IdLevel123]],'B-Business Capability'!B:L,11,FALSE) -> 0 | U39: =_xlfn.CONCAT(KamstrupData[[#This Row],[CountryCode]],"_",KamstrupData[[#This Row],[Business Area]],"_",KamstrupData[[#This Row],[DepartmentTeam]]) -> AT10_AT_Customer Service_ | V39: =VLOOKUP(KamstrupData[[#This Row],[ORG_Concat]],'O-Organization'!F:H,3,FALSE) -> 11025_AT10_Customer Service_AT_Customer Service_
D40: 998-Not mapped to capability-- | E40: =VLOOKUP(D40,'B-Business Capability'!B:H,5,FALSE) -> Not mapped to capability | F40: =VLOOKUP(D40,'B-Business Capability'!B:H,6,FALSE) -> 0 | G40: =VLOOKUP(D40,'B-Business Capability'!B:H,7,FALSE) -> 0 | I40: AT10 | J40: AT_Customer Service | L40: 149 - SnagIt | M40: =VLOOKUP(L40,'A-Applications'!B:D,3,FALSE) -> SnagIt | N40: Tolerate | O40: Business Operational | P40: P-Not mapped to process-- | Q40: =VLOOKUP(KamstrupData[[#This Row],[IdLevel123]],'B-Business Capability'!B:L,10,FALSE) -> N/A | R40: =VLOOKUP(KamstrupData[[#This Row],[IdLevel123]],'B-Business Capability'!B:L,11,FALSE) -> 0 | U40: =_xlfn.CONCAT(KamstrupData[[#This Row],[CountryCode]],"_",KamstrupData[[#This Row],[Business Area]],"_",KamstrupData[[#This Row],[DepartmentTeam]]) -> AT10_AT_Customer Service_ | V40: =VLOOKUP(KamstrupData[[#This Row],[ORG_Concat]],'O-Organization'!F:H,3,FALSE) -> 11025_AT10_Customer Service_AT_Customer Service_
D41: 4203-Customer Service-Customer Service and Support-Service Request Management | E41: =VLOOKUP(D41,'B-Business Capability'!B:H,5,FALSE) -> Customer Service | F41: =VLOOKUP(D41,'B-Business Capability'!B:H,6,FALSE) -> Customer Service and Support | G41: =VLOOKUP(D41,'B-Business Capability'!B:H,7,FALSE) -> Service Request Management | I41: AT10 | J41: AT_Customer Service | L41: 15 - JIRA | M41: =VLOOKUP(L41,'A-Applications'!B:D,3,FALSE) -> JIRA | N41: Tolerate | O41: Business Operational | P41: P13-Customer Service & Operation-- | Q41: =VLOOKUP(KamstrupData[[#This Row],[IdLevel123]],'B-Business Capability'!B:L,10,FALSE) -> Customer Service and Support | R41: =VLOOKUP(KamstrupData[[#This Row],[IdLevel123]],'B-Business Capability'!B:L,11,FALSE) -> 0 | U41: =_xlfn.CONCAT(KamstrupData[[#This Row],[CountryCode]],"_",KamstrupData[[#This Row],[Business Area]],"_",KamstrupData[[#This Row],[DepartmentTeam]]) -> AT10_AT_Customer Service_ | V41: =VLOOKUP(KamstrupData[[#This Row],[ORG_Concat]],'O-Organization'!F:H,3,FALSE) -> 11025_AT10_Customer Service_AT_Customer Service_
D42: 4233-Customer Service-Customer Project Management-Project Management | E42: =VLOOKUP(D42,'B-Business Capability'!B:H,5,FALSE) -> Customer Service | F42: =VLOOKUP(D42,'B-Business Capability'!B:H,6,FALSE) -> Customer Project Management | G42: =VLOOKUP(D42,'B-Business Capability'!B:H,7,FALSE) -> Project Management | I42: AT10 | J42: AT_Customer Service | L42: 15 - JIRA | M42: =VLOOKUP(L42,'A-Applications'!B:D,3,FALSE) -> JIRA | N42: Tolerate | O42: Business Operational | P42: P12-Customer Solution Deployment-- | Q42: =VLOOKUP(KamstrupData[[#This Row],[IdLevel123]],'B-Business Capability'!B:L,10,FALSE) -> Order-to-Cash (O2C) | R42: =VLOOKUP(KamstrupData[[#This Row],[IdLevel123]],'B-Business Capability'!B:L,11,FALSE) -> 0 | U42: =_xlfn.CONCAT(KamstrupData[[#This Row],[CountryCode]],"_",KamstrupData[[#This Row],[Business Area]],"_",KamstrupData[[#This Row],[DepartmentTeam]]) -> AT10_AT_Customer Service_ | V42: =VLOOKUP(KamstrupData[[#This Row],[ORG_Concat]],'O-Organization'!F:H,3,FALSE) -> 11025_AT10_Customer Service_AT_Customer Service_
D43: 998-Not mapped to capability-- | E43: =VLOOKUP(D43,'B-Business Capability'!B:H,5,FALSE) -> Not mapped to capability | F43: =VLOOKUP(D43,'B-Business Capability'!B:H,6,FALSE) -> 0 | G43: =VLOOKUP(D43,'B-Business Capability'!B:H,7,FALSE) -> 0 | I43: AT10 | J43: AT_Customer Service | L43: 151 - TeraTerm | M43: =VLOOKUP(L43,'A-Applications'!B:D,3,FALSE) -> TeraTerm | P43: P-Not mapped to process-- | Q43: =VLOOKUP(KamstrupData[[#This Row],[IdLevel123]],'B-Business Capability'!B:L,10,FALSE) -> N/A | R43: =VLOOKUP(KamstrupData[[#This Row],[IdLevel123]],'B-Business Capability'!B:L,11,FALSE) -> 0 | U43: =_xlfn.CONCAT(KamstrupData[[#This Row],[CountryCode]],"_",KamstrupData[[#This Row],[Business Area]],"_",KamstrupData[[#This Row],[DepartmentTeam]]) -> AT10_AT_Customer Service_ | V43: =VLOOKUP(KamstrupData[[#This Row],[ORG_Concat]],'O-Organization'!F:H,3,FALSE) -> 11025_AT10_Customer Service_AT_Customer Service_
D44: 1132-Finance-Financial Planning & Analysis-Cost Accounting_Plan | E44: =VLOOKUP(D44,'B-Business Capability'!B:H,5,FALSE) -> Finance | F44: =VLOOKUP(D44,'B-Business Capability'!B:H,6,FALSE) -> Financial Planning & Analysis | G44: =VLOOKUP(D44,'B-Business Capability'!B:H,7,FALSE) -> Cost Accounting_Plan | I44: AT10 | J44: AT_Customer Service | L44: 171 - VIS | M44: =VLOOKUP(L44,'A-Applications'!B:D,3,FALSE) -> VIS | N44: Migrate | O44: Business Critical | P44: P18-Budget-- | Q44: =VLOOKUP(KamstrupData[[#This Row],[IdLevel123]],'B-Business Capability'!B:L,10,FALSE) -> N/A | R44: =VLOOKUP(KamstrupData[[#This Row],[IdLevel123]],'B-Business Capability'!B:L,11,FALSE) -> 0 | U44: =_xlfn.CONCAT(KamstrupData[[#This Row],[CountryCode]],"_",KamstrupData[[#This Row],[Business Area]],"_",KamstrupData[[#This Row],[DepartmentTeam]]) -> AT10_AT_Customer Service_ | V44: =VLOOKUP(KamstrupData[[#This Row],[ORG_Concat]],'O-Organization'!F:H,3,FALSE) -> 11025_AT10_Customer Service_AT_Customer Service_
D45: 1133-Finance-Financial Planning & Analysis-Forecasting | E45: =VLOOKUP(D45,'B-Business Capability'!B:H,5,FALSE) -> Finance | F45: =VLOOKUP(D45,'B-Business Capability'!B:H,6,FALSE) -> Financial Planning & Analysis | G45: =VLOOKUP(D45,'B-Business Capability'!B:H,7,FALSE) -> Forecasting | I45: AT10 | J45: AT_Customer Service | L45: 171 - VIS | M45: =VLOOKUP(L45,'A-Applications'!B:D,3,FALSE) -> VIS | N45: Migrate | O45: Business Critical | P45: P18-Budget-- | Q45: =VLOOKUP(KamstrupData[[#This Row],[IdLevel123]],'B-Business Capability'!B:L,10,FALSE) -> N/A | R45: =VLOOKUP(KamstrupData[[#This Row],[IdLevel123]],'B-Business Capability'!B:L,11,FALSE) -> 0 | U45: =_xlfn.CONCAT(KamstrupData[[#This Row],[CountryCode]],"_",KamstrupData[[#This Row],[Business Area]],"_",KamstrupData[[#This Row],[DepartmentTeam]]) -> AT10_AT_Customer Service_ | V45: =VLOOKUP(KamstrupData[[#This Row],[ORG_Concat]],'O-Organization'!F:H,3,FALSE) -> 11025_AT10_Customer Service_AT_Customer Service_
D46: 1291-Strategic Management-Manage Core Business-Manage Projects | E46: =VLOOKUP(D46,'B-Business Capability'!B:H,5,FALSE) -> Strategic Management | F46: =VLOOKUP(D46,'B-Business Capability'!B:H,6,FALSE) -> Manage Core Business | G46: =VLOOKUP(D46,'B-Business Capability'!B:H,7,FALSE) -> Manage Projects | I46: AT10 | J46: AT_Customer Service | L46: 171 - VIS | M46: =VLOOKUP(L46,'A-Applications'!B:D,3,FALSE) -> VIS | N46: Migrate | O46: Business Critical | P46: P12-Customer Solution Deployment-- | Q46: =VLOOKUP(KamstrupData[[#This Row],[IdLevel123]],'B-Business Capability'!B:L,10,FALSE) -> N/A | R46: =VLOOKUP(KamstrupData[[#This Row],[IdLevel123]],'B-Business Capability'!B:L,11,FALSE) -> 0 | U46: =_xlfn.CONCAT(KamstrupData[[#This Row],[CountryCode]],"_",KamstrupData[[#This Row],[Business Area]],"_",KamstrupData[[#This Row],[DepartmentTeam]]) -> AT10_AT_Customer Service_ | V46: =VLOOKUP(KamstrupData[[#This Row],[ORG_Concat]],'O-Organization'!F:H,3,FALSE) -> 11025_AT10_Customer Service_AT_Customer Service_
D47: 1291-Strategic Management-Manage Core Business-Manage Projects | E47: =VLOOKUP(D47,'B-Business Capability'!B:H,5,FALSE) -> Strategic Management | F47: =VLOOKUP(D47,'B-Business Capability'!B:H,6,FALSE) -> Manage Core Business | G47: =VLOOKUP(D47,'B-Business Capability'!B:H,7,FALSE) -> Manage Projects | I47: AT10 | J47: AT_Customer Service | L47: 185 - Microsoft Visio | M47: =VLOOKUP(L47,'A-Applications'!B:D,3,FALSE) -> Microsoft Visio | N47: Tolerate | O47: Business Operational | P47: P12-Customer Solution Deployment-- | Q47: =VLOOKUP(KamstrupData[[#This Row],[IdLevel123]],'B-Business Capability'!B:L,10,FALSE) -> N/A | R47: =VLOOKUP(KamstrupData[[#This Row],[IdLevel123]],'B-Business Capability'!B:L,11,FALSE) -> 0 | U47: =_xlfn.CONCAT(KamstrupData[[#This Row],[CountryCode]],"_",KamstrupData[[#This Row],[Business Area]],"_",KamstrupData[[#This Row],[DepartmentTeam]]) -> AT10_AT_Customer Service_ | V47: =VLOOKUP(KamstrupData[[#This Row],[ORG_Concat]],'O-Organization'!F:H,3,FALSE) -> 11025_AT10_Customer Service_AT_Customer Service_
D48: 4203-Customer Service-Customer Service and Support-Service Request Management | E48: =VLOOKUP(D48,'B-Business Capability'!B:H,5,FALSE) -> Customer Service | F48: =VLOOKUP(D48,'B-Business Capability'!B:H,6,FALSE) -> Customer Service and Support | G48: =VLOOKUP(D48,'B-Business Capability'!B:H,7,FALSE) -> Service Request Management | I48: AT10 | J48: AT_Customer Service | L48: 194 - Putty | M48: =VLOOKUP(L48,'A-Applications'!B:D,3,FALSE) -> Putty | N48: Tolerate | O48: Business Operational | P48: P12-Customer Solution Deployment-- | Q48: =VLOOKUP(KamstrupData[[#This Row],[IdLevel123]],'B-Business Capability'!B:L,10,FALSE) -> Customer Service and Support | R48: =VLOOKUP(KamstrupData[[#This Row],[IdLevel123]],'B-Business Capability'!B:L,11,FALSE) -> 0 | U48: =_xlfn.CONCAT(KamstrupData[[#This Row],[CountryCode]],"_",KamstrupData[[#This Row],[Business Area]],"_",KamstrupData[[#This Row],[DepartmentTeam]]) -> AT10_AT_Customer Service_ | V48: =VLOOKUP(KamstrupData[[#This Row],[ORG_Concat]],'O-Organization'!F:H,3,FALSE) -> 11025_AT10_Customer Service_AT_Customer Service_
D49: 4233-Customer Service-Customer Project Management-Project Management | E49: =VLOOKUP(D49,'B-Business Capability'!B:H,5,FALSE) -> Customer Service | F49: =VLOOKUP(D49,'B-Business Capability'!B:H,6,FALSE) -> Customer Project Management | G49: =VLOOKUP(D49,'B-Business Capability'!B:H,7,FALSE) -> Project Management | I49: AT10 | J49: AT_Customer Service | L49: 199 - GITLAB | M49: =VLOOKUP(L49,'A-Applications'!B:D,3,FALSE) -> GITLAB | N49: Tolerate | O49: Business Operational | P49: P12-Customer Solution Deployment-- | Q49: =VLOOKUP(KamstrupData[[#This Row],[IdLevel123]],'B-Business Capability'!B:L,10,FALSE) -> Order-to-Cash (O2C) | R49: =VLOOKUP(KamstrupData[[#This Row],[IdLevel123]],'B-Business Capability'!B:L,11,FALSE) -> 0 | U49: =_xlfn.CONCAT(KamstrupData[[#This Row],[CountryCode]],"_",KamstrupData[[#This Row],[Business Area]],"_",KamstrupData[[#This Row],[DepartmentTeam]]) -> AT10_AT_Customer Service_ | V49: =VLOOKUP(KamstrupData[[#This Row],[ORG_Concat]],'O-Organization'!F:H,3,FALSE) -> 11025_AT10_Customer Service_AT_Customer Service_
D50: 4233-Customer Service-Customer Project Management-Project Management | E50: =VLOOKUP(D50,'B-Business Capability'!B:H,5,FALSE) -> Customer Service | F50: =VLOOKUP(D50,'B-Business Capability'!B:H,6,FALSE) -> Customer Project Management | G50: =VLOOKUP(D50,'B-Business Capability'!B:H,7,FALSE) -> Project Management | I50: AT10 | J50: AT_Customer Service | L50: 2 - QAD ERP | M50: =VLOOKUP(L50,'A-Applications'!B:D,3,FALSE) -> QAD ERP | N50: Tolerate | O50: Business Operational | P50: P12-Customer Solution Deployment-- | Q50: =VLOOKUP(KamstrupData[[#This Row],[IdLevel123]],'B-Business Capability'!B:L,10,FALSE) -> Order-to-Cash (O2C) | R50: =VLOOKUP(KamstrupData[[#This Row],[IdLevel123]],'B-Business Capability'!B:L,11,FALSE) -> 0 | U50: =_xlfn.CONCAT(KamstrupData[[#This Row],[CountryCode]],"_",KamstrupData[[#This Row],[Business Area]],"_",KamstrupData[[#This Row],[DepartmentTeam]]) -> AT10_AT_Customer Service_ | V50: =VLOOKUP(KamstrupData[[#This Row],[ORG_Concat]],'O-Organization'!F:H,3,FALSE) -> 11025_AT10_Customer Service_AT_Customer Service_
D51: 4203-Customer Service-Customer Service and Support-Service Request Management | E51: =VLOOKUP(D51,'B-Business Capability'!B:H,5,FALSE) -> Customer Service | F51: =VLOOKUP(D51,'B-Business Capability'!B:H,6,FALSE) -> Customer Service and Support | G51: =VLOOKUP(D51,'B-Business Capability'!B:H,7,FALSE) -> Service Request Management | I51: AT10 | J51: AT_Customer Service | L51: 201 - Kamstrup GPRS Portal | M51: =VLOOKUP(L51,'A-Applications'!B:D,3,FALSE) -> Kamstrup GPRS Portal | N51: Tolerate | O51: Business Operational | P51: P13-Customer Service & Operation-- | Q51: =VLOOKUP(KamstrupData[[#This Row],[IdLevel123]],'B-Business Capability'!B:L,10,FALSE) -> Customer Service and Support | R51: =VLOOKUP(KamstrupData[[#This Row],[IdLevel123]],'B-Business Capability'!B:L,11,FALSE) -> 0 | U51: =_xlfn.CONCAT(KamstrupData[[#This Row],[CountryCode]],"_",KamstrupData[[#This Row],[Business Area]],"_",KamstrupData[[#This Row],[DepartmentTeam]]) -> AT10_AT_Customer Service_ | V51: =VLOOKUP(KamstrupData[[#This Row],[ORG_Concat]],'O-Organization'!F:H,3,FALSE) -> 11025_AT10_Customer Service_AT_Customer Service_
D52: 4233-Customer Service-Customer Project Management-Project Management | E52: =VLOOKUP(D52,'B-Business Capability'!B:H,5,FALSE) -> Customer Service | F52: =VLOOKUP(D52,'B-Business Capability'!B:H,6,FALSE) -> Customer Project Management | G52: =VLOOKUP(D52,'B-Business Capability'!B:H,7,FALSE) -> Project Management | I52: AT10 | J52: AT_Customer Service | L52: 201 - Kamstrup GPRS Portal | M52: =VLOOKUP(L52,'A-Applications'!B:D,3,FALSE) -> Kamstrup GPRS Portal | N52: Tolerate | O52: Business Operational | P52: P12-Customer Solution Deployment-- | Q52: =VLOOKUP(KamstrupData[[#This Row],[IdLevel123]],'B-Business Capability'!B:L,10,FALSE) -> Order-to-Cash (O2C) | R52: =VLOOKUP(KamstrupData[[#This Row],[IdLevel123]],'B-Business Capability'!B:L,11,FALSE) -> 0 | U52: =_xlfn.CONCAT(KamstrupData[[#This Row],[CountryCode]],"_",KamstrupData[[#This Row],[Business Area]],"_",KamstrupData[[#This Row],[DepartmentTeam]]) -> AT10_AT_Customer Service_ | V52: =VLOOKUP(KamstrupData[[#This Row],[ORG_Concat]],'O-Organization'!F:H,3,FALSE) -> 11025_AT10_Customer Service_AT_Customer Service_
D53: 4203-Customer Service-Customer Service and Support-Service Request Management | E53: =VLOOKUP(D53,'B-Business Capability'!B:H,5,FALSE) -> Customer Service | F53: =VLOOKUP(D53,'B-Business Capability'!B:H,6,FALSE) -> Customer Service and Support | G53: =VLOOKUP(D53,'B-Business Capability'!B:H,7,FALSE) -> Service Request Management | I53: AT10 | J53: AT_Customer Service | L53: 257 - Bomgar/BeyondTrust | M53: =VLOOKUP(L53,'A-Applications'!B:D,3,FALSE) -> Bomgar/BeyondTrust | N53: Tolerate | O53: Business Operational | P53: P13-Customer Service & Operation-- | Q53: =VLOOKUP(KamstrupData[[#This Row],[IdLevel123]],'B-Business Capability'!B:L,10,FALSE) -> Customer Service and Support | R53: =VLOOKUP(KamstrupData[[#This Row],[IdLevel123]],'B-Business Capability'!B:L,11,FALSE) -> 0 | U53: =_xlfn.CONCAT(KamstrupData[[#This Row],[CountryCode]],"_",KamstrupData[[#This Row],[Business Area]],"_",KamstrupData[[#This Row],[DepartmentTeam]]) -> AT10_AT_Customer Service_ | V53: =VLOOKUP(KamstrupData[[#This Row],[ORG_Concat]],'O-Organization'!F:H,3,FALSE) -> 11025_AT10_Customer Service_AT_Customer Service_
D54: 4233-Customer Service-Customer Project Management-Project Management | E54: =VLOOKUP(D54,'B-Business Capability'!B:H,5,FALSE) -> Customer Service | F54: =VLOOKUP(D54,'B-Business Capability'!B:H,6,FALSE) -> Customer Project Management | G54: =VLOOKUP(D54,'B-Business Capability'!B:H,7,FALSE) -> Project Management | I54: AT10 | J54: AT_Customer Service | L54: 257 - Bomgar/BeyondTrust | M54: =VLOOKUP(L54,'A-Applications'!B:D,3,FALSE) -> Bomgar/BeyondTrust | N54: Tolerate | O54: Business Operational | P54: P12-Customer Solution Deployment-- | Q54: =VLOOKUP(KamstrupData[[#This Row],[IdLevel123]],'B-Business Capability'!B:L,10,FALSE) -> Order-to-Cash (O2C) | R54: =VLOOKUP(KamstrupData[[#This Row],[IdLevel123]],'B-Business Capability'!B:L,11,FALSE) -> 0 | U54: =_xlfn.CONCAT(KamstrupData[[#This Row],[CountryCode]],"_",KamstrupData[[#This Row],[Business Area]],"_",KamstrupData[[#This Row],[DepartmentTeam]]) -> AT10_AT_Customer Service_ | V54: =VLOOKUP(KamstrupData[[#This Row],[ORG_Concat]],'O-Organization'!F:H,3,FALSE) -> 11025_AT10_Customer Service_AT_Customer Service_
D55: 4233-Customer Service-Customer Project Management-Project Management | E55: =VLOOKUP(D55,'B-Business Capability'!B:H,5,FALSE) -> Customer Service | F55: =VLOOKUP(D55,'B-Business Capability'!B:H,6,FALSE) -> Customer Project Management | G55: =VLOOKUP(D55,'B-Business Capability'!B:H,7,FALSE) -> Project Management | I55: AT10 | J55: AT_Customer Service | L55: 257 - Bomgar/BeyondTrust | M55: =VLOOKUP(L55,'A-Applications'!B:D,3,FALSE) -> Bomgar/BeyondTrust | N55: Tolerate | O55: Business Operational | P55: P12-Customer Solution Deployment-- | Q55: =VLOOKUP(KamstrupData[[#This Row],[IdLevel123]],'B-Business Capability'!B:L,10,FALSE) -> Order-to-Cash (O2C) | R55: =VLOOKUP(KamstrupData[[#This Row],[IdLevel123]],'B-Business Capability'!B:L,11,FALSE) -> 0 | U55: =_xlfn.CONCAT(KamstrupData[[#This Row],[CountryCode]],"_",KamstrupData[[#This Row],[Business Area]],"_",KamstrupData[[#This Row],[DepartmentTeam]]) -> AT10_AT_Customer Service_ | V55: =VLOOKUP(KamstrupData[[#This Row],[ORG_Concat]],'O-Organization'!F:H,3,FALSE) -> 11025_AT10_Customer Service_AT_Customer Service_
... D60: 4233-Customer Service-Customer Project Management-Project Management | E60: =VLOOKUP(D60,'B-Business Capability'!B:H,5,FALSE) -> Customer Service | F60: =VLOOKUP(D60,'B-Business Capability'!B:H,6,FALSE) -> Customer Project Management | G60: =VLOOKUP(D60,'B-Business Capability'!B:H,7,FALSE) -> Project Management | I60: AT10 | J60: AT_Customer Service | L60: 282 - FTP services | M60: =VLOOKUP(L60,'A-Applications'!B:D,3,FALSE) -> FTP services | N60: Tolerate | O60: Business Critical | P60: P12-Customer Solution Deployment-- | Q60: =VLOOKUP(KamstrupData[[#This Row],[IdLevel123]],'B-Business Capability'!B:L,10,FALSE) -> Order-to-Cash (O2C) | R60: =VLOOKUP(KamstrupData[[#This Row],[IdLevel123]],'B-Business Capability'!B:L,11,FALSE) -> 0 | U60: =_xlfn.CONCAT(KamstrupData[[#This Row],[CountryCode]],"_",KamstrupData[[#This Row],[Business Area]],"_",KamstrupData[[#This Row],[DepartmentTeam]]) -> AT10_AT_Customer Service_ | V60: =VLOOKUP(KamstrupData[[#This Row],[ORG_Concat]],'O-Organization'!F:H,3,FALSE) -> 11025_AT10_Customer Service_AT_Customer Service_
D61: 3113-Marketing-Corporate communication and brand management-Internal communications | E61: =VLOOKUP(D61,'B-Business Capability'!B:H,5,FALSE) -> Marketing | F61: =VLOOKUP(D61,'B-Business Capability'!B:H,6,FALSE) -> Corporate communication and brand management | G61: =VLOOKUP(D61,'B-Business Capability'!B:H,7,FALSE) -> Internal communications | I61: AT10 | J61: AT_Customer Service | L61: 293 - KamSite | M61: =VLOOKUP(L61,'A-Applications'!B:D,3,FALSE) -> KamSite | N61: Tolerate | O61: Administrative Service | Q61: =VLOOKUP(KamstrupData[[#This Row],[IdLevel123]],'B-Business Capability'!B:L,10,FALSE) -> N/A | R61: =VLOOKUP(KamstrupData[[#This Row],[IdLevel123]],'B-Business Capability'!B:L,11,FALSE) -> 0 | U61: =_xlfn.CONCAT(KamstrupData[[#This Row],[CountryCode]],"_",KamstrupData[[#This Row],[Business Area]],"_",KamstrupData[[#This Row],[DepartmentTeam]]) -> AT10_AT_Customer Service_ | V61: =VLOOKUP(KamstrupData[[#This Row],[ORG_Concat]],'O-Organization'!F:H,3,FALSE) -> 11025_AT10_Customer Service_AT_Customer Service_
D62: 4200-Customer Service-- | E62: =VLOOKUP(D62,'B-Business Capability'!B:H,5,FALSE) -> Customer Service | F62: =VLOOKUP(D62,'B-Business Capability'!B:H,6,FALSE) -> 0 | G62: =VLOOKUP(D62,'B-Business Capability'!B:H,7,FALSE) -> 0 | I62: AT10 | J62: AT_Customer Service | L62: 299 - Microsoft Teams | M62: =VLOOKUP(L62,'A-Applications'!B:D,3,FALSE) -> Microsoft Teams | N62: Tolerate | O62: Business Critical | P62: P00-All-- | Q62: =VLOOKUP(KamstrupData[[#This Row],[IdLevel123]],'B-Business Capability'!B:L,10,FALSE) -> Customer Service and Support | R62: =VLOOKUP(KamstrupData[[#This Row],[IdLevel123]],'B-Business Capability'!B:L,11,FALSE) -> 0 | U62: =_xlfn.CONCAT(KamstrupData[[#This Row],[CountryCode]],"_",KamstrupData[[#This Row],[Business Area]],"_",KamstrupData[[#This Row],[DepartmentTeam]]) -> AT10_AT_Customer Service_ | V62: =VLOOKUP(KamstrupData[[#This Row],[ORG_Concat]],'O-Organization'!F:H,3,FALSE) -> 11025_AT10_Customer Service_AT_Customer Service_
D63: 4201-Customer Service-Customer Service and Support- | E63: =VLOOKUP(D63,'B-Business Capability'!B:H,5,FALSE) -> Customer Service | F63: =VLOOKUP(D63,'B-Business Capability'!B:H,6,FALSE) -> Customer Service and Support | G63: =VLOOKUP(D63,'B-Business Capability'!B:H,7,FALSE) -> 0 | I63: AT10 | J63: AT_Customer Service | L63: 299 - Microsoft Teams | M63: =VLOOKUP(L63,'A-Applications'!B:D,3,FALSE) -> Microsoft Teams | N63: Tolerate | O63: Business Operational | P63: P00-All-- | Q63: =VLOOKUP(KamstrupData[[#This Row],[IdLevel123]],'B-Business Capability'!B:L,10,FALSE) -> Customer Service and Support | R63: =VLOOKUP(KamstrupData[[#This Row],[IdLevel123]],'B-Business Capability'!B:L,11,FALSE) -> 0 | U63: =_xlfn.CONCAT(KamstrupData[[#This Row],[CountryCode]],"_",KamstrupData[[#This Row],[Business Area]],"_",KamstrupData[[#This Row],[DepartmentTeam]]) -> AT10_AT_Customer Service_ | V63: =VLOOKUP(KamstrupData[[#This Row],[ORG_Concat]],'O-Organization'!F:H,3,FALSE) -> 11025_AT10_Customer Service_AT_Customer Service_
D64: 4203-Customer Service-Customer Service and Support-Service Request Management | E64: =VLOOKUP(D64,'B-Business Capability'!B:H,5,FALSE) -> Customer Service | F64: =VLOOKUP(D64,'B-Business Capability'!B:H,6,FALSE) -> Customer Service and Support | G64: =VLOOKUP(D64,'B-Business Capability'!B:H,7,FALSE) -> Service Request Management | I64: AT10 | J64: AT_Customer Service | L64: 339 - Trio | M64: =VLOOKUP(L64,'A-Applications'!B:D,3,FALSE) -> Trio | N64: Migrate | O64: Business Critical | P64: P13-Customer Service & Operation-- | Q64: =VLOOKUP(KamstrupData[[#This Row],[IdLevel123]],'B-Business Capability'!B:L,10,FALSE) -> Customer Service and Support | R64: =VLOOKUP(KamstrupData[[#This Row],[IdLevel123]],'B-Business Capability'!B:L,11,FALSE) -> 0 | U64: =_xlfn.CONCAT(KamstrupData[[#This Row],[CountryCode]],"_",KamstrupData[[#This Row],[Business Area]],"_",KamstrupData[[#This Row],[DepartmentTeam]]) -> AT10_AT_Customer Service_ | V64: =VLOOKUP(KamstrupData[[#This Row],[ORG_Concat]],'O-Organization'!F:H,3,FALSE) -> 11025_AT10_Customer Service_AT_Customer Service_
D65: 4709-OT Hosting-OT Operations & Service- | E65: =VLOOKUP(D65,'B-Business Capability'!B:H,5,FALSE) -> OT Hosting | F65: =VLOOKUP(D65,'B-Business Capability'!B:H,6,FALSE) -> OT Operations & Service | G65: =VLOOKUP(D65,'B-Business Capability'!B:H,7,FALSE) -> 0 | I65: AT10 | J65: AT_Customer Service | L65: 339 - Trio | M65: =VLOOKUP(L65,'A-Applications'!B:D,3,FALSE) -> Trio | N65: Migrate | O65: Business Critical | P65: P13-Customer Service & Operation-- | Q65: =VLOOKUP(KamstrupData[[#This Row],[IdLevel123]],'B-Business Capability'!B:L,10,FALSE) -> N/A | R65: =VLOOKUP(KamstrupData[[#This Row],[IdLevel123]],'B-Business Capability'!B:L,11,FALSE) -> 0 | U65: =_xlfn.CONCAT(KamstrupData[[#This Row],[CountryCode]],"_",KamstrupData[[#This Row],[Business Area]],"_",KamstrupData[[#This Row],[DepartmentTeam]]) -> AT10_AT_Customer Service_ | V65: =VLOOKUP(KamstrupData[[#This Row],[ORG_Concat]],'O-Organization'!F:H,3,FALSE) -> 11025_AT10_Customer Service_AT_Customer Service_
D66: 1132-Finance-Financial Planning & Analysis-Cost Accounting_Plan | E66: =VLOOKUP(D66,'B-Business Capability'!B:H,5,FALSE) -> Finance | F66: =VLOOKUP(D66,'B-Business Capability'!B:H,6,FALSE) -> Financial Planning & Analysis | G66: =VLOOKUP(D66,'B-Business Capability'!B:H,7,FALSE) -> Cost Accounting_Plan | I66: AT10 | J66: AT_Customer Service | L66: 351 - PowerBI | M66: =VLOOKUP(L66,'A-Applications'!B:D,3,FALSE) -> PowerBI | N66: Tolerate | O66: Administrative Service | P66: P18-Budget-- | Q66: =VLOOKUP(KamstrupData[[#This Row],[IdLevel123]],'B-Business Capability'!B:L,10,FALSE) -> N/A | R66: =VLOOKUP(KamstrupData[[#This Row],[IdLevel123]],'B-Business Capability'!B:L,11,FALSE) -> 0 | U66: =_xlfn.CONCAT(KamstrupData[[#This Row],[CountryCode]],"_",KamstrupData[[#This Row],[Business Area]],"_",KamstrupData[[#This Row],[DepartmentTeam]]) -> AT10_AT_Customer Service_ | V66: =VLOOKUP(KamstrupData[[#This Row],[ORG_Concat]],'O-Organization'!F:H,3,FALSE) -> 11025_AT10_Customer Service_AT_Customer Service_
D67: 1291-Strategic Management-Manage Core Business-Manage Projects | E67: =VLOOKUP(D67,'B-Business Capability'!B:H,5,FALSE) -> Strategic Management | F67: =VLOOKUP(D67,'B-Business Capability'!B:H,6,FALSE) -> Manage Core Business | G67: =VLOOKUP(D67,'B-Business Capability'!B:H,7,FALSE) -> Manage Projects | I67: AT10 | J67: AT_Customer Service | L67: 351 - PowerBI | M67: =VLOOKUP(L67,'A-Applications'!B:D,3,FALSE) -> PowerBI | N67: Tolerate | O67: Administrative Service | P67: P12-Customer Solution Deployment-- | Q67: =VLOOKUP(KamstrupData[[#This Row],[IdLevel123]],'B-Business Capability'!B:L,10,FALSE) -> N/A | R67: =VLOOKUP(KamstrupData[[#This Row],[IdLevel123]],'B-Business Capability'!B:L,11,FALSE) -> 0 | U67: =_xlfn.CONCAT(KamstrupData[[#This Row],[CountryCode]],"_",KamstrupData[[#This Row],[Business Area]],"_",KamstrupData[[#This Row],[DepartmentTeam]]) -> AT10_AT_Customer Service_ | V67: =VLOOKUP(KamstrupData[[#This Row],[ORG_Concat]],'O-Organization'!F:H,3,FALSE) -> 11025_AT10_Customer Service_AT_Customer Service_
D68: 4214-Customer Service-Customer Service Strategy and Planning-Customer Service Analytics | E68: =VLOOKUP(D68,'B-Business Capability'!B:H,5,FALSE) -> Customer Service | F68: =VLOOKUP(D68,'B-Business Capability'!B:H,6,FALSE) -> Customer Service Strategy and Planning | G68: =VLOOKUP(D68,'B-Business Capability'!B:H,7,FALSE) -> Customer Service Analytics | I68: AT10 | J68: AT_Customer Service | L68: 351 - PowerBI | M68: =VLOOKUP(L68,'A-Applications'!B:D,3,FALSE) -> PowerBI | N68: Tolerate | O68: Administrative Service | P68: P13-Customer Service & Operation-- | Q68: =VLOOKUP(KamstrupData[[#This Row],[IdLevel123]],'B-Business Capability'!B:L,10,FALSE) -> Customer Service and Support | R68: =VLOOKUP(KamstrupData[[#This Row],[IdLevel123]],'B-Business Capability'!B:L,11,FALSE) -> 0 | U68: =_xlfn.CONCAT(KamstrupData[[#This Row],[CountryCode]],"_",KamstrupData[[#This Row],[Business Area]],"_",KamstrupData[[#This Row],[DepartmentTeam]]) -> AT10_AT_Customer Service_ | V68: =VLOOKUP(KamstrupData[[#This Row],[ORG_Concat]],'O-Organization'!F:H,3,FALSE) -> 11025_AT10_Customer Service_AT_Customer Service_
D69: 4232-Customer Service-Customer Project Management-Financial Analytics and Management | E69: =VLOOKUP(D69,'B-Business Capability'!B:H,5,FALSE) -> Customer Service | F69: =VLOOKUP(D69,'B-Business Capability'!B:H,6,FALSE) -> Customer Project Management | G69: =VLOOKUP(D69,'B-Business Capability'!B:H,7,FALSE) -> Financial Analytics and Management | I69: AT10 | J69: AT_Customer Service | L69: 351 - PowerBI | M69: =VLOOKUP(L69,'A-Applications'!B:D,3,FALSE) -> PowerBI | N69: Tolerate | O69: Administrative Service | P69: P12-Customer Solution Deployment-- | Q69: =VLOOKUP(KamstrupData[[#This Row],[IdLevel123]],'B-Business Capability'!B:L,10,FALSE) -> Order-to-Cash (O2C) | R69: =VLOOKUP(KamstrupData[[#This Row],[IdLevel123]],'B-Business Capability'!B:L,11,FALSE) -> 0 | U69: =_xlfn.CONCAT(KamstrupData[[#This Row],[CountryCode]],"_",KamstrupData[[#This Row],[Business Area]],"_",KamstrupData[[#This Row],[DepartmentTeam]]) -> AT10_AT_Customer Service_ | V69: =VLOOKUP(KamstrupData[[#This Row],[ORG_Concat]],'O-Organization'!F:H,3,FALSE) -> 11025_AT10_Customer Service_AT_Customer Service_
D70: 4232-Customer Service-Customer Project Management-Financial Analytics and Management | E70: =VLOOKUP(D70,'B-Business Capability'!B:H,5,FALSE) -> Customer Service | F70: =VLOOKUP(D70,'B-Business Capability'!B:H,6,FALSE) -> Customer Project Management | G70: =VLOOKUP(D70,'B-Business Capability'!B:H,7,FALSE) -> Financial Analytics and Management | I70: AT10 | J70: AT_Customer Service | L70: 351 - PowerBI | M70: =VLOOKUP(L70,'A-Applications'!B:D,3,FALSE) -> PowerBI | N70: Tolerate | O70: Administrative Service | P70: P12-Customer Solution Deployment-- | Q70: =VLOOKUP(KamstrupData[[#This Row],[IdLevel123]],'B-Business Capability'!B:L,10,FALSE) -> Order-to-Cash (O2C) | R70: =VLOOKUP(KamstrupData[[#This Row],[IdLevel123]],'B-Business Capability'!B:L,11,FALSE) -> 0 | U70: =_xlfn.CONCAT(KamstrupData[[#This Row],[CountryCode]],"_",KamstrupData[[#This Row],[Business Area]],"_",KamstrupData[[#This Row],[DepartmentTeam]]) -> AT10_AT_Customer Service_ | V70: =VLOOKUP(KamstrupData[[#This Row],[ORG_Concat]],'O-Organization'!F:H,3,FALSE) -> 11025_AT10_Customer Service_AT_Customer Service_
D71: 4233-Customer Service-Customer Project Management-Project Management | E71: =VLOOKUP(D71,'B-Business Capability'!B:H,5,FALSE) -> Customer Service | F71: =VLOOKUP(D71,'B-Business Capability'!B:H,6,FALSE) -> Customer Project Management | G71: =VLOOKUP(D71,'B-Business Capability'!B:H,7,FALSE) -> Project Management | I71: AT10 | J71: AT_Customer Service | L71: 351 - PowerBI | M71: =VLOOKUP(L71,'A-Applications'!B:D,3,FALSE) -> PowerBI | N71: Tolerate | O71: Administrative Service | P71: P12-Customer Solution Deployment-- | Q71: =VLOOKUP(KamstrupData[[#This Row],[IdLevel123]],'B-Business Capability'!B:L,10,FALSE) -> Order-to-Cash (O2C) | R71: =VLOOKUP(KamstrupData[[#This Row],[IdLevel123]],'B-Business Capability'!B:L,11,FALSE) -> 0 | U71: =_xlfn.CONCAT(KamstrupData[[#This Row],[CountryCode]],"_",KamstrupData[[#This Row],[Business Area]],"_",KamstrupData[[#This Row],[DepartmentTeam]]) -> AT10_AT_Customer Service_ | V71: =VLOOKUP(KamstrupData[[#This Row],[ORG_Concat]],'O-Organization'!F:H,3,FALSE) -> 11025_AT10_Customer Service_AT_Customer Service_
D72: 4233-Customer Service-Customer Project Management-Project Management | E72: =VLOOKUP(D72,'B-Business Capability'!B:H,5,FALSE) -> Customer Service | F72: =VLOOKUP(D72,'B-Business Capability'!B:H,6,FALSE) -> Customer Project Management | G72: =VLOOKUP(D72,'B-Business Capability'!B:H,7,FALSE) -> Project Management | I72: AT10 | J72: AT_Customer Service | L72: 351 - PowerBI | M72: =VLOOKUP(L72,'A-Applications'!B:D,3,FALSE) -> PowerBI | N72: Tolerate | O72: Administrative Service | P72: P12-Customer Solution Deployment-- | Q72: =VLOOKUP(KamstrupData[[#This Row],[IdLevel123]],'B-Business Capability'!B:L,10,FALSE) -> Order-to-Cash (O2C) | R72: =VLOOKUP(KamstrupData[[#This Row],[IdLevel123]],'B-Business Capability'!B:L,11,FALSE) -> 0 | U72: =_xlfn.CONCAT(KamstrupData[[#This Row],[CountryCode]],"_",KamstrupData[[#This Row],[Business Area]],"_",KamstrupData[[#This Row],[DepartmentTeam]]) -> AT10_AT_Customer Service_ | V72: =VLOOKUP(KamstrupData[[#This Row],[ORG_Concat]],'O-Organization'!F:H,3,FALSE) -> 11025_AT10_Customer Service_AT_Customer Service_
D73: 1140-Finance-Settlements & Payments-Travel & Expense Management | E73: =VLOOKUP(D73,'B-Business Capability'!B:H,5,FALSE) -> Finance | F73: =VLOOKUP(D73,'B-Business Capability'!B:H,6,FALSE) -> Settlements & Payments | G73: =VLOOKUP(D73,'B-Business Capability'!B:H,7,FALSE) -> Travel & Expense Management | I73: AT10 | J73: AT_Customer Service | L73: 36 - Concur | M73: =VLOOKUP(L73,'A-Applications'!B:D,3,FALSE) -> Concur | N73: Tolerate | O73: Business Operational | P73: P34-Salary & Incentives-SP34.3-Reimbursement - DK | Q73: =VLOOKUP(KamstrupData[[#This Row],[IdLevel123]],'B-Business Capability'!B:L,10,FALSE) -> Hire-to-Retire (H2R) | R73: =VLOOKUP(KamstrupData[[#This Row],[IdLevel123]],'B-Business Capability'!B:L,11,FALSE) -> 750 | U73: =_xlfn.CONCAT(KamstrupData[[#This Row],[CountryCode]],"_",KamstrupData[[#This Row],[Business Area]],"_",KamstrupData[[#This Row],[DepartmentTeam]]) -> AT10_AT_Customer Service_ | V73: =VLOOKUP(KamstrupData[[#This Row],[ORG_Concat]],'O-Organization'!F:H,3,FALSE) -> 11025_AT10_Customer Service_AT_Customer Service_
... D78: 4233-Customer Service-Customer Project Management-Project Management | E78: =VLOOKUP(D78,'B-Business Capability'!B:H,5,FALSE) -> Customer Service | F78: =VLOOKUP(D78,'B-Business Capability'!B:H,6,FALSE) -> Customer Project Management | G78: =VLOOKUP(D78,'B-Business Capability'!B:H,7,FALSE) -> Project Management | I78: AT10 | J78: AT_Customer Service | L78: 361 - DocuSign | M78: =VLOOKUP(L78,'A-Applications'!B:D,3,FALSE) -> DocuSign | N78: Tolerate | O78: Business Operational | P78: P12-Customer Solution Deployment-- | Q78: =VLOOKUP(KamstrupData[[#This Row],[IdLevel123]],'B-Business Capability'!B:L,10,FALSE) -> Order-to-Cash (O2C) | R78: =VLOOKUP(KamstrupData[[#This Row],[IdLevel123]],'B-Business Capability'!B:L,11,FALSE) -> 0 | U78: =_xlfn.CONCAT(KamstrupData[[#This Row],[CountryCode]],"_",KamstrupData[[#This Row],[Business Area]],"_",KamstrupData[[#This Row],[DepartmentTeam]]) -> AT10_AT_Customer Service_ | V78: =VLOOKUP(KamstrupData[[#This Row],[ORG_Concat]],'O-Organization'!F:H,3,FALSE) -> 11025_AT10_Customer Service_AT_Customer Service_
D79: 3204-Strategic Management-Business Process Management-Business Process Modeling | E79: =VLOOKUP(D79,'B-Business Capability'!B:H,5,FALSE) -> Strategic Management | F79: =VLOOKUP(D79,'B-Business Capability'!B:H,6,FALSE) -> Business Process Management | G79: =VLOOKUP(D79,'B-Business Capability'!B:H,7,FALSE) -> Business Process Modeling | I79: AT10 | J79: AT_Customer Service | L79: 373 - Ipw | M79: =VLOOKUP(L79,'A-Applications'!B:D,3,FALSE) -> Ipw | N79: Tolerate | O79: Business Operational | Q79: =VLOOKUP(KamstrupData[[#This Row],[IdLevel123]],'B-Business Capability'!B:L,10,FALSE) -> N/A | R79: =VLOOKUP(KamstrupData[[#This Row],[IdLevel123]],'B-Business Capability'!B:L,11,FALSE) -> 0 | U79: =_xlfn.CONCAT(KamstrupData[[#This Row],[CountryCode]],"_",KamstrupData[[#This Row],[Business Area]],"_",KamstrupData[[#This Row],[DepartmentTeam]]) -> AT10_AT_Customer Service_ | V79: =VLOOKUP(KamstrupData[[#This Row],[ORG_Concat]],'O-Organization'!F:H,3,FALSE) -> 11025_AT10_Customer Service_AT_Customer Service_
D80: 3204-Strategic Management-Business Process Management-Business Process Modeling | E80: =VLOOKUP(D80,'B-Business Capability'!B:H,5,FALSE) -> Strategic Management | F80: =VLOOKUP(D80,'B-Business Capability'!B:H,6,FALSE) -> Business Process Management | G80: =VLOOKUP(D80,'B-Business Capability'!B:H,7,FALSE) -> Business Process Modeling | I80: AT10 | J80: AT_Customer Service | L80: 373 - Ipw | M80: =VLOOKUP(L80,'A-Applications'!B:D,3,FALSE) -> Ipw | N80: Tolerate | O80: Business Operational | P80: No-NoProcess-- | Q80: =VLOOKUP(KamstrupData[[#This Row],[IdLevel123]],'B-Business Capability'!B:L,10,FALSE) -> N/A | R80: =VLOOKUP(KamstrupData[[#This Row],[IdLevel123]],'B-Business Capability'!B:L,11,FALSE) -> 0 | U80: =_xlfn.CONCAT(KamstrupData[[#This Row],[CountryCode]],"_",KamstrupData[[#This Row],[Business Area]],"_",KamstrupData[[#This Row],[DepartmentTeam]]) -> AT10_AT_Customer Service_ | V80: =VLOOKUP(KamstrupData[[#This Row],[ORG_Concat]],'O-Organization'!F:H,3,FALSE) -> 11025_AT10_Customer Service_AT_Customer Service_
D81: 3069-Sales-Sales Execution and Customer Engagement-Project selling | E81: =VLOOKUP(D81,'B-Business Capability'!B:H,5,FALSE) -> Sales | F81: =VLOOKUP(D81,'B-Business Capability'!B:H,6,FALSE) -> Sales Execution and Customer Engagement | G81: =VLOOKUP(D81,'B-Business Capability'!B:H,7,FALSE) -> Project selling | I81: AT10 | J81: AT_Customer Service | L81: 4 - Microsoft Dynamics 365 CE (Sales) | M81: =VLOOKUP(L81,'A-Applications'!B:D,3,FALSE) -> Microsoft Dynamics 365 CE (Sales) | N81: Tolerate | O81: Business Operational | P81: P12-Customer Solution Deployment-- | Q81: =VLOOKUP(KamstrupData[[#This Row],[IdLevel123]],'B-Business Capability'!B:L,10,FALSE) -> Order-to-Cash (O2C) | R81: =VLOOKUP(KamstrupData[[#This Row],[IdLevel123]],'B-Business Capability'!B:L,11,FALSE) -> 550 | U81: =_xlfn.CONCAT(KamstrupData[[#This Row],[CountryCode]],"_",KamstrupData[[#This Row],[Business Area]],"_",KamstrupData[[#This Row],[DepartmentTeam]]) -> AT10_AT_Customer Service_ | V81: =VLOOKUP(KamstrupData[[#This Row],[ORG_Concat]],'O-Organization'!F:H,3,FALSE) -> 11025_AT10_Customer Service_AT_Customer Service_
D82: 3210-Sales-Quotation, Order, and Contract Management-Tender or Bid management | E82: =VLOOKUP(D82,'B-Business Capability'!B:H,5,FALSE) -> Sales | F82: =VLOOKUP(D82,'B-Business Capability'!B:H,6,FALSE) -> Quotation, Order, and Contract Management | G82: =VLOOKUP(D82,'B-Business Capability'!B:H,7,FALSE) -> Tender or Bid management | I82: AT10 | J82: AT_Customer Service | L82: 4 - Microsoft Dynamics 365 CE (Sales) | M82: =VLOOKUP(L82,'A-Applications'!B:D,3,FALSE) -> Microsoft Dynamics 365 CE (Sales) | N82: Tolerate | O82: Business Operational | P82: P09-Sales & Business Development-SP09.2-Solution Sales Non-Standard | Q82: =VLOOKUP(KamstrupData[[#This Row],[IdLevel123]],'B-Business Capability'!B:L,10,FALSE) -> Order-to-Cash (O2C) | R82: =VLOOKUP(KamstrupData[[#This Row],[IdLevel123]],'B-Business Capability'!B:L,11,FALSE) -> 104 | U82: =_xlfn.CONCAT(KamstrupData[[#This Row],[CountryCode]],"_",KamstrupData[[#This Row],[Business Area]],"_",KamstrupData[[#This Row],[DepartmentTeam]]) -> AT10_AT_Customer Service_ | V82: =VLOOKUP(KamstrupData[[#This Row],[ORG_Concat]],'O-Organization'!F:H,3,FALSE) -> 11025_AT10_Customer Service_AT_Customer Service_
D83: 4203-Customer Service-Customer Service and Support-Service Request Management | E83: =VLOOKUP(D83,'B-Business Capability'!B:H,5,FALSE) -> Customer Service | F83: =VLOOKUP(D83,'B-Business Capability'!B:H,6,FALSE) -> Customer Service and Support | G83: =VLOOKUP(D83,'B-Business Capability'!B:H,7,FALSE) -> Service Request Management | I83: AT10 | J83: AT_Customer Service | L83: 40 - Omnia | M83: =VLOOKUP(L83,'A-Applications'!B:D,3,FALSE) -> Omnia | N83: Tolerate | O83: Business Critical | P83: P13-Customer Service & Operation-- | Q83: =VLOOKUP(KamstrupData[[#This Row],[IdLevel123]],'B-Business Capability'!B:L,10,FALSE) -> Customer Service and Support | R83: =VLOOKUP(KamstrupData[[#This Row],[IdLevel123]],'B-Business Capability'!B:L,11,FALSE) -> 0 | U83: =_xlfn.CONCAT(KamstrupData[[#This Row],[CountryCode]],"_",KamstrupData[[#This Row],[Business Area]],"_",KamstrupData[[#This Row],[DepartmentTeam]]) -> AT10_AT_Customer Service_ | V83: =VLOOKUP(KamstrupData[[#This Row],[ORG_Concat]],'O-Organization'!F:H,3,FALSE) -> 11025_AT10_Customer Service_AT_Customer Service_
D84: 4233-Customer Service-Customer Project Management-Project Management | E84: =VLOOKUP(D84,'B-Business Capability'!B:H,5,FALSE) -> Customer Service | F84: =VLOOKUP(D84,'B-Business Capability'!B:H,6,FALSE) -> Customer Project Management | G84: =VLOOKUP(D84,'B-Business Capability'!B:H,7,FALSE) -> Project Management | I84: AT10 | J84: AT_Customer Service | L84: 40 - Omnia | M84: =VLOOKUP(L84,'A-Applications'!B:D,3,FALSE) -> Omnia | N84: Tolerate | O84: Business Critical | P84: P12-Customer Solution Deployment-- | Q84: =VLOOKUP(KamstrupData[[#This Row],[IdLevel123]],'B-Business Capability'!B:L,10,FALSE) -> Order-to-Cash (O2C) | R84: =VLOOKUP(KamstrupData[[#This Row],[IdLevel123]],'B-Business Capability'!B:L,11,FALSE) -> 0 | U84: =_xlfn.CONCAT(KamstrupData[[#This Row],[CountryCode]],"_",KamstrupData[[#This Row],[Business Area]],"_",KamstrupData[[#This Row],[DepartmentTeam]]) -> AT10_AT_Customer Service_ | V84: =VLOOKUP(KamstrupData[[#This Row],[ORG_Concat]],'O-Organization'!F:H,3,FALSE) -> 11025_AT10_Customer Service_AT_Customer Service_
D85: 4234-Customer Service-Customer Service and Support-Customer Operations | E85: =VLOOKUP(D85,'B-Business Capability'!B:H,5,FALSE) -> Customer Service | F85: =VLOOKUP(D85,'B-Business Capability'!B:H,6,FALSE) -> Customer Service and Support | G85: =VLOOKUP(D85,'B-Business Capability'!B:H,7,FALSE) -> Customer Operations | I85: AT10 | J85: AT_Customer Service | L85: 40 - Omnia | M85: =VLOOKUP(L85,'A-Applications'!B:D,3,FALSE) -> Omnia | N85: Tolerate | O85: Business Critical | P85: P12-Customer Solution Deployment-- | Q85: =VLOOKUP(KamstrupData[[#This Row],[IdLevel123]],'B-Business Capability'!B:L,10,FALSE) -> Order-to-Cash (O2C) | R85: =VLOOKUP(KamstrupData[[#This Row],[IdLevel123]],'B-Business Capability'!B:L,11,FALSE) -> 0 | U85: =_xlfn.CONCAT(KamstrupData[[#This Row],[CountryCode]],"_",KamstrupData[[#This Row],[Business Area]],"_",KamstrupData[[#This Row],[DepartmentTeam]]) -> AT10_AT_Customer Service_ | V85: =VLOOKUP(KamstrupData[[#This Row],[ORG_Concat]],'O-Organization'!F:H,3,FALSE) -> 11025_AT10_Customer Service_AT_Customer Service_
D86: 4203-Customer Service-Customer Service and Support-Service Request Management | E86: =VLOOKUP(D86,'B-Business Capability'!B:H,5,FALSE) -> Customer Service | F86: =VLOOKUP(D86,'B-Business Capability'!B:H,6,FALSE) -> Customer Service and Support | G86: =VLOOKUP(D86,'B-Business Capability'!B:H,7,FALSE) -> Service Request Management | I86: AT10 | J86: AT_Customer Service | L86: 41 - READy | M86: =VLOOKUP(L86,'A-Applications'!B:D,3,FALSE) -> READy | N86: Migrate | O86: Business Operational | P86: P13-Customer Service & Operation-- | Q86: =VLOOKUP(KamstrupData[[#This Row],[IdLevel123]],'B-Business Capability'!B:L,10,FALSE) -> Customer Service and Support | R86: =VLOOKUP(KamstrupData[[#This Row],[IdLevel123]],'B-Business Capability'!B:L,11,FALSE) -> 0 | U86: =_xlfn.CONCAT(KamstrupData[[#This Row],[CountryCode]],"_",KamstrupData[[#This Row],[Business Area]],"_",KamstrupData[[#This Row],[DepartmentTeam]]) -> AT10_AT_Customer Service_ | V86: =VLOOKUP(KamstrupData[[#This Row],[ORG_Concat]],'O-Organization'!F:H,3,FALSE) -> 11025_AT10_Customer Service_AT_Customer Service_
D87: 4233-Customer Service-Customer Project Management-Project Management | E87: =VLOOKUP(D87,'B-Business Capability'!B:H,5,FALSE) -> Customer Service | F87: =VLOOKUP(D87,'B-Business Capability'!B:H,6,FALSE) -> Customer Project Management | G87: =VLOOKUP(D87,'B-Business Capability'!B:H,7,FALSE) -> Project Management | I87: AT10 | J87: AT_Customer Service | L87: 41 - READy | M87: =VLOOKUP(L87,'A-Applications'!B:D,3,FALSE) -> READy | N87: Migrate | O87: Business Operational | P87: P12-Customer Solution Deployment-- | Q87: =VLOOKUP(KamstrupData[[#This Row],[IdLevel123]],'B-Business Capability'!B:L,10,FALSE) -> Order-to-Cash (O2C) | R87: =VLOOKUP(KamstrupData[[#This Row],[IdLevel123]],'B-Business Capability'!B:L,11,FALSE) -> 0 | U87: =_xlfn.CONCAT(KamstrupData[[#This Row],[CountryCode]],"_",KamstrupData[[#This Row],[Business Area]],"_",KamstrupData[[#This Row],[DepartmentTeam]]) -> AT10_AT_Customer Service_ | V87: =VLOOKUP(KamstrupData[[#This Row],[ORG_Concat]],'O-Organization'!F:H,3,FALSE) -> 11025_AT10_Customer Service_AT_Customer Service_
D88: 4233-Customer Service-Customer Project Management-Project Management | E88: =VLOOKUP(D88,'B-Business Capability'!B:H,5,FALSE) -> Customer Service | F88: =VLOOKUP(D88,'B-Business Capability'!B:H,6,FALSE) -> Customer Project Management | G88: =VLOOKUP(D88,'B-Business Capability'!B:H,7,FALSE) -> Project Management | I88: AT10 | J88: AT_Customer Service | L88: 41 - READy | M88: =VLOOKUP(L88,'A-Applications'!B:D,3,FALSE) -> READy | N88: Migrate | O88: Business Critical | P88: P12-Customer Solution Deployment-- | Q88: =VLOOKUP(KamstrupData[[#This Row],[IdLevel123]],'B-Business Capability'!B:L,10,FALSE) -> Order-to-Cash (O2C) | R88: =VLOOKUP(KamstrupData[[#This Row],[IdLevel123]],'B-Business Capability'!B:L,11,FALSE) -> 0 | U88: =_xlfn.CONCAT(KamstrupData[[#This Row],[CountryCode]],"_",KamstrupData[[#This Row],[Business Area]],"_",KamstrupData[[#This Row],[DepartmentTeam]]) -> AT10_AT_Customer Service_ | V88: =VLOOKUP(KamstrupData[[#This Row],[ORG_Concat]],'O-Organization'!F:H,3,FALSE) -> 11025_AT10_Customer Service_AT_Customer Service_
D89: 4234-Customer Service-Customer Service and Support-Customer Operations | E89: =VLOOKUP(D89,'B-Business Capability'!B:H,5,FALSE) -> Customer Service | F89: =VLOOKUP(D89,'B-Business Capability'!B:H,6,FALSE) -> Customer Service and Support | G89: =VLOOKUP(D89,'B-Business Capability'!B:H,7,FALSE) -> Customer Operations | I89: AT10 | J89: AT_Customer Service | L89: 41 - READy | M89: =VLOOKUP(L89,'A-Applications'!B:D,3,FALSE) -> READy | N89: Migrate | O89: Business Operational | P89: P13-Customer Service & Operation-- | Q89: =VLOOKUP(KamstrupData[[#This Row],[IdLevel123]],'B-Business Capability'!B:L,10,FALSE) -> Order-to-Cash (O2C) | R89: =VLOOKUP(KamstrupData[[#This Row],[IdLevel123]],'B-Business Capability'!B:L,11,FALSE) -> 0 | U89: =_xlfn.CONCAT(KamstrupData[[#This Row],[CountryCode]],"_",KamstrupData[[#This Row],[Business Area]],"_",KamstrupData[[#This Row],[DepartmentTeam]]) -> AT10_AT_Customer Service_ | V89: =VLOOKUP(KamstrupData[[#This Row],[ORG_Concat]],'O-Organization'!F:H,3,FALSE) -> 11025_AT10_Customer Service_AT_Customer Service_
D90: 1291-Strategic Management-Manage Core Business-Manage Projects | E90: =VLOOKUP(D90,'B-Business Capability'!B:H,5,FALSE) -> Strategic Management | F90: =VLOOKUP(D90,'B-Business Capability'!B:H,6,FALSE) -> Manage Core Business | G90: =VLOOKUP(D90,'B-Business Capability'!B:H,7,FALSE) -> Manage Projects | I90: AT10 | J90: AT_Customer Service | L90: 421 - Microsoft Project | M90: =VLOOKUP(L90,'A-Applications'!B:D,3,FALSE) -> Microsoft Project | N90: Tolerate | O90: Business Operational | P90: P12-Customer Solution Deployment-- | Q90: =VLOOKUP(KamstrupData[[#This Row],[IdLevel123]],'B-Business Capability'!B:L,10,FALSE) -> N/A | R90: =VLOOKUP(KamstrupData[[#This Row],[IdLevel123]],'B-Business Capability'!B:L,11,FALSE) -> 0 | U90: =_xlfn.CONCAT(KamstrupData[[#This Row],[CountryCode]],"_",KamstrupData[[#This Row],[Business Area]],"_",KamstrupData[[#This Row],[DepartmentTeam]]) -> AT10_AT_Customer Service_ | V90: =VLOOKUP(KamstrupData[[#This Row],[ORG_Concat]],'O-Organization'!F:H,3,FALSE) -> 11025_AT10_Customer Service_AT_Customer Service_
D91: 4700-OT Hosting-OT Platform & Hosting- | E91: =VLOOKUP(D91,'B-Business Capability'!B:H,5,FALSE) -> OT Hosting | F91: =VLOOKUP(D91,'B-Business Capability'!B:H,6,FALSE) -> OT Platform & Hosting | G91: =VLOOKUP(D91,'B-Business Capability'!B:H,7,FALSE) -> 0 | I91: AT10 | J91: AT_Customer Service | L91: 426 - Azure Monitoring | M91: =VLOOKUP(L91,'A-Applications'!B:D,3,FALSE) -> Azure Monitoring | N91: Tolerate | O91: Business Operational | P91: P13-Customer Service & Operation-- | Q91: =VLOOKUP(KamstrupData[[#This Row],[IdLevel123]],'B-Business Capability'!B:L,10,FALSE) -> N/A | R91: =VLOOKUP(KamstrupData[[#This Row],[IdLevel123]],'B-Business Capability'!B:L,11,FALSE) -> 0 | U91: =_xlfn.CONCAT(KamstrupData[[#This Row],[CountryCode]],"_",KamstrupData[[#This Row],[Business Area]],"_",KamstrupData[[#This Row],[DepartmentTeam]]) -> AT10_AT_Customer Service_ | V91: =VLOOKUP(KamstrupData[[#This Row],[ORG_Concat]],'O-Organization'!F:H,3,FALSE) -> 11025_AT10_Customer Service_AT_Customer Service_
D92: 1140-Finance-Settlements & Payments-Travel & Expense Management | E92: =VLOOKUP(D92,'B-Business Capability'!B:H,5,FALSE) -> Finance | F92: =VLOOKUP(D92,'B-Business Capability'!B:H,6,FALSE) -> Settlements & Payments | G92: =VLOOKUP(D92,'B-Business Capability'!B:H,7,FALSE) -> Travel & Expense Management | I92: AT10 | J92: AT_Customer Service | L92: 466 - Travelpool | M92: =VLOOKUP(L92,'A-Applications'!B:D,3,FALSE) -> Travelpool | N92: Tolerate | O92: Administrative Service | P92: P37-Travel-- | Q92: =VLOOKUP(KamstrupData[[#This Row],[IdLevel123]],'B-Business Capability'!B:L,10,FALSE) -> Hire-to-Retire (H2R) | R92: =VLOOKUP(KamstrupData[[#This Row],[IdLevel123]],'B-Business Capability'!B:L,11,FALSE) -> 750 | U92: =_xlfn.CONCAT(KamstrupData[[#This Row],[CountryCode]],"_",KamstrupData[[#This Row],[Business Area]],"_",KamstrupData[[#This Row],[DepartmentTeam]]) -> AT10_AT_Customer Service_ | V92: =VLOOKUP(KamstrupData[[#This Row],[ORG_Concat]],'O-Organization'!F:H,3,FALSE) -> 11025_AT10_Customer Service_AT_Customer Service_
D93: 4233-Customer Service-Customer Project Management-Project Management | E93: =VLOOKUP(D93,'B-Business Capability'!B:H,5,FALSE) -> Customer Service | F93: =VLOOKUP(D93,'B-Business Capability'!B:H,6,FALSE) -> Customer Project Management | G93: =VLOOKUP(D93,'B-Business Capability'!B:H,7,FALSE) -> Project Management | I93: AT10 | J93: AT_Customer Service | L93: 475 - Mulesoft | M93: =VLOOKUP(L93,'A-Applications'!B:D,3,FALSE) -> Mulesoft | P93: P12-Customer Solution Deployment-- | Q93: =VLOOKUP(KamstrupData[[#This Row],[IdLevel123]],'B-Business Capability'!B:L,10,FALSE) -> Order-to-Cash (O2C) | R93: =VLOOKUP(KamstrupData[[#This Row],[IdLevel123]],'B-Business Capability'!B:L,11,FALSE) -> 0 | U93: =_xlfn.CONCAT(KamstrupData[[#This Row],[CountryCode]],"_",KamstrupData[[#This Row],[Business Area]],"_",KamstrupData[[#This Row],[DepartmentTeam]]) -> AT10_AT_Customer Service_ | V93: =VLOOKUP(KamstrupData[[#This Row],[ORG_Concat]],'O-Organization'!F:H,3,FALSE) -> 11025_AT10_Customer Service_AT_Customer Service_
D94: 1096-People and Culture-Retentation- | E94: =VLOOKUP(D94,'B-Business Capability'!B:H,5,FALSE) -> People and Culture | F94: =VLOOKUP(D94,'B-Business Capability'!B:H,6,FALSE) -> Retentation | G94: =VLOOKUP(D94,'B-Business Capability'!B:H,7,FALSE) -> 0 | I94: AT10 | J94: AT_Customer Service | L94: 477 - Oracle People Hub | M94: =VLOOKUP(L94,'A-Applications'!B:D,3,FALSE) -> Oracle People Hub | N94: Tolerate | O94: Business Operational | P94: P32-People Development-- | Q94: =VLOOKUP(KamstrupData[[#This Row],[IdLevel123]],'B-Business Capability'!B:L,10,FALSE) -> Hire-to-Retire (H2R) | R94: =VLOOKUP(KamstrupData[[#This Row],[IdLevel123]],'B-Business Capability'!B:L,11,FALSE) -> 600 | U94: =_xlfn.CONCAT(KamstrupData[[#This Row],[CountryCode]],"_",KamstrupData[[#This Row],[Business Area]],"_",KamstrupData[[#This Row],[DepartmentTeam]]) -> AT10_AT_Customer Service_ | V94: =VLOOKUP(KamstrupData[[#This Row],[ORG_Concat]],'O-Organization'!F:H,3,FALSE) -> 11025_AT10_Customer Service_AT_Customer Service_
D95: 4233-Customer Service-Customer Project Management-Project Management | E95: =VLOOKUP(D95,'B-Business Capability'!B:H,5,FALSE) -> Customer Service | F95: =VLOOKUP(D95,'B-Business Capability'!B:H,6,FALSE) -> Customer Project Management | G95: =VLOOKUP(D95,'B-Business Capability'!B:H,7,FALSE) -> Project Management | I95: AT10 | J95: AT_Customer Service | L95: 481 - Google Earth | M95: =VLOOKUP(L95,'A-Applications'!B:D,3,FALSE) -> Google Earth | N95: Tolerate | O95: Business Operational | P95: P12-Customer Solution Deployment-- | Q95: =VLOOKUP(KamstrupData[[#This Row],[IdLevel123]],'B-Business Capability'!B:L,10,FALSE) -> Order-to-Cash (O2C) | R95: =VLOOKUP(KamstrupData[[#This Row],[IdLevel123]],'B-Business Capability'!B:L,11,FALSE) -> 0 | U95: =_xlfn.CONCAT(KamstrupData[[#This Row],[CountryCode]],"_",KamstrupData[[#This Row],[Business Area]],"_",KamstrupData[[#This Row],[DepartmentTeam]]) -> AT10_AT_Customer Service_ | V95: =VLOOKUP(KamstrupData[[#This Row],[ORG_Concat]],'O-Organization'!F:H,3,FALSE) -> 11025_AT10_Customer Service_AT_Customer Service_
D96: 4203-Customer Service-Customer Service and Support-Service Request Management | E96: =VLOOKUP(D96,'B-Business Capability'!B:H,5,FALSE) -> Customer Service | F96: =VLOOKUP(D96,'B-Business Capability'!B:H,6,FALSE) -> Customer Service and Support | G96: =VLOOKUP(D96,'B-Business Capability'!B:H,7,FALSE) -> Service Request Management | I96: AT10 | J96: AT_Customer Service | L96: 482 - Google Earth Pro | M96: =VLOOKUP(L96,'A-Applications'!B:D,3,FALSE) -> Google Earth Pro | N96: Tolerate | O96: Business Operational | P96: P13-Customer Service & Operation-- | Q96: =VLOOKUP(KamstrupData[[#This Row],[IdLevel123]],'B-Business Capability'!B:L,10,FALSE) -> Customer Service and Support | R96: =VLOOKUP(KamstrupData[[#This Row],[IdLevel123]],'B-Business Capability'!B:L,11,FALSE) -> 0 | U96: =_xlfn.CONCAT(KamstrupData[[#This Row],[CountryCode]],"_",KamstrupData[[#This Row],[Business Area]],"_",KamstrupData[[#This Row],[DepartmentTeam]]) -> AT10_AT_Customer Service_ | V96: =VLOOKUP(KamstrupData[[#This Row],[ORG_Concat]],'O-Organization'!F:H,3,FALSE) -> 11025_AT10_Customer Service_AT_Customer Service_
D97: 4233-Customer Service-Customer Project Management-Project Management | E97: =VLOOKUP(D97,'B-Business Capability'!B:H,5,FALSE) -> Customer Service | F97: =VLOOKUP(D97,'B-Business Capability'!B:H,6,FALSE) -> Customer Project Management | G97: =VLOOKUP(D97,'B-Business Capability'!B:H,7,FALSE) -> Project Management | I97: AT10 | J97: AT_Customer Service | L97: 482 - Google Earth Pro | M97: =VLOOKUP(L97,'A-Applications'!B:D,3,FALSE) -> Google Earth Pro | N97: Tolerate | O97: Business Operational | P97: P12-Customer Solution Deployment-- | Q97: =VLOOKUP(KamstrupData[[#This Row],[IdLevel123]],'B-Business Capability'!B:L,10,FALSE) -> Order-to-Cash (O2C) | R97: =VLOOKUP(KamstrupData[[#This Row],[IdLevel123]],'B-Business Capability'!B:L,11,FALSE) -> 0 | U97: =_xlfn.CONCAT(KamstrupData[[#This Row],[CountryCode]],"_",KamstrupData[[#This Row],[Business Area]],"_",KamstrupData[[#This Row],[DepartmentTeam]]) -> AT10_AT_Customer Service_ | V97: =VLOOKUP(KamstrupData[[#This Row],[ORG_Concat]],'O-Organization'!F:H,3,FALSE) -> 11025_AT10_Customer Service_AT_Customer Service_
D98: 4233-Customer Service-Customer Project Management-Project Management | E98: =VLOOKUP(D98,'B-Business Capability'!B:H,5,FALSE) -> Customer Service | F98: =VLOOKUP(D98,'B-Business Capability'!B:H,6,FALSE) -> Customer Project Management | G98: =VLOOKUP(D98,'B-Business Capability'!B:H,7,FALSE) -> Project Management | I98: AT10 | J98: AT_Customer Service | L98: 482 - Google Earth Pro | M98: =VLOOKUP(L98,'A-Applications'!B:D,3,FALSE) -> Google Earth Pro | N98: Tolerate | O98: Business Operational | P98: P13-Customer Service & Operation-- | Q98: =VLOOKUP(KamstrupData[[#This Row],[IdLevel123]],'B-Business Capability'!B:L,10,FALSE) -> Order-to-Cash (O2C) | R98: =VLOOKUP(KamstrupData[[#This Row],[IdLevel123]],'B-Business Capability'!B:L,11,FALSE) -> 0 | U98: =_xlfn.CONCAT(KamstrupData[[#This Row],[CountryCode]],"_",KamstrupData[[#This Row],[Business Area]],"_",KamstrupData[[#This Row],[DepartmentTeam]]) -> AT10_AT_Customer Service_ | V98: =VLOOKUP(KamstrupData[[#This Row],[ORG_Concat]],'O-Organization'!F:H,3,FALSE) -> 11025_AT10_Customer Service_AT_Customer Service_
D99: 4203-Customer Service-Customer Service and Support-Service Request Management | E99: =VLOOKUP(D99,'B-Business Capability'!B:H,5,FALSE) -> Customer Service | F99: =VLOOKUP(D99,'B-Business Capability'!B:H,6,FALSE) -> Customer Service and Support | G99: =VLOOKUP(D99,'B-Business Capability'!B:H,7,FALSE) -> Service Request Management | I99: AT10 | J99: AT_Customer Service | L99: 488 - Microsoft CoPilot | M99: =VLOOKUP(L99,'A-Applications'!B:D,3,FALSE) -> Microsoft CoPilot | N99: Invest | O99: Business Operational | P99: P13-Customer Service & Operation-- | Q99: =VLOOKUP(KamstrupData[[#This Row],[IdLevel123]],'B-Business Capability'!B:L,10,FALSE) -> Customer Service and Support | R99: =VLOOKUP(KamstrupData[[#This Row],[IdLevel123]],'B-Business Capability'!B:L,11,FALSE) -> 0 | U99: =_xlfn.CONCAT(KamstrupData[[#This Row],[CountryCode]],"_",KamstrupData[[#This Row],[Business Area]],"_",KamstrupData[[#This Row],[DepartmentTeam]]) -> AT10_AT_Customer Service_ | V99: =VLOOKUP(KamstrupData[[#This Row],[ORG_Concat]],'O-Organization'!F:H,3,FALSE) -> 11025_AT10_Customer Service_AT_Customer Service_
D100: 4233-Customer Service-Customer Project Management-Project Management | E100: =VLOOKUP(D100,'B-Business Capability'!B:H,5,FALSE) -> Customer Service | F100: =VLOOKUP(D100,'B-Business Capability'!B:H,6,FALSE) -> Customer Project Management | G100: =VLOOKUP(D100,'B-Business Capability'!B:H,7,FALSE) -> Project Management | I100: AT10 | J100: AT_Customer Service | L100: 488 - Microsoft CoPilot | M100: =VLOOKUP(L100,'A-Applications'!B:D,3,FALSE) -> Microsoft CoPilot | N100: Invest | O100: Business Operational | P100: P12-Customer Solution Deployment-- | Q100: =VLOOKUP(KamstrupData[[#This Row],[IdLevel123]],'B-Business Capability'!B:L,10,FALSE) -> Order-to-Cash (O2C) | R100: =VLOOKUP(KamstrupData[[#This Row],[IdLevel123]],'B-Business Capability'!B:L,11,FALSE) -> 0 | U100: =_xlfn.CONCAT(KamstrupData[[#This Row],[CountryCode]],"_",KamstrupData[[#This Row],[Business Area]],"_",KamstrupData[[#This Row],[DepartmentTeam]]) -> AT10_AT_Customer Service_ | V100: =VLOOKUP(KamstrupData[[#This Row],[ORG_Concat]],'O-Organization'!F:H,3,FALSE) -> 11025_AT10_Customer Service_AT_Customer Service_
D101: 4233-Customer Service-Customer Project Management-Project Management | E101: =VLOOKUP(D101,'B-Business Capability'!B:H,5,FALSE) -> Customer Service | F101: =VLOOKUP(D101,'B-Business Capability'!B:H,6,FALSE) -> Customer Project Management | G101: =VLOOKUP(D101,'B-Business Capability'!B:H,7,FALSE) -> Project Management | I101: AT10 | J101: AT_Customer Service | L101: 488 - Microsoft CoPilot | M101: =VLOOKUP(L101,'A-Applications'!B:D,3,FALSE) -> Microsoft CoPilot | N101: Tolerate | O101: Business Operational | P101: P12-Customer Solution Deployment-- | Q101: =VLOOKUP(KamstrupData[[#This Row],[IdLevel123]],'B-Business Capability'!B:L,10,FALSE) -> Order-to-Cash (O2C) | R101: =VLOOKUP(KamstrupData[[#This Row],[IdLevel123]],'B-Business Capability'!B:L,11,FALSE) -> 0 | U101: =_xlfn.CONCAT(KamstrupData[[#This Row],[CountryCode]],"_",KamstrupData[[#This Row],[Business Area]],"_",KamstrupData[[#This Row],[DepartmentTeam]]) -> AT10_AT_Customer Service_ | V101: =VLOOKUP(KamstrupData[[#This Row],[ORG_Concat]],'O-Organization'!F:H,3,FALSE) -> 11025_AT10_Customer Service_AT_Customer Service_
D102: 4233-Customer Service-Customer Project Management-Project Management | E102: =VLOOKUP(D102,'B-Business Capability'!B:H,5,FALSE) -> Customer Service | F102: =VLOOKUP(D102,'B-Business Capability'!B:H,6,FALSE) -> Customer Project Management | G102: =VLOOKUP(D102,'B-Business Capability'!B:H,7,FALSE) -> Project Management | I102: AT10 | J102: AT_Customer Service | L102: 5 - Oracle CPQ | M102: =VLOOKUP(L102,'A-Applications'!B:D,3,FALSE) -> Oracle CPQ | N102: Tolerate | O102: Business Operational | P102: P12-Customer Solution Deployment-- | Q102: =VLOOKUP(KamstrupData[[#This Row],[IdLevel123]],'B-Business Capability'!B:L,10,FALSE) -> Order-to-Cash (O2C) | R102: =VLOOKUP(KamstrupData[[#This Row],[IdLevel123]],'B-Business Capability'!B:L,11,FALSE) -> 0 | U102: =_xlfn.CONCAT(KamstrupData[[#This Row],[CountryCode]],"_",KamstrupData[[#This Row],[Business Area]],"_",KamstrupData[[#This Row],[DepartmentTeam]]) -> AT10_AT_Customer Service_ | V102: =VLOOKUP(KamstrupData[[#This Row],[ORG_Concat]],'O-Organization'!F:H,3,FALSE) -> 11025_AT10_Customer Service_AT_Customer Service_
D103: 1133-Finance-Financial Planning & Analysis-Forecasting | E103: =VLOOKUP(D103,'B-Business Capability'!B:H,5,FALSE) -> Finance | F103: =VLOOKUP(D103,'B-Business Capability'!B:H,6,FALSE) -> Financial Planning & Analysis | G103: =VLOOKUP(D103,'B-Business Capability'!B:H,7,FALSE) -> Forecasting | I103: AT10 | J103: AT_Customer Service | L103: 505 - SAP Analytics Cloud | M103: =VLOOKUP(L103,'A-Applications'!B:D,3,FALSE) -> SAP Analytics Cloud | N103: Tolerate | O103: Business Operational | P103: P18-Budget-- | Q103: =VLOOKUP(KamstrupData[[#This Row],[IdLevel123]],'B-Business Capability'!B:L,10,FALSE) -> N/A | R103: =VLOOKUP(KamstrupData[[#This Row],[IdLevel123]],'B-Business Capability'!B:L,11,FALSE) -> 0 | U103: =_xlfn.CONCAT(KamstrupData[[#This Row],[CountryCode]],"_",KamstrupData[[#This Row],[Business Area]],"_",KamstrupData[[#This Row],[DepartmentTeam]]) -> AT10_AT_Customer Service_ | V103: =VLOOKUP(KamstrupData[[#This Row],[ORG_Concat]],'O-Organization'!F:H,3,FALSE) -> 11025_AT10_Customer Service_AT_Customer Service_
D104: 1291-Strategic Management-Manage Core Business-Manage Projects | E104: =VLOOKUP(D104,'B-Business Capability'!B:H,5,FALSE) -> Strategic Management | F104: =VLOOKUP(D104,'B-Business Capability'!B:H,6,FALSE) -> Manage Core Business | G104: =VLOOKUP(D104,'B-Business Capability'!B:H,7,FALSE) -> Manage Projects | I104: AT10 | J104: AT_Customer Service | L104: 505 - SAP Analytics Cloud | M104: =VLOOKUP(L104,'A-Applications'!B:D,3,FALSE) -> SAP Analytics Cloud | N104: Tolerate | O104: Business Critical | P104: P12-Customer Solution Deployment-- | Q104: =VLOOKUP(KamstrupData[[#This Row],[IdLevel123]],'B-Business Capability'!B:L,10,FALSE) -> N/A | R104: =VLOOKUP(KamstrupData[[#This Row],[IdLevel123]],'B-Business Capability'!B:L,11,FALSE) -> 0 | U104: =_xlfn.CONCAT(KamstrupData[[#This Row],[CountryCode]],"_",KamstrupData[[#This Row],[Business Area]],"_",KamstrupData[[#This Row],[DepartmentTeam]]) -> AT10_AT_Customer Service_ | V104: =VLOOKUP(KamstrupData[[#This Row],[ORG_Concat]],'O-Organization'!F:H,3,FALSE) -> 11025_AT10_Customer Service_AT_Customer Service_
D105: 3069-Sales-Sales Execution and Customer Engagement-Project selling | E105: =VLOOKUP(D105,'B-Business Capability'!B:H,5,FALSE) -> Sales | F105: =VLOOKUP(D105,'B-Business Capability'!B:H,6,FALSE) -> Sales Execution and Customer Engagement | G105: =VLOOKUP(D105,'B-Business Capability'!B:H,7,FALSE) -> Project selling | I105: AT10 | J105: AT_Customer Service | L105: 508 - VIS-Quote Calculation Tool | M105: =VLOOKUP(L105,'A-Applications'!B:D,3,FALSE) -> VIS-Quote Calculation Tool | O105: Business Operational | P105: P12-Customer Solution Deployment-- | Q105: =VLOOKUP(KamstrupData[[#This Row],[IdLevel123]],'B-Business Capability'!B:L,10,FALSE) -> Order-to-Cash (O2C) | R105: =VLOOKUP(KamstrupData[[#This Row],[IdLevel123]],'B-Business Capability'!B:L,11,FALSE) -> 550 | U105: =_xlfn.CONCAT(KamstrupData[[#This Row],[CountryCode]],"_",KamstrupData[[#This Row],[Business Area]],"_",KamstrupData[[#This Row],[DepartmentTeam]]) -> AT10_AT_Customer Service_ | V105: =VLOOKUP(KamstrupData[[#This Row],[ORG_Concat]],'O-Organization'!F:H,3,FALSE) -> 11025_AT10_Customer Service_AT_Customer Service_
D106: 3210-Sales-Quotation, Order, and Contract Management-Tender or Bid management | E106: =VLOOKUP(D106,'B-Business Capability'!B:H,5,FALSE) -> Sales | F106: =VLOOKUP(D106,'B-Business Capability'!B:H,6,FALSE) -> Quotation, Order, and Contract Management | G106: =VLOOKUP(D106,'B-Business Capability'!B:H,7,FALSE) -> Tender or Bid management | I106: AT10 | J106: AT_Customer Service | L106: 508 - VIS-Quote Calculation Tool | M106: =VLOOKUP(L106,'A-Applications'!B:D,3,FALSE) -> VIS-Quote Calculation Tool | O106: Business Operational | P106: P09-Sales & Business Development-SP09.2-Solution Sales Non-Standard | Q106: =VLOOKUP(KamstrupData[[#This Row],[IdLevel123]],'B-Business Capability'!B:L,10,FALSE) -> Order-to-Cash (O2C) | R106: =VLOOKUP(KamstrupData[[#This Row],[IdLevel123]],'B-Business Capability'!B:L,11,FALSE) -> 104 | U106: =_xlfn.CONCAT(KamstrupData[[#This Row],[CountryCode]],"_",KamstrupData[[#This Row],[Business Area]],"_",KamstrupData[[#This Row],[DepartmentTeam]]) -> AT10_AT_Customer Service_ | V106: =VLOOKUP(KamstrupData[[#This Row],[ORG_Concat]],'O-Organization'!F:H,3,FALSE) -> 11025_AT10_Customer Service_AT_Customer Service_
D107: 4232-Customer Service-Customer Project Management-Financial Analytics and Management | E107: =VLOOKUP(D107,'B-Business Capability'!B:H,5,FALSE) -> Customer Service | F107: =VLOOKUP(D107,'B-Business Capability'!B:H,6,FALSE) -> Customer Project Management | G107: =VLOOKUP(D107,'B-Business Capability'!B:H,7,FALSE) -> Financial Analytics and Management | I107: AT10 | J107: AT_Customer Service | L107: 508 - VIS-Quote Calculation Tool | M107: =VLOOKUP(L107,'A-Applications'!B:D,3,FALSE) -> VIS-Quote Calculation Tool | O107: Business Operational | P107: P12-Customer Solution Deployment-- | Q107: =VLOOKUP(KamstrupData[[#This Row],[IdLevel123]],'B-Business Capability'!B:L,10,FALSE) -> Order-to-Cash (O2C) | R107: =VLOOKUP(KamstrupData[[#This Row],[IdLevel123]],'B-Business Capability'!B:L,11,FALSE) -> 0 | U107: =_xlfn.CONCAT(KamstrupData[[#This Row],[CountryCode]],"_",KamstrupData[[#This Row],[Business Area]],"_",KamstrupData[[#This Row],[DepartmentTeam]]) -> AT10_AT_Customer Service_ | V107: =VLOOKUP(KamstrupData[[#This Row],[ORG_Concat]],'O-Organization'!F:H,3,FALSE) -> 11025_AT10_Customer Service_AT_Customer Service_
D108: 4203-Customer Service-Customer Service and Support-Service Request Management | E108: =VLOOKUP(D108,'B-Business Capability'!B:H,5,FALSE) -> Customer Service | F108: =VLOOKUP(D108,'B-Business Capability'!B:H,6,FALSE) -> Customer Service and Support | G108: =VLOOKUP(D108,'B-Business Capability'!B:H,7,FALSE) -> Service Request Management | I108: AT10 | J108: AT_Customer Service | L108: 515 - Metertool X | M108: =VLOOKUP(L108,'A-Applications'!B:D,3,FALSE) -> Metertool X | N108: Tolerate | O108: Business Operational | P108: P13-Customer Service & Operation-- | Q108: =VLOOKUP(KamstrupData[[#This Row],[IdLevel123]],'B-Business Capability'!B:L,10,FALSE) -> Customer Service and Support | R108: =VLOOKUP(KamstrupData[[#This Row],[IdLevel123]],'B-Business Capability'!B:L,11,FALSE) -> 0 | U108: =_xlfn.CONCAT(KamstrupData[[#This Row],[CountryCode]],"_",KamstrupData[[#This Row],[Business Area]],"_",KamstrupData[[#This Row],[DepartmentTeam]]) -> AT10_AT_Customer Service_ | V108: =VLOOKUP(KamstrupData[[#This Row],[ORG_Concat]],'O-Organization'!F:H,3,FALSE) -> 11025_AT10_Customer Service_AT_Customer Service_
D109: 4233-Customer Service-Customer Project Management-Project Management | E109: =VLOOKUP(D109,'B-Business Capability'!B:H,5,FALSE) -> Customer Service | F109: =VLOOKUP(D109,'B-Business Capability'!B:H,6,FALSE) -> Customer Project Management | G109: =VLOOKUP(D109,'B-Business Capability'!B:H,7,FALSE) -> Project Management | I109: AT10 | J109: AT_Customer Service | L109: 515 - Metertool X | M109: =VLOOKUP(L109,'A-Applications'!B:D,3,FALSE) -> Metertool X | N109: Tolerate | O109: Business Operational | P109: P12-Customer Solution Deployment-- | Q109: =VLOOKUP(KamstrupData[[#This Row],[IdLevel123]],'B-Business Capability'!B:L,10,FALSE) -> Order-to-Cash (O2C) | R109: =VLOOKUP(KamstrupData[[#This Row],[IdLevel123]],'B-Business Capability'!B:L,11,FALSE) -> 0 | U109: =_xlfn.CONCAT(KamstrupData[[#This Row],[CountryCode]],"_",KamstrupData[[#This Row],[Business Area]],"_",KamstrupData[[#This Row],[DepartmentTeam]]) -> AT10_AT_Customer Service_ | V109: =VLOOKUP(KamstrupData[[#This Row],[ORG_Concat]],'O-Organization'!F:H,3,FALSE) -> 11025_AT10_Customer Service_AT_Customer Service_
...

Sheet A-Applications
D1: Name of the application | E1: Application group | F1: Introduction date of application. (Before 1/8-2025 all applications are set to 01-01-2025) | G1: Install Type - On Prem - Cloud - 3 party hosted - Edge Computing - Distributed Applications | H1: The Gartner TIME (Tolerate, Invest, Migrate, Eliminate) framework is the industry standard for planning and executing an application rationalization. It is a proven methodology for maximizing the business value of your application portfolio. | J1: Vendor Kamstrup purchace the application from | L1: Consultancy for the application | M1: The number of users for the application | N1: The current stage of the application | O1: End of life or Phase out date for the application (Format 31-06-2026) | R1: The URL of the application | S1: Business Owner of the application. Used for applications with no cost if handled in business | V1: Owner of the application. From cost sheet or if empty from Business owner | W1: Delete,Superusers of the application | Y1: Delete | Z1: EA Information related to closure of the application | AA1: Not relevant, SLA for the application | AB1: Not relevant, License responsible of the application | AC1: Sub component to applicatoin | AD1: Which applications are supported by the application. Eg. READy, OMNIA, etc | AE1: Primary in relation to cleanup track | AF1: The application contain AI features. If Yes the risk should be evaluated. | AG1: Set to "No" if the application are not used in capability mapping. Used for server licenses and so. | AH1: If the application are part of a Platform chose the platform. | AI1: Note on the application | AJ1: The recomendation for clean up | AK1: Reason for the recommendation | AL1: Workpackage size of the clousure (S, M, Project) | AM1: Security approved application | AN1: Security approved date | AO1: Security debt. Low Medium High (Inveigate are beeing security investigated) | AP1: Is this application seen as a crown jewel
H2: https://www.leanix.net/en/download/applying-the-gartner-time-framework-for-application-rationalization?utm_term=gartner%20time%20model&utm_source=bing&utm_medium=ppc&utm_campaign=EMEA-NORDIC_Application-Rationalization_AR_Search_ENG_B&hsa_acc=9751618594&hsa_cam=590193139&hsa_grp=1136896741662464&hsa_kw=gartner%20time%20model&hsa_mt=e&hsa_net=bing&hsa_src=o&hsa_tgt=kwd-71056741979861:loc-53&hsa_ad=&hsa_ver=3&msclkid=a7b7b4e697911d431c1dd255b34cacf3&utm_content=NORDIC_gartner-time-framework
B3: NoApplication | C3: No | D3: Application | E3: Application Group | F3: Introduction date | G3: Install type | H3: Gartner TIME | I3: Application Type | J3: Software Vendor | K3: ItemNumber | L3: Consultancy | M3: User base | N3: Lifecycle stage status | O3: Expected End-of-Life Year | P3: Replaced by | Q3: Details | R3: URL | S3: Business Owner | T3: Tier | U3: Details2 | V3: Owner | W3: Super User | X3: Named users | Y3: OLD-Data integration | Z3: Temp | AA3: SLA | AB3: Licens responsible | AC3: Sub component to | AD3: Supporting applications | AE3: Org | AF3: AI | AG3: Used in capabilitiy mapping | AH3: Platform | AI3: Clean up: Note | AJ3: Clean up: Recomendation | AK3: Clean up: Reason | AL3: Clean up: WP Size | AM3: Security approved | AN3: Security Approved date | AO3: Security debt | AP3: Crown Jewels
B4: =_xlfn.CONCAT(Applications[[#This Row],[No]]," - ",Applications[[#This Row],[Application]]) -> 1 - IFS ERP | C4: 1 | D4: IFS ERP | E4: Enterprise Platforms | F4: 45658 | G4: On Premise | H4: Invest | I4: Standard solutions | J4: IFS AB | L4: IFS | M4: 1000-> | N4: 1-Strategic | O4: 46813 | Q4: IFS Apps 10 has End of life 1-3-2028. Transsition for new version are projected. | T4: T0 | U4: Ny licensaftale, generel prisstigning | V4: =_xlfn.XLOOKUP(Applications[[#This Row],[NoApplication]],AApplicationCosts[NoApplication],AApplicationCosts[License Owner],Applications[[#This Row],[Business Owner]],0,1) -> KRNO | AB4: KRTI | AE4: Finans | AH4: IFS | AI4: Note for cleanup | AJ4: Keep as strategic | AK4: It is our ERP system | AM4: Yes | AN4: 45658 | AO4: Low | AP4: Crown Jewel_1
B5: =_xlfn.CONCAT(Applications[[#This Row],[No]]," - ",Applications[[#This Row],[Application]]) -> 2 - QAD ERP | C5: 2 | D5: QAD ERP | E5: Business | F5: 45658 | G5: On Premise | H5: Eliminate | I5: Standard solutions | J5: QAD Inc. | L5: Kamstrup | M5: 50-99 | N5: 8-Phase out | O5: 47484 | P5: IFS ERP | Q5: QAD ERP: QAD ERP is a cloud-based enterprise resource planning solution designed specifically for manufacturers. It offers comprehensive solutions for supply chain management, production planning, inventory control, quality management, and regulatory compliance | T5: T1-D | U5: Old ERP system, are only used for viewing of old data. Serial no., Sales invoice, Purchase invoice. Comment 20/11-2024 Ole F har talt lidt med div. I Service vedr. deres aktuelle brug af systemet. Det lyder til (og der kommer en opfølgning på det) at der er brug for meget lidt data. Så jeg vil foreslå at vi laver en analyse / export af disse data til et Excel ark, og derefter officielt lukker systemet 😊 /Ole | V5: =_xlfn.XLOOKUP(Applications[[#This Row],[NoApplication]],AApplicationCosts[NoApplication],AApplicationCosts[License Owner],Applications[[#This Row],[Business Owner]],0,1) -> KRNO | AB5: KRTI | AE5: Supply Chain | AH5: QAD | AI5: Jf. bogføringsloven skal noget data gemmes i 5 år (sidste fakturering i 2021). Fra Ole: Jeg tænker det betyder at MFG (som er endnu ældre - data fra 1997 .. 2011) også skal med. Blot til info: - Tænker det er et projekt o Vi skal have information om vores serienumre i mindst 20 år så vidt jeg ved. o Og mere detaljeret i ca 10 år o Begge dele må kunne gemmes i BI på en eller anden måde o Det vil også kræve ændringer i Integration – da de så vil skulle lave serial lookup i BI istedet for i QAD/MFG - En anden udfordring er nok at jeg er den eneste med QAD/MFG viden i Kamstrup. Ole | AL5: M
B6: =_xlfn.CONCAT(Applications[[#This Row],[No]]," - ",Applications[[#This Row],[Application]]) -> 3 - Aras Innovator PLM | C6: 3 | D6: Aras Innovator PLM | E6: Business | F6: 45658 | G6: On Premise | I6: Standard solutions | J6: Aras Corporation | L6: Aras | M6: 100-499 | N6: 1-Strategic | O6: 54788 | Q6: Aras Innovator PLM: Aras Innovator PLM is a flexible, scalable, and upgradeable product lifecycle management software. It supports manufacturers of complex, connected products in digitally transforming their engineering business. It includes features like parts management, change management, document management, and quality management | T6: T0 | U6: non-standard / potentiale for forbedring | V6: =_xlfn.XLOOKUP(Applications[[#This Row],[NoApplication]],AApplicationCosts[NoApplication],AApplicationCosts[License Owner],Applications[[#This Row],[Business Owner]],0,1) -> KRNO | X6: JES, AOE, FHB | AB6: FRFS | AE6: Supply Chain | AH6: Aras Innovator
B7: =_xlfn.CONCAT(Applications[[#This Row],[No]]," - ",Applications[[#This Row],[Application]]) -> 4 - Microsoft Dynamics 365 CE (Sales) | C7: 4 | D7: Microsoft Dynamics 365 CE (Sales) | E7: Enterprise Platforms | F7: 45658 | G7: Cloud | I7: Standard solutions | J7: Microsoft | K7: DGP-00003 | L7: Netcompany | M7: 100-499 | N7: 1-Strategic | O7: 54788 | Q7: Microsoft Dynamics 365 CE (Sales): Microsoft Dynamics 365 Customer Engagement (CE) Sales is a customer relationship management (CRM) solution that helps sales teams build strong relationships with customers, take actions based on insights, and close deals faster. It includes features like account and contact management, lead and opportunity management, and sales forecasting | R7: https://kamstrup.crm4.dynamics.com/ | S7: MIBN | T7: T0 | V7: =_xlfn.XLOOKUP(Applications[[#This Row],[NoApplication]],AApplicationCosts[NoApplication],AApplicationCosts[License Owner],Applications[[#This Row],[Business Owner]],0,1) -> ALK | AA7: SLA | AB7: Susanne, JTBN | AE7: Sales & Marketing | AF7: Yes | AH7: Dynamics 365
B8: =_xlfn.CONCAT(Applications[[#This Row],[No]]," - ",Applications[[#This Row],[Application]]) -> 5 - Oracle CPQ | C8: 5 | D8: Oracle CPQ | E8: Enterprise Platforms | F8: 45658 | I8: Standard solutions | J8: Oracle Corporation | L8: Solutionspace | M8: 100-499 | N8: 1-Strategic | O8: 54788 | Q8: Oracle CPQ: Oracle Configure, Price, Quote (CPQ) is a cloud-based application that helps sellers configure the right mix of products or services and create accurate, professional quotes to quickly meet their customers’ pricing needs. It streamlines the entire opportunity-to-quote-to-order process | T8: T0 | U8: General stigning | V8: =_xlfn.XLOOKUP(Applications[[#This Row],[NoApplication]],AApplicationCosts[NoApplication],AApplicationCosts[License Owner],Applications[[#This Row],[Business Owner]],0,1) -> ALK | AB8: JTBN | AE8: Sales & Marketing | AH8: Oracle
B9: =_xlfn.CONCAT(Applications[[#This Row],[No]]," - ",Applications[[#This Row],[Application]]) -> 6 - ServiceNow | C9: 6 | D9: ServiceNow | E9: Business | F9: 45658 | G9: Cloud | H9: Invest | I9: Standard solutions | J9: ServiceNow Inc. | L9: Devoteam | M9: 1000-> | N9: 1-Strategic | O9: 54788 | Q9: ServiceNow: ServiceNow is a cloud-based enterprise workflow automation platform delivered as Software-as-a-Service (SaaS). It automates various business processes, including IT service management, customer service management, and project approvals, on a single, centralized platform | T9: T0 | U9: ITSM, Web portal | V9: =_xlfn.XLOOKUP(Applications[[#This Row],[NoApplication]],AApplicationCosts[NoApplication],AApplicationCosts[License Owner],Applications[[#This Row],[Business Owner]],0,1) -> JEHT | AB9: JEHT | AE9: Supply Chain | AF9: Yes - Minimal Risk | AH9: ServiceNow
B10: =_xlfn.CONCAT(Applications[[#This Row],[No]]," - ",Applications[[#This Row],[Application]]) -> 7 - Reliance | C10: 7 | D10: Reliance | E10: Quality Management System | F10: 45658 | G10: Cloud | I10: Standard solutions | J10: Reliance Industries Limited | L10: ETQ | N10: 8-Phase out | O10: 46477 | Q10: Reliance: Reliance is a governance, risk, and compliance (GRC) software solution that helps organizations streamline their risk management processes, ensure regulatory compliance, and enhance overall operational efficiency | T10: T1-D | U10: QMS - Quality Management System | V10: =_xlfn.XLOOKUP(Applications[[#This Row],[NoApplication]],AApplicationCosts[NoApplication],AApplicationCosts[License Owner],Applications[[#This Row],[Business Owner]],0,1) -> KRNO | AE10: Quality | AI10: Phase out and move to IFS, ServiceNow and IPW. Info on phase out from KRNO. | AL10: Project-paused
B11: =_xlfn.CONCAT(Applications[[#This Row],[No]]," - ",Applications[[#This Row],[Application]]) -> 8 - Neuron | C11: 8 | D11: Neuron | E11: Integration Platforms | F11: 45658 | I11: Standard solutions | J11: Neuron ESB | L11: Integrator | N11: 8-Phase out | O11: 46387 | P11: Azure | Q11: Neuron: Neuron is a simulation environment for modeling individual neurons and networks of neurons. It provides tools for building, managing, and using models in a way that is numerically sound and computationally efficient | T11: T1-D | U11: Integration | V11: =_xlfn.XLOOKUP(Applications[[#This Row],[NoApplication]],AApplicationCosts[NoApplication],AApplicationCosts[License Owner],Applications[[#This Row],[Business Owner]],0,1) -> KRNO | AB11: FFM | AC11: 8 - Neuron | AE11: Digitalization | AI11: Project of phase out are started with Jeyant in integration team | AL11: Project-initiated
B12: =_xlfn.CONCAT(Applications[[#This Row],[No]]," - ",Applications[[#This Row],[Application]]) -> 9 - Orbit | C12: 9 | D12: Orbit | E12: Communication | F12: 45658 | G12: Cloud | I12: Standard solutions | J12: Secoya A/S, Orbit Online A/S | L12: Secoya A/S | M12: 50-99 | N12: 7-Potential for phase out | O12: 54788 | Q12: Orbit: Orbit is a reporting and analytics solution suitable for businesses of any size. It includes features like automated reporting, report exporting, and interactive dashboards to monitor business metrics and KPIs in real-time | T12: T1-D | U12: Project Sales, replaces Sharepoint 2003 site | V12: =_xlfn.XLOOKUP(Applications[[#This Row],[NoApplication]],AApplicationCosts[NoApplication],AApplicationCosts[License Owner],Applications[[#This Row],[Business Owner]],0,1) -> ASRN | AB12: FRFS | AE12: Supply Chain | AI12: Close | AL12: Project-paused
B13: =_xlfn.CONCAT(Applications[[#This Row],[No]]," - ",Applications[[#This Row],[Application]]) -> 10 - Encryption Key Service (EKS) | C13: 10 | D13: Encryption Key Service (EKS) | E13: Kamstrup - Customer Software | F13: 45658 | I13: Customer Experience | J13: Kamstrup | N13: 3-Kamstrup application | O13: 54788 | Q13: Encryption Key Service (EKS): EKS is a service that provides encryption key management for securing sensitive data. It integrates with various applications to ensure data is encrypted and protected throughout its lifecycle. Consist of many services | T13: T2 | V13: =_xlfn.XLOOKUP(Applications[[#This Row],[NoApplication]],AApplicationCosts[NoApplication],AApplicationCosts[License Owner],Applications[[#This Row],[Business Owner]],0,1) -> SSY, GCPE | AP13: Crown Jewel_1
B14: =_xlfn.CONCAT(Applications[[#This Row],[No]]," - ",Applications[[#This Row],[Application]]) -> 12 - My Kamstrup | C14: 12 | D14: My Kamstrup | E14: Business | F14: 45658 | I14: Customer Experience | J14: Kamstrup | M14: 1000-> | N14: 2-Important application | O14: 54788 | Q14: My Kamstrup: My Kamstrup is a customer portal platform that provides access to various Kamstrup applications and services. It includes features like user administration, encryption key management, subscription management, and case creation | T14: T2 | U14: FRFS info from US: MyKamstrup virker ikke ordentligt, aktiveringsmail ryger i spam ofte. Her burde man virkelig ændre på customer experience. | V14: =_xlfn.XLOOKUP(Applications[[#This Row],[NoApplication]],AApplicationCosts[NoApplication],AApplicationCosts[License Owner],Applications[[#This Row],[Business Owner]],0,1) -> 0 | AE14: Sales & Marketing
B15: =_xlfn.CONCAT(Applications[[#This Row],[No]]," - ",Applications[[#This Row],[Application]]) -> 15 - JIRA | C15: 15 | D15: JIRA | E15: Business | F15: 45658 | G15: Cloud | I15: Development Tools | J15: Atlassian | L15: Atlassian, Eficode A/S | M15: 500-999 | N15: 1-Strategic | O15: 54788 | Q15: JIRA: JIRA is a project management and issue-tracking software developed by Atlassian. It is used for bug tracking, issue tracking, and project management, and is widely used by software development teams. | T15: T0 | U15: Bitbucket is mostly used for code and code review | V15: =_xlfn.XLOOKUP(Applications[[#This Row],[NoApplication]],AApplicationCosts[NoApplication],AApplicationCosts[License Owner],Applications[[#This Row],[Business Owner]],0,1) -> LAAG | AB15: FRFS | AE15: Software, Hardware Departments | AH15: Atlassian | AK15: Strategic decision to use it
B16: =_xlfn.CONCAT(Applications[[#This Row],[No]]," - ",Applications[[#This Row],[Application]]) -> 16 - BitBucket | C16: 16 | D16: BitBucket | E16: Development and Programming | F16: 45658 | G16: Cloud | I16: Development Tools | J16: Atlassian | N16: 5-Investigate | O16: 54788 | Q16: BitBucket: BitBucket is a web-based version control repository hosting service owned by Atlassian. It supports Git and Mercurial version control systems and is used for source code management and collaboration. | S16: LAAG | T16: T1-D | U16: Jira is used for issue tracking and project management | V16: =_xlfn.XLOOKUP(Applications[[#This Row],[NoApplication]],AApplicationCosts[NoApplication],AApplicationCosts[License Owner],Applications[[#This Row],[Business Owner]],0,1) -> LAAG | AH16: Atlassian
B17: =_xlfn.CONCAT(Applications[[#This Row],[No]]," - ",Applications[[#This Row],[Application]]) -> 17 - TFS | C17: 17 | D17: TFS | E17: Development and Programming | F17: 45658 | I17: Development Tools | J17: Microsoft | N17: 5-Investigate | O17: 54788 | Q17: TFS: Team Foundation Server (TFS) is a Microsoft product that provides source code management, project management, and build automation for software development projects. It supports version control, work item tracking, and continuous integration. | T17: T2 | V17: =_xlfn.XLOOKUP(Applications[[#This Row],[NoApplication]],AApplicationCosts[NoApplication],AApplicationCosts[License Owner],Applications[[#This Row],[Business Owner]],0,1) -> 0
B18: =_xlfn.CONCAT(Applications[[#This Row],[No]]," - ",Applications[[#This Row],[Application]]) -> 18 - Microsoft Visual Studio Pro MSDN | C18: 18 | D18: Microsoft Visual Studio Pro MSDN | E18: Development and Programming | F18: 45658 | G18: Distributed Applications | I18: Development Tools | J18: Microsoft | K18: 77D-00111 | M18: 50-99 | N18: 1-Strategic | O18: 54788 | Q18: Microsoft Visual Studio: Microsoft Visual Studio is an integrated development environment (IDE) used for developing applications, websites, and services. It supports various programming languages and includes features like code editing, debugging, and testing. | T18: T0 | V18: =_xlfn.XLOOKUP(Applications[[#This Row],[NoApplication]],AApplicationCosts[NoApplication],AApplicationCosts[License Owner],Applications[[#This Row],[Business Owner]],0,1) -> LAAG | AB18: Susanne | AD18: IDE | AE18: Software, Hardware Departments | AH18: Microsoft Developper | AJ18: Tolerate/Invest | AK18: Widely used for .NET development
B19: =_xlfn.CONCAT(Applications[[#This Row],[No]]," - ",Applications[[#This Row],[Application]]) -> 19 - TMS | C19: 19 | D19: TMS | E19: Utilities and Miscellaneous | F19: 45658 | I19: ERP Integrated Solutions | J19: Transporeon | N19: 4-Saved for now | O19: 54788 | Q19: TMS: Transportation Management System (TMS) is a software solution that helps organizations manage and optimize their transportation operations. It includes features like route planning, carrier selection, shipment tracking, and freight payment. | S19: KRNO | T19: T3 | V19: =_xlfn.XLOOKUP(Applications[[#This Row],[NoApplication]],AApplicationCosts[NoApplication],AApplicationCosts[License Owner],Applications[[#This Row],[Business Owner]],0,1) -> KRNO | AE19: Supply Chain
B20: =_xlfn.CONCAT(Applications[[#This Row],[No]]," - ",Applications[[#This Row],[Application]]) -> 21 - Subscription Manager | C20: 21 | D20: Subscription Manager | E20: Utilities and Miscellaneous | F20: 45658 | I20: ERP Integrated Solutions | J20: Flexera Software | N20: 5-Investigate | O20: 54788 | Q20: Subscription Manager: Subscription Manager is a software solution that helps organizations manage their subscription-based services. It includes features like subscription billing, customer management, and analytics. | T20: T2 | V20: =_xlfn.XLOOKUP(Applications[[#This Row],[NoApplication]],AApplicationCosts[NoApplication],AApplicationCosts[License Owner],Applications[[#This Row],[Business Owner]],0,1) -> 0
B21: =_xlfn.CONCAT(Applications[[#This Row],[No]]," - ",Applications[[#This Row],[Application]]) -> 23 - Readsoft | C21: 23 | D21: Readsoft | E21: Business | F21: 45658 | I21: ERP Integrated Solutions | J21: Kofax | M21: 10-49 | N21: 4-Saved for now | O21: 54788 | Q21: Readsoft: Readsoft is a software solution for automating document processing. It includes features like optical character recognition (OCR), data extraction, and workflow automation to streamline document management processes. | T21: T2 | V21: =_xlfn.XLOOKUP(Applications[[#This Row],[NoApplication]],AApplicationCosts[NoApplication],AApplicationCosts[License Owner],Applications[[#This Row],[Business Owner]],0,1) -> 0 | AB21: KRTI | AE21: Finans | AI21: Set to Save for now with KRTI
B22: =_xlfn.CONCAT(Applications[[#This Row],[No]]," - ",Applications[[#This Row],[Application]]) -> 24 - Pipechain | C22: 24 | D22: Pipechain | E22: Utilities and Miscellaneous | F22: 45658 | I22: ERP Integrated Solutions | J22: Pipechain, Inc. | N22: 5-Investigate | O22: 54788 | T22: T2 | V22: =_xlfn.XLOOKUP(Applications[[#This Row],[NoApplication]],AApplicationCosts[NoApplication],AApplicationCosts[License Owner],Applications[[#This Row],[Business Owner]],0,1) -> 0
B23: =_xlfn.CONCAT(Applications[[#This Row],[No]]," - ",Applications[[#This Row],[Application]]) -> 25 - PJD 3P | C23: 25 | D23: PJD 3P | E23: Utilities and Miscellaneous | F23: 45658 | I23: Production IT | J23: PJD Group | N23: 5-Investigate | O23: 54788 | T23: T2 | V23: =_xlfn.XLOOKUP(Applications[[#This Row],[NoApplication]],AApplicationCosts[NoApplication],AApplicationCosts[License Owner],Applications[[#This Row],[Business Owner]],0,1) -> 0
B24: =_xlfn.CONCAT(Applications[[#This Row],[No]]," - ",Applications[[#This Row],[Application]]) -> 30 - Billing Com | C24: 30 | D24: Billing Com | E24: Utilities and Miscellaneous | F24: 45658 | I24: Service Tools | J24: Amdocs | N24: 5-Investigate | O24: 54788 | T24: T3 | V24: =_xlfn.XLOOKUP(Applications[[#This Row],[NoApplication]],AApplicationCosts[NoApplication],AApplicationCosts[License Owner],Applications[[#This Row],[Business Owner]],0,1) -> 0 | AE24: Supply Chain
B25: =_xlfn.CONCAT(Applications[[#This Row],[No]]," - ",Applications[[#This Row],[Application]]) -> 31 - SIM Service | C25: 31 | D25: SIM Service | E25: Utilities and Miscellaneous | F25: 45658 | I25: Service Tools | J25: SIM Service. | N25: 5-Investigate | O25: 54788 | T25: T3 | V25: =_xlfn.XLOOKUP(Applications[[#This Row],[NoApplication]],AApplicationCosts[NoApplication],AApplicationCosts[License Owner],Applications[[#This Row],[Business Owner]],0,1) -> 0
B26: =_xlfn.CONCAT(Applications[[#This Row],[No]]," - ",Applications[[#This Row],[Application]]) -> 33 - TLF Service | C26: 33 | D26: TLF Service | E26: Utilities and Miscellaneous | F26: 45658 | I26: Service Tools | J26: The Software Vendor for the application TLF Service is TLF Technology. | N26: 5-Investigate | O26: 54788 | T26: T2 | V26: =_xlfn.XLOOKUP(Applications[[#This Row],[NoApplication]],AApplicationCosts[NoApplication],AApplicationCosts[License Owner],Applications[[#This Row],[Business Owner]],0,1) -> 0
B27: =_xlfn.CONCAT(Applications[[#This Row],[No]]," - ",Applications[[#This Row],[Application]]) -> 34 - Custom SIM | C27: 34 | D27: Custom SIM | E27: Utilities and Miscellaneous | F27: 45658 | I27: Service Tools | J27: Custom SIM Technologies | N27: 5-Investigate | O27: 54788 | T27: T2 | V27: =_xlfn.XLOOKUP(Applications[[#This Row],[NoApplication]],AApplicationCosts[NoApplication],AApplicationCosts[License Owner],Applications[[#This Row],[Business Owner]],0,1) -> 0
B28: =_xlfn.CONCAT(Applications[[#This Row],[No]]," - ",Applications[[#This Row],[Application]]) -> 35 - Lessor PM | C28: 35 | D28: Lessor PM | E28: Business | F28: 45658 | G28: Cloud | I28: Other Tools | J28: Lessor PM is developed by Lessor. | N28: 8-Phase out | O28: 46752 | P28: LessorLøn Cloud | Q28: OBS - High spend - could be renigosiated | S28: HAA | T28: T2 | V28: =_xlfn.XLOOKUP(Applications[[#This Row],[NoApplication]],AApplicationCosts[NoApplication],AApplicationCosts[License Owner],Applications[[#This Row],[Business Owner]],0,1) -> HAA | AB28: KRTI | AE28: People | AI28: Business case for upgrading to LessorLøn (cloud) is in the making | AJ28: Convert from LessorPM to LessorLøn Cloud. Exp. June 2027 | AL28: Project
B29: =_xlfn.CONCAT(Applications[[#This Row],[No]]," - ",Applications[[#This Row],[Application]]) -> 36 - Concur | C29: 36 | D29: Concur | E29: Business | F29: 45658 | G29: Cloud | I29: Other Tools | J29: SAP Concur | M29: 1000-> | N29: 7-Potential for phase out | O29: 54788 | T29: T2 | U29: FIN | V29: =_xlfn.XLOOKUP(Applications[[#This Row],[NoApplication]],AApplicationCosts[NoApplication],AApplicationCosts[License Owner],Applications[[#This Row],[Business Owner]],0,1) -> KRSM | AB29: KRTI | AE29: Finans | AH29: SAP | AL29: Project
B30: =_xlfn.CONCAT(Applications[[#This Row],[No]]," - ",Applications[[#This Row],[Application]]) -> 37 - OpenLM | C30: 37 | D30: OpenLM | E30: Utilities and Miscellaneous | F30: 45658 | G30: Cloud | I30: Other Tools | J30: OpenLM. | M30: 0-9 | N30: 4-Saved for now | O30: 54788 | Q30: FRFS: Look on if this can be used in general license use in Kamstrup | R30: License Management Services | OpenLM | T30: T2 | V30: =_xlfn.XLOOKUP(Applications[[#This Row],[NoApplication]],AApplicationCosts[NoApplication],AApplicationCosts[License Owner],Applications[[#This Row],[Business Owner]],0,1) -> DBR | AE30: Software, Hardware Departments | AI30: Åben licens manager - akal underøges nærmere hvis der skal gøres noget.
B31: =_xlfn.CONCAT(Applications[[#This Row],[No]]," - ",Applications[[#This Row],[Application]]) -> 38 - SP TID | C31: 38 | D31: SP TID | E31: Utilities and Miscellaneous | F31: 45658 | I31: Other Tools | J31: SAP | N31: 5-Investigate | O31: 54788 | T31: T2 | V31: =_xlfn.XLOOKUP(Applications[[#This Row],[NoApplication]],AApplicationCosts[NoApplication],AApplicationCosts[License Owner],Applications[[#This Row],[Business Owner]],0,1) -> 0
B32: =_xlfn.CONCAT(Applications[[#This Row],[No]]," - ",Applications[[#This Row],[Application]]) -> 39 - EPOS | C32: 39 | D32: EPOS | E32: Utilities and Miscellaneous | F32: 45658 | I32: Other Tools | J32: NCR Corporation | N32: 5-Investigate | O32: 54788 | T32: T2 | V32: =_xlfn.XLOOKUP(Applications[[#This Row],[NoApplication]],AApplicationCosts[NoApplication],AApplicationCosts[License Owner],Applications[[#This Row],[Business Owner]],0,1) -> 0
B33: =_xlfn.CONCAT(Applications[[#This Row],[No]]," - ",Applications[[#This Row],[Application]]) -> 40 - Omnia | C33: 40 | D33: Omnia | E33: Kamstrup - Customer Software | F33: 45658 | I33: Kamstrup Software | J33: Kamstrup | N33: 3-Kamstrup application | O33: 54788 | Q33: Custom software and hardware solutions | S33: MIA | T33: T2 | V33: =_xlfn.XLOOKUP(Applications[[#This Row],[NoApplication]],AApplicationCosts[NoApplication],AApplicationCosts[License Owner],Applications[[#This Row],[Business Owner]],0,1) -> MLNN / JIN | AE33: Software, Hardware Departments | AP33: Crown Jewel_1
B34: =_xlfn.CONCAT(Applications[[#This Row],[No]]," - ",Applications[[#This Row],[Application]]) -> 41 - READy | C34: 41 | D34: READy | E34: Kamstrup - Customer Software | F34: 45658 | I34: Kamstrup Software | J34: Kamstrup | N34: 3-Kamstrup application | O34: 54788 | Q34: Visualisation of meters and reading data, heat reports, alarm notification, meter exchange, data export mm. FRFS Rename to READY Manager | S34: JEMR | T34: T2 | U34: Remote reading tool for water and heat meters | V34: =_xlfn.XLOOKUP(Applications[[#This Row],[NoApplication]],AApplicationCosts[NoApplication],AApplicationCosts[License Owner],Applications[[#This Row],[Business Owner]],0,1) -> MHP / HELI | AE34: Supply Chain | AP34: Crown Jewel_1
B35: =_xlfn.CONCAT(Applications[[#This Row],[No]]," - ",Applications[[#This Row],[Application]]) -> 43 - Ceedling | C35: 43 | D35: Ceedling | E35: Development and Programming | F35: 45658 | G35: Distributed Applications | J35: ThrowTheSwitch, LLC | N35: 1-Strategic | O35: 54788 | Q35: Test tool for 'c language' programming. Ceedling is primarily targeted at Test-Driven Development | T35: T2 | U35: Test tool (unit test) | V35: =_xlfn.XLOOKUP(Applications[[#This Row],[NoApplication]],AApplicationCosts[NoApplication],AApplicationCosts[License Owner],Applications[[#This Row],[Business Owner]],0,1) -> 0 | W35: RUP | X35: Fra egen afd: JDP,AGR,SAS,TPT,JKI,JML,MTR,RUP,DGG,CKS,KSC,TRL,ACP | Y35: GCC, IAR, (Ruby) | AA35: Opensource | AB35: Opensource | AE35: Software, Hardware Departments | AI35: Test framework for C based tools. | AJ35: Subcomponent for C | AK35: CLI tool used to test C code. | AO35: Investigate
B36: =_xlfn.CONCAT(Applications[[#This Row],[No]]," - ",Applications[[#This Row],[Application]]) -> 44 - C-Spy | C36: 44 | D36: C-Spy | E36: Development and Programming | F36: 45658 | J36: ELM Technology. | N36: 5-Investigate | O36: 54788 | T36: T2 | U36: Debugger | V36: =_xlfn.XLOOKUP(Applications[[#This Row],[NoApplication]],AApplicationCosts[NoApplication],AApplicationCosts[License Owner],Applications[[#This Row],[Business Owner]],0,1) -> 0 | W36: KER | X36: Fra egen afd: LTS,JDP,AGR,SAS,TPT,JKI,JML,MTR,RUP,DGG,CKS,KSC,TRL,ACP | Y36: IAR | AA36: IAR | AB36: KER
B37: =_xlfn.CONCAT(Applications[[#This Row],[No]]," - ",Applications[[#This Row],[Application]]) -> 45 - DockLight | C37: 45 | D37: DockLight | E37: Development and Programming | F37: 45658 | G37: Distributed Applications | J37: DockLight Software | N37: 2-Important application | O37: 54788 | Q37: Docklight is a testing, analysis and simulation tool for serial communication protocols. | T37: T1-D | U37: Serial script/trace | V37: =_xlfn.XLOOKUP(Applications[[#This Row],[NoApplication]],AApplicationCosts[NoApplication],AApplicationCosts[License Owner],Applications[[#This Row],[Business Owner]],0,1) -> 0 | W37: Ved ikke | X37: Fra egen afd: LTS,JDP,AGR,SAS,TPT,JKI,JML,MTR,RUP,DGG,CKS,KSC,TRL,ACP | AA37: Købt licens + x antal gratis | AB37: Ved ikke | AE37: Software, Hardware Departments | AF37: No | AI37: Investigate this and terraterm, Evaluate for security, FRFS | AJ37: Tolerate | AK37: Investigate usage
B38: =_xlfn.CONCAT(Applications[[#This Row],[No]]," - ",Applications[[#This Row],[Application]]) -> 46 - Doxygen | C38: 46 | D38: Doxygen | E38: Development and Programming | F38: 45658 | J38: Affero, Inc. | N38: 4-Saved for now | O38: 54788 | Q38: dokumentere software ud fra kildekoden | T38: T2 | U38: Kodedokumentationsprogram til dokumentation | V38: =_xlfn.XLOOKUP(Applications[[#This Row],[NoApplication]],AApplicationCosts[NoApplication],AApplicationCosts[License Owner],Applications[[#This Row],[Business Owner]],0,1) -> 0 | W38: Ved ikke | X38: Fra egen afd: LTS,JDP,AGR,SAS,TPT,JKI,KKA,BTH,JML,STK,MTR,LAA,ARO,RUP,DGG,CKS,KSC,TRL,ACP; PMB | AA38: Opensource | AB38: Opensource | AE38: Software, Hardware Departments | AI38: Free and automated documentation software. | AJ38: Tolerate/migrate | AK38: Free and open source client system
B39: =_xlfn.CONCAT(Applications[[#This Row],[No]]," - ",Applications[[#This Row],[Application]]) -> 47 - FABric | C39: 47 | D39: FABric | E39: Utilities and Miscellaneous | F39: 45658 | J39: FABric is developed by the company Fabric Software. | N39: 5-Investigate | O39: 54788 | Q39: Fabric is a platform that helps your mobile team build better apps, understand your users, and grow your business. | T39: T2 | U39: Python framework - Vedligeholdes internt i R&D | V39: =_xlfn.XLOOKUP(Applications[[#This Row],[NoApplication]],AApplicationCosts[NoApplication],AApplicationCosts[License Owner],Applications[[#This Row],[Business Owner]],0,1) -> 0 | W39: Individuelt pr. bruger | X39: Fra egen afd: LTS,KKA,BTH,STK,MTR,LAA, | AA39: Ved ikke | AB39: Ved ikke
B40: =_xlfn.CONCAT(Applications[[#This Row],[No]]," - ",Applications[[#This Row],[Application]]) -> 48 - FreeRTOS | C40: 48 | D40: FreeRTOS | E40: Development and Programming | F40: 45658 | J40: Amazon Web Services, Inc. | N40: 5-Investigate | O40: 54788 | Q40: MIT Licens, FreeRTOS er blevet porteret til 31 forskellige microcontrollerfamilier, kodning | T40: T2 | U40: Development/support to development | V40: =_xlfn.XLOOKUP(Applications[[#This Row],[NoApplication]],AApplicationCosts[NoApplication],AApplicationCosts[License Owner],Applications[[#This Row],[Business Owner]],0,1) -> 0 | W40: Ved ikke | X40: Fra egen afd: JDP,JKI,RUP,DGG,TRL | Y40: IAR, GCC | AA40: Opensource | AB40: Opensource
B41: =_xlfn.CONCAT(Applications[[#This Row],[No]]," - ",Applications[[#This Row],[Application]]) -> 49 - GCC | C41: 49 | D41: GCC | E41: Development and Programming | F41: 45658 | N41: 5-Investigate | O41: 54788 | T41: T3 | U41: Compiler - Vedligeholdes internt i R&D | V41: =_xlfn.XLOOKUP(Applications[[#This Row],[NoApplication]],AApplicationCosts[NoApplication],AApplicationCosts[License Owner],Applications[[#This Row],[Business Owner]],0,1) -> 0 | W41: Ved ikke | X41: Fra egen afd: LTS,JDP,AGR,SAS,TPT,JKI,KKA,BTH,JML,STK,MTR,LAA,ARO,RUP,DGG,CKS,KSC,TRL,ACP | Y41: Ceedling | AA41: Opensource | AB41: Opensource
B42: =_xlfn.CONCAT(Applications[[#This Row],[No]]," - ",Applications[[#This Row],[Application]]) -> 50 - GDB | C42: 50 | D42: GDB | E42: Development and Programming | F42: 45658 | J42: GNU | N42: 5-Investigate | O42: 54788 | T42: T2 | U42: Debugger Linux | V42: =_xlfn.XLOOKUP(Applications[[#This Row],[NoApplication]],AApplicationCosts[NoApplication],AApplicationCosts[License Owner],Applications[[#This Row],[Business Owner]],0,1) -> 0 | W42: Individuelt | X42: Fra egen afd: LTS,KKA,BTH,STK,MTR,LAA, | AA42: Opensource | AB42: Opensource
B43: =_xlfn.CONCAT(Applications[[#This Row],[No]]," - ",Applications[[#This Row],[Application]]) -> 51 - NEC Compiler | C43: 51 | D43: NEC Compiler | E43: Development and Programming | F43: 45658 | G43: Distributed Applications | J43: NEC Corporation | M43: 0-9 | N43: 1-Strategic | O43: 47118 | Q43: Not used anymore, but need to be availabel for HC Technologi Hardware Ref. JESP | T43: T2 | U43: Compiler (MSP, EFM, NEC) - No support but continued access to compiler | V43: =_xlfn.XLOOKUP(Applications[[#This Row],[NoApplication]],AApplicationCosts[NoApplication],AApplicationCosts[License Owner],Applications[[#This Row],[Business Owner]],0,1) -> 0 | W43: KER | X43: Fra egen afd: LTS,JDP,AGR,SAS,TPT,JKI,JML,MTR,RUP,DGG,CKS,KSC,TRL,ACP | Y43: Teamcity, Jenkins | AA43: Ved ikke | AB43: KER | AE43: Software, Hardware Departments | AJ43: ? | AK43: ?
B44: =_xlfn.CONCAT(Applications[[#This Row],[No]]," - ",Applications[[#This Row],[Application]]) -> 52 - Orcad | C44: 52 | D44: Orcad | E44: Simulations and Engineering | F44: 45658 | G44: Distributed Applications | I44: Development Tools | J44: Cadence Design Systems | N44: 1-Strategic | O44: 54788 | Q44: The OrCAD suite is the central part of en electronics engineers daily life. OrCAD suite is integrated to the PLM system from which information about partnumbers, descriptions, partstatuses and more is grapped. | T44: T2 | U44: PCB Layout - Har du inputs via afd. 0144 (JLU)? | V44: =_xlfn.XLOOKUP(Applications[[#This Row],[NoApplication]],AApplicationCosts[NoApplication],AApplicationCosts[License Owner],Applications[[#This Row],[Business Owner]],0,1) -> TES | W44: JLU | X44: Fra egen afd: PPH;JLU;BHR;CLR | AA44: Nordcad | AB44: JHD | AE44: Software, Hardware Departments | AH44: Cadance
B45: =_xlfn.CONCAT(Applications[[#This Row],[No]]," - ",Applications[[#This Row],[Application]]) -> 53 - OSELAS | C45: 53 | D45: OSELAS | E45: Utilities and Miscellaneous | F45: 45658 | J45: OSELAS Technologies GmbH | N45: 5-Investigate | O45: 54788 | Q45: The OSELAS.Toolchain() project provides cross development tools for embedded Linux projects: GCC, GNU binutils, GDB and glibc. | T45: T2 | U45: Compiler C++, Linux Toolchain - Vedligeholdes internt i R&D | V45: =_xlfn.XLOOKUP(Applications[[#This Row],[NoApplication]],AApplicationCosts[NoApplication],AApplicationCosts[License Owner],Applications[[#This Row],[Business Owner]],0,1) -> 0 | W45: BTH | X45: Fra egen afd: LTS,KKA,BTH,STK,MTR,LAA, | AA45: Opensource | AB45: Opensource
B46: =_xlfn.CONCAT(Applications[[#This Row],[No]]," - ",Applications[[#This Row],[Application]]) -> 55 - QT Creator | C46: 55 | D46: QT Creator | E46: Development and Programming | F46: 45658 | J46: The Qt Company | N46: 5-Investigate | O46: 54788 | Q46: Qt Creator er et platforms C ++, JavaScript og QML integreret udviklingsmiljø, som er en del af SDK for Qt GUI applikationsudviklingsrammen. Den indeholder en visuel debugger og et integreret GUI layout og form designer | T46: T2 | U46: IDE - Vedligeholdes internt i R&D | V46: =_xlfn.XLOOKUP(Applications[[#This Row],[NoApplication]],AApplicationCosts[NoApplication],AApplicationCosts[License Owner],Applications[[#This Row],[Business Owner]],0,1) -> 0 | W46: BTH | X46: Fra egen afd: LTS,KKA,BTH,STK,MTR,LAA, | AA46: Opensource | AB46: Opensource
B47: =_xlfn.CONCAT(Applications[[#This Row],[No]]," - ",Applications[[#This Row],[Application]]) -> 56 - QT Unit | C47: 56 | D47: QT Unit | E47: Development and Programming | F47: 45658 | J47: The Qt Company | N47: 5-Investigate | O47: 54788 | T47: T2 | U47: Test tool (unit test) Linux - Vedligeholdes internt i R&D | V47: =_xlfn.XLOOKUP(Applications[[#This Row],[NoApplication]],AApplicationCosts[NoApplication],AApplicationCosts[License Owner],Applications[[#This Row],[Business Owner]],0,1) -> 0 | W47: Individuelt pr. bruger | X47: Fra egen afd: LTS,KKA,BTH,STK,MTR,LAA, | AA47: Ved ikke | AB47: Ved ikke
B48: =_xlfn.CONCAT(Applications[[#This Row],[No]]," - ",Applications[[#This Row],[Application]]) -> 57 - SMX | C48: 57 | D48: SMX | E48: Utilities and Miscellaneous | F48: 45658 | J48: SMX Corporation | N48: 5-Investigate | O48: 54788 | T48: T2 | U48: Realtids operativ system | V48: =_xlfn.XLOOKUP(Applications[[#This Row],[NoApplication]],AApplicationCosts[NoApplication],AApplicationCosts[License Owner],Applications[[#This Row],[Business Owner]],0,1) -> 0 | W48: Ved ikke En eller anden fra HFR's afd… | X48: AGR,SAS,TPT,JML,CKS,KSC,ACP | AA48: Ved ikke | AB48: Ved ikke
B49: =_xlfn.CONCAT(Applications[[#This Row],[No]]," - ",Applications[[#This Row],[Application]]) -> 58 - GitKraken | C49: 58 | D49: GitKraken | E49: Development and Programming | F49: 45658 | G49: Distributed Applications | J49: Axosoft | M49: 10-49 | N49: 2-Important application | O49: 54788 | Q49: ERC: Bruges på tværs. Alle licenser er i brug (must have) Det bør undersøges om netværkslicens er en mulighed | T49: T1-D | U49: Git GUI klient. Tool til visualisering og håndtering af source control via Git. | V49: =_xlfn.XLOOKUP(Applications[[#This Row],[NoApplication]],AApplicationCosts[NoApplication],AApplicationCosts[License Owner],Applications[[#This Row],[Business Owner]],0,1) -> LAAG | W49: CKS, DGG | X49: DGG, CKS, RUP, TPT, KSC, ACP, AGR, MBD, JML, TRL, JKI | AA49: Licens købes til 25 brugere, et år af gangen. (ikke flydende). | AE49: Software, Hardware Departments | AI49: Better altarnatives is appreciated
B50: =_xlfn.CONCAT(Applications[[#This Row],[No]]," - ",Applications[[#This Row],[Application]]) -> 59 - Advanced Serial Port Monitor | C50: 59 | D50: Advanced Serial Port Monitor | E50: Utilities and Miscellaneous | F50: 45658 | J50: Fabula Tech | N50: 4-Saved for now | O50: 54788 | T50: T2 | U50: Analyserer data på computerens comport - Vi har 10 Licenser | V50: =_xlfn.XLOOKUP(Applications[[#This Row],[NoApplication]],AApplicationCosts[NoApplication],AApplicationCosts[License Owner],Applications[[#This Row],[Business Owner]],0,1) -> 0 | W50: KER | X50: CSS, MVN, KRF, IBV, NCJ, GEK, RNY, RMK, MAT | AA50: Licensen købes pr. versionpr. Bruger. Ved ny version eller ny bruger, skal der købes ny licnes. | AB50: KER | AE50: Software, Hardware Departments
B51: =_xlfn.CONCAT(Applications[[#This Row],[No]]," - ",Applications[[#This Row],[Application]]) -> 60 - Astah professional | C51: 60 | D51: Astah professional | E51: Simulations and Engineering | F51: 45658 | J51: Change Vision Inc. | N51: 5-Investigate | O51: 54788 | T51: T2 | U51: Tegneprogram til kode design (Vi bruger det kun til C kode). | V51: =_xlfn.XLOOKUP(Applications[[#This Row],[NoApplication]],AApplicationCosts[NoApplication],AApplicationCosts[License Owner],Applications[[#This Row],[Business Owner]],0,1) -> 0 | W51: MLW; MVN; CSS; GEK | X51: CSS;MLW;HSS;ANG;MVN;KRF;IBV;JAJ;NCJ;MAT;RMK;GEK;RNY | AA51: Licensen købes en gang om året. Snak med KER omkring antal. | AB51: KER
B52: =_xlfn.CONCAT(Applications[[#This Row],[No]]," - ",Applications[[#This Row],[Application]]) -> 61 - Conformance Test Tool 3.0 | C52: 61 | D52: Conformance Test Tool 3.0 | E52: Quality Management System | F52: 45658 | J52: Siemens | N52: 5-Investigate | O52: 54788 | T52: T2 | U52: Officielt tool til conformance test og godkendelse af DLMS protokol implementeringen - 3 licenser | V52: =_xlfn.XLOOKUP(Applications[[#This Row],[NoApplication]],AApplicationCosts[NoApplication],AApplicationCosts[License Owner],Applications[[#This Row],[Business Owner]],0,1) -> 0 | W52: MLW, MVN, CSS | X52: ANG, MLW, CSS, MVN, KRF, JAJ, IBV, NCJ, GEK, RNY, RMK, MAT | AA52: Licensen købes pr. major version. Ved ny major version, skal der normalt købes ny licnes.Der medfølger 3 licenser | AB52: Licens installeret hos IT på License1
B53: =_xlfn.CONCAT(Applications[[#This Row],[No]]," - ",Applications[[#This Row],[Application]]) -> 62 - Eclipse | C53: 62 | D53: Eclipse | E53: Development and Programming | F53: 45658 | J53: Eclipse Foundation | N53: 4-Saved for now | O53: 54788 | Q53: JDP, Cool editor for development, alternative to Notepad | T53: T2 | U53: Et IDE (Integrated Development Environment). Bliver benyttet af ca. 60% af alle el-meter firmware udviklere - Bliver primært brugt for at kunne benytte parasoft | V53: =_xlfn.XLOOKUP(Applications[[#This Row],[NoApplication]],AApplicationCosts[NoApplication],AApplicationCosts[License Owner],Applications[[#This Row],[Business Owner]],0,1) -> 0 | X53: MLW, CSS, MVN, ANG, HSS (konsulet), RNY, MAT, GEK, RMK, TPT, AGR, RUP, DAG; MAJ,TLC,KHB,HRJ;PMB;AHG;DGG;AHG;LTS,JDP,AGR,SAS,TPT,JKI,JML,MTR,RUP,DGG,CKS,KSC,TRL,ACP;JLY | Y53: DATA FROM: Ja, IAR's compiler/linker iccarm, icclink;Parasoft; Java JDK, DATA TO:Ja, FW releases produceres med dette system. IAR, Parasoft | AA53: Ingen, freeware. Der kommer dog nyt release hver 6. måned | AB53: Freeware | AC53: 190 - Parasoft | AD53: IDE | AE53: Software, Hardware Departments | AI53: Is it used and how much? | AJ53: Tolerate/migrate | AK53: Free and open source client system
B54: =_xlfn.CONCAT(Applications[[#This Row],[No]]," - ",Applications[[#This Row],[Application]]) -> 63 - ElDevScripts | C54: 63 | D54: ElDevScripts | E54: Development and Programming | F54: 45658 | J54: ElDevScripts | N54: 5-Investigate | O54: 54788 | T54: T2 | U54: En samling scripts der automatiserer at lave releases, og som letter byrden med at lave logiske branches betydeligt. - Grupper der har svn:externals i deres SW-udtræk vil kunne have glæde af ElDevScripts | V54: =_xlfn.XLOOKUP(Applications[[#This Row],[NoApplication]],AApplicationCosts[NoApplication],AApplicationCosts[License Owner],Applications[[#This Row],[Business Owner]],0,1) -> 0 | W54: Alle der kan checke ElDevScripts ud fra VisualSVN på el-svn | X54: MLW, CSS, MVN, ANG, IBV, KRF, JAJ, NCJ, HSS (konsulet), RNY, MAT, GEK, RMK, TPT, AGR, RUP (måske) | Y54: SVN på "standard" Kamstrup SVN leverer sådan set de "rå-data" som ElDevScripts opererer på | AA54: Ingen, det er en flok internt udviklede scripts | AB54: Internt udviklet freeware
B55: =_xlfn.CONCAT(Applications[[#This Row],[No]]," - ",Applications[[#This Row],[Application]]) -> 66 - KEMA Test Facility Generic | C55: 66 | D55: KEMA Test Facility Generic | E55: Development and Programming | F55: 45658 | N55: 5-Investigate | O55: 54788 | T55: T2 | U55: Test program til at teste DLMS protokollen i målere - License WebAdmin. http://license1:22350/ | V55: =_xlfn.XLOOKUP(Applications[[#This Row],[NoApplication]],AApplicationCosts[NoApplication],AApplicationCosts[License Owner],Applications[[#This Row],[Business Owner]],0,1) -> 0 | W55: NCJ, CSS | X55: ANG, MLW, CSS, MVN, KRF, JAJ, IBV, NCJ, GEK, RNY, RMK, MAT | AA55: Licens købt pr bruger. Support & Upgrade aftale forlænges med et år ad gangen | AB55: Flydende licens på License1. Hardware Dongle hos IT.
B56: =_xlfn.CONCAT(Applications[[#This Row],[No]]," - ",Applications[[#This Row],[Application]]) -> 67 - Mathcad | C56: 67 | D56: Mathcad | E56: Simulations and Engineering | F56: 45658 | J56: PTC Inc. | M56: 0-9 | N56: 2-Important application | O56: 54788 | T56: T2 | U56: Regneprogram som kan sidestilles med en avanceret lommeregner | V56: =_xlfn.XLOOKUP(Applications[[#This Row],[NoApplication]],AApplicationCosts[NoApplication],AApplicationCosts[License Owner],Applications[[#This Row],[Business Owner]],0,1) -> 0 | W56: JPN, BRI | X56: BRI, UCH, GBH, DKI, SLH;JPN, MTM, JJS | AA56: Vi har en flydende licens. BRI og JPN individuelle licenser. Desuden har afdelingen en meget gammel udgave af Mathcad (2001) hvor licensforholdet ikke kendes./ 1 flydende licens (en gangs) + to faste licenser Alfasoft | AB56: JPN eller IT? | AE56: Software, Hardware Departments
B57: =_xlfn.CONCAT(Applications[[#This Row],[No]]," - ",Applications[[#This Row],[Application]]) -> 68 - ModelSim | C57: 68 | D57: ModelSim | E57: Development and Programming | F57: 45658 | G57: Distributed Applications | J57: Innofour. | M57: 0-9 | N57: 1-Strategic | O57: 54788 | Q57: JESP: Nødvendig for vores FPGA kerne på SDR produkter (MIDI/READy Concentrator MKII etc) | T57: T2 | U57: PADS består af 2 programmer. PADS Layout, program til at designe pcb. PADS Logic, program til at lave schematic. PCB Layout program + PADS Logic til at lave schematic - Til info.Vi har 6 PADS layout licenser og 2 PADS logic licenser. PADS bruges i dag kun til vedligehold af eksisterende pcb design, små ændringer på et pcb laves i PADS. Ved nye design / størrer ændringer laves det i OrCAD. OrCad blev indført sidste år. | V57: =_xlfn.XLOOKUP(Applications[[#This Row],[NoApplication]],AApplicationCosts[NoApplication],AApplicationCosts[License Owner],Applications[[#This Row],[Business Owner]],0,1) -> 0 | W57: PPH, JLU, BRH, CLR | X57: UCH, SLH, BRI, DKI, CSK, GBH, MHO, JJS, MTM, SAR, JBR, TES, CJO; JPN, JJS, MTM, SAR, JBR | Y57: PADS Logic | AA57: www.innofour.com | AB57: PPH | AE57: Software, Hardware Departments | AJ57: Tolerate | AK57: Investigate usage
B58: =_xlfn.CONCAT(Applications[[#This Row],[No]]," - ",Applications[[#This Row],[Application]]) -> 69 - Seqzap fra CIM Software Testing | C58: 69 | D58: Seqzap fra CIM Software Testing | E58: Quality Management System | F58: 45658 | J58: CIM Software Testing | M58: 0-9 | N58: 3-Kamstrup application | O58: 54788 | T58: T2 | U58: Windows program til at udvikle og afvikle scripts til automatiseret test af elmåleren | V58: =_xlfn.XLOOKUP(Applications[[#This Row],[NoApplication]],AApplicationCosts[NoApplication],AApplicationCosts[License Owner],Applications[[#This Row],[Business Owner]],0,1) -> 0 | W58: RNY; JAJ | X58: CSS;MLW;HSS;ANG;MVN;KRF;IBV;JAJ;NCJ;MAT;RMK;GEK;RNY | Y58: Kamstrup Firmwaremodeller (5098-1221) | AA58: CIM Software Testing, Business Park Nord, Østre Allé 6, 9530 Støvring. Vi har pt. 7 flydende licenser, der betales support, service og opdateringsaftale for en gang om året. | AB58: RNY | AE58: Software, Hardware Departments
B59: =_xlfn.CONCAT(Applications[[#This Row],[No]]," - ",Applications[[#This Row],[Application]]) -> 70 - WikiMedia | C59: 70 | D59: WikiMedia | E59: Utilities and Miscellaneous | F59: 45658 | J59: Unknown | N59: 8-Phase out | O59: 46023 | Q59: Info of Phase out from meeting with MLNN the 17/1-2025 | R59: http://wiki.kamstrup.dk | T59: T2 | U59: Wiki for Elmåler-, NetworkManager- og Concentrator-gruppen | V59: =_xlfn.XLOOKUP(Applications[[#This Row],[NoApplication]],AApplicationCosts[NoApplication],AApplicationCosts[License Owner],Applications[[#This Row],[Business Owner]],0,1) -> 0 | W59: SMB; RNY | X59: CSS;MLW;HSS;ANG;MVN;KRF;IBV;JAJ;NCJ;MAT;RMK;GEK;RNY | AA59: Opensource | AE59: Software, Hardware Departments | AI59: Remember to ask Electricity if they are still using it. Used for wiki.kamstrup.dk | AJ59: FRFS: moved from 31-12-2025 to 01-01-2026 for reporting | AL59: M
B60: =_xlfn.CONCAT(Applications[[#This Row],[No]]," - ",Applications[[#This Row],[Application]]) -> 71 - AD Link | C60: 71 | D60: AD Link | E60: Development and Programming | F60: 45658 | N60: 5-Investigate | O60: 54788 | T60: T2 | U60: SW til A/D og I/O kort i PC | V60: =_xlfn.XLOOKUP(Applications[[#This Row],[NoApplication]],AApplicationCosts[NoApplication],AApplicationCosts[License Owner],Applications[[#This Row],[Business Owner]],0,1) -> 0 | X60: LHB | AB60: Leveres sammen med HW
B61: =_xlfn.CONCAT(Applications[[#This Row],[No]]," - ",Applications[[#This Row],[Application]]) -> 72 - APEX SQL | C61: 72 | D61: APEX SQL | E61: Data and Analytics | F61: 45658 | J61: APEX SQL, Inc. | N61: 5-Investigate | O61: 54788 | T61: T2 | U61: Database værktøj | V61: =_xlfn.XLOOKUP(Applications[[#This Row],[NoApplication]],AApplicationCosts[NoApplication],AApplicationCosts[License Owner],Applications[[#This Row],[Business Owner]],0,1) -> 0 | X61: klu | AB61: klu
B62: =_xlfn.CONCAT(Applications[[#This Row],[No]]," - ",Applications[[#This Row],[Application]]) -> 73 - ApexSQL Edit | C62: 73 | D62: ApexSQL Edit | E62: Development and Programming | F62: 45658 | J62: ApexSQL | N62: 5-Investigate | O62: 54788 | T62: T2 | U62: Database designer - PTA software har nogle licenser | V62: =_xlfn.XLOOKUP(Applications[[#This Row],[NoApplication]],AApplicationCosts[NoApplication],AApplicationCosts[License Owner],Applications[[#This Row],[Business Owner]],0,1) -> 0 | X62: klu | AB62: Licensen købes pr. bruger
B63: =_xlfn.CONCAT(Applications[[#This Row],[No]]," - ",Applications[[#This Row],[Application]]) -> 74 - AppFabric | C63: 74 | D63: AppFabric | E63: Development and Programming | F63: 45658 | J63: Microsoft | N63: 5-Investigate | O63: 54788 | T63: T2 | U63: Hosting container til WCF services | V63: =_xlfn.XLOOKUP(Applications[[#This Row],[NoApplication]],AApplicationCosts[NoApplication],AApplicationCosts[License Owner],Applications[[#This Row],[Business Owner]],0,1) -> 0 | W63: EMG | X63: EMG | AB63: Gratis addon til Windows Server
B64: =_xlfn.CONCAT(Applications[[#This Row],[No]]," - ",Applications[[#This Row],[Application]]) -> 75 - Blend | C64: 75 | D64: Blend | E64: Development and Programming | F64: 45658 | J64: Blend Labs, Inc. | N64: 5-Investigate | O64: 54788 | T64: T2 | U64: GUI design værktøj for Visual Studio | V64: =_xlfn.XLOOKUP(Applications[[#This Row],[NoApplication]],AApplicationCosts[NoApplication],AApplicationCosts[License Owner],Applications[[#This Row],[Business Owner]],0,1) -> 0 | X64: MCF, MEV | AA64: MSDN | AB64: IT
B65: =_xlfn.CONCAT(Applications[[#This Row],[No]]," - ",Applications[[#This Row],[Application]]) -> 79 - Code::Blocks (www.codeblocks.org) | C65: 79 | D65: Code::Blocks (www.codeblocks.org) | E65: Development and Programming | F65: 45658 | J65: The Code::Blocks application is developed by Code::Blocks Team. | N65: 5-Investigate | O65: 54788 | T65: T2 | U65: Open source IDE til C/C++. Kan anvendes sammen med en række compilere. | V65: =_xlfn.XLOOKUP(Applications[[#This Row],[NoApplication]],AApplicationCosts[NoApplication],AApplicationCosts[License Owner],Applications[[#This Row],[Business Owner]],0,1) -> 0 | W65: EMG | X65: EMG | AB65: Freeware
B66: =_xlfn.CONCAT(Applications[[#This Row],[No]]," - ",Applications[[#This Row],[Application]]) -> 82 - Crystal Reports | C66: 82 | D66: Crystal Reports | E66: Data and Analytics | F66: 45658 | J66: SAP | N66: 7-Potential for phase out | O66: 54788 | T66: T2 | U66: Designprogram til bl.a. dagsrapporter | V66: =_xlfn.XLOOKUP(Applications[[#This Row],[NoApplication]],AApplicationCosts[NoApplication],AApplicationCosts[License Owner],Applications[[#This Row],[Business Owner]],0,1) -> 0 | X66: KLU;LSH;JJB, KLU, KLU, JJB | AA66: Licensen købes pr. versionpr. Bruger. Ved ny version eller ny bruger, skal der købes ny licnes. | AB66: Bruger selv | AE66: Supply Chain | AI66: FRFS: Set to potential for phase out based on info from business of MIGRATE. For software to List and Label and for certificates to PowerBI | AJ66: Phase out/Migrate
B67: =_xlfn.CONCAT(Applications[[#This Row],[No]]," - ",Applications[[#This Row],[Application]]) -> 83 - DOSBox (www.dosbox.com) | C67: 83 | D67: DOSBox (www.dosbox.com) | E67: Utilities and Miscellaneous | F67: 45658 | J67: DOSBox Team | N67: 5-Investigate | O67: 54788 | T67: T2 | U67: DOS emulator til Windows. Gør det muligt at afvikle 16-bit DOS programmer på en Windows PC. | V67: =_xlfn.XLOOKUP(Applications[[#This Row],[NoApplication]],AApplicationCosts[NoApplication],AApplicationCosts[License Owner],Applications[[#This Row],[Business Owner]],0,1) -> 0 | W67: EMG | X67: EMG | AB67: Freeware
B68: =_xlfn.CONCAT(Applications[[#This Row],[No]]," - ",Applications[[#This Row],[Application]]) -> 84 - Dr. Memory (http://drmemory.org/) | C68: 84 | D68: Dr. Memory (http://drmemory.org/) | E68: Utilities and Miscellaneous | F68: 45658 | J68: The Dr. Memory application is developed by the company named "University of Hawaii". | N68: 5-Investigate | O68: 54788 | T68: T2 | U68: Statisk kodeanalyse af memory management i C kode | V68: =_xlfn.XLOOKUP(Applications[[#This Row],[NoApplication]],AApplicationCosts[NoApplication],AApplicationCosts[License Owner],Applications[[#This Row],[Business Owner]],0,1) -> 0 | W68: EMG | X68: EMG | AB68: LGPL license
B69: =_xlfn.CONCAT(Applications[[#This Row],[No]]," - ",Applications[[#This Row],[Application]]) -> 85 - Eltima Serial Port Monitor (www.eltima.com) | C69: 85 | D69: Eltima Serial Port Monitor (www.eltima.com) | E69: Utilities and Miscellaneous | F69: 45658 | J69: Eltima Software | N69: 7-Potential for phase out | O69: 46173 | T69: T2 | U69: COMPort analyse værktøj; til RS232 kommunikation | V69: =_xlfn.XLOOKUP(Applications[[#This Row],[NoApplication]],AApplicationCosts[NoApplication],AApplicationCosts[License Owner],Applications[[#This Row],[Business Owner]],0,1) -> 0 | X69: EMG, klu, hlb, jax;KLU | AB69: klu | AE69: Software, Hardware Departments | AI69: Needed in Tools and aps. But an alternative can be used - but we have lifetime licens for this
B70: =_xlfn.CONCAT(Applications[[#This Row],[No]]," - ",Applications[[#This Row],[Application]]) -> 86 - ExactFile | C70: 86 | D70: ExactFile | E70: Utilities and Miscellaneous | F70: 45658 | J70: ExactFile, Inc. | N70: 5-Investigate | O70: 54788 | T70: T2 | U70: Tool til beregning af checksum | V70: =_xlfn.XLOOKUP(Applications[[#This Row],[NoApplication]],AApplicationCosts[NoApplication],AApplicationCosts[License Owner],Applications[[#This Row],[Business Owner]],0,1) -> 0 | X70: EMG | AB70: Freeware
B71: =_xlfn.CONCAT(Applications[[#This Row],[No]]," - ",Applications[[#This Row],[Application]]) -> 88 - KEPWare | C71: 88 | D71: KEPWare | E71: Utilities and Miscellaneous | F71: 45658 | J71: Parker Hannifin Corporation | N71: 5-Investigate | O71: 54788 | T71: T2 | U71: OPC værktøj | V71: =_xlfn.XLOOKUP(Applications[[#This Row],[NoApplication]],AApplicationCosts[NoApplication],AApplicationCosts[License Owner],Applications[[#This Row],[Business Owner]],0,1) -> 0 | X71: klu | AB71: klu
B72: =_xlfn.CONCAT(Applications[[#This Row],[No]]," - ",Applications[[#This Row],[Application]]) -> 89 - Kepware KEPServerEX | C72: 89 | D72: Kepware KEPServerEX | E72: Development and Programming | F72: 45658 | N72: 5-Investigate | O72: 54788 | T72: T2 | U72: OPC server til kommunikation til PLCer | V72: =_xlfn.XLOOKUP(Applications[[#This Row],[NoApplication]],AApplicationCosts[NoApplication],AApplicationCosts[License Owner],Applications[[#This Row],[Business Owner]],0,1) -> 0 | X72: klu, lhb | AB72: 2 timers demo mode.
B73: =_xlfn.CONCAT(Applications[[#This Row],[No]]," - ",Applications[[#This Row],[Application]]) -> 90 - Microsoft FX Cops | C73: 90 | D73: Microsoft FX Cops | E73: Quality Management System | F73: 45658 | J73: Microsoft | N73: 5-Investigate | O73: 54788 | T73: T2 | U73: Kode analyse værktøj | V73: =_xlfn.XLOOKUP(Applications[[#This Row],[NoApplication]],AApplicationCosts[NoApplication],AApplicationCosts[License Owner],Applications[[#This Row],[Business Owner]],0,1) -> 0 | X73: JLM, MEV | AB73: Freeware
B74: =_xlfn.CONCAT(Applications[[#This Row],[No]]," - ",Applications[[#This Row],[Application]]) -> 91 - Microsoft SQL server Standard | C74: 91 | D74: Microsoft SQL server Standard | E74: Data and Analytics | F74: 45658 | J74: Microsoft | K74: 7NQ-00292 | N74: 1-Strategic | O74: 54788 | T74: T0 | U74: Databaser | V74: =_xlfn.XLOOKUP(Applications[[#This Row],[NoApplication]],AApplicationCosts[NoApplication],AApplicationCosts[License Owner],Applications[[#This Row],[Business Owner]],0,1) -> JEDT | X74: klu | AA74: IT | AB74: Susanne | AE74: Digital workplace | AH74: Microsoft Data Platform
B75: =_xlfn.CONCAT(Applications[[#This Row],[No]]," - ",Applications[[#This Row],[Application]]) -> 96 - Microsoft team Foundation server | C75: 96 | D75: Microsoft team Foundation server | E75: Development and Programming | F75: 45658 | J75: Microsoft | N75: 9-End of Life | O75: 46023 | T75: T2 | U75: Source safe værktøj | V75: =_xlfn.XLOOKUP(Applications[[#This Row],[NoApplication]],AApplicationCosts[NoApplication],AApplicationCosts[License Owner],Applications[[#This Row],[Business Owner]],0,1) -> 0 | W75: JAX;LHB | X75: mailgrupper: pta sw hcw, technology heat | AB75: MSDN Abonnement | AE75: Software, Hardware Departments | AJ75: FRFS: moved from 15-09-2025 to 01-01-2026 for reporting | AL75: S
B76: =_xlfn.CONCAT(Applications[[#This Row],[No]]," - ",Applications[[#This Row],[Application]]) -> 102 - Microsoft Windows virtual PC | C76: 102 | D76: Microsoft Windows virtual PC | E76: Utilities and Miscellaneous | F76: 45658 | J76: Microsoft | N76: 5-Investigate | O76: 54788 | T76: T2 | U76: Bruges til at oprette og køre virtuelle maskiner | V76: =_xlfn.XLOOKUP(Applications[[#This Row],[NoApplication]],AApplicationCosts[NoApplication],AApplicationCosts[License Owner],Applications[[#This Row],[Business Owner]],0,1) -> 0 | X76: LSH | AA76: MSDN
B77: =_xlfn.CONCAT(Applications[[#This Row],[No]]," - ",Applications[[#This Row],[Application]]) -> 103 - Motorola EMDK for .NET | C77: 103 | D77: Motorola EMDK for .NET | E77: Development and Programming | F77: 45658 | J77: Motorola Solutions | N77: 5-Investigate | O77: 54788 | T77: T2 | U77: SDK til Motorola MT2090 scannere | V77: =_xlfn.XLOOKUP(Applications[[#This Row],[NoApplication]],AApplicationCosts[NoApplication],AApplicationCosts[License Owner],Applications[[#This Row],[Business Owner]],0,1) -> 0 | W77: EMG | X77: EMG | AB77: Freeware
B78: =_xlfn.CONCAT(Applications[[#This Row],[No]]," - ",Applications[[#This Row],[Application]]) -> 104 - Open Watcom IDE (www.openwacom.org) | C78: 104 | D78: Open Watcom IDE (www.openwacom.org) | E78: Development and Programming | F78: 45658 | J78: Open Watcom Project | N78: 5-Investigate | O78: 54788 | T78: T2 | U78: IDE til Open Watcom compiler. Bruges som Cross Compiler til MS-DOS 6.22 - IDE'et er ikke det mest moderne. Men compileren og de øvrige værktøjer kan med fordel anvendes fra Code::Blocks. | V78: =_xlfn.XLOOKUP(Applications[[#This Row],[NoApplication]],AApplicationCosts[NoApplication],AApplicationCosts[License Owner],Applications[[#This Row],[Business Owner]],0,1) -> 0 | W78: EMG | X78: EMG | AB78: Sybase Open Watcom Public License
B79: =_xlfn.CONCAT(Applications[[#This Row],[No]]," - ",Applications[[#This Row],[Application]]) -> 105 - PhotoFiltre 7 | C79: 105 | D79: PhotoFiltre 7 | E79: Utilities and Miscellaneous | F79: 45658 | J79: PhotoFiltre Studio | N79: 5-Investigate | O79: 54788 | T79: T2 | U79: Billede behandling/ tegneprogram | V79: =_xlfn.XLOOKUP(Applications[[#This Row],[NoApplication]],AApplicationCosts[NoApplication],AApplicationCosts[License Owner],Applications[[#This Row],[Business Owner]],0,1) -> 0 | X79: MEV | AB79: Freeware
B80: =_xlfn.CONCAT(Applications[[#This Row],[No]]," - ",Applications[[#This Row],[Application]]) -> 106 - SciChart | C80: 106 | D80: SciChart | E80: Development and Programming-Library | F80: 45658 | J80: SciChart Limited | N80: 2.5-Warenty based applications | O80: 54788 | T80: T3 | U80: Grafværktøj til Visual Studio. Bruges til visning af data fra målerne. | V80: =_xlfn.XLOOKUP(Applications[[#This Row],[NoApplication]],AApplicationCosts[NoApplication],AApplicationCosts[License Owner],Applications[[#This Row],[Business Owner]],0,1) -> 0 | X80: mfc | Y80: DATA TO:LogView og LabTool, JAX have info of this | AA80: Licensen købes pr. versionpr. Bruger. Ved ny version eller ny bruger, skal der købes ny licnes. | AD80: READy | AE80: Software, Hardware Departments | AJ80: Will be expensive to remove. Used extensively in READy | AK80: Is a library | AO80: Investigate
B81: =_xlfn.CONCAT(Applications[[#This Row],[No]]," - ",Applications[[#This Row],[Application]]) -> 107 - Serial port monitor 5.0 | C81: 107 | D81: Serial port monitor 5.0 | E81: Utilities and Miscellaneous | F81: 45658 | J81: Roma Software. | N81: 5-Investigate | O81: 54788 | T81: T2 | U81: Overvågning/snifning af seriel port | V81: =_xlfn.XLOOKUP(Applications[[#This Row],[NoApplication]],AApplicationCosts[NoApplication],AApplicationCosts[License Owner],Applications[[#This Row],[Business Owner]],0,1) -> 0 | X81: LSH | AA81: Licensen købes pr. versionpr. Bruger. Ved ny version eller ny bruger, skal der købes ny licnes.
B82: =_xlfn.CONCAT(Applications[[#This Row],[No]]," - ",Applications[[#This Row],[Application]]) -> 108 - Snoop | C82: 108 | D82: Snoop | E82: Utilities and Miscellaneous | F82: 45658 | J82: Snoop Software Ltd. | N82: 5-Investigate | O82: 54788 | R82: https://snoopwpf.codeplex.com | T82: T2 | U82: WPF spy | V82: =_xlfn.XLOOKUP(Applications[[#This Row],[NoApplication]],AApplicationCosts[NoApplication],AApplicationCosts[License Owner],Applications[[#This Row],[Business Owner]],0,1) -> 0 | X82: EMG | AB82: Ms-PL (Microsoft Public License)
B83: =_xlfn.CONCAT(Applications[[#This Row],[No]]," - ",Applications[[#This Row],[Application]]) -> 109 - SonicMQ .NET | C83: 109 | D83: SonicMQ .NET | E83: Development and Programming | F83: 45658 | J83: Progress Software Corporation | N83: 5-Investigate | O83: 54788 | T83: T2 | U83: Klient til SonicMQ integration mod QAD | V83: =_xlfn.XLOOKUP(Applications[[#This Row],[NoApplication]],AApplicationCosts[NoApplication],AApplicationCosts[License Owner],Applications[[#This Row],[Business Owner]],0,1) -> 0 | X83: EMG | AB83: IT
B84: =_xlfn.CONCAT(Applications[[#This Row],[No]]," - ",Applications[[#This Row],[Application]]) -> 110 - SQLDigger | C84: 110 | D84: SQLDigger | E84: Data and Analytics | F84: 45658 | J84: SQLDigger is developed by**SQLDigger, Inc.** | N84: 5-Investigate | O84: 54788 | T84: T2 | U84: Reverse engernering. Søge program til SQL server | V84: =_xlfn.XLOOKUP(Applications[[#This Row],[NoApplication]],AApplicationCosts[NoApplication],AApplicationCosts[License Owner],Applications[[#This Row],[Business Owner]],0,1) -> 0 | X84: JLM | AB84: Ældre freeware
B85: =_xlfn.CONCAT(Applications[[#This Row],[No]]," - ",Applications[[#This Row],[Application]]) -> 111 - WinMerge | C85: 111 | D85: WinMerge | E85: Utilities and Miscellaneous | F85: 45658 | G85: Distributed Applications | J85: WinMerge is developed by WinMerge.org. | N85: 2-Important application | O85: 54788 | Q85: Filecomparison / merge | T85: T2 | U85: Værktøj til sammenligning af filer/biblioteker | V85: =_xlfn.XLOOKUP(Applications[[#This Row],[NoApplication]],AApplicationCosts[NoApplication],AApplicationCosts[License Owner],Applications[[#This Row],[Business Owner]],0,1) -> 0 | X85: LHB | AB85: Freeware | AE85: Software, Hardware Departments | AI85: JESP: i stedet for beyondCompare. Alterntiver skal tages I betragtning,. Toool til code merge skal findes.
B86: =_xlfn.CONCAT(Applications[[#This Row],[No]]," - ",Applications[[#This Row],[Application]]) -> 113 - Keysight ADS | C86: 113 | D86: Keysight ADS | E86: Simulations and Engineering | F86: 45658 | G86: Distributed Applications | J86: Keysight Technologies | N86: 7-Potential for phase out | O86: 46173 | Q86: ADS Core, Layout, Harmonic Balance,Momentum G2 bundled license JESP: Nødvendigt til RF Hardware design og RF simulering under udvikling | T86: T2 | U86: RF Simulering | V86: =_xlfn.XLOOKUP(Applications[[#This Row],[NoApplication]],AApplicationCosts[NoApplication],AApplicationCosts[License Owner],Applications[[#This Row],[Business Owner]],0,1) -> BOR | W86: MTM, JFB | X86: TES, JFB, BOR, LAZ, CJO, PEM, KAR, JCS | AA86: Floating license | AE86: Software, Hardware Departments
B87: =_xlfn.CONCAT(Applications[[#This Row],[No]]," - ",Applications[[#This Row],[Application]]) -> 114 - Labview | C87: 114 | D87: Labview | E87: Simulations and Engineering | F87: 45658 | J87: National Instruments | N87: 5-Investigate | O87: 54788 | T87: T2 | U87: Test | V87: =_xlfn.XLOOKUP(Applications[[#This Row],[NoApplication]],AApplicationCosts[NoApplication],AApplicationCosts[License Owner],Applications[[#This Row],[Business Owner]],0,1) -> 0 | X87: TES | AA87: Single license | AB87: TES
B88: =_xlfn.CONCAT(Applications[[#This Row],[No]]," - ",Applications[[#This Row],[Application]]) -> 116 - Orcad / Cadence | C88: 116 | D88: Orcad / Cadence | E88: Simulations and Engineering | F88: 45658 | G88: Distributed Applications | J88: Cadence Design Systems | N88: 1-Strategic | O88: 54788 | T88: T2 | U88: Diagram tegning og Print udlægning | V88: =_xlfn.XLOOKUP(Applications[[#This Row],[NoApplication]],AApplicationCosts[NoApplication],AApplicationCosts[License Owner],Applications[[#This Row],[Business Owner]],0,1) -> TES | W88: JLU | X88: LBU, JLU, TES, JFB, BOR, LAZ, CJO, PEM, KAR, JCS | AA88: Floating license | AE88: Software, Hardware Departments | AH88: Cadance
B89: =_xlfn.CONCAT(Applications[[#This Row],[No]]," - ",Applications[[#This Row],[Application]]) -> 117 - Pads | C89: 117 | D89: Pads | E89: Utilities and Miscellaneous | F89: 45658 | G89: Distributed Applications | J89: PADS Software | N89: 2-Important application | O89: 46173 | T89: T2 | U89: Diagram tegning og Print udlægning | V89: =_xlfn.XLOOKUP(Applications[[#This Row],[NoApplication]],AApplicationCosts[NoApplication],AApplicationCosts[License Owner],Applications[[#This Row],[Business Owner]],0,1) -> 0 | X89: LBU, JLU, TES, JFB, BOR, LAZ, CJO, PEM, KAR, JCS | AA89: Dongle | AE89: Software, Hardware Departments | AI89: FRFS: Set to potential for phase out based on info from business of ELIMINATE | AJ89: Eliminate | AO89: Investigate
B90: =_xlfn.CONCAT(Applications[[#This Row],[No]]," - ",Applications[[#This Row],[Application]]) -> 118 - Python | C90: 118 | D90: Python | E90: Development and Programming | F90: 45658 | G90: Distributed Applications | J90: Python Software Foundation | N90: 1-Strategic | O90: 54788 | T90: T0 | U90: Scripting | V90: =_xlfn.XLOOKUP(Applications[[#This Row],[NoApplication]],AApplicationCosts[NoApplication],AApplicationCosts[License Owner],Applications[[#This Row],[Business Owner]],0,1) -> 0 | X90: LBU, JLU, TES, JFB, BOR, LAZ, CJO, PEM, KAR, JCS | AB90: Freeware | AC90: 118 - Python | AE90: Software, Hardware Departments | AH90: Python | AJ90: Tolerate/Invest
B91: =_xlfn.CONCAT(Applications[[#This Row],[No]]," - ",Applications[[#This Row],[Application]]) -> 119 - R&S EMC32 | C91: 119 | D91: R&S EMC32 | E91: Simulations and Engineering | F91: 45658 | J91: Rohde & Schwarz | M91: 0-9 | N91: 5-Investigate | O91: 54788 | T91: T2 | U91: Test - EMC kammer | V91: =_xlfn.XLOOKUP(Applications[[#This Row],[NoApplication]],AApplicationCosts[NoApplication],AApplicationCosts[License Owner],Applications[[#This Row],[Business Owner]],0,1) -> MILA | W91: JLK | X91: TES, JFB, BOR, LAZ, CJO, PEM, KAR, JCS | AA91: 2xDongle
B92: =_xlfn.CONCAT(Applications[[#This Row],[No]]," - ",Applications[[#This Row],[Application]]) -> 120 - SolidWorks | C92: 120 | D92: SolidWorks | E92: Simulations and Engineering | F92: 45658 | G92: Distributed Applications | J92: Dassault Systèmes | N92: 1-Strategic | O92: 54788 | Q92: 3D tegneprogram.Mekanisk konstruktion | T92: T2 | U92: 3D tegneprogram.Mekanisk konstruktion | V92: =_xlfn.XLOOKUP(Applications[[#This Row],[NoApplication]],AApplicationCosts[NoApplication],AApplicationCosts[License Owner],Applications[[#This Row],[Business Owner]],0,1) -> MEG | X92: BOR, JLU, NAN, LPI, JES,LAM;IRA | AA92: No yearly licens | AE92: Software, Hardware Departments | AI92: Tegningsgrundlag for alt, vil ikke kunne skiftes, look into the licenses of this, not same versioning and used in Kamstrup, we should use same versions, files in new versions can not be opend by all users.
B93: =_xlfn.CONCAT(Applications[[#This Row],[No]]," - ",Applications[[#This Row],[Application]]) -> 121 - Balsamiq Mockups | C93: 121 | D93: Balsamiq Mockups | E93: Productivity | F93: 45658 | J93: Balsamiq Studios, LLC | N93: 5-Investigate | O93: 54788 | T93: T2 | U93: GUI Prototyping - Vi har ikke nyeste versioner | V93: =_xlfn.XLOOKUP(Applications[[#This Row],[NoApplication]],AApplicationCosts[NoApplication],AApplicationCosts[License Owner],Applications[[#This Row],[Business Owner]],0,1) -> 0 | W93: JLY | X93: JLY;KAK | AB93: Egne personlige licenser
B94: =_xlfn.CONCAT(Applications[[#This Row],[No]]," - ",Applications[[#This Row],[Application]]) -> 122 - List&Label | C94: 122 | D94: List&Label | E94: Business | F94: 45658 | J94: Combit GmbH | M94: 0-9 | N94: 4-Saved for now | O94: 54788 | R94: Software für Entwicklung und Kontaktmanagement von combit | T94: T2 | U94: Label / rapport Design/Udskrivning | V94: =_xlfn.XLOOKUP(Applications[[#This Row],[NoApplication]],AApplicationCosts[NoApplication],AApplicationCosts[License Owner],Applications[[#This Row],[Business Owner]],0,1) -> KLU | W94: JLY;RBA;KAK;MDA | X94: JLY;RBA;KAK;MDA;KLU | Y94: DATA TO:All main products. KAMES, Integration owner JAX | AB94: KJN | AE94: Supply Chain
B95: =_xlfn.CONCAT(Applications[[#This Row],[No]]," - ",Applications[[#This Row],[Application]]) -> 124 - Pluralsight Skills | C95: 124 | D95: Pluralsight Skills | E95: Productivity | F95: 45658 | J95: Pluralsight, Inc. | M95: 10-49 | N95: 5-Investigate | O95: 54788 | Q95: Learning platform | T95: T2 | U95: Online kursusmatriale til bla. udviklingsmetoder og værktøjer - Vi deler en licens | V95: =_xlfn.XLOOKUP(Applications[[#This Row],[NoApplication]],AApplicationCosts[NoApplication],AApplicationCosts[License Owner],Applications[[#This Row],[Business Owner]],0,1) -> JLY | X95: JLY;MCR;RBA;MDA;KAK;KJN | AB95: KAK | AE95: Supply Chain
B96: =_xlfn.CONCAT(Applications[[#This Row],[No]]," - ",Applications[[#This Row],[Application]]) -> 125 - Raylase Weldmark | C96: 125 | D96: Raylase Weldmark | E96: Simulations and Engineering | F96: 45658 | J96: Raylase GmbH | N96: 5-Investigate | O96: 54788 | T96: T2 | U96: Laser markerings program | V96: =_xlfn.XLOOKUP(Applications[[#This Row],[NoApplication]],AApplicationCosts[NoApplication],AApplicationCosts[License Owner],Applications[[#This Row],[Business Owner]],0,1) -> 0 | X96: KAK;KJN;kamstrup-pta3 | AA96: Raylase | AB96: KJN via dongels
B97: =_xlfn.CONCAT(Applications[[#This Row],[No]]," - ",Applications[[#This Row],[Application]]) -> 126 - Renorex | C97: 126 | D97: Renorex | E97: Quality Management System | F97: 45658 | J97: Renuex GmbH | N97: 5-Investigate | O97: 54788 | T97: T2 | U97: Visual test automatisering | V97: =_xlfn.XLOOKUP(Applications[[#This Row],[NoApplication]],AApplicationCosts[NoApplication],AApplicationCosts[License Owner],Applications[[#This Row],[Business Owner]],0,1) -> 0 | X97: JHL;KJN | AA97: Renorex via dansk forhandler | AB97: KJN
B98: =_xlfn.CONCAT(Applications[[#This Row],[No]]," - ",Applications[[#This Row],[Application]]) -> 128 - AnkSVN | C98: 128 | D98: AnkSVN | E98: Development and Programming | F98: 45658 | J98: AnkSVN is developed by Ank God. | N98: 5-Investigate | O98: 54788 | T98: T2 | V98: =_xlfn.XLOOKUP(Applications[[#This Row],[NoApplication]],AApplicationCosts[NoApplication],AApplicationCosts[License Owner],Applications[[#This Row],[Business Owner]],0,1) -> 0 | X98: SHG;BBH;ARD;LAO;MRE; | AB98: Freeware
B99: =_xlfn.CONCAT(Applications[[#This Row],[No]]," - ",Applications[[#This Row],[Application]]) -> 129 - Chocolatey | C99: 129 | D99: Chocolatey | E99: Utilities and Miscellaneous | F99: 45658 | J99: Chocolatey Software, Inc. | N99: 2-Important application | O99: 54788 | T99: T2 | U99: NuGet pakke manager | V99: =_xlfn.XLOOKUP(Applications[[#This Row],[NoApplication]],AApplicationCosts[NoApplication],AApplicationCosts[License Owner],Applications[[#This Row],[Business Owner]],0,1) -> 0 | W99: ARD;KMO; | X99: SHG;MBM;ARD;KMO;MAH; | AB99: Freeware | AE99: Software, Hardware Departments | AI99: Er tidsbesparende at anvende. | AJ99: A significant time-investment is needed to remove this.
B100: =_xlfn.CONCAT(Applications[[#This Row],[No]]," - ",Applications[[#This Row],[Application]]) -> 130 - Emacs | C100: 130 | D100: Emacs | E100: Development and Programming | F100: 45658 | G100: Distributed Applications | J100: GNU Project | N100: 4-Saved for now | O100: 54788 | T100: T3 | U100: Editor og med det rette plugin alt hvad de andre programmer på listen kan. | V100: =_xlfn.XLOOKUP(Applications[[#This Row],[NoApplication]],AApplicationCosts[NoApplication],AApplicationCosts[License Owner],Applications[[#This Row],[Business Owner]],0,1) -> 0 | X100: TLJ; | AB100: Freeware | AD100: IDE | AE100: Software, Hardware Departments | AI100: Editor | AJ100: Tolerate/migrate | AK100: Free and open source client system
...

Sheet A-Application_Costs
B1: Chose the application | C1: Cost grouping of the appication | D1: Auto fill from A-Applications | E1: Auto fill from A-Applications | F1: Cost type - License - Support - Maintance - FTE (Actual/Recuired) - OPEX - CAPEX If mutipel types apply then create multipel lines | G1: Update by Supply Chain From date for the contract | H1: Update by Supply Chain To date for the contract | I1: Update by Supply Chain Interval of renewal Ever green=Run until termination, PO= Purchse order | J1: Update by Supply Chain Termination notice (in days) | K1: No of FTE working with this application | L1: OPEX rate for the FTE's | M1: Currency for the transaction | N1: Yearly license | O1: Update by Supply Chain VendorID for this applikation and costtype. | P1: Update by Supply Chain and Finance Vendor for this applikation and costtype. | Q1: Yearly license. Validated by Finance. Same currency as Yearly costs column | R1: Comment to the row | S1: Auto fill from A-Applications | T1: Update by Supply Chain Owner of the license Initials | U1: Update by Supply Chain Approver of the license Initials | V1: Auto fill from userlist | W1: Auto fill from userlist | X1: Update by Supply Chain Date when the contract are terminated from. This date is ONLY filled for terminatede contracts and are for historical purpose
B3: NoApplication | C3: CostGroup | D3: Supplier | E3: ItemNumber | F3: CostType | G3: FromDate | H3: ToDate | I3: Interval | J3: Termination notice | K3: FTE | L3: Opex rate | M3: Currency | N3: Yearly costs | O3: VendorID | P3: Vendor | Q3: Finance info on yearly licence | R3: Comment | S3: Used in capabilitiy mapping | T3: License Owner | U3: License Approver | V3: Department (Approver) | W3: Country | X3: Termination date
B4: 615 - Passolo | C4: RWS | D4: =VLOOKUP(AApplicationCosts[[#This Row],[NoApplication]],'A-Applications'!B:K,9,FALSE) -> RWS | E4: =VLOOKUP(AApplicationCosts[[#This Row],[NoApplication]],'A-Applications'!B:K,10,FALSE) -> 0 | F4: License | G4: 45374 | H4: 45738 | I4: Terminated - Still in use | J4: 30 | M4: EUR | N4: 0 | O4: 20000563 | P4: SDL Limited | R4: RWS cost on Passolo, Multiterm, Trados former yearly cost 8.807. All your licenses are permanent and belong to Kamstrup. This means they can continue being used regardless of a Support & Maintenance Agreement (SMA). The SMA provides priority access to technical support and free software upgrades. This means your account is up to date with the latest versions of the products on there. If you cancel this year’s SMA renewal and want to start a new SMA in the future this would involve purchasing an upgrade for any of the products which have had a new version released in the meantime. There are other options too, such as migrating to cloud versions of the products. Cloud would be my recommendation once you have identified your language strategy and requirements. Potentially linguistic AI too. FRFS: Price set to 0 due to contract termination, we can stil use the license | S4: =_xlfn.XLOOKUP(AApplicationCosts[[#This Row],[NoApplication]],'A-Applications'!B:B,'A-Applications'!AG:AG,,0,1) -> 0 | T4: AFR | U4: KRNO | V4: =IFERROR(VLOOKUP(AApplicationCosts[[#This Row],[License Approver]],Tabels!BD:BF,3,FALSE),"N/A") -> Digitalization | W4: =IFERROR(VLOOKUP(AApplicationCosts[[#This Row],[License Approver]],Tabels!BD:BG,4,FALSE),"N/A") -> DK10 | X4: 45738
B5: 616 - Multiterm | C5: RWS | D5: =VLOOKUP(AApplicationCosts[[#This Row],[NoApplication]],'A-Applications'!B:K,9,FALSE) -> RWS | E5: =VLOOKUP(AApplicationCosts[[#This Row],[NoApplication]],'A-Applications'!B:K,10,FALSE) -> 0 | F5: License | G5: 45374 | H5: 45738 | I5: Terminated - Still in use | J5: 30 | M5: EUR | N5: 0 | O5: 20000563 | P5: SDL Limited | R5: RWS cost on Passolo (see comment on license), Multiterm, Trados | S5: =_xlfn.XLOOKUP(AApplicationCosts[[#This Row],[NoApplication]],'A-Applications'!B:B,'A-Applications'!AG:AG,,0,1) -> 0 | T5: AFR | U5: KRNO | V5: =IFERROR(VLOOKUP(AApplicationCosts[[#This Row],[License Approver]],Tabels!BD:BF,3,FALSE),"N/A") -> Digitalization | W5: =IFERROR(VLOOKUP(AApplicationCosts[[#This Row],[License Approver]],Tabels!BD:BG,4,FALSE),"N/A") -> DK10 | X5: 45738
B6: 618 - Trados | C6: RWS | D6: =VLOOKUP(AApplicationCosts[[#This Row],[NoApplication]],'A-Applications'!B:K,9,FALSE) -> RWS | E6: =VLOOKUP(AApplicationCosts[[#This Row],[NoApplication]],'A-Applications'!B:K,10,FALSE) -> 0 | F6: License | G6: 45374 | H6: 45738 | I6: Terminated - Still in use | J6: 30 | M6: EUR | N6: 0 | O6: 20000563 | P6: SDL Limited | R6: RWS cost on Passolo (see comment on license), Multiterm, Trados | S6: =_xlfn.XLOOKUP(AApplicationCosts[[#This Row],[NoApplication]],'A-Applications'!B:B,'A-Applications'!AG:AG,,0,1) -> 0 | T6: AFR | U6: KRNO | V6: =IFERROR(VLOOKUP(AApplicationCosts[[#This Row],[License Approver]],Tabels!BD:BF,3,FALSE),"N/A") -> Digitalization | W6: =IFERROR(VLOOKUP(AApplicationCosts[[#This Row],[License Approver]],Tabels!BD:BG,4,FALSE),"N/A") -> DK10 | X6: 45738
B7: 136 - Microsoft SQL Management Studio | C7: Servere RDS CAL og VS Pro/Ent | D7: =VLOOKUP(AApplicationCosts[[#This Row],[NoApplication]],'A-Applications'!B:K,9,FALSE) -> Microsoft | E7: =VLOOKUP(AApplicationCosts[[#This Row],[NoApplication]],'A-Applications'!B:K,10,FALSE) -> 0 | F7: License | G7: 45627 | H7: 45807 | I7: Half Year | J7: 30 | M7: DKR | N7: 0 | O7: 90455922 | P7: Microsoft | S7: =_xlfn.XLOOKUP(AApplicationCosts[[#This Row],[NoApplication]],'A-Applications'!B:B,'A-Applications'!AG:AG,,0,1) -> 0 | T7: LUCB | U7: ANJL | V7: =IFERROR(VLOOKUP(AApplicationCosts[[#This Row],[License Approver]],Tabels!BD:BF,3,FALSE),"N/A") -> Digitalization | W7: =IFERROR(VLOOKUP(AApplicationCosts[[#This Row],[License Approver]],Tabels!BD:BG,4,FALSE),"N/A") -> DK10
B8: 378 - Manged Keys | C8: Servere RDS CAL og VS Pro/Ent | D8: =VLOOKUP(AApplicationCosts[[#This Row],[NoApplication]],'A-Applications'!B:K,9,FALSE) -> Microsoft | E8: =VLOOKUP(AApplicationCosts[[#This Row],[NoApplication]],'A-Applications'!B:K,10,FALSE) -> 0 | F8: License | G8: 45627 | H8: 45807 | I8: Half Year | J8: 30 | M8: DKR | N8: 60000 | O8: 90455922 | P8: Microsoft | S8: =_xlfn.XLOOKUP(AApplicationCosts[[#This Row],[NoApplication]],'A-Applications'!B:B,'A-Applications'!AG:AG,,0,1) -> 0 | T8: JEDT | U8: ANUP | V8: =IFERROR(VLOOKUP(AApplicationCosts[[#This Row],[License Approver]],Tabels!BD:BF,3,FALSE),"N/A") -> Digitalization | W8: =IFERROR(VLOOKUP(AApplicationCosts[[#This Row],[License Approver]],Tabels!BD:BG,4,FALSE),"N/A") -> DK10
B9: 452 - Microsoft Customer Voice | C9: Dynamics CRM | D9: =VLOOKUP(AApplicationCosts[[#This Row],[NoApplication]],'A-Applications'!B:K,9,FALSE) -> Microsoft | E9: =VLOOKUP(AApplicationCosts[[#This Row],[NoApplication]],'A-Applications'!B:K,10,FALSE) -> RUC-00005 | F9: License | G9: 45627 | H9: 45807 | I9: Half Year | J9: 30 | M9: DKR | N9: 0 | O9: 90455922 | P9: Microsoft | S9: =_xlfn.XLOOKUP(AApplicationCosts[[#This Row],[NoApplication]],'A-Applications'!B:B,'A-Applications'!AG:AG,,0,1) -> 0 | T9: ALK | U9: ANJL | V9: =IFERROR(VLOOKUP(AApplicationCosts[[#This Row],[License Approver]],Tabels!BD:BF,3,FALSE),"N/A") -> Digitalization | W9: =IFERROR(VLOOKUP(AApplicationCosts[[#This Row],[License Approver]],Tabels!BD:BG,4,FALSE),"N/A") -> DK10
B10: 472 - Azure Integration Services | C10: Integration | D10: =VLOOKUP(AApplicationCosts[[#This Row],[NoApplication]],'A-Applications'!B:K,9,FALSE) -> Microsoft | E10: =VLOOKUP(AApplicationCosts[[#This Row],[NoApplication]],'A-Applications'!B:K,10,FALSE) -> 0 | F10: License | G10: 45627 | H10: 45807 | I10: Half Year | J10: 30 | M10: DKR | N10: 350000 | O10: 90455922 | P10: Microsoft | R10: Info from Fabrizio (FFM), SABK? | S10: =_xlfn.XLOOKUP(AApplicationCosts[[#This Row],[NoApplication]],'A-Applications'!B:B,'A-Applications'!AG:AG,,0,1) -> 0 | T10: FFM | U10: ANJL | V10: =IFERROR(VLOOKUP(AApplicationCosts[[#This Row],[License Approver]],Tabels!BD:BF,3,FALSE),"N/A") -> Digitalization | W10: =IFERROR(VLOOKUP(AApplicationCosts[[#This Row],[License Approver]],Tabels!BD:BG,4,FALSE),"N/A") -> DK10
B11: 532 - Exchange Online P2 Sub Per User | C11: M365 | D11: =VLOOKUP(AApplicationCosts[[#This Row],[NoApplication]],'A-Applications'!B:K,9,FALSE) -> Microsoft | E11: =VLOOKUP(AApplicationCosts[[#This Row],[NoApplication]],'A-Applications'!B:K,10,FALSE) -> TQA-00001 | F11: License | G11: 45627 | H11: 45807 | I11: Half Year | J11: 30 | M11: DKR | N11: 570 | O11: 90455922 | P11: Microsoft | S11: =_xlfn.XLOOKUP(AApplicationCosts[[#This Row],[NoApplication]],'A-Applications'!B:B,'A-Applications'!AG:AG,,0,1) -> No | T11: LUCB | U11: ANJL | V11: =IFERROR(VLOOKUP(AApplicationCosts[[#This Row],[License Approver]],Tabels!BD:BF,3,FALSE),"N/A") -> Digitalization | W11: =IFERROR(VLOOKUP(AApplicationCosts[[#This Row],[License Approver]],Tabels!BD:BG,4,FALSE),"N/A") -> DK10
B12: 546 - Win Server Standard Core ALng SA 2L | C12: Servere RDS CAL og VS Pro/Ent | D12: =VLOOKUP(AApplicationCosts[[#This Row],[NoApplication]],'A-Applications'!B:K,9,FALSE) -> Microsoft | E12: =VLOOKUP(AApplicationCosts[[#This Row],[NoApplication]],'A-Applications'!B:K,10,FALSE) -> 9EM-00270 | F12: License | G12: 45627 | H12: 45807 | I12: Half Year | J12: 30 | M12: DKR | N12: 30904.32 | O12: 90455922 | P12: Microsoft | S12: =_xlfn.XLOOKUP(AApplicationCosts[[#This Row],[NoApplication]],'A-Applications'!B:B,'A-Applications'!AG:AG,,0,1) -> No | T12: JEDT | U12: ANUP | V12: =IFERROR(VLOOKUP(AApplicationCosts[[#This Row],[License Approver]],Tabels!BD:BF,3,FALSE),"N/A") -> Digitalization | W12: =IFERROR(VLOOKUP(AApplicationCosts[[#This Row],[License Approver]],Tabels!BD:BG,4,FALSE),"N/A") -> DK10
B13: 547 - Win Remote Desktop Services CAL ALng SA UCAL | C13: Servere RDS CAL og VS Pro/Ent | D13: =VLOOKUP(AApplicationCosts[[#This Row],[NoApplication]],'A-Applications'!B:K,9,FALSE) -> Microsoft | E13: =VLOOKUP(AApplicationCosts[[#This Row],[NoApplication]],'A-Applications'!B:K,10,FALSE) -> 6VC-01254 | F13: License | G13: 45627 | H13: 45807 | I13: Half Year | J13: 30 | M13: DKR | N13: 25848 | O13: 90455922 | P13: Microsoft | S13: =_xlfn.XLOOKUP(AApplicationCosts[[#This Row],[NoApplication]],'A-Applications'!B:B,'A-Applications'!AG:AG,,0,1) -> No | T13: JEDT | U13: ANUP | V13: =IFERROR(VLOOKUP(AApplicationCosts[[#This Row],[License Approver]],Tabels!BD:BF,3,FALSE),"N/A") -> Digitalization | W13: =IFERROR(VLOOKUP(AApplicationCosts[[#This Row],[License Approver]],Tabels!BD:BG,4,FALSE),"N/A") -> DK10
B14: 550 - D365 Customer Insights Journeys T1 | C14: Dynamics CRM | D14: =VLOOKUP(AApplicationCosts[[#This Row],[NoApplication]],'A-Applications'!B:K,9,FALSE) -> Microsoft | E14: =VLOOKUP(AApplicationCosts[[#This Row],[NoApplication]],'A-Applications'!B:K,10,FALSE) -> 6BL-00001 | F14: License | G14: 45627 | H14: 45807 | I14: Half Year | J14: 30 | M14: DKR | N14: =58362+52389 -> 110751 | O14: 90455922 | P14: Microsoft | R14: CSP Agrement (58362) | S14: =_xlfn.XLOOKUP(AApplicationCosts[[#This Row],[NoApplication]],'A-Applications'!B:B,'A-Applications'!AG:AG,,0,1) -> 0 | T14: ALK | U14: ANJL | V14: =IFERROR(VLOOKUP(AApplicationCosts[[#This Row],[License Approver]],Tabels!BD:BF,3,FALSE),"N/A") -> Digitalization | W14: =IFERROR(VLOOKUP(AApplicationCosts[[#This Row],[License Approver]],Tabels!BD:BG,4,FALSE),"N/A") -> DK10
B15: NoApplication | D15: =VLOOKUP(AApplicationCosts[[#This Row],[NoApplication]],'A-Applications'!B:K,9,FALSE) -> Software Vendor | E15: =VLOOKUP(AApplicationCosts[[#This Row],[NoApplication]],'A-Applications'!B:K,10,FALSE) -> ItemNumber | F15: OPEX/Professional Service | G15: 44713 | H15: 45809 | I15: 3 Year | J15: 31 | M15: DKR | N15: =135010*12 -> 1620120 | O15: 20000899 | P15: Truesec | R15: EDR - SOC - Manage inspect response. 13/1-2026 Michael to negotiate new contract. | S15: =_xlfn.XLOOKUP(AApplicationCosts[[#This Row],[NoApplication]],'A-Applications'!B:B,'A-Applications'!AG:AG,,0,1) -> Used in capabilitiy mapping | T15: KRKE | U15: KRKE | V15: =IFERROR(VLOOKUP(AApplicationCosts[[#This Row],[License Approver]],Tabels!BD:BF,3,FALSE),"N/A") -> Digitalization | W15: =IFERROR(VLOOKUP(AApplicationCosts[[#This Row],[License Approver]],Tabels!BD:BG,4,FALSE),"N/A") -> DK10
B16: 956 - Figma | D16: =VLOOKUP(AApplicationCosts[[#This Row],[NoApplication]],'A-Applications'!B:K,9,FALSE) -> Figma.com | E16: =VLOOKUP(AApplicationCosts[[#This Row],[NoApplication]],'A-Applications'!B:K,10,FALSE) -> 0 | F16: License | G16: 45835 | H16: 46199 | I16: Year - No contract | J16: 30 | M16: USD | N16: =11925+187.5 -> 12112.5 | P16: Figma.com | R16: 10/4-25: 25 users. Payed by Creditcard but should be moved to invoice. HCJ would like to have the license transfered to digitalization. | S16: =_xlfn.XLOOKUP(AApplicationCosts[[#This Row],[NoApplication]],'A-Applications'!B:B,'A-Applications'!AG:AG,,0,1) -> 0 | T16: LAAG | U16: ANUP | V16: =IFERROR(VLOOKUP(AApplicationCosts[[#This Row],[License Approver]],Tabels!BD:BF,3,FALSE),"N/A") -> Digitalization | W16: =IFERROR(VLOOKUP(AApplicationCosts[[#This Row],[License Approver]],Tabels!BD:BG,4,FALSE),"N/A") -> DK10
B17: 469 - Citilytics | D17: =VLOOKUP(AApplicationCosts[[#This Row],[NoApplication]],'A-Applications'!B:K,9,FALSE) -> Speridian Technologies | E17: =VLOOKUP(AApplicationCosts[[#This Row],[NoApplication]],'A-Applications'!B:K,10,FALSE) -> 0 | F17: License | G17: 45565 | H17: 45930 | I17: Year | J17: 60 | M17: USD | N17: 43660 | R17: paid by Kamstrup U.S. for bid purposes (US10) US informed price 10.915. Supply info price 43.660 | S17: =_xlfn.XLOOKUP(AApplicationCosts[[#This Row],[NoApplication]],'A-Applications'!B:B,'A-Applications'!AG:AG,,0,1) -> 0 | T17: JST | U17: BRBT | V17: =IFERROR(VLOOKUP(AApplicationCosts[[#This Row],[License Approver]],Tabels!BD:BF,3,FALSE),"N/A") -> Sales & Marketing | W17: =IFERROR(VLOOKUP(AApplicationCosts[[#This Row],[License Approver]],Tabels!BD:BG,4,FALSE),"N/A") -> US10
B18: 478 - IAR Embedded Workbench for ARM Cortex-M | C18: IAR | D18: =VLOOKUP(AApplicationCosts[[#This Row],[NoApplication]],'A-Applications'!B:K,9,FALSE) -> IAR Systems | E18: =VLOOKUP(AApplicationCosts[[#This Row],[NoApplication]],'A-Applications'!B:K,10,FALSE) -> 0 | F18: License | G18: 45930 | H18: 46296 | I18: No contract | M18: DKR | N18: 161216 | O18: 90450098 | P18: IAR Systems | Q18: 154000 | S18: =_xlfn.XLOOKUP(AApplicationCosts[[#This Row],[NoApplication]],'A-Applications'!B:B,'A-Applications'!AG:AG,,0,1) -> 0 | T18: JDP | U18: MKI | V18: =IFERROR(VLOOKUP(AApplicationCosts[[#This Row],[License Approver]],Tabels!BD:BF,3,FALSE),"N/A") -> Water - Technology Hardware | W18: =IFERROR(VLOOKUP(AApplicationCosts[[#This Row],[License Approver]],Tabels!BD:BG,4,FALSE),"N/A") -> DK10
B19: 479 - IAR Embedded Workbench for MSP430 | C19: IAR | D19: =VLOOKUP(AApplicationCosts[[#This Row],[NoApplication]],'A-Applications'!B:K,9,FALSE) -> IAR Systems | E19: =VLOOKUP(AApplicationCosts[[#This Row],[NoApplication]],'A-Applications'!B:K,10,FALSE) -> 0 | F19: License | G19: 45930 | H19: 46296 | I19: No contract | M19: DKR | N19: 79699 | O19: 90450098 | P19: IAR Systems | S19: =_xlfn.XLOOKUP(AApplicationCosts[[#This Row],[NoApplication]],'A-Applications'!B:B,'A-Applications'!AG:AG,,0,1) -> 0 | T19: JDP | U19: MKI | V19: =IFERROR(VLOOKUP(AApplicationCosts[[#This Row],[License Approver]],Tabels!BD:BF,3,FALSE),"N/A") -> Water - Technology Hardware | W19: =IFERROR(VLOOKUP(AApplicationCosts[[#This Row],[License Approver]],Tabels!BD:BG,4,FALSE),"N/A") -> DK10
B20: 646 - IAR | C20: IAR | D20: =VLOOKUP(AApplicationCosts[[#This Row],[NoApplication]],'A-Applications'!B:K,9,FALSE) -> IAR Systems | E20: =VLOOKUP(AApplicationCosts[[#This Row],[NoApplication]],'A-Applications'!B:K,10,FALSE) -> 0 | F20: License | G20: 45930 | H20: 46296 | I20: No contract | M20: DKR | N20: 0 | O20: 90450098 | P20: IAR Systems | S20: =_xlfn.XLOOKUP(AApplicationCosts[[#This Row],[NoApplication]],'A-Applications'!B:B,'A-Applications'!AG:AG,,0,1) -> 0 | T20: JDP | U20: MKI | V20: =IFERROR(VLOOKUP(AApplicationCosts[[#This Row],[License Approver]],Tabels!BD:BF,3,FALSE),"N/A") -> Water - Technology Hardware | W20: =IFERROR(VLOOKUP(AApplicationCosts[[#This Row],[License Approver]],Tabels!BD:BG,4,FALSE),"N/A") -> DK10
B21: 835 - IAR Embedded Workbench for 78K | C21: IAR | D21: =VLOOKUP(AApplicationCosts[[#This Row],[NoApplication]],'A-Applications'!B:K,9,FALSE) -> IAR Systems | E21: =VLOOKUP(AApplicationCosts[[#This Row],[NoApplication]],'A-Applications'!B:K,10,FALSE) -> 0 | F21: License | G21: 45930 | H21: 46296 | I21: No contract | M21: DKR | N21: 10737 | O21: 90450098 | P21: IAR Systems | S21: =_xlfn.XLOOKUP(AApplicationCosts[[#This Row],[NoApplication]],'A-Applications'!B:B,'A-Applications'!AG:AG,,0,1) -> 0 | T21: JDP | U21: MKI | V21: =IFERROR(VLOOKUP(AApplicationCosts[[#This Row],[License Approver]],Tabels!BD:BF,3,FALSE),"N/A") -> Water - Technology Hardware | W21: =IFERROR(VLOOKUP(AApplicationCosts[[#This Row],[License Approver]],Tabels!BD:BG,4,FALSE),"N/A") -> DK10
B22: 986 - Attention Web Manager | D22: =VLOOKUP(AApplicationCosts[[#This Row],[NoApplication]],'A-Applications'!B:K,9,FALSE) -> Attention Solution | E22: =VLOOKUP(AApplicationCosts[[#This Row],[NoApplication]],'A-Applications'!B:K,10,FALSE) -> 0 | F22: License | G22: 45960 | H22: 46324 | I22: Year - No contract | J22: 15 | M22: DKR | N22: 3375 | O22: 90453590 | P22: Attention solution | S22: =_xlfn.XLOOKUP(AApplicationCosts[[#This Row],[NoApplication]],'A-Applications'!B:B,'A-Applications'!AG:AG,,0,1) -> 0 | T22: AFR | U22: AFR | V22: =IFERROR(VLOOKUP(AApplicationCosts[[#This Row],[License Approver]],Tabels!BD:BF,3,FALSE),"N/A") -> Heat/Cooling - Product Management | W22: =IFERROR(VLOOKUP(AApplicationCosts[[#This Row],[License Approver]],Tabels!BD:BG,4,FALSE),"N/A") -> DK10
B23: 941 - Codemeter (DNV-tools) | C23: DNV | D23: =VLOOKUP(AApplicationCosts[[#This Row],[NoApplication]],'A-Applications'!B:K,9,FALSE) -> DNV | E23: =VLOOKUP(AApplicationCosts[[#This Row],[NoApplication]],'A-Applications'!B:K,10,FALSE) -> 0 | F23: License | G23: 45230 | H23: 45960 | I23: 2 Year | J23: 60 | M23: EUR | N23: 2295 | O23: 90453550 | P23: DNV | R23: Invoice with info from JKI, 3/2-26 Michael to investigate | S23: =_xlfn.XLOOKUP(AApplicationCosts[[#This Row],[NoApplication]],'A-Applications'!B:B,'A-Applications'!AG:AG,,0,1) -> 0 | U23: JKI | V23: =IFERROR(VLOOKUP(AApplicationCosts[[#This Row],[License Approver]],Tabels!BD:BF,3,FALSE),"N/A") -> Electricity - Technology Hardware | W23: =IFERROR(VLOOKUP(AApplicationCosts[[#This Row],[License Approver]],Tabels!BD:BG,4,FALSE),"N/A") -> DK10
B24: 942 - DNV DLMS Test Client | C24: DNV | D24: =VLOOKUP(AApplicationCosts[[#This Row],[NoApplication]],'A-Applications'!B:K,9,FALSE) -> DNV | E24: =VLOOKUP(AApplicationCosts[[#This Row],[NoApplication]],'A-Applications'!B:K,10,FALSE) -> 0 | F24: License | G24: 45230 | H24: 45960 | I24: 2 Year | J24: 60 | M24: EUR | N24: 2465 | O24: 90453550 | P24: DNV | R24: Invoice with info from JKI, 3/2-26 Michael to investigate | S24: =_xlfn.XLOOKUP(AApplicationCosts[[#This Row],[NoApplication]],'A-Applications'!B:B,'A-Applications'!AG:AG,,0,1) -> 0 | U24: JKI | V24: =IFERROR(VLOOKUP(AApplicationCosts[[#This Row],[License Approver]],Tabels!BD:BF,3,FALSE),"N/A") -> Electricity - Technology Hardware | W24: =IFERROR(VLOOKUP(AApplicationCosts[[#This Row],[License Approver]],Tabels!BD:BG,4,FALSE),"N/A") -> DK10
B25: 943 - DNV TFT test suite | C25: DNV | D25: =VLOOKUP(AApplicationCosts[[#This Row],[NoApplication]],'A-Applications'!B:K,9,FALSE) -> DNV | E25: =VLOOKUP(AApplicationCosts[[#This Row],[NoApplication]],'A-Applications'!B:K,10,FALSE) -> 0 | F25: License | G25: 45230 | H25: 45960 | I25: 2 Year | J25: 60 | M25: EUR | N25: =4335 -> 4335 | O25: 90453550 | P25: DNV | R25: Invoice with info from JKI, 3/2-26 Michael to investigate | S25: =_xlfn.XLOOKUP(AApplicationCosts[[#This Row],[NoApplication]],'A-Applications'!B:B,'A-Applications'!AG:AG,,0,1) -> 0 | U25: JKI | V25: =IFERROR(VLOOKUP(AApplicationCosts[[#This Row],[License Approver]],Tabels!BD:BF,3,FALSE),"N/A") -> Electricity - Technology Hardware | W25: =IFERROR(VLOOKUP(AApplicationCosts[[#This Row],[License Approver]],Tabels!BD:BG,4,FALSE),"N/A") -> DK10
B26: 981 - Sysarb | D26: =VLOOKUP(AApplicationCosts[[#This Row],[NoApplication]],'A-Applications'!B:K,9,FALSE) -> Sysarb | E26: =VLOOKUP(AApplicationCosts[[#This Row],[NoApplication]],'A-Applications'!B:K,10,FALSE) -> 0 | F26: License | G26: 45962 | H26: 46326 | I26: Year | J26: 93 | M26: SEK | N26: 51827 | O26: 20001069 | P26: Sysarb | R26: Salery system Sweden | S26: =_xlfn.XLOOKUP(AApplicationCosts[[#This Row],[NoApplication]],'A-Applications'!B:B,'A-Applications'!AG:AG,,0,1) -> 0 | T26: LANY | U26: JEHS | V26: =IFERROR(VLOOKUP(AApplicationCosts[[#This Row],[License Approver]],Tabels!BD:BF,3,FALSE),"N/A") -> Sales & Marketing | W26: =IFERROR(VLOOKUP(AApplicationCosts[[#This Row],[License Approver]],Tabels!BD:BG,4,FALSE),"N/A") -> SE10
B27: 169 - TestComplete | D27: =VLOOKUP(AApplicationCosts[[#This Row],[NoApplication]],'A-Applications'!B:K,9,FALSE) -> SmartBear Software | E27: =VLOOKUP(AApplicationCosts[[#This Row],[NoApplication]],'A-Applications'!B:K,10,FALSE) -> 0 | F27: License | G27: 45963 | H27: 46327 | I27: No contract | M27: DKR | N27: =95596+33915 -> 129511 | O27: 90450860 | P27: Nordic Software Group | R27: Combining TestComplete and Test Execute | S27: =_xlfn.XLOOKUP(AApplicationCosts[[#This Row],[NoApplication]],'A-Applications'!B:B,'A-Applications'!AG:AG,,0,1) -> 0 | T27: MKI | U27: MOEP | V27: =IFERROR(VLOOKUP(AApplicationCosts[[#This Row],[License Approver]],Tabels!BD:BF,3,FALSE),"N/A") -> Heat/Cooling - Technology Software | W27: =IFERROR(VLOOKUP(AApplicationCosts[[#This Row],[License Approver]],Tabels!BD:BG,4,FALSE),"N/A") -> DK10
B28: 403 - Synthesia Enterprise Package | D28: =VLOOKUP(AApplicationCosts[[#This Row],[NoApplication]],'A-Applications'!B:K,9,FALSE) -> Synthesia | E28: =VLOOKUP(AApplicationCosts[[#This Row],[NoApplication]],'A-Applications'!B:K,10,FALSE) -> 0 | F28: License | G28: 45974 | H28: 46338 | I28: Year - No contract | J28: 30 | M28: USD | N28: 23940 | O28: 20002076 | P28: Synthesia | R28: Someone said it was free currently, but we pay for it. FRFS S&M WP1 | S28: =_xlfn.XLOOKUP(AApplicationCosts[[#This Row],[NoApplication]],'A-Applications'!B:B,'A-Applications'!AG:AG,,0,1) -> 0 | T28: JABE | U28: BRBT | V28: =IFERROR(VLOOKUP(AApplicationCosts[[#This Row],[License Approver]],Tabels!BD:BF,3,FALSE),"N/A") -> Sales & Marketing | W28: =IFERROR(VLOOKUP(AApplicationCosts[[#This Row],[License Approver]],Tabels!BD:BG,4,FALSE),"N/A") -> US10
B29: 1097 - Nemtilmeld | D29: =VLOOKUP(AApplicationCosts[[#This Row],[NoApplication]],'A-Applications'!B:K,9,FALSE) -> Nemtilmeld | E29: =VLOOKUP(AApplicationCosts[[#This Row],[NoApplication]],'A-Applications'!B:K,10,FALSE) -> 0 | F29: License | G29: 45992 | H29: 46357 | I29: Year | J29: 30 | M29: DKR | N29: 30800 | O29: 90455343 | P29: NemTilmed | R29: Info om denne fra Gitte GFS, mail sendt videre til KRNO for anden løsning. Ny pris skulle være 50.900,- | S29: =_xlfn.XLOOKUP(AApplicationCosts[[#This Row],[NoApplication]],'A-Applications'!B:B,'A-Applications'!AG:AG,,0,1) -> 0 | T29: KRNO | U29: ANJL | V29: =IFERROR(VLOOKUP(AApplicationCosts[[#This Row],[License Approver]],Tabels!BD:BF,3,FALSE),"N/A") -> Digitalization | W29: =IFERROR(VLOOKUP(AApplicationCosts[[#This Row],[License Approver]],Tabels!BD:BG,4,FALSE),"N/A") -> DK10
B30: 558 - VenzoAI (Kamassist) | D30: =VLOOKUP(AApplicationCosts[[#This Row],[NoApplication]],'A-Applications'!B:K,9,FALSE) -> Venzo | E30: =VLOOKUP(AApplicationCosts[[#This Row],[NoApplication]],'A-Applications'!B:K,10,FALSE) -> 0 | F30: License | G30: 45962 | H30: 46326 | I30: Year | J30: 93 | M30: DKR | N30: 135000 | O30: 20001615 | P30: Venzo | Q30: 150000 | R30: Venzo Private Copilot | S30: =_xlfn.XLOOKUP(AApplicationCosts[[#This Row],[NoApplication]],'A-Applications'!B:B,'A-Applications'!AG:AG,,0,1) -> 0 | T30: MIBL | U30: ALK | V30: =IFERROR(VLOOKUP(AApplicationCosts[[#This Row],[License Approver]],Tabels!BD:BF,3,FALSE),"N/A") -> Digitalization | W30: =IFERROR(VLOOKUP(AApplicationCosts[[#This Row],[License Approver]],Tabels!BD:BG,4,FALSE),"N/A") -> DK10
